/*     */ package org.a.c.f;
/*     */ 
/*     */ import java.io.ByteArrayInputStream;
/*     */ import java.util.ArrayList;
/*     */ import java.util.List;
/*     */ import org.a.a.a.a;
/*     */ import org.a.a.a.c;
/*     */ import org.a.c.a.a;
/*     */ 
/*     */ 
/*     */ 
/*     */ 
/*     */ 
/*     */ 
/*     */ 
/*     */ 
/*     */ 
/*     */ 
/*     */ 
/*     */ 
/*     */ 
/*     */ 
/*     */ 
/*     */ 
/*     */ 
/*     */ 
/*     */ 
/*     */ 
/*     */ 
/*     */ 
/*     */ 
/*     */ 
/*     */ 
/*     */ 
/*     */ 
/*     */ 
/*     */ 
/*     */ 
/*     */ 
/*     */ 
/*     */ 
/*     */ 
/*     */ 
/*     */ 
/*     */ 
/*     */ public class g
/*     */   extends a
/*     */ {
/*  49 */   private static final a c = c.a(g.class);
/*     */   
/*  51 */   private final List<Object> d = new ArrayList(100);
/*     */ 
/*     */   
/*  54 */   private final byte[] e = new byte[10];
/*     */ 
/*     */ 
/*     */ 
/*     */ 
/*     */ 
/*     */ 
/*     */ 
/*     */ 
/*     */ 
/*     */ 
/*     */ 
/*     */ 
/*     */ 
/*     */ 
/*     */ 
/*     */ 
/*     */ 
/*     */ 
/*     */ 
/*     */ 
/*     */ 
/*     */ 
/*     */ 
/*     */ 
/*     */ 
/*     */ 
/*     */ 
/*     */ 
/*     */ 
/*     */ 
/*     */ 
/*     */ 
/*     */ 
/*     */ 
/*     */ 
/*     */   
/*     */   public g(a parama) {
/*  92 */     super(new d(parama.a()));
/*     */   }
/*     */ 
/*     */ 
/*     */ 
/*     */ 
/*     */ 
/*     */ 
/*     */ 
/*     */   
/*     */   public g(byte[] paramArrayOfbyte) {
/* 103 */     super(new d(new ByteArrayInputStream(paramArrayOfbyte)));
/*     */   }
/*     */ 
/*     */ 
/*     */ 
/*     */ 
/*     */ 
/*     */ 
/*     */ 
/*     */   
/*     */   public final void p() {
/*     */     Object object;
/* 115 */     while ((object = r()) != null)
/*     */     {
/* 117 */       this.d.add(object);
/*     */     }
/*     */   }
/*     */ 
/*     */ 
/*     */ 
/*     */ 
/*     */ 
/*     */ 
/*     */   
/*     */   public final List<Object> q() {
/* 128 */     return this.d;
/*     */   }
/*     */ 
/*     */ 
/*     */ 
/*     */ 
/*     */ 
/*     */ 
/*     */ 
/*     */ 
/*     */ 
/*     */ 
/*     */ 
/*     */ 
/*     */ 
/*     */ 
/*     */ 
/*     */ 
/*     */ 
/*     */ 
/*     */ 
/*     */ 
/*     */ 
/*     */ 
/*     */ 
/*     */ 
/*     */ 
/*     */ 
/*     */ 
/*     */ 
/*     */ 
/*     */ 
/*     */ 
/*     */ 
/*     */ 
/*     */ 
/*     */ 
/*     */ 
/*     */ 
/*     */ 
/*     */ 
/*     */ 
/*     */ 
/*     */ 
/*     */ 
/*     */ 
/*     */ 
/*     */ 
/*     */ 
/*     */ 
/*     */ 
/*     */ 
/*     */ 
/*     */ 
/*     */ 
/*     */ 
/*     */ 
/*     */ 
/*     */ 
/*     */ 
/*     */ 
/*     */ 
/*     */ 
/*     */ 
/*     */ 
/*     */ 
/*     */ 
/*     */ 
/*     */ 
/*     */ 
/*     */ 
/*     */ 
/*     */ 
/*     */ 
/*     */ 
/*     */ 
/*     */ 
/*     */ 
/*     */ 
/*     */ 
/*     */ 
/*     */ 
/*     */ 
/*     */ 
/*     */ 
/*     */ 
/*     */ 
/*     */ 
/*     */ 
/*     */ 
/*     */ 
/*     */ 
/*     */ 
/*     */ 
/*     */ 
/*     */ 
/*     */ 
/*     */ 
/*     */ 
/*     */ 
/*     */ 
/*     */ 
/*     */ 
/*     */ 
/*     */ 
/*     */ 
/*     */ 
/*     */ 
/*     */ 
/*     */ 
/*     */ 
/*     */ 
/*     */ 
/*     */ 
/*     */ 
/*     */ 
/*     */ 
/*     */ 
/*     */ 
/*     */ 
/*     */ 
/*     */ 
/*     */ 
/*     */ 
/*     */   
/*     */   public final Object r() {
/*     */     // Byte code:
/*     */     //   0: aload_0
/*     */     //   1: invokevirtual l : ()V
/*     */     //   4: aload_0
/*     */     //   5: getfield a : Lorg/a/c/f/k;
/*     */     //   8: invokeinterface c : ()I
/*     */     //   13: dup
/*     */     //   14: istore_1
/*     */     //   15: i2b
/*     */     //   16: iconst_m1
/*     */     //   17: if_icmpne -> 22
/*     */     //   20: aconst_null
/*     */     //   21: areturn
/*     */     //   22: iload_1
/*     */     //   23: i2c
/*     */     //   24: dup
/*     */     //   25: istore_1
/*     */     //   26: tableswitch default -> 1051, 40 -> 409, 41 -> 1051, 42 -> 1051, 43 -> 533, 44 -> 1051, 45 -> 533, 46 -> 533, 47 -> 417, 48 -> 533, 49 -> 533, 50 -> 533, 51 -> 533, 52 -> 533, 53 -> 533, 54 -> 533, 55 -> 533, 56 -> 533, 57 -> 533, 58 -> 1051, 59 -> 1051, 60 -> 348, 61 -> 1051, 62 -> 1051, 63 -> 1051, 64 -> 1051, 65 -> 1051, 66 -> 678, 67 -> 1051, 68 -> 1051, 69 -> 1051, 70 -> 1051, 71 -> 1051, 72 -> 1051, 73 -> 816, 74 -> 1051, 75 -> 1051, 76 -> 1051, 77 -> 1051, 78 -> 1051, 79 -> 1051, 80 -> 1051, 81 -> 1051, 82 -> 499, 83 -> 1051, 84 -> 1051, 85 -> 1051, 86 -> 1051, 87 -> 1051, 88 -> 1051, 89 -> 1051, 90 -> 1051, 91 -> 401, 92 -> 1051, 93 -> 1034, 94 -> 1051, 95 -> 1051, 96 -> 1051, 97 -> 1051, 98 -> 1051, 99 -> 1051, 100 -> 1051, 101 -> 1051, 102 -> 454, 103 -> 1051, 104 -> 1051, 105 -> 1051, 106 -> 1051, 107 -> 1051, 108 -> 1051, 109 -> 1051, 110 -> 425, 111 -> 1051, 112 -> 1051, 113 -> 1051, 114 -> 1051, 115 -> 1051, 116 -> 454
/*     */     //   348: aload_0
/*     */     //   349: getfield a : Lorg/a/c/f/k;
/*     */     //   352: invokeinterface a : ()I
/*     */     //   357: istore_2
/*     */     //   358: aload_0
/*     */     //   359: getfield a : Lorg/a/c/f/k;
/*     */     //   362: invokeinterface c : ()I
/*     */     //   367: i2c
/*     */     //   368: istore_1
/*     */     //   369: aload_0
/*     */     //   370: getfield a : Lorg/a/c/f/k;
/*     */     //   373: iload_2
/*     */     //   374: invokeinterface a : (I)V
/*     */     //   379: iload_1
/*     */     //   380: bipush #60
/*     */     //   382: if_icmpne -> 393
/*     */     //   385: aload_0
/*     */     //   386: invokevirtual a : ()Lorg/a/c/b/d;
/*     */     //   389: astore_1
/*     */     //   390: goto -> 1076
/*     */     //   393: aload_0
/*     */     //   394: invokevirtual c : ()Lorg/a/c/b/s;
/*     */     //   397: astore_1
/*     */     //   398: goto -> 1076
/*     */     //   401: aload_0
/*     */     //   402: invokevirtual d : ()Lorg/a/c/b/a;
/*     */     //   405: astore_1
/*     */     //   406: goto -> 1076
/*     */     //   409: aload_0
/*     */     //   410: invokevirtual c : ()Lorg/a/c/b/s;
/*     */     //   413: astore_1
/*     */     //   414: goto -> 1076
/*     */     //   417: aload_0
/*     */     //   418: invokevirtual e : ()Lorg/a/c/b/j;
/*     */     //   421: astore_1
/*     */     //   422: goto -> 1076
/*     */     //   425: aload_0
/*     */     //   426: invokevirtual g : ()Ljava/lang/String;
/*     */     //   429: dup
/*     */     //   430: astore_2
/*     */     //   431: ldc 'null'
/*     */     //   433: invokevirtual equals : (Ljava/lang/Object;)Z
/*     */     //   436: ifeq -> 446
/*     */     //   439: getstatic org/a/c/b/k.a : Lorg/a/c/b/k;
/*     */     //   442: astore_1
/*     */     //   443: goto -> 1076
/*     */     //   446: aload_2
/*     */     //   447: invokestatic a : (Ljava/lang/String;)Lorg/a/c/a/a/a;
/*     */     //   450: astore_1
/*     */     //   451: goto -> 1076
/*     */     //   454: aload_0
/*     */     //   455: invokevirtual g : ()Ljava/lang/String;
/*     */     //   458: dup
/*     */     //   459: astore_2
/*     */     //   460: ldc 'true'
/*     */     //   462: invokevirtual equals : (Ljava/lang/Object;)Z
/*     */     //   465: ifeq -> 475
/*     */     //   468: getstatic org/a/c/b/c.a : Lorg/a/c/b/c;
/*     */     //   471: astore_1
/*     */     //   472: goto -> 1076
/*     */     //   475: aload_2
/*     */     //   476: ldc 'false'
/*     */     //   478: invokevirtual equals : (Ljava/lang/Object;)Z
/*     */     //   481: ifeq -> 491
/*     */     //   484: getstatic org/a/c/b/c.b : Lorg/a/c/b/c;
/*     */     //   487: astore_1
/*     */     //   488: goto -> 1076
/*     */     //   491: aload_2
/*     */     //   492: invokestatic a : (Ljava/lang/String;)Lorg/a/c/a/a/a;
/*     */     //   495: astore_1
/*     */     //   496: goto -> 1076
/*     */     //   499: aload_0
/*     */     //   500: invokevirtual g : ()Ljava/lang/String;
/*     */     //   503: dup
/*     */     //   504: astore_2
/*     */     //   505: ldc 'R'
/*     */     //   507: invokevirtual equals : (Ljava/lang/Object;)Z
/*     */     //   510: ifeq -> 525
/*     */     //   513: new org/a/c/b/m
/*     */     //   516: dup
/*     */     //   517: aconst_null
/*     */     //   518: invokespecial <init> : (Lorg/a/c/b/b;)V
/*     */     //   521: astore_1
/*     */     //   522: goto -> 1076
/*     */     //   525: aload_2
/*     */     //   526: invokestatic a : (Ljava/lang/String;)Lorg/a/c/a/a/a;
/*     */     //   529: astore_1
/*     */     //   530: goto -> 1076
/*     */     //   533: new java/lang/StringBuilder
/*     */     //   536: dup
/*     */     //   537: invokespecial <init> : ()V
/*     */     //   540: dup
/*     */     //   541: astore_2
/*     */     //   542: iload_1
/*     */     //   543: invokevirtual append : (C)Ljava/lang/StringBuilder;
/*     */     //   546: pop
/*     */     //   547: aload_0
/*     */     //   548: getfield a : Lorg/a/c/f/k;
/*     */     //   551: invokeinterface a : ()I
/*     */     //   556: pop
/*     */     //   557: iload_1
/*     */     //   558: bipush #45
/*     */     //   560: if_icmpne -> 586
/*     */     //   563: aload_0
/*     */     //   564: getfield a : Lorg/a/c/f/k;
/*     */     //   567: invokeinterface c : ()I
/*     */     //   572: iload_1
/*     */     //   573: if_icmpne -> 586
/*     */     //   576: aload_0
/*     */     //   577: getfield a : Lorg/a/c/f/k;
/*     */     //   580: invokeinterface a : ()I
/*     */     //   585: pop
/*     */     //   586: iload_1
/*     */     //   587: bipush #46
/*     */     //   589: if_icmpeq -> 596
/*     */     //   592: iconst_1
/*     */     //   593: goto -> 597
/*     */     //   596: iconst_0
/*     */     //   597: istore_3
/*     */     //   598: aload_0
/*     */     //   599: getfield a : Lorg/a/c/f/k;
/*     */     //   602: invokeinterface c : ()I
/*     */     //   607: i2c
/*     */     //   608: dup
/*     */     //   609: istore_1
/*     */     //   610: invokestatic isDigit : (C)Z
/*     */     //   613: ifne -> 632
/*     */     //   616: iload_3
/*     */     //   617: ifeq -> 626
/*     */     //   620: iload_1
/*     */     //   621: bipush #46
/*     */     //   623: if_icmpeq -> 632
/*     */     //   626: iload_1
/*     */     //   627: bipush #45
/*     */     //   629: if_icmpne -> 667
/*     */     //   632: iload_1
/*     */     //   633: bipush #45
/*     */     //   635: if_icmpeq -> 644
/*     */     //   638: aload_2
/*     */     //   639: iload_1
/*     */     //   640: invokevirtual append : (C)Ljava/lang/StringBuilder;
/*     */     //   643: pop
/*     */     //   644: aload_0
/*     */     //   645: getfield a : Lorg/a/c/f/k;
/*     */     //   648: invokeinterface a : ()I
/*     */     //   653: pop
/*     */     //   654: iload_3
/*     */     //   655: ifeq -> 598
/*     */     //   658: iload_1
/*     */     //   659: bipush #46
/*     */     //   661: if_icmpne -> 598
/*     */     //   664: goto -> 596
/*     */     //   667: aload_2
/*     */     //   668: invokevirtual toString : ()Ljava/lang/String;
/*     */     //   671: invokestatic a : (Ljava/lang/String;)Lorg/a/c/b/l;
/*     */     //   674: astore_1
/*     */     //   675: goto -> 1076
/*     */     //   678: aload_0
/*     */     //   679: invokevirtual g : ()Ljava/lang/String;
/*     */     //   682: dup
/*     */     //   683: astore_2
/*     */     //   684: invokestatic a : (Ljava/lang/String;)Lorg/a/c/a/a/a;
/*     */     //   687: astore_1
/*     */     //   688: aload_2
/*     */     //   689: ldc 'BI'
/*     */     //   691: invokevirtual equals : (Ljava/lang/Object;)Z
/*     */     //   694: ifeq -> 1076
/*     */     //   697: aload_1
/*     */     //   698: checkcast org/a/c/a/a/a
/*     */     //   701: astore_3
/*     */     //   702: new org/a/c/b/d
/*     */     //   705: dup
/*     */     //   706: invokespecial <init> : ()V
/*     */     //   709: astore_2
/*     */     //   710: aload_3
/*     */     //   711: aload_2
/*     */     //   712: invokevirtual a : (Lorg/a/c/b/d;)V
/*     */     //   715: aload_0
/*     */     //   716: invokevirtual r : ()Ljava/lang/Object;
/*     */     //   719: dup
/*     */     //   720: astore #4
/*     */     //   722: instanceof org/a/c/b/j
/*     */     //   725: ifeq -> 751
/*     */     //   728: aload_0
/*     */     //   729: invokevirtual r : ()Ljava/lang/Object;
/*     */     //   732: astore #5
/*     */     //   734: aload_2
/*     */     //   735: aload #4
/*     */     //   737: checkcast org/a/c/b/j
/*     */     //   740: aload #5
/*     */     //   742: checkcast org/a/c/b/b
/*     */     //   745: invokevirtual a : (Lorg/a/c/b/j;Lorg/a/c/b/b;)V
/*     */     //   748: goto -> 715
/*     */     //   751: aload #4
/*     */     //   753: instanceof org/a/c/a/a/a
/*     */     //   756: ifeq -> 813
/*     */     //   759: aload #4
/*     */     //   761: checkcast org/a/c/a/a/a
/*     */     //   764: dup
/*     */     //   765: astore #5
/*     */     //   767: invokevirtual b : ()[B
/*     */     //   770: ifnull -> 782
/*     */     //   773: aload #5
/*     */     //   775: invokevirtual b : ()[B
/*     */     //   778: arraylength
/*     */     //   779: ifne -> 804
/*     */     //   782: new java/lang/StringBuilder
/*     */     //   785: dup
/*     */     //   786: ldc 'empty inline image at stream offset '
/*     */     //   788: invokespecial <init> : (Ljava/lang/String;)V
/*     */     //   791: aload_0
/*     */     //   792: getfield a : Lorg/a/c/f/k;
/*     */     //   795: invokeinterface b : ()J
/*     */     //   800: invokevirtual append : (J)Ljava/lang/StringBuilder;
/*     */     //   803: pop
/*     */     //   804: aload_3
/*     */     //   805: aload #5
/*     */     //   807: invokevirtual b : ()[B
/*     */     //   810: invokevirtual a : ([B)V
/*     */     //   813: goto -> 1076
/*     */     //   816: new java/lang/StringBuilder
/*     */     //   819: dup
/*     */     //   820: invokespecial <init> : ()V
/*     */     //   823: aload_0
/*     */     //   824: getfield a : Lorg/a/c/f/k;
/*     */     //   827: invokeinterface a : ()I
/*     */     //   832: i2c
/*     */     //   833: invokevirtual append : (C)Ljava/lang/StringBuilder;
/*     */     //   836: aload_0
/*     */     //   837: getfield a : Lorg/a/c/f/k;
/*     */     //   840: invokeinterface a : ()I
/*     */     //   845: i2c
/*     */     //   846: invokevirtual append : (C)Ljava/lang/StringBuilder;
/*     */     //   849: invokevirtual toString : ()Ljava/lang/String;
/*     */     //   852: dup
/*     */     //   853: astore_2
/*     */     //   854: ldc 'ID'
/*     */     //   856: invokevirtual equals : (Ljava/lang/Object;)Z
/*     */     //   859: ifne -> 903
/*     */     //   862: new java/io/IOException
/*     */     //   865: dup
/*     */     //   866: new java/lang/StringBuilder
/*     */     //   869: dup
/*     */     //   870: ldc 'Error: Expected operator 'ID' actual=''
/*     */     //   872: invokespecial <init> : (Ljava/lang/String;)V
/*     */     //   875: aload_2
/*     */     //   876: invokevirtual append : (Ljava/lang/String;)Ljava/lang/StringBuilder;
/*     */     //   879: ldc '' at stream offset '
/*     */     //   881: invokevirtual append : (Ljava/lang/String;)Ljava/lang/StringBuilder;
/*     */     //   884: aload_0
/*     */     //   885: getfield a : Lorg/a/c/f/k;
/*     */     //   888: invokeinterface b : ()J
/*     */     //   893: invokevirtual append : (J)Ljava/lang/StringBuilder;
/*     */     //   896: invokevirtual toString : ()Ljava/lang/String;
/*     */     //   899: invokespecial <init> : (Ljava/lang/String;)V
/*     */     //   902: athrow
/*     */     //   903: new java/io/ByteArrayOutputStream
/*     */     //   906: dup
/*     */     //   907: invokespecial <init> : ()V
/*     */     //   910: astore_3
/*     */     //   911: aload_0
/*     */     //   912: invokevirtual i : ()Z
/*     */     //   915: ifeq -> 928
/*     */     //   918: aload_0
/*     */     //   919: getfield a : Lorg/a/c/f/k;
/*     */     //   922: invokeinterface a : ()I
/*     */     //   927: pop
/*     */     //   928: aload_0
/*     */     //   929: getfield a : Lorg/a/c/f/k;
/*     */     //   932: invokeinterface a : ()I
/*     */     //   937: istore_2
/*     */     //   938: aload_0
/*     */     //   939: getfield a : Lorg/a/c/f/k;
/*     */     //   942: invokeinterface a : ()I
/*     */     //   947: istore #4
/*     */     //   949: iload_2
/*     */     //   950: bipush #69
/*     */     //   952: if_icmpne -> 980
/*     */     //   955: iload #4
/*     */     //   957: bipush #73
/*     */     //   959: if_icmpne -> 980
/*     */     //   962: aload_0
/*     */     //   963: invokespecial t : ()Z
/*     */     //   966: ifeq -> 980
/*     */     //   969: aload_0
/*     */     //   970: dup
/*     */     //   971: getfield a : Lorg/a/c/f/k;
/*     */     //   974: invokespecial a : (Lorg/a/c/f/k;)Z
/*     */     //   977: ifne -> 1014
/*     */     //   980: aload_0
/*     */     //   981: getfield a : Lorg/a/c/f/k;
/*     */     //   984: invokeinterface d : ()Z
/*     */     //   989: ifne -> 1014
/*     */     //   992: aload_3
/*     */     //   993: iload_2
/*     */     //   994: invokevirtual write : (I)V
/*     */     //   997: iload #4
/*     */     //   999: istore_2
/*     */     //   1000: aload_0
/*     */     //   1001: getfield a : Lorg/a/c/f/k;
/*     */     //   1004: invokeinterface a : ()I
/*     */     //   1009: istore #4
/*     */     //   1011: goto -> 949
/*     */     //   1014: ldc 'ID'
/*     */     //   1016: invokestatic a : (Ljava/lang/String;)Lorg/a/c/a/a/a;
/*     */     //   1019: dup
/*     */     //   1020: astore_1
/*     */     //   1021: checkcast org/a/c/a/a/a
/*     */     //   1024: aload_3
/*     */     //   1025: invokevirtual toByteArray : ()[B
/*     */     //   1028: invokevirtual a : ([B)V
/*     */     //   1031: goto -> 1076
/*     */     //   1034: aload_0
/*     */     //   1035: getfield a : Lorg/a/c/f/k;
/*     */     //   1038: invokeinterface a : ()I
/*     */     //   1043: pop
/*     */     //   1044: getstatic org/a/c/b/k.a : Lorg/a/c/b/k;
/*     */     //   1047: astore_1
/*     */     //   1048: goto -> 1076
/*     */     //   1051: aload_0
/*     */     //   1052: invokevirtual s : ()Ljava/lang/String;
/*     */     //   1055: dup
/*     */     //   1056: astore_2
/*     */     //   1057: invokevirtual trim : ()Ljava/lang/String;
/*     */     //   1060: invokevirtual length : ()I
/*     */     //   1063: ifne -> 1071
/*     */     //   1066: aconst_null
/*     */     //   1067: astore_1
/*     */     //   1068: goto -> 1076
/*     */     //   1071: aload_2
/*     */     //   1072: invokestatic a : (Ljava/lang/String;)Lorg/a/c/a/a/a;
/*     */     //   1075: astore_1
/*     */     //   1076: aload_1
/*     */     //   1077: areturn
/*     */     // Line number table:
/*     */     //   Java source line number -> byte code offset
/*     */     //   #142	-> 0
/*     */     //   #143	-> 4
/*     */     //   #144	-> 14
/*     */     //   #146	-> 20
/*     */     //   #148	-> 22
/*     */     //   #149	-> 25
/*     */     //   #154	-> 348
/*     */     //   #157	-> 358
/*     */     //   #160	-> 369
/*     */     //   #162	-> 379
/*     */     //   #164	-> 385
/*     */     //   #168	-> 393
/*     */     //   #170	-> 398
/*     */     //   #175	-> 401
/*     */     //   #176	-> 406
/*     */     //   #180	-> 409
/*     */     //   #181	-> 414
/*     */     //   #184	-> 417
/*     */     //   #185	-> 422
/*     */     //   #189	-> 425
/*     */     //   #190	-> 430
/*     */     //   #192	-> 439
/*     */     //   #196	-> 446
/*     */     //   #198	-> 451
/*     */     //   #203	-> 454
/*     */     //   #204	-> 459
/*     */     //   #206	-> 468
/*     */     //   #207	-> 472
/*     */     //   #209	-> 475
/*     */     //   #211	-> 484
/*     */     //   #215	-> 491
/*     */     //   #217	-> 496
/*     */     //   #221	-> 499
/*     */     //   #222	-> 504
/*     */     //   #224	-> 513
/*     */     //   #228	-> 525
/*     */     //   #230	-> 530
/*     */     //   #248	-> 533
/*     */     //   #249	-> 541
/*     */     //   #250	-> 547
/*     */     //   #253	-> 557
/*     */     //   #255	-> 576
/*     */     //   #258	-> 586
/*     */     //   #259	-> 598
/*     */     //   #261	-> 632
/*     */     //   #264	-> 638
/*     */     //   #266	-> 644
/*     */     //   #268	-> 654
/*     */     //   #270	-> 664
/*     */     //   #273	-> 667
/*     */     //   #274	-> 675
/*     */     //   #278	-> 678
/*     */     //   #279	-> 683
/*     */     //   #280	-> 688
/*     */     //   #282	-> 697
/*     */     //   #283	-> 702
/*     */     //   #284	-> 710
/*     */     //   #286	-> 715
/*     */     //   #288	-> 728
/*     */     //   #289	-> 734
/*     */     //   #290	-> 748
/*     */     //   #292	-> 751
/*     */     //   #294	-> 759
/*     */     //   #295	-> 765
/*     */     //   #297	-> 782
/*     */     //   #299	-> 804
/*     */     //   #301	-> 813
/*     */     //   #307	-> 816
/*     */     //   #308	-> 853
/*     */     //   #310	-> 862
/*     */     //   #311	-> 888
/*     */     //   #313	-> 903
/*     */     //   #314	-> 911
/*     */     //   #317	-> 918
/*     */     //   #319	-> 928
/*     */     //   #320	-> 938
/*     */     //   #325	-> 949
/*     */     //   #327	-> 963
/*     */     //   #328	-> 974
/*     */     //   #329	-> 984
/*     */     //   #331	-> 992
/*     */     //   #332	-> 997
/*     */     //   #333	-> 1000
/*     */     //   #336	-> 1014
/*     */     //   #338	-> 1020
/*     */     //   #339	-> 1031
/*     */     //   #345	-> 1034
/*     */     //   #348	-> 1044
/*     */     //   #349	-> 1048
/*     */     //   #354	-> 1051
/*     */     //   #355	-> 1056
/*     */     //   #358	-> 1066
/*     */     //   #362	-> 1071
/*     */     //   #366	-> 1076
/*     */   }
/*     */ 
/*     */ 
/*     */ 
/*     */ 
/*     */ 
/*     */ 
/*     */ 
/*     */ 
/*     */ 
/*     */ 
/*     */ 
/*     */ 
/*     */ 
/*     */ 
/*     */ 
/*     */ 
/*     */ 
/*     */ 
/*     */ 
/*     */ 
/*     */ 
/*     */ 
/*     */ 
/*     */ 
/*     */ 
/*     */ 
/*     */ 
/*     */ 
/*     */ 
/*     */ 
/*     */ 
/*     */ 
/*     */ 
/*     */ 
/*     */ 
/*     */ 
/*     */ 
/*     */ 
/*     */ 
/*     */ 
/*     */ 
/*     */ 
/*     */ 
/*     */ 
/*     */ 
/*     */ 
/*     */ 
/*     */ 
/*     */ 
/*     */ 
/*     */ 
/*     */ 
/*     */ 
/*     */ 
/*     */ 
/*     */ 
/*     */ 
/*     */ 
/*     */ 
/*     */ 
/*     */ 
/*     */ 
/*     */ 
/*     */ 
/*     */ 
/*     */ 
/*     */ 
/*     */ 
/*     */ 
/*     */ 
/*     */ 
/*     */ 
/*     */ 
/*     */ 
/*     */ 
/*     */ 
/*     */ 
/*     */ 
/*     */ 
/*     */ 
/*     */ 
/*     */ 
/*     */ 
/*     */ 
/*     */ 
/*     */ 
/*     */ 
/*     */ 
/*     */ 
/*     */ 
/*     */ 
/*     */ 
/*     */ 
/*     */ 
/*     */ 
/*     */ 
/*     */ 
/*     */ 
/*     */ 
/*     */ 
/*     */ 
/*     */ 
/*     */ 
/*     */ 
/*     */ 
/*     */ 
/*     */ 
/*     */ 
/*     */ 
/*     */ 
/*     */ 
/*     */ 
/*     */ 
/*     */ 
/*     */ 
/*     */ 
/*     */ 
/*     */ 
/*     */ 
/*     */ 
/*     */ 
/*     */ 
/*     */   
/*     */   private boolean a(k paramk) {
/* 380 */     int i = paramk.a(this.e, 0, 10);
/* 381 */     boolean bool = true;
/* 382 */     byte b1 = -1;
/* 383 */     byte b2 = -1;
/*     */     
/* 385 */     if (i > 0) {
/*     */       
/* 387 */       for (byte b = 0; b < i; b++) {
/*     */         byte b3;
/*     */         
/* 390 */         if (((b3 = this.e[b]) != 0 && b3 < 9) || (b3 > 10 && b3 < 32 && b3 != 13)) {
/*     */ 
/*     */           
/* 393 */           bool = false;
/*     */           
/*     */           break;
/*     */         } 
/* 397 */         if (b1 == -1 && b3 != 0 && b3 != 9 && b3 != 32 && b3 != 10 && b3 != 13) {
/*     */           
/* 399 */           b1 = b;
/*     */         }
/* 401 */         else if (b1 != -1 && b2 == -1 && (b3 == 0 || b3 == 9 || b3 == 32 || b3 == 10 || b3 == 13)) {
/*     */ 
/*     */           
/* 404 */           b2 = b;
/*     */         } 
/*     */       } 
/*     */ 
/*     */       
/* 409 */       if (b2 != -1 && b1 != -1) {
/*     */ 
/*     */         
/* 412 */         String str = new String(this.e, b1, b2 - b1);
/* 413 */         if (!"Q".equals(str) && !"EMC".equals(str) && !"S".equals(str))
/*     */         {
/* 415 */           bool = false;
/*     */         }
/*     */       } 
/*     */ 
/*     */       
/* 420 */       if (i == 10) {
/*     */ 
/*     */         
/* 423 */         if (b1 != -1 && b2 == -1)
/*     */         {
/* 425 */           b2 = 10;
/*     */         }
/* 427 */         if (b2 != -1 && b1 != -1 && b2 - b1 > 3)
/*     */         {
/* 429 */           bool = false;
/*     */         }
/*     */       } 
/* 432 */       paramk.b(this.e, 0, i);
/*     */     } 
/* 434 */     if (!bool)
/*     */     {
/* 436 */       (new StringBuilder("ignoring 'EI' assumed to be in the middle of inline image at stream offset "))
/* 437 */         .append(paramk.b());
/*     */     }
/* 439 */     return bool;
/*     */   }
/*     */ 
/*     */ 
/*     */ 
/*     */ 
/*     */ 
/*     */ 
/*     */ 
/*     */ 
/*     */   
/*     */   private String s() {
/* 451 */     l();
/*     */ 
/*     */ 
/*     */     
/* 455 */     StringBuilder stringBuilder = new StringBuilder(4);
/* 456 */     int i = this.a.c();
/* 457 */     while (i != -1 && 
/*     */       
/* 459 */       !c(i) && 
/* 460 */       !b(i) && i != 91 && i != 60 && i != 40 && i != 47 && (i < 48 || i > 57)) {
/*     */ 
/*     */ 
/*     */ 
/*     */ 
/*     */ 
/*     */ 
/*     */       
/* 468 */       char c = (char)this.a.a();
/* 469 */       i = this.a.c();
/* 470 */       stringBuilder.append(c);
/*     */       
/* 472 */       if (c == 'd' && (i == 48 || i == 49)) {
/*     */         
/* 474 */         stringBuilder.append((char)this.a.a());
/* 475 */         i = this.a.c();
/*     */       } 
/*     */     } 
/* 478 */     return stringBuilder.toString();
/*     */   }
/*     */ 
/*     */ 
/*     */   
/*     */   private static boolean e(int paramInt) {
/* 484 */     return (paramInt == 10 || paramInt == 13 || paramInt == 32);
/*     */   }
/*     */ 
/*     */ 
/*     */ 
/*     */ 
/*     */ 
/*     */ 
/*     */ 
/*     */   
/*     */   private boolean t() {
/* 495 */     return e(this.a.c());
/*     */   }
/*     */ }


/* Location:              C:\Program Files (x86)\Steam\steamapps\common\Infinitode 2\infinitode-2.jar!\org\a\c\f\g.class
 * Java compiler version: 6 (50.0)
 * JD-Core Version:       1.1.3
 */