/*      */ package com.d.c.d;
/*      */ 
/*      */ import java.io.Reader;
/*      */ 
/*      */ 
/*      */ 
/*      */ 
/*      */ 
/*      */ 
/*      */ 
/*      */ 
/*      */ 
/*      */ 
/*      */ 
/*      */ 
/*      */ 
/*      */ 
/*      */ 
/*      */ 
/*      */ 
/*      */ 
/*      */ 
/*      */ 
/*      */ 
/*      */ 
/*      */ 
/*      */ 
/*      */ 
/*      */ 
/*      */ 
/*      */ 
/*      */ 
/*      */ 
/*      */ 
/*      */ 
/*      */ 
/*      */ 
/*      */ 
/*      */ 
/*      */ 
/*      */ 
/*      */ 
/*      */ 
/*      */ 
/*      */ 
/*      */ 
/*      */ 
/*      */ 
/*      */ 
/*      */ 
/*      */ 
/*      */ 
/*      */ 
/*      */ 
/*      */ 
/*      */ 
/*      */ 
/*      */ 
/*      */ final class i
/*      */ {
/*   61 */   private static final char[] a = a("\t\002\001\006\001\005\001\002\001\007\001\004\022\002\0018\001+\001\n\0015\0011\0019\001\017\001\013\001<\001=\001\r\0013\0014\001\t\001\016\001\f\001\021\001\023\001\001\001\026\001\022\001\031\001\024\001\033\001\035\001\037\001@\001?\001*\001.\001,\001\017\0016\001\020\001!\001\025\001\027\001\030\001\b\001\032\001\034\001\036\001\000\001 \001;\001\"\001#\0017\001$\001\000\001%\001&\001'\001:\002\000\001(\001\000\001)\001A\001\003\001B\0010\001\000\001\017\001\020\001!\001\025\001\027\001\030\001\b\001\032\001\034\001\036\001\000\001 \001;\001\"\001#\0017\001$\001\000\001%\001&\001'\001:\002\000\001(\001\000\001)\0012\001/\001>\001-\001\002ﾀ\000");
/*      */ 
/*      */ 
/*      */ 
/*      */   
/*   66 */   private static final int[] b = e();
/*      */ 
/*      */ 
/*      */ 
/*      */ 
/*      */ 
/*      */ 
/*      */ 
/*      */ 
/*      */ 
/*      */ 
/*      */ 
/*      */ 
/*      */ 
/*      */ 
/*      */ 
/*      */ 
/*      */ 
/*      */ 
/*      */ 
/*      */ 
/*      */ 
/*      */ 
/*      */ 
/*      */ 
/*      */ 
/*      */ 
/*      */ 
/*      */ 
/*      */ 
/*      */ 
/*      */ 
/*      */ 
/*      */ 
/*      */   
/*      */   private static int[] e() {
/*  102 */     int[] arrayOfInt = new int[518];
/*      */     
/*  104 */     a("\001\000\001\001\001\002\002\003\001\004\001\005\002\006\001\007\001\b\001\t\002\003\001\n\001\003\001\013\001\f\002\003\001\r\001\016\001\017\002\003\001\001\001\020\001\021\001\022\001\023\001\024\001\025\001\000\001\026\001\027\003\000\n\027\001\030\001\031\001\001\002\000\001\032\002\000\001\033\001\002\004\000\001\034\001\035\001\036\001\037\001 \001\000\001!\001\000\001!\001\000\005!\001\001\001\000\004\027\001\000\001\"\001\000\001\027\001\000\001#\001$\002\000\001%\001\000\001&\002\000\001'\001\000\001(\001)\001*\001\000\001\027\002\001\001+\004\006\004\000\001 \007!\001\001\017\027\001\030\004\027\001\000\001,\023\027\001\000\001\001\002\006\001-\001.\002\000\002 \b!\001\026\016\027\001\030\f\027\001(\001\030\002\027\001\"\b\027\001#\001$\004\027\001%\002\027\001&\005\027\001'\003\027\001(\001)\001*\005\027\001\001\002\006\001\000\001 \006!\001/\005\000\0010\016\027\001\030\002\027\001(\001,\002\027\002\"\006\027\001,\003\027\001#\001$\001#\001$\004\027\002%\002\027\002&\005\027\002'\003\027\001(\001)\001*\001(\001)\001*\004\027\001,\002\027\001\001\002\006\001\000\001 \004!\0011\001!\002\000\0010\002\000\r\027\001\030\002\027\001(\001,\002\027\001\"\005\027\002,\003\027\001#\001$\004\027\001%\002\027\001&\005\027\001'\003\027\001(\001)\001*\005\027\001\001\002\006\001\000\001 \003!\0012\001!\006\000\013\027\001\030\002\027\001(\001,\001\027\001\"\004\027\001,\002\027\001#\001$\002\027\001%\001\027\001&\003\027\001'\002\027\001(\001)\001*\004\027\002\006\001\000\001 \004!\003\000\001\"\002\027\001,\001#\001$\001%\001&\001'\001(\001)\001*\002\027\001\000\001!\0013\001!\003\000\001,\0014\0015\0016\b\000", 0, arrayOfInt);
/*  105 */     return arrayOfInt;
/*      */   }
/*      */   
/*      */   private static int a(String paramString, int paramInt, int[] paramArrayOfint) {
/*  109 */     paramInt = 0;
/*  110 */     byte b = 0;
/*  111 */     int j = paramString.length();
/*  112 */     label10: while (paramInt < j) {
/*  113 */       char c1 = paramString.charAt(paramInt++);
/*  114 */       char c2 = paramString.charAt(paramInt++); while (true)
/*  115 */       { paramArrayOfint[b++] = c2; if (--c1 <= '\000')
/*      */           continue label10;  } 
/*  117 */     }  return b;
/*      */   }
/*      */ 
/*      */ 
/*      */ 
/*      */ 
/*      */   
/*  124 */   private static final int[] c = f();
/*      */ 
/*      */ 
/*      */ 
/*      */ 
/*      */ 
/*      */ 
/*      */ 
/*      */ 
/*      */ 
/*      */ 
/*      */ 
/*      */ 
/*      */ 
/*      */ 
/*      */ 
/*      */ 
/*      */ 
/*      */ 
/*      */ 
/*      */ 
/*      */ 
/*      */ 
/*      */ 
/*      */ 
/*      */ 
/*      */ 
/*      */ 
/*      */ 
/*      */ 
/*      */ 
/*      */ 
/*      */ 
/*      */ 
/*      */ 
/*      */ 
/*      */ 
/*      */ 
/*      */ 
/*      */ 
/*      */ 
/*      */ 
/*      */ 
/*      */ 
/*      */ 
/*      */ 
/*      */ 
/*      */ 
/*      */ 
/*      */ 
/*      */ 
/*      */ 
/*      */ 
/*      */ 
/*      */ 
/*      */ 
/*      */ 
/*      */ 
/*      */ 
/*      */ 
/*      */ 
/*      */ 
/*      */ 
/*      */ 
/*      */ 
/*      */ 
/*      */ 
/*      */ 
/*      */   
/*      */   private static int[] f() {
/*  194 */     int[] arrayOfInt = new int[518];
/*      */     
/*  196 */     b("\000\000\000C\000\000É\000Č\000ŏ\000ƒ\000Ǖ\000Ș\000ɛ\000ʞ\000ˡ\000̤\000ͧ\000É\000Ϊ\000É\000ϭ\000а\000ѳ\000É\000É\000É\000Ҷ\000ӹ\000Լ\000É\000É\000É\000É\000É\000É\000Č\000É\000տ\000ׂ\000؅\000ˡ\000و\000ڋ\000ێ\000ܑ\000ݔ\000ޗ\000ߚ\000ࠝ\000ࡠ\000ࢣ\000տ\000É\000ࣦ\000ऩ\000६\000É\000য\000৲\000É\000ਵ\000੸\000ͧ\000઻\000૾\000É\000É\000É\000É\000Ҷ\000ୁ\000஄\000ே\000ఊ\000్\000ಐ\000೓\000ഖ\000൙\000ග\000ෟ\000ย\000๥\000ຨ\000໫\000༮\000ཱ\000տ\000ྴ\000࿷\000်\000տ\000տ\000ၽ\000Ⴠ\000տ\000ᄃ\000տ\000ᅆ\000ᆉ\000տ\000ᇌ\000տ\000տ\000տ\000ሏ\000ቒ\000ን\000ዘ\000É\000ጛ\000፞\000Ꭱ\000Ꮴ\000ᐧ\000ᑪ\000ᒭ\000ᓰ\000ᔳ\000ᕶ\000ᖹ\000ᗼ\000ᘿ\000ᚂ\000ᛅ\000ᜈ\000ᝋ\000ណ\000៑\000᠔\000ᡗ\000ᢚ\000ᣝ\000ᤠ\000ᥣ\000ᦦ\000᧩\000ᨬ\000ᩯ\000᪲\000᫵\000ᬸ\000᭻\000ᮾ\000ᰁ\000᱄\000ᲇ\000᳊\000տ\000ᴍ\000ᵐ\000ᶓ\000ᷖ\000ḙ\000Ṝ\000ẟ\000Ợ\000ἥ\000Ὠ\000ᾫ\000΅\000‱\000⁴\000₷\000⃺\000ℽ\000ↀ\000⇃\000∆\000≉\000⊌\000⋏\000É\000É\000⌒\000⍕\000⎘\000⏛\000␞\000②\000⒤\000ⓧ\000┪\000╭\000▰\000◳\000☶\000♹\000⚼\000⛿\000❂\000➅\000⟈\000⠋\000⡎\000⢑\000⣔\000⤗\000⥚\000⦝\000⧠\000⨣\000⩦\000⪩\000⫬\000⬯\000⭲\000⮵\000⯸\000ⰻ\000Ȿ\000ⳁ\000ⴄ\000ⵇ\000♹\000ⶊ\000ⷍ\000⸐\000⹓\000⺖\000⻙\000⼜\000⽟\000⾢\000⿥\000〨\000に\000ギ\000ヱ\000ㄴ\000ㅷ\000ㆺ\000ㇽ\000㉀\000㊃\000㋆\000㌉\000㍌\000㎏\000㏒\000㐕\000㑘\000㒛\000㓞\000㔡\000㕤\000㖧\000㗪\000㘭\000㙰\000㚳\000㛶\000㜹\000㝼\000㞿\000㠂\000㡅\000㢈\000㣋\000㤎\000㥑\000㦔\000㧗\000㨚\000㩝\000஄\000㪠\000㫣\000☶\000㬦\000㭩\000É\000㮬\000㯯\000㰲\000㱵\000㲸\000㳻\000㴾\000㶁\000㷄\000㸇\000㹊\000㺍\000㻐\000㼓\000㽖\000㾙\000㿜\000㮬\000㮬\000䀟\000䁢\000䂥\000䃨\000䄫\000䅮\000䆱\000䇴\000䈷\000䉺\000䊽\000䌀\000䍃\000䎆\000䏉\000䐌\000䑏\000䒒\000䓕\000䔘\000䕛\000䖞\000䗡\000䘤\000䙧\000䚪\000䛭\000䜰\000䝳\000䞶\000䟹\000䠼\000䡿\000䣂\000䤅\000䥈\000䦋\000䧎\000䨑\000䩔\000䪗\000䫚\000䬝\000䭠\000䮣\000䯦\000䰩\000䱬\000♹\000䲯\000䳲\000䴵\000䵸\000䶻\000䷾\000乁\000亄\000仇\000伊\000位\000஄\000侐\000俓\000倖\000㪠\000偙\000傜\000僟\000儢\000入\000冨\000凫\000刮\000剱\000労\000勷\000区\000卽\000叀\000吃\000呆\000咉\000哌\000僟\000僟\000唏\000啒\000喕\000嗘\000嘛\000噞\000嚡\000囤\000圧\000坪\000垭\000埰\000堳\000塶\000墹\000壼\000夿\000如\000姅\000娈\000婋\000媎\000嫑\000嬔\000字\000定\000寝\000尠\000屣\000岦\000峩\000崬\000嵯\000嶲\000巵\000常\000幻\000庾\000弁\000彄\000徇\000忊\000怍\000恐\000悓\000惖\000愙\000慜\000஄\000憟\000懢\000戥\000扨\000披\000拮\000挱\000捴\000掷\000揺\000搽\000撀\000擃\000攆\000敉\000斌\000族\000昒\000晕\000暘\000曛\000捴\000捴\000朞\000条\000枤\000柧\000株\000桭\000械\000棳\000椶\000楹\000榼\000槿\000橂\000檅\000櫈\000欋\000歎\000殑\000比\000気\000汚\000沝\000泠\000洣\000浦\000涩\000淬\000港\000湲\000溵\000滸\000漻\000潾\000濁\000瀄\000灇\000炊\000烍\000焐\000煓\000熖\000燙\000爜\000牟\000犢\000狥\000猨\000獫\000玮\000珱\000琴\000瑷\000璺\000瓽\000畀\000疃\000É\000痆\000瘉\000癌\000皏\000盒\000É\000஄\000஄\000眕\000睘\000瞛\000矞\000砡\000硤\000碧\000磪", 0, arrayOfInt);
/*  197 */     return arrayOfInt;
/*      */   }
/*      */   
/*      */   private static int b(String paramString, int paramInt, int[] paramArrayOfint) {
/*  201 */     paramInt = 0;
/*  202 */     byte b = 0;
/*  203 */     int j = paramString.length();
/*  204 */     while (paramInt < j) {
/*  205 */       int k = paramString.charAt(paramInt++) << 16;
/*  206 */       paramArrayOfint[b++] = k | paramString.charAt(paramInt++);
/*      */     } 
/*  208 */     return b;
/*      */   }
/*      */ 
/*      */ 
/*      */ 
/*      */   
/*  214 */   private static final int[] d = g();
/*      */ 
/*      */ 
/*      */ 
/*      */ 
/*      */ 
/*      */ 
/*      */ 
/*      */ 
/*      */ 
/*      */ 
/*      */ 
/*      */ 
/*      */ 
/*      */ 
/*      */ 
/*      */ 
/*      */ 
/*      */ 
/*      */ 
/*      */ 
/*      */ 
/*      */ 
/*      */ 
/*      */ 
/*      */ 
/*      */ 
/*      */ 
/*      */ 
/*      */ 
/*      */ 
/*      */ 
/*      */ 
/*      */ 
/*      */ 
/*      */ 
/*      */ 
/*      */ 
/*      */ 
/*      */ 
/*      */ 
/*      */ 
/*      */ 
/*      */ 
/*      */ 
/*      */ 
/*      */ 
/*      */ 
/*      */ 
/*      */ 
/*      */ 
/*      */ 
/*      */ 
/*      */ 
/*      */ 
/*      */ 
/*      */ 
/*      */ 
/*      */ 
/*      */ 
/*      */ 
/*      */ 
/*      */ 
/*      */ 
/*      */ 
/*      */ 
/*      */ 
/*      */ 
/*      */ 
/*      */ 
/*      */ 
/*      */ 
/*      */ 
/*      */ 
/*      */ 
/*      */ 
/*      */ 
/*      */ 
/*      */ 
/*      */ 
/*      */ 
/*      */ 
/*      */ 
/*      */ 
/*      */ 
/*      */ 
/*      */ 
/*      */ 
/*      */ 
/*      */ 
/*      */ 
/*      */ 
/*      */ 
/*      */ 
/*      */ 
/*      */ 
/*      */ 
/*      */ 
/*      */ 
/*      */ 
/*      */ 
/*      */ 
/*      */ 
/*      */ 
/*      */ 
/*      */ 
/*      */ 
/*      */ 
/*      */ 
/*      */ 
/*      */ 
/*      */ 
/*      */ 
/*      */ 
/*      */ 
/*      */ 
/*      */ 
/*      */ 
/*      */ 
/*      */ 
/*      */ 
/*      */ 
/*      */ 
/*      */ 
/*      */ 
/*      */ 
/*      */ 
/*      */ 
/*      */ 
/*      */ 
/*      */ 
/*      */ 
/*      */ 
/*      */ 
/*      */ 
/*      */ 
/*      */ 
/*      */ 
/*      */ 
/*      */ 
/*      */ 
/*      */ 
/*      */ 
/*      */ 
/*      */ 
/*      */ 
/*      */ 
/*      */ 
/*      */ 
/*      */ 
/*      */ 
/*      */ 
/*      */ 
/*      */ 
/*      */ 
/*      */ 
/*      */ 
/*      */ 
/*      */ 
/*      */ 
/*      */ 
/*      */ 
/*      */ 
/*      */ 
/*      */ 
/*      */ 
/*      */ 
/*      */ 
/*      */ 
/*      */ 
/*      */ 
/*      */ 
/*      */ 
/*      */ 
/*      */ 
/*      */ 
/*      */ 
/*      */ 
/*      */ 
/*      */ 
/*      */ 
/*      */ 
/*      */ 
/*      */ 
/*      */ 
/*      */ 
/*      */ 
/*      */ 
/*      */ 
/*      */ 
/*      */ 
/*      */ 
/*      */ 
/*      */ 
/*      */ 
/*      */ 
/*      */ 
/*      */ 
/*      */ 
/*      */ 
/*      */ 
/*      */ 
/*      */ 
/*      */ 
/*      */ 
/*      */ 
/*      */ 
/*      */ 
/*      */ 
/*      */ 
/*      */ 
/*      */ 
/*      */ 
/*      */ 
/*      */ 
/*      */ 
/*      */ 
/*      */ 
/*      */ 
/*      */ 
/*      */ 
/*      */ 
/*      */ 
/*      */ 
/*      */ 
/*      */ 
/*      */ 
/*      */ 
/*      */ 
/*      */ 
/*      */ 
/*      */ 
/*      */ 
/*      */ 
/*      */ 
/*      */ 
/*      */ 
/*      */ 
/*      */ 
/*      */ 
/*      */ 
/*      */ 
/*      */ 
/*      */ 
/*      */ 
/*      */ 
/*      */ 
/*      */ 
/*      */ 
/*      */ 
/*      */ 
/*      */ 
/*      */ 
/*      */ 
/*      */ 
/*      */ 
/*      */ 
/*      */ 
/*      */ 
/*      */ 
/*      */ 
/*      */ 
/*      */ 
/*      */ 
/*      */ 
/*      */ 
/*      */ 
/*      */ 
/*      */ 
/*      */ 
/*      */ 
/*      */ 
/*      */ 
/*      */ 
/*      */ 
/*      */ 
/*      */ 
/*      */ 
/*      */ 
/*      */ 
/*      */ 
/*      */ 
/*      */ 
/*      */ 
/*      */ 
/*      */ 
/*      */ 
/*      */ 
/*      */ 
/*      */ 
/*      */ 
/*      */ 
/*      */ 
/*      */ 
/*      */ 
/*      */ 
/*      */ 
/*      */ 
/*      */ 
/*      */ 
/*      */ 
/*      */ 
/*      */ 
/*      */ 
/*      */ 
/*      */ 
/*      */ 
/*      */ 
/*      */ 
/*      */ 
/*      */ 
/*      */ 
/*      */ 
/*      */ 
/*      */ 
/*      */ 
/*      */ 
/*      */ 
/*      */ 
/*      */ 
/*      */ 
/*      */ 
/*      */ 
/*      */ 
/*      */ 
/*      */ 
/*      */ 
/*      */ 
/*      */ 
/*      */ 
/*      */ 
/*      */ 
/*      */ 
/*      */ 
/*      */ 
/*      */ 
/*      */ 
/*      */ 
/*      */ 
/*      */ 
/*      */ 
/*      */ 
/*      */ 
/*      */ 
/*      */ 
/*      */ 
/*      */ 
/*      */ 
/*      */ 
/*      */ 
/*      */ 
/*      */ 
/*      */ 
/*      */ 
/*      */ 
/*      */ 
/*      */ 
/*      */ 
/*      */ 
/*      */ 
/*      */ 
/*      */ 
/*      */ 
/*      */ 
/*      */ 
/*      */ 
/*      */ 
/*      */ 
/*      */ 
/*      */ 
/*      */ 
/*      */ 
/*      */ 
/*      */ 
/*      */ 
/*      */ 
/*      */ 
/*      */ 
/*      */ 
/*      */ 
/*      */ 
/*      */ 
/*      */ 
/*      */ 
/*      */ 
/*      */ 
/*      */ 
/*      */ 
/*      */ 
/*      */ 
/*      */ 
/*      */ 
/*      */ 
/*      */ 
/*      */ 
/*      */ 
/*      */ 
/*      */ 
/*      */ 
/*      */ 
/*      */ 
/*      */ 
/*      */ 
/*      */ 
/*      */ 
/*      */ 
/*      */ 
/*      */ 
/*      */ 
/*      */ 
/*      */ 
/*      */ 
/*      */ 
/*      */ 
/*      */ 
/*      */ 
/*      */ 
/*      */ 
/*      */ 
/*      */ 
/*      */ 
/*      */ 
/*      */ 
/*      */ 
/*      */ 
/*      */ 
/*      */ 
/*      */ 
/*      */ 
/*      */ 
/*      */ 
/*      */ 
/*      */ 
/*      */ 
/*      */ 
/*      */ 
/*      */ 
/*      */ 
/*      */ 
/*      */ 
/*      */ 
/*      */ 
/*      */ 
/*      */ 
/*      */ 
/*      */ 
/*      */ 
/*      */ 
/*      */ 
/*      */ 
/*      */ 
/*      */ 
/*      */ 
/*      */ 
/*      */ 
/*      */ 
/*      */ 
/*      */ 
/*      */ 
/*      */ 
/*      */ 
/*      */ 
/*      */ 
/*      */ 
/*      */ 
/*      */ 
/*      */ 
/*      */ 
/*      */ 
/*      */ 
/*      */ 
/*      */ 
/*      */ 
/*      */ 
/*      */ 
/*      */ 
/*      */ 
/*      */ 
/*      */ 
/*      */ 
/*      */ 
/*      */ 
/*      */ 
/*      */ 
/*      */ 
/*      */ 
/*      */ 
/*      */ 
/*      */ 
/*      */ 
/*      */ 
/*      */ 
/*      */ 
/*      */ 
/*      */ 
/*      */ 
/*      */ 
/*      */ 
/*      */ 
/*      */ 
/*      */ 
/*      */ 
/*      */ 
/*      */ 
/*      */ 
/*      */ 
/*      */ 
/*      */ 
/*      */ 
/*      */ 
/*      */ 
/*      */ 
/*      */ 
/*      */ 
/*      */ 
/*      */ 
/*      */ 
/*      */ 
/*      */ 
/*      */ 
/*      */ 
/*      */ 
/*      */ 
/*      */ 
/*      */ 
/*      */ 
/*      */ 
/*      */ 
/*      */ 
/*      */ 
/*      */ 
/*      */ 
/*      */ 
/*      */ 
/*      */ 
/*      */ 
/*      */ 
/*      */ 
/*      */ 
/*      */ 
/*      */ 
/*      */ 
/*      */ 
/*      */ 
/*      */ 
/*      */ 
/*      */ 
/*      */ 
/*      */ 
/*      */ 
/*      */ 
/*      */ 
/*      */ 
/*      */ 
/*      */ 
/*      */ 
/*      */ 
/*      */ 
/*      */ 
/*      */ 
/*      */ 
/*      */ 
/*      */ 
/*      */ 
/*      */ 
/*      */ 
/*      */ 
/*      */ 
/*      */ 
/*      */ 
/*      */ 
/*      */ 
/*      */ 
/*      */ 
/*      */ 
/*      */ 
/*      */ 
/*      */ 
/*      */ 
/*      */ 
/*      */ 
/*      */ 
/*      */ 
/*      */ 
/*      */ 
/*      */ 
/*      */ 
/*      */ 
/*      */ 
/*      */ 
/*      */ 
/*      */ 
/*      */ 
/*      */ 
/*      */ 
/*      */ 
/*      */ 
/*      */ 
/*      */ 
/*      */ 
/*      */ 
/*      */ 
/*      */ 
/*      */ 
/*      */ 
/*      */ 
/*      */ 
/*      */ 
/*      */ 
/*      */ 
/*      */ 
/*      */ 
/*      */ 
/*      */ 
/*      */ 
/*      */ 
/*      */ 
/*      */ 
/*      */ 
/*      */ 
/*      */ 
/*      */ 
/*      */ 
/*      */ 
/*      */ 
/*      */ 
/*      */ 
/*      */ 
/*      */ 
/*      */ 
/*      */ 
/*      */ 
/*      */ 
/*      */ 
/*      */ 
/*      */ 
/*      */ 
/*      */ 
/*      */ 
/*      */ 
/*      */ 
/*      */ 
/*      */ 
/*      */ 
/*      */ 
/*      */ 
/*      */ 
/*      */ 
/*      */ 
/*      */ 
/*      */ 
/*      */ 
/*      */ 
/*      */ 
/*      */ 
/*      */ 
/*      */ 
/*      */ 
/*      */ 
/*      */ 
/*      */ 
/*      */ 
/*      */ 
/*      */ 
/*      */ 
/*      */ 
/*      */ 
/*      */ 
/*      */ 
/*      */ 
/*      */ 
/*      */ 
/*      */ 
/*      */ 
/*      */ 
/*      */ 
/*      */ 
/*      */ 
/*      */ 
/*      */ 
/*      */ 
/*      */ 
/*      */ 
/*      */ 
/*      */ 
/*      */ 
/*      */ 
/*      */ 
/*      */ 
/*      */ 
/*      */ 
/*      */ 
/*      */ 
/*      */ 
/*      */ 
/*      */ 
/*      */ 
/*      */ 
/*      */ 
/*      */ 
/*      */ 
/*      */ 
/*      */ 
/*      */ 
/*      */ 
/*      */ 
/*      */ 
/*      */ 
/*      */ 
/*      */ 
/*      */ 
/*      */ 
/*      */ 
/*      */ 
/*      */ 
/*      */ 
/*      */ 
/*      */ 
/*      */ 
/*      */ 
/*      */ 
/*      */ 
/*      */ 
/*      */ 
/*      */ 
/*      */ 
/*      */ 
/*      */ 
/*      */ 
/*      */ 
/*      */ 
/*      */ 
/*      */ 
/*      */ 
/*      */ 
/*      */ 
/*      */ 
/*      */ 
/*      */ 
/*      */ 
/*      */ 
/*      */ 
/*      */ 
/*      */ 
/*      */ 
/*      */ 
/*      */ 
/*      */ 
/*      */ 
/*      */ 
/*      */ 
/*      */ 
/*      */ 
/*      */ 
/*      */ 
/*      */ 
/*      */ 
/*      */ 
/*      */ 
/*      */ 
/*      */ 
/*      */ 
/*      */ 
/*      */ 
/*      */ 
/*      */ 
/*      */ 
/*      */ 
/*      */ 
/*      */ 
/*      */ 
/*      */ 
/*      */ 
/*      */ 
/*      */ 
/*      */ 
/*      */ 
/*      */ 
/*      */ 
/*      */ 
/*      */ 
/*      */ 
/*      */ 
/*      */ 
/*      */ 
/*      */ 
/*      */ 
/*      */ 
/*      */ 
/*      */ 
/*      */ 
/*      */ 
/*      */ 
/*      */ 
/*      */ 
/*      */ 
/*      */ 
/*      */ 
/*      */ 
/*      */ 
/*      */ 
/*      */ 
/*      */ 
/*      */ 
/*      */ 
/*      */ 
/*      */ 
/*      */ 
/*      */ 
/*      */ 
/*      */ 
/*      */ 
/*      */ 
/*      */ 
/*      */ 
/*      */ 
/*      */ 
/*      */ 
/*      */ 
/*      */ 
/*      */ 
/*      */ 
/*      */ 
/*      */ 
/*      */ 
/*      */ 
/*      */ 
/*      */ 
/*      */ 
/*      */ 
/*      */ 
/*      */ 
/*      */ 
/*      */ 
/*      */ 
/*      */ 
/*      */ 
/*      */ 
/*      */ 
/*      */ 
/*      */ 
/*      */ 
/*      */ 
/*      */ 
/*      */ 
/*      */ 
/*      */ 
/*      */ 
/*      */ 
/*      */ 
/*      */ 
/*      */ 
/*      */ 
/*      */ 
/*      */ 
/*      */ 
/*      */ 
/*      */ 
/*      */ 
/*      */ 
/*      */ 
/*      */ 
/*      */ 
/*      */ 
/*      */ 
/*      */ 
/*      */ 
/*      */ 
/*      */ 
/*      */ 
/*      */ 
/*      */ 
/*      */ 
/*      */ 
/*      */ 
/*      */ 
/*      */ 
/*      */ 
/*      */ 
/*      */ 
/*      */ 
/*      */ 
/*      */ 
/*      */ 
/*      */ 
/*      */ 
/*      */ 
/*      */ 
/*      */ 
/*      */ 
/*      */ 
/*      */ 
/*      */ 
/*      */ 
/*      */ 
/*      */ 
/*      */ 
/*      */ 
/*      */ 
/*      */ 
/*      */ 
/*      */ 
/*      */ 
/*      */ 
/*      */ 
/*      */ 
/*      */ 
/*      */ 
/*      */ 
/*      */ 
/*      */ 
/*      */ 
/*      */ 
/*      */ 
/*      */ 
/*      */ 
/*      */ 
/*      */ 
/*      */ 
/*      */ 
/*      */ 
/*      */ 
/*      */ 
/*      */ 
/*      */ 
/*      */ 
/*      */ 
/*      */ 
/*      */ 
/*      */ 
/*      */ 
/*      */ 
/*      */ 
/*      */ 
/*      */ 
/*      */ 
/*      */ 
/*      */ 
/*      */ 
/*      */ 
/*      */ 
/*      */ 
/*      */ 
/*      */ 
/*      */ 
/*      */ 
/*      */ 
/*      */ 
/*      */ 
/*      */ 
/*      */ 
/*      */ 
/*      */ 
/*      */ 
/*      */ 
/*      */ 
/*      */ 
/*      */ 
/*      */ 
/*      */ 
/*      */ 
/*      */ 
/*      */ 
/*      */ 
/*      */ 
/*      */ 
/*      */ 
/*      */ 
/*      */ 
/*      */ 
/*      */ 
/*      */ 
/*      */ 
/*      */ 
/*      */ 
/*      */ 
/*      */ 
/*      */ 
/*      */ 
/*      */ 
/*      */ 
/*      */ 
/*      */ 
/*      */ 
/*      */ 
/*      */ 
/*      */ 
/*      */ 
/*      */ 
/*      */ 
/*      */ 
/*      */ 
/*      */ 
/*      */ 
/*      */ 
/*      */ 
/*      */ 
/*      */ 
/*      */ 
/*      */ 
/*      */ 
/*      */ 
/*      */ 
/*      */ 
/*      */ 
/*      */ 
/*      */ 
/*      */ 
/*      */ 
/*      */ 
/*      */ 
/*      */ 
/*      */ 
/*      */ 
/*      */ 
/*      */ 
/*      */ 
/*      */ 
/*      */ 
/*      */ 
/*      */ 
/*      */ 
/*      */ 
/*      */ 
/*      */ 
/*      */ 
/*      */ 
/*      */ 
/*      */ 
/*      */ 
/*      */ 
/*      */ 
/*      */ 
/*      */ 
/*      */ 
/*      */ 
/*      */ 
/*      */ 
/*      */ 
/*      */ 
/*      */ 
/*      */ 
/*      */ 
/*      */ 
/*      */ 
/*      */ 
/*      */ 
/*      */ 
/*      */ 
/*      */ 
/*      */ 
/*      */ 
/*      */ 
/*      */ 
/*      */ 
/*      */ 
/*      */ 
/*      */ 
/*      */ 
/*      */ 
/*      */ 
/*      */ 
/*      */ 
/*      */ 
/*      */ 
/*      */ 
/*      */ 
/*      */ 
/*      */ 
/*      */ 
/*      */ 
/*      */ 
/*      */ 
/*      */ 
/*      */ 
/*      */ 
/*      */ 
/*      */ 
/*      */ 
/*      */ 
/*      */ 
/*      */ 
/*      */ 
/*      */ 
/*      */ 
/*      */ 
/*      */ 
/*      */ 
/*      */ 
/*      */ 
/*      */ 
/*      */ 
/*      */ 
/*      */ 
/*      */ 
/*      */ 
/*      */ 
/*      */ 
/*      */ 
/*      */ 
/*      */ 
/*      */ 
/*      */ 
/*      */ 
/*      */ 
/*      */ 
/*      */ 
/*      */ 
/*      */ 
/*      */ 
/*      */ 
/*      */ 
/*      */ 
/*      */ 
/*      */ 
/*      */ 
/*      */ 
/*      */ 
/*      */ 
/*      */ 
/*      */ 
/*      */ 
/*      */ 
/*      */ 
/*      */ 
/*      */ 
/*      */ 
/*      */ 
/*      */ 
/*      */ 
/*      */ 
/*      */ 
/*      */ 
/*      */ 
/*      */ 
/*      */ 
/*      */ 
/*      */ 
/*      */ 
/*      */ 
/*      */ 
/*      */ 
/*      */ 
/*      */ 
/*      */ 
/*      */ 
/*      */ 
/*      */ 
/*      */ 
/*      */ 
/*      */ 
/*      */ 
/*      */ 
/*      */ 
/*      */ 
/*      */ 
/*      */ 
/*      */ 
/*      */ 
/*      */ 
/*      */ 
/*      */ 
/*      */ 
/*      */ 
/*      */ 
/*      */ 
/*      */ 
/*      */ 
/*      */ 
/*      */ 
/*      */ 
/*      */ 
/*      */ 
/*      */ 
/*      */ 
/*      */ 
/*      */ 
/*      */ 
/*      */ 
/*      */ 
/*      */ 
/*      */ 
/*      */ 
/*      */ 
/*      */ 
/*      */ 
/*      */ 
/*      */ 
/*      */ 
/*      */ 
/*      */ 
/*      */ 
/*      */ 
/*      */ 
/*      */ 
/*      */ 
/*      */ 
/*      */ 
/*      */ 
/*      */ 
/*      */ 
/*      */ 
/*      */ 
/*      */ 
/*      */ 
/*      */ 
/*      */ 
/*      */ 
/*      */ 
/*      */ 
/*      */ 
/*      */ 
/*      */ 
/*      */ 
/*      */ 
/*      */ 
/*      */ 
/*      */ 
/*      */   
/*      */   private static int[] g() {
/* 1434 */     int[] arrayOfInt = new int[31021];
/*      */     
/* 1436 */     c("\001\002\001\003\001\004\001\005\004\006\001\002\001\007\001\b\001\t\001\n\001\013\001\f\001\004\001\002\004\003\001\002\001\003\002\002\001\003\001\002\001\003\001\002\001\003\001\002\001\003\n\002\001\r\001\016\001\017\001\020\001\021\001\022\001\023\001\024\001\025\001\026\001\027\001\030\001\031\001\002\001\006\001\004\001\032\001\002\001\004\001\033\001\034\001\035\001\036\001\037\001 \002\002\001\000\001!\004\000\002\002\006\000\032\002\r\000\001\002\002\000\002\002\001\"\006\000\001#\001\003\001\000\001$\004\000\001#\001%\004\000\001&\001\000\001#\004\003\001'\001\003\001(\001)\001\003\001*\001\003\001+\001\003\001,\001\003\001-\001#\001.\001#\001/\0010\0011\003#\r\000\001#\001\000\0012\002#J\000\001\002\0013\002\002\002\000\001\002\001\000\0013\007\002\n3\001\002\0013\001\002\0013\001\002\0013\001\002\0013!\002\004\000\004\006$\000\001\017\005\000\001\025\001\026\001\027\003\000\001\006\n\000\001\002\002\000\001!\004\000\001\002\0014\006\000\001\002\004\000\001\002\001\000\002\002\001\000\001\002\001\000\001\002\001\000\001\002\001\000\n\002\r\000\001\002\002\000\002\002\007\000\003\b\0015\002\000\001\b\001\000\002\b\00168\b\003\t\0017\002\000\001\t\001\000\003\t\00167\t\r\000\0018c\000\0019\025\000\001:\017\000\004:\001\000\001:\002\000\001:\001\000\001:\001\000\001:\001\000\001:N\000\001;\033\000\004<\004\000\001=\021\000\001>\031\000\001<8\000\001?B\000\001@B\000\001AB\000\001B\024\000\002C\001\000\001D\004\000\002C\006\000\032C\r\000\001C\002\000\002C\007\000\001E\002\000\001F\004\000\001G\001H\006\000\001E\004\000\001I\001\000\002E\001\000\001E\001\000\001E\001\000\001J\001\000\002E\001K\001L\001M\005E\r\000\001E\002\000\002E\007\000\002\002\001\000\001!\004\000\002\002\006\000\025\002\001N\004\002\r\000\001\002\002\000\002\002\001\"\006\000\002#\001\000\001O\004\000\002#\006\000\032#\r\000\001#\002\000\002#\007\000\001#\001P\002#\002\000\001#\001\000\001P\007#\001P\001Q\001R\001P\001R\004P\001S\001*\001S\001+\001P\001,\001P\001-\001P\001.\001#\001/\0010\0011\035#\002\000\001O\004\000\001#\007\000\001#\004\000\001#\001\000\002#\001\000\001#\001\000\001#\001\000\001#\001\000\n#\r\000\001#\002\000\002#\007\000\002#\001\000\001T\004\000\002#\006\000\022#\001U\007#\r\000\001#\002\000\002#\007\000\002#\001\000\001V\004\000\002#\006\000\b#\001W\021#\r\000\001#\002\000\002#\007\000\002#\001\000\001X\004\000\002#\006\000\022#\001Y\005#\001Z\001#\r\000\001#\002\000\002#\007\000\002#\001\000\001[\004\000\002#\006\000\025#\0010\004#\r\000\001#\002\000\002#\007\000\002#\001\000\001\\\004\000\002#\006\000\031#\001]\r\000\001#\002\000\002#\007\000\002#\001\000\001^\004\000\002#\006\000\023#\001_\006#\r\000\001#\002\000\002#\007\000\002#\001\000\001`\004\000\002#\006\000\f#\001+\r#\r\000\001#\002\000\002#\007\000\002#\001\000\001a\004\000\002#\006\000\022#\001b\003#\0011\003#\r\000\001#\002\000\002#\007\000\002#\001\000\001c\004\000\002#\006\000\005#\001d\021#\001e\001f\001#\r\000\001#\002\000\002#\007\000\002#\001\000\001g\004\000\002#\006\000\001h\031#\r\000\001#\002\000\002#\007\000\001\002\001i\001\000\001!\001j\003\002\001i\001\002\006\000\ni\001\002\001i\001\002\001i\001\002\001i\001\002\001i\b\002\r\000\002\002\001\000\002\002\001\"2\000\001k\026\000\001\b\001l\002\b\001m\003\b\001l\007\b\nl\001\b\001l\001\b\001l\001\b\001l\001\b\001l!\b\001\t\001n\002\t\001o\003\t\001n\007\t\nn\001\t\001n\001\t\001n\001\t\001n\001\t\001n!\t\r8\001p58\001#\001:\001\000\001$\004\000\001#\001%\006\000\001#\004:\001'\001:\001(\001)\001:\001*\001:\001+\001:\001,\001:\001-\001#\001.\001#\001/\0010\0011\003#\r\000\001#\001\000\0012\002#\020\000\001qF\000\001rW\000\001s \000\001C\001t\002C\002\000\001C\001\000\001t\007C\nt\001C\001t\001C\001t\001C\001t\001C\001t!C\002E\001\000\001F\004\000\002E\006\000\032E\r\000\001E\002\000\002E\007\000\001E\001u\002E\002\000\001E\001\000\001u\007E\nu\001E\001u\001E\001u\001E\001u\001E\001u#E\001\000\001F\004\000\002E\006\000\032E\r\000\001v\002\000\002E\007\000\001E\002\000\001F\004\000\001E\007\000\001E\004\000\001E\001\000\002E\001\000\001E\001\000\001E\001\000\001E\001\000\nE\r\000\001E\002\000\002E\007\000\002E\001\000\001F\004\000\002E\006\000\fE\001w\rE\r\000\001E\002\000\002E\007\000\002E\001\000\001F\004\000\002E\006\000\022E\001x\007E\r\000\001E\002\000\002E\007\000\002E\001\000\001F\004\000\002E\006\000\bE\001y\021E\r\000\001E\002\000\002E\007\000\002E\001\000\001F\004\000\002E\006\000\001z\031E\r\000\001E\002\000\002E\007\000\002E\001\000\001F\004\000\002E\006\000\001{\031E\r\000\001E\002\000\002E\007\000\002\002\001\000\001!\004\000\002\002\006\000\032\002\r\000\001\002\002\000\001\002\001|\001\"\006\000\001#\001P\002#\002\000\001#\001\000\001P\007#\nP\001#\001P\001#\001P\001#\001P\001#\001P\"#\001}\001\000\001O\001~\003#\001}\001#\006\000\n}\001#\001}\001#\001}\001#\001}\001#\001}\b#\r\000\002#\001\000\002#\007\000\001#\001}\001\000\001O\001~\003#\001}\001#\006\000\001}\001\001\001}\001\004}\001\001#\001\001#\001}\001#\001}\001#\001}\b#\r\000\002#\001\000\002#\007\000\001#\001}\001\000\001O\001~\003#\001}\001#\006\000\002}\001\003}\001\001\001}\001\001#\001\001#\001\001#\001\001#\001\b#\r\000\002#\001\000\002#\007\000\001#\001\001\000\001O\001~\003#\001}\001#\006\000\001}\001\004}\001\003}\001#\001}\001#\001}\001#\001}\001#\001}\b#\r\000\002#\001\000\002#\007\000\001#\001P\002#\002\000\001#\001\000\001P\007#\001P\001\001\001P\001\005P\001#\001P\001#\001P\001#\001P\001#\001P\001U!#\001P\002#\002\000\001#\001\000\001P\007#\001P\001\001\001P\001\005P\001#\001P\001#\001P\001#\001P\001#\001P##\001\000\001\004\000\002#\006\000\n#\001\017#\r\000\001#\002\000\002#\007\000\001#\001P\002#\002\000\001#\001\000\001P\007#\001P\001\001\001P\001\004P\001\001#\001\001#\001P\001#\001P\001#\001P\001Y\005#\001Z\033#\001P\002#\002\000\001#\001\000\001P\007#\001P\001\007P\001\001#\001\001#\001P\001#\001P\001#\001P\003#\0010\036#\001P\002#\002\000\001#\001\000\001P\007#\001P\001\007P\001\001#\001\001#\001P\001#\001P\001#\001P\007#\001]\032#\001P\002#\002\000\001#\001\000\001P\007#\001P\001\001\001P\001\005P\001#\001P\001#\001P\001#\001P\001#\001P\001#\001_ #\001P\002#\002\000\001#\001\000\001P\007#\001P\001\001\001P\001\005P\001#\001P\001+\001P\001#\001P\001#\001P\"#\001P\002#\002\000\001#\001\000\001P\007#\001P\001\001\001P\001\004P\001 \001#\001 \001#\001P\001#\001P\001#\001P\001b\003#\0011\035#\001P\002#\002\000\001#\001\000\001P\007#\001P\001¡\001¢\001P\001¢\004P\001£\001#\001£\001#\001P\001#\001P\001#\001P\005#\001e\001f\033#\001P\002#\002\000\001#\001\000\001P\007#\001P\001¤\001¥\001P\001¥\005P\001#\001P\001#\001P\001#\001P\001#\001P##\001\000\001¦\004\000\002#\006\000\007#\001\022#\r\000\001#\002\000\002#\007\000\001\002\001§\001\000\001!\001j\003\002\001§\001\002\006\000\n§\001\002\001§\001\002\001§\001\002\001§\001\002\001§\b\002\r\000\002\002\001\000\002\002\001\"\006\000\002\002\001\000\001!\001\000\001\002\002\000\002\002\006\000\032\002\r\000\001\002\002\000\002\002\001\"\006\000\001\b\001¨\001\b\0015\001m\003\b\001¨\001\b\0016\005\b\n¨\001\b\001¨\001\b\001¨\001\b\001¨\001\b\001¨$\b\0015\001\000\002\b\001\000\002\b\00168\b\001\t\001©\001\t\0017\001o\003\t\001©\002\t\0016\004\t\n©\001\t\001©\001\t\001©\001\t\001©\001\t\001©$\t\0017\001\000\002\t\001\000\003\t\00167\t\f8\001ª\001p58\t\000\001«9\000\rr\001¬5r$\000\001­\036\000\001C\001®\001\000\001D\001¯\003C\001®\001C\006\000\n®\001C\001®\001C\001®\001C\001®\001C\001®\bC\r\000\002C\001\000\002C\007\000\001E\001°\001\000\001F\001±\003E\001°\001E\006\000\n°\001E\001°\001E\001°\001E\001°\001E\001°\bE\r\000\002E\001\000\002E\007\000\002E\001\000\001F\004\000\002E\006\000\023E\001²\006E\r\000\001E\002\000\002E\007\000\002E\001\000\001F\004\000\002E\006\000\001³\031E\r\000\001E\002\000\002E\007\000\002E\001\000\001F\004\000\002E\006\000\024E\001´\005E\r\000\001E\002\000\002E\007\000\002E\001\000\001F\004\000\002E\006\000\007E\001µ\022E\r\000\001E\002\000\002E\007\000\002E\001\000\001F\004\000\002E\006\000\022E\001¶\007E\r\000\001E\002\000\002E\007\000\002E\001\000\001F\004\000\002E\006\000\nE\001·\017E\r\000\001E\002\000\002E\007\000\002\002\001\000\001!\004\000\002\002\006\000\032\002\r\000\001\002\002\000\002\002\001¸\006\000\001#\001¹\001\000\001O\001~\003#\001¹\001#\006\000\n¹\001#\001¹\001#\001¹\001#\001¹\001#\001¹\b#\r\000\002#\001\000\002#\007\000\002#\001\000\001O\001\000\001#\002\000\002#\006\000\032#\r\000\001#\002\000\002#\007\000\001#\001¹\001\000\001O\001~\003#\001¹\001#\006\000\001¹\001º\001»\001¹\001»\004¹\001¼\001#\001¼\001#\001¹\001#\001¹\001#\001¹\b#\r\000\002#\001\000\002#\007\000\001#\001¹\001\000\001O\001~\003#\001¹\001#\006\000\002¹\001½\003¹\001¾\001¿\001¹\001À\001#\001Á\001#\001Â\001#\001Ã\001#\001Ä\b#\r\000\002#\001\000\002#\007\000\001#\001Å\001\000\001O\001~\003#\001¹\001#\006\000\001¹\001Æ\004¹\001Ç\003¹\001#\001¹\001#\001¹\001#\001¹\001#\001¹\b#\r\000\002#\001\000\002#\007\000\001#\001¹\001\000\001V\001È\003(\001¹\001#\006\000\b¹\001É\001¹\001#\001¹\001#\001¹\001#\001¹\001#\001¹\b#\r\000\001#\001(\001\000\002#\007\000\001#\001¹\001\000\001T\001Ê\003'\001¹\001#\006\000\n¹\001#\001¹\001#\001¹\001#\001¹\001#\001¹\001U\007#\r\000\001#\001'\001\000\002#\007\000\001#\001¹\001\000\001a\001Ë\003.\001¹\001#\006\000\n¹\001#\001¹\001#\001¹\001#\001¹\001#\001¹\001b\003#\0011\003#\r\000\001#\001.\001\000\002#\007\000\001#\001¹\001\000\001X\001Ì\003)\001¹\001#\006\000\n¹\001#\001¹\001#\001¹\001#\001¹\001#\001¹\001Y\005#\001Z\001#\r\000\001#\001)\001\000\002#\007\000\001#\001¹\001\000\001[\001Í\003*\001¹\001#\006\000\n¹\001#\001¹\001#\001¹\001#\001¹\001#\001¹\003#\0010\004#\r\000\001#\001*\001\000\002#\007\000\001#\001¹\001\000\001\\\001Î\003+\001¹\001#\006\000\n¹\001#\001¹\001#\001¹\001#\001¹\001#\001¹\007#\001]\r\000\001#\001+\001\000\002#\007\000\001#\001¹\001\000\001^\001Ï\003,\001¹\001#\006\000\n¹\001#\001¹\001#\001¹\001#\001¹\001#\001¹\001#\001_\006#\r\000\001#\001,\001\000\002#\007\000\001#\001¹\001\000\001`\001Ð\003-\001¹\001#\006\000\n¹\001#\001¹\001+\001¹\001#\001¹\001#\001¹\b#\r\000\001#\001-\001\000\002#\007\000\001#\001¹\001\000\001g\001Ñ\0030\001¹\001#\006\000\001Ò\t¹\001#\001¹\001#\001¹\001#\001¹\001#\001¹\b#\r\000\001#\0010\001\000\002#\007\000\001#\001¹\001\000\001c\001Ó\003/\001¹\001#\006\000\005¹\001Ô\004¹\001#\001¹\001#\001¹\001#\001¹\001#\001¹\005#\001e\001f\001#\r\000\001#\001/\001\000\002#\007\000\001#\001¹\001\000\001O\001Õ\0031\001¹\001#\006\000\n¹\001#\001¹\001#\001¹\001#\001¹\001#\001¹\b#\r\000\001#\0011\001\000\002#\007\000\001#\001}\001\000\001O\001~\003#\001}\001#\006\000\001}\001Ö\001×\001}\001×\005}\001#\001}\001#\001}\001#\001}\001#\001}\b#\r\000\002#\001\000\002#\007\000\001#\001}\001\000\001O\001~\003#\001}\001#\006\000\007}\001Ø\002}\001#\001}\001#\001}\001#\001}\001#\001}\b#\r\000\002#\001\000\002#\007\000\001#\001}\001\000\001O\001~\003#\001}\001#\006\000\001}\001Ù\001Ú\001}\001Ú\005}\001#\001}\001#\001}\001#\001}\001#\001}\b#\r\000\002#\001\000\002#\007\000\001#\001}\001\000\001O\001~\003#\001}\001#\006\000\t}\001Û\001#\001}\001#\001}\001#\001}\001#\001}\b#\r\000\002#\001\000\002#\007\000\001#\001P\002#\002\000\001#\001\000\001P\007#\001P\001Ü\001Ý\001P\001Ý\005P\001\001P\001#\001P\001#\001P\001#\001P\"#\001}\001\000\001O\001~\003#\001}\001#\006\000\001}\001Þ\001ß\001}\001ß\004}\001à\001#\001à\001#\001}\001#\001}\001#\001}\b#\r\000\002#\001\000\002#\007\000\001#\001}\001\000\001O\001~\003#\001}\001#\006\000\007}\001á\002}\001#\001}\001#\001}\001#\001}\001#\001}\b#\r\000\002#\001\000\002#\007\000\001#\001}\001\000\001O\001~\003#\001}\001#\006\000\n}\001#\001}\001#\001â\001#\001}\001#\001}\b#\r\000\002#\001\000\002#\007\000\001#\001}\001\000\001O\001~\003#\001}\001#\006\000\001}\001ã\007}\001ä\001#\001ä\001#\001}\001#\001}\001#\001}\b#\r\000\002#\001\000\002#\007\000\001#\001\001\000\001O\001~\003#\001}\001#\006\000\n}\001#\001}\001#\001}\001#\001}\001#\001}\b#\r\000\002#\001\000\002#\007\000\001#\001}\001\000\001O\001~\003#\001}\001#\006\000\001}\001å\007}\001æ\001#\001æ\001#\001}\001#\001}\001#\001}\b#\r\000\002#\001\000\002#\007\000\001#\001}\001\000\001O\001~\003#\001}\001#\006\000\001ç\t}\001#\001}\001#\001}\001#\001}\001#\001}\b#\r\000\002#\001\000\002#\007\000\001#\001}\001\000\001O\001~\003#\001}\001#\006\000\001}\001è\001é\001}\001é\005}\001#\001}\001#\001}\001#\001}\001#\001}\b#\r\000\002#\001\000\002#\007\000\001#\001}\001\000\001O\001~\003#\001}\001#\006\000\b}\001ê\001}\001#\001}\001#\001}\001#\001}\001#\001}\b#\r\000\002#\001\000\002#\007\000\001#\001}\001\000\001O\001~\003#\001}\001#\006\000\001}\001ë\001ì\001}\001ì\005}\001#\001}\001#\001}\001#\001}\001#\001}\b#\r\000\002#\001\000\002#\007\000\001#\001}\001\000\001O\001~\003#\001}\001#\006\000\n}\001#\001}\001#\001\001#\001}\001#\001}\b#\r\000\002#\001\000\002#\007\000\001#\001}\001\000\001O\001~\003#\001}\001#\006\000\001}\001í\001î\001}\001î\004}\001ï\001#\001ï\001#\001}\001#\001}\001#\001}\b#\r\000\002#\001\000\002#\007\000\001#\001}\001\000\001O\001~\003#\001}\001#\006\000\007}\001ð\002}\001#\001}\001#\001}\001#\001}\001#\001}\b#\r\000\002#\001\000\002#\007\000\001#\001}\001\000\001O\001~\003#\001}\001#\006\000\006}\001\003}\001#\001}\001#\001}\001#\001}\001#\001}\b#\r\000\002#\001\000\002#\007\000\001#\001}\001\000\001O\001~\003#\001}\001#\006\000\001}\001ñ\001ò\001}\001ò\004}\001ó\001#\001ó\001#\001}\001#\001}\001#\001}\b#\r\000\002#\001\000\002#\007\000\001#\001}\001\000\001O\001~\003#\001}\001#\006\000\006}\001ô\003}\001#\001}\001#\001}\001#\001}\001#\001}\b#\r\000\002#\001\000\002#\007\000\001#\001}\001\000\001O\001~\003#\001}\001#\006\000\002}\001õ\007}\001#\001}\001#\001ö\001#\001}\001#\001}\b#\r\000\002#\001\000\002#\007\000\001#\001}\001\000\001O\001~\003#\001}\001#\006\000\001}\001÷\001ø\001}\001ø\005}\001#\001}\001#\001}\001#\001}\001#\001}\b#\r\000\002#\001\000\002#\007\000\001#\001}\001\000\001O\001~\003#\001}\001#\006\000\003}\001ù\006}\001#\001}\001#\001}\001#\001}\001#\001}\b#\r\000\002#\001\000\002#\007\000\001#\001P\002#\002\000\001#\001\000\001P\007#\001P\001ú\001û\001P\001û\005P\001#\001P\001#\001P\001#\001P\001#\001P!#\001\002\001ü\001\000\001!\001j\003\002\001ü\001\002\006\000\nü\001\002\001ü\001\002\001ü\001\002\001ü\001\002\001ü\b\002\r\000\002\002\001\000\002\002\001\"\006\000\001\b\001ý\001\b\0015\001m\003\b\001ý\001\b\0016\005\b\ný\001\b\001ý\001\b\001ý\001\b\001ý\001\b\001ý!\b\001\t\001þ\001\t\0017\001o\003\t\001þ\002\t\0016\004\t\nþ\001\t\001þ\001\t\001þ\001\t\001þ\001\t\001þ!\t\fr\001<\001¬5r7\000\001ÿ\013\000\001C\001Ā\001\000\001D\001¯\003C\001Ā\001C\006\000\nĀ\001C\001Ā\001C\001Ā\001C\001Ā\001C\001Ā\bC\r\000\002C\001\000\002C\007\000\002C\001\000\001D\001\000\001C\002\000\002C\006\000\032C\r\000\001C\002\000\002C\007\000\001E\001ā\001\000\001F\001±\003E\001ā\001E\006\000\nā\001E\001ā\001E\001ā\001E\001ā\001E\001ā\bE\r\000\002E\001\000\002E\007\000\002E\001\000\001F\001\000\001E\002\000\002E\006\000\032E\r\000\001E\002\000\002E\007\000\002E\001\000\001F\004\000\002E\006\000\027E\001Ă\002E\r\000\001E\002\000\002E\007\000\002E\001\000\001F\004\000\002E\006\000\025E\001ă\004E\r\000\001E\002\000\002E\007\000\002E\001\000\001F\004\000\002E\006\000\032E\r\000\001Ą\002\000\002E\007\000\002E\001\000\001F\004\000\002E\006\000\016E\001ą\013E\r\000\001E\002\000\002E\007\000\002E\001\000\001F\004\000\002E\006\000\bE\001Ć\021E\r\000\001E\002\000\002E\007\000\002E\001\000\001F\004\000\002E\006\000\bE\001ć\021E\r\000\001E\002\000\002E\007\000\002Ĉ\001\000\001ĉ\004Ċ\002Ĉ\001ċ\001Č,Ĉ\001Ċ\003Ĉ\001\000\001č\005Ĉ\001#\001Ď\001\000\001O\001~\003#\001Ď\001#\006\000\nĎ\001#\001Ď\001#\001Ď\001#\001Ď\001#\001Ď\b#\r\000\002#\001\000\002#\007\000\001#\001Ď\001\000\001O\001~\003#\001Ď\001#\006\000\001Ď\001ď\001Đ\001Ď\001Đ\004Ď\001đ\001#\001đ\001#\001Ď\001#\001Ď\001#\001Ď\b#\r\000\002#\001\000\002#\007\000\001#\001Ď\001\000\001O\001~\003#\001Ď\001#\006\000\002Ď\001Ē\003Ď\001ē\001Ĕ\001Ď\001ĕ\001#\001Ė\001#\001ė\001#\001Ę\001#\001ę\b#\r\000\002#\001\000\002#\007\000\001#\001Ě\001\000\001O\001~\003#\001Ď\001#\006\000\001Ď\001ě\004Ď\001Ĝ\003Ď\001#\001Ď\001#\001Ď\001#\001Ď\001#\001Ď\b#\r\000\002#\001\000\002#\007\000\001#\001Ď\001\000\001V\001È\003(\001Ď\001#\006\000\bĎ\001ĝ\001Ď\001#\001Ď\001#\001Ď\001#\001Ď\001#\001Ď\b#\r\000\001#\001(\001\000\002#\007\000\001#\001Ď\001\000\001T\001Ê\003'\001Ď\001#\006\000\nĎ\001#\001Ď\001#\001Ď\001#\001Ď\001#\001Ď\001U\007#\r\000\001#\001'\001\000\002#\007\000\001#\001Ď\001\000\001a\001Ë\003.\001Ď\001#\006\000\nĎ\001#\001Ď\001#\001Ď\001#\001Ď\001#\001Ď\001b\003#\0011\003#\r\000\001#\001.\001\000\002#\007\000\001#\001Ď\001\000\001X\001Ì\003)\001Ď\001#\006\000\nĎ\001#\001Ď\001#\001Ď\001#\001Ď\001#\001Ď\001Y\005#\001Z\001#\r\000\001#\001)\001\000\002#\007\000\001#\001Ď\001\000\001[\001Í\003*\001Ď\001#\006\000\nĎ\001#\001Ď\001#\001Ď\001#\001Ď\001#\001Ď\003#\0010\004#\r\000\001#\001*\001\000\002#\007\000\001#\001Ď\001\000\001\\\001Î\003+\001Ď\001#\006\000\nĎ\001#\001Ď\001#\001Ď\001#\001Ď\001#\001Ď\007#\001]\r\000\001#\001+\001\000\002#\007\000\001#\001Ď\001\000\001^\001Ï\003,\001Ď\001#\006\000\nĎ\001#\001Ď\001#\001Ď\001#\001Ď\001#\001Ď\001#\001_\006#\r\000\001#\001,\001\000\002#\007\000\001#\001Ď\001\000\001`\001Ð\003-\001Ď\001#\006\000\nĎ\001#\001Ď\001+\001Ď\001#\001Ď\001#\001Ď\b#\r\000\001#\001-\001\000\002#\007\000\001#\001Ď\001\000\001g\001Ñ\0030\001Ď\001#\006\000\001Ğ\tĎ\001#\001Ď\001#\001Ď\001#\001Ď\001#\001Ď\b#\r\000\001#\0010\001\000\002#\007\000\001#\001Ď\001\000\001c\001Ó\003/\001Ď\001#\006\000\005Ď\001ğ\004Ď\001#\001Ď\001#\001Ď\001#\001Ď\001#\001Ď\005#\001e\001f\001#\r\000\001#\001/\001\000\002#\007\000\001#\001Ď\001\000\001O\001Õ\0031\001Ď\001#\006\000\nĎ\001#\001Ď\001#\001Ď\001#\001Ď\001#\001Ď\b#\r\000\001#\0011\001\000\002#\007\000\002#\001\000\001V\001\000\001(\002\000\002#\006\000\b#\001W\021#\r\000\001#\002\000\002#\007\000\001#\001Ď\001\000\001\001~\003#\001Ď\001#\006\000\nĎ\001\001Ď\001#\001Ď\001#\001Ď\001#\001Ď\b#\r\000\002#\001\000\002#\007\000\002#\001\000\001T\001\000\001'\002\000\002#\006\000\022#\001U\007#\r\000\001#\002\000\002#\007\000\002#\001\000\001a\001\000\001.\002\000\002#\006\000\022#\001b\003#\0011\003#\r\000\001#\002\000\002#\007\000\002#\001\000\001X\001\000\001)\002\000\002#\006\000\022#\001Y\005#\001Z\001#\r\000\001#\002\000\002#\007\000\002#\001\000\001[\001\000\001*\002\000\002#\006\000\025#\0010\004#\r\000\001#\002\000\002#\007\000\002#\001\000\001\\\001\000\001+\002\000\002#\006\000\031#\001]\r\000\001#\002\000\002#\007\000\002#\001\000\001^\001\000\001,\002\000\002#\006\000\023#\001_\006#\r\000\001#\002\000\002#\007\000\002#\001\000\001`\001\000\001-\002\000\002#\006\000\f#\001+\r#\r\000\001#\002\000\002#\007\000\002#\001\000\001g\001\000\0010\002\000\002#\006\000\001h\031#\r\000\001#\002\000\002#\007\000\001#\001Ď\001\000\001¦\001~\003#\001Ď\001#\006\000\007Ď\001Ġ\002Ď\001#\001Ď\001#\001Ď\001#\001Ď\001#\001Ď\b#\r\000\002#\001\000\002#\007\000\002#\001\000\001c\001\000\001/\002\000\002#\006\000\005#\001d\021#\001e\001f\001#\r\000\001#\002\000\002#\007\000\002#\001\000\001O\001\000\0011\002\000\002#\006\000\032#\r\000\001#\002\000\002#\007\000\001#\001¹\001\000\001O\001~\003#\001¹\001#\006\000\001¹\001ġ\001Ģ\001¹\001Ģ\005¹\001#\001¹\001#\001¹\001#\001¹\001#\001¹\b#\r\000\002#\001\000\002#\007\000\001#\001¹\001\000\001O\001~\003#\001¹\001#\006\000\007¹\001ģ\002¹\001#\001¹\001#\001¹\001#\001¹\001#\001¹\b#\r\000\002#\001\000\002#\007\000\001#\001¹\001\000\001O\001Ĥ\003U\001¹\001#\006\000\n¹\001#\001¹\001#\001¹\001#\001¹\001#\001¹\b#\r\000\001#\001U\001\000\002#\007\000\001#\001¹\001\000\001O\001~\003#\001¹\001#\006\000\001¹\001ĥ\001Ħ\001¹\001Ħ\005¹\001#\001¹\001#\001¹\001#\001¹\001#\001¹\b#\r\000\002#\001\000\002#\007\000\001#\001¹\001\000\001O\001~\003#\001¹\001#\006\000\t¹\001ħ\001#\001¹\001#\001¹\001#\001¹\001#\001¹\b#\r\000\002#\001\000\002#\007\000\001#\001¹\001\000\001\001Ĩ\003W\001¹\001#\006\000\n¹\001\001¹\001#\001¹\001#\001¹\001#\001¹\b#\r\000\001#\001W\001\000\002#\007\000\001#\001}\001\000\001O\001~\003#\001}\001#\006\000\001}\001ĩ\001Ī\001}\001Ī\005}\001#\001}\001#\001}\001#\001}\001#\001}\b#\r\000\002#\001\000\002#\007\000\001#\001}\001\000\001O\001~\003#\001}\001#\006\000\n}\001#\001ī\001#\001}\001#\001}\001#\001}\b#\r\000\002#\001\000\002#\007\000\001#\001¹\001\000\001O\001~\003#\001¹\001#\006\000\001¹\001Ĭ\001ĭ\001¹\001ĭ\004¹\001Į\001#\001Į\001#\001¹\001#\001¹\001#\001¹\b#\r\000\002#\001\000\002#\007\000\001#\001¹\001\000\001O\001~\003#\001¹\001#\006\000\007¹\001į\002¹\001#\001¹\001#\001¹\001#\001¹\001#\001¹\b#\r\000\002#\001\000\002#\007\000\001#\001¹\001\000\001O\001~\003#\001¹\001#\006\000\n¹\001#\001¹\001#\001İ\001#\001¹\001#\001¹\b#\r\000\002#\001\000\002#\007\000\001#\001¹\001\000\001O\001ı\003Y\001¹\001#\006\000\n¹\001#\001¹\001#\001¹\001#\001¹\001#\001¹\b#\r\000\001#\001Y\001\000\002#\007\000\001#\001¹\001\000\001O\001Ĳ\003Z\001¹\001#\006\000\n¹\001#\001¹\001#\001¹\001#\001¹\001#\001¹\b#\r\000\001#\001Z\001\000\002#\007\000\001#\001¹\001\000\001O\001~\003#\001¹\001#\006\000\001¹\001ĳ\007¹\001Ĵ\001#\001Ĵ\001#\001¹\001#\001¹\001#\001¹\b#\r\000\002#\001\000\002#\007\000\001#\001Å\001\000\001O\001~\003#\001¹\001#\006\000\n¹\001#\001¹\001#\001¹\001#\001¹\001#\001¹\b#\r\000\002#\001\000\002#\007\000\001#\001¹\001\000\001O\001~\003#\001¹\001#\006\000\001¹\001ĵ\007¹\001Ķ\001#\001Ķ\001#\001¹\001#\001¹\001#\001¹\b#\r\000\002#\001\000\002#\007\000\001#\001¹\001\000\001O\001~\003#\001¹\001#\006\000\001ķ\t¹\001#\001¹\001#\001¹\001#\001¹\001#\001¹\b#\r\000\002#\001\000\002#\007\000\001#\001¹\001\000\001O\001ĸ\003]\001¹\001#\006\000\n¹\001#\001¹\001#\001¹\001#\001¹\001#\001¹\b#\r\000\001#\001]\001\000\002#\007\000\001#\001¹\001\000\001O\001~\003#\001¹\001#\006\000\001¹\001Ĺ\001ĺ\001¹\001ĺ\005¹\001#\001¹\001#\001¹\001#\001¹\001#\001¹\b#\r\000\002#\001\000\002#\007\000\001#\001¹\001\000\001O\001~\003#\001¹\001#\006\000\b¹\001Ļ\001¹\001#\001¹\001#\001¹\001#\001¹\001#\001¹\b#\r\000\002#\001\000\002#\007\000\001#\001¹\001\000\001O\001ļ\003_\001¹\001#\006\000\n¹\001#\001¹\001#\001¹\001#\001¹\001#\001¹\b#\r\000\001#\001_\001\000\002#\007\000\001#\001¹\001\000\001O\001~\003#\001¹\001#\006\000\001¹\001Ľ\001ľ\001¹\001ľ\005¹\001#\001¹\001#\001¹\001#\001¹\001#\001¹\b#\r\000\002#\001\000\002#\007\000\001#\001¹\001\000\001O\001~\003#\001¹\001#\006\000\n¹\001#\001¹\001#\001Â\001#\001¹\001#\001¹\b#\r\000\002#\001\000\002#\007\000\001#\001¹\001\000\001O\001~\003#\001¹\001#\006\000\001¹\001Ŀ\001ŀ\001¹\001ŀ\004¹\001Ł\001#\001Ł\001#\001¹\001#\001¹\001#\001¹\b#\r\000\002#\001\000\002#\007\000\001#\001¹\001\000\001O\001~\003#\001¹\001#\006\000\007¹\001ł\002¹\001#\001¹\001#\001¹\001#\001¹\001#\001¹\b#\r\000\002#\001\000\002#\007\000\001#\001¹\001\000\001O\001~\003#\001¹\001#\006\000\006¹\001Ç\003¹\001#\001¹\001#\001¹\001#\001¹\001#\001¹\b#\r\000\002#\001\000\002#\007\000\001#\001¹\001\000\001O\001Ń\003b\001¹\001#\006\000\n¹\001#\001¹\001#\001¹\001#\001¹\001#\001¹\b#\r\000\001#\001b\001\000\002#\007\000\001#\001¹\001\000\001O\001~\003#\001¹\001#\006\000\001¹\001ń\001Ņ\001¹\001Ņ\004¹\001ņ\001#\001ņ\001#\001¹\001#\001¹\001#\001¹\b#\r\000\002#\001\000\002#\007\000\001#\001¹\001\000\001O\001~\003#\001¹\001#\006\000\006¹\001Ň\003¹\001#\001¹\001#\001¹\001#\001¹\001#\001¹\b#\r\000\002#\001\000\002#\007\000\001#\001¹\001\000\001O\001~\003#\001¹\001#\006\000\002¹\001ň\007¹\001#\001¹\001#\001ŉ\001#\001¹\001#\001¹\b#\r\000\002#\001\000\002#\007\000\001#\001¹\001\000\001O\001Ŋ\003d\001¹\001#\006\000\n¹\001#\001¹\001#\001¹\001#\001¹\001#\001¹\b#\r\000\001#\001d\001\000\002#\007\000\001#\001¹\001\000\001O\001ŋ\003e\001¹\001#\006\000\n¹\001#\001¹\001#\001¹\001#\001¹\001#\001¹\b#\r\000\001#\001e\001\000\002#\007\000\001#\001¹\001\000\001O\001Ō\003f\001¹\001#\006\000\n¹\001#\001¹\001#\001¹\001#\001¹\001#\001¹\b#\r\000\001#\001f\001\000\002#\007\000\001#\001¹\001\000\001O\001~\003#\001¹\001#\006\000\001¹\001ō\001Ŏ\001¹\001Ŏ\005¹\001#\001¹\001#\001¹\001#\001¹\001#\001¹\b#\r\000\002#\001\000\002#\007\000\001#\001¹\001\000\001O\001~\003#\001¹\001#\006\000\003¹\001ŏ\006¹\001#\001¹\001#\001¹\001#\001¹\001#\001¹\b#\r\000\002#\001\000\002#\007\000\001#\001¹\001\000\001¦\001Ő\003h\001¹\001#\006\000\007¹\001ő\002¹\001#\001¹\001#\001¹\001#\001¹\001#\001¹\b#\r\000\001#\001h\001\000\002#\007\000\001#\001}\001\000\001O\001~\003#\001}\001#\006\000\001}\001Œ\001œ\001}\001œ\005}\001#\001}\001#\001}\001#\001}\001#\001}\b#\r\000\002#\001\000\002#\007\000\001#\001}\001\000\001O\001~\003#\001}\001#\006\000\002}\001ī\007}\001#\001}\001#\001}\001#\001}\001#\001}\b#\r\000\002#\001\000\002#\007\000\001\002\001Ŕ\001\000\001!\001j\003\002\001Ŕ\001\002\006\000\nŔ\001\002\001Ŕ\001\002\001Ŕ\001\002\001Ŕ\001\002\001Ŕ\b\002\r\000\002\002\001\000\002\002\001\"\006\000\001\b\001ŕ\001\b\0015\001m\003\b\001ŕ\001\b\0016\005\b\nŕ\001\b\001ŕ\001\b\001ŕ\001\b\001ŕ\001\b\001ŕ!\b\001\t\001Ŗ\001\t\0017\001o\003\t\001Ŗ\002\t\0016\004\t\nŖ\001\t\001Ŗ\001\t\001Ŗ\001\t\001Ŗ\001\t\001Ŗ!\t%\000\001ŗ\035\000\001C\001Ř\001\000\001D\001¯\003C\001Ř\001C\006\000\nŘ\001C\001Ř\001C\001Ř\001C\001Ř\001C\001Ř\bC\r\000\002C\001\000\002C\007\000\001E\001ř\001\000\001F\001±\003E\001ř\001E\006\000\nř\001E\001ř\001E\001ř\001E\001ř\001E\001ř\bE\r\000\002E\001\000\002E\007\000\002E\001\000\001F\004\000\001E\001Ś\006\000\032E\r\000\001E\002\000\002E\007\000\002E\001\000\001F\004\000\002E\006\000\026E\001ś\003E\r\000\001E\002\000\002E\007\000\002E\001\000\001F\004\000\002E\006\000\025E\001Ŝ\004E\r\000\001E\002\000\002E\007\000\002E\001\000\001F\004\000\002E\006\000\001ŝ\031E\r\000\001E\002\000\002E\007\000\002E\001\000\001F\004\000\002E\006\000\026E\001Ş\003E\r\000\001E\002\000\002E\007\000\002Ĉ\001\000\001ĉ\004ş\002Ĉ\002\000,Ĉ\001ş\003Ĉ\001\000\001č\006Ĉ\001Š\001Ĉ\001ĉ\002ş\001Ĉ\001ş\001Š\007Ĉ\nŠ\001Ĉ\001Š\001Ĉ\001Š\001Ĉ\001Š\001Ĉ\001Š\033Ĉ\001š\005Ĉ\003ċ\001Ţ\002\000\001ċ\001\000\002ċ\001ş8ċ\003Č\001ţ\002\000\001Č\001\000\003Č\001ş7Č\001#\001Ť\001\000\001O\001~\003#\001Ť\001#\006\000\nŤ\001#\001Ť\001#\001Ť\001#\001Ť\001#\001Ť\b#\r\000\002#\001\000\002#\007\000\001#\001Ť\001\000\001O\001~\003#\001Ť\001#\006\000\002Ť\001ť\001Ť\001ť\004Ť\001Ŧ\001#\001Ŧ\001#\001Ť\001#\001Ť\001#\001Ť\b#\r\000\002#\001\000\002#\007\000\001#\001Ť\001\000\001O\001~\003#\001Ť\001#\006\000\002Ť\001ŧ\003Ť\001Ũ\001ũ\001Ť\001Ū\001#\001ū\001#\001Ŭ\001#\001ŭ\001#\001Ů\b#\r\000\002#\001\000\002#\007\000\001#\001ů\001\000\001O\001~\003#\001Ť\001#\006\000\001Ť\001Ű\004Ť\001ű\003Ť\001#\001Ť\001#\001Ť\001#\001Ť\001#\001Ť\b#\r\000\002#\001\000\002#\007\000\001#\001Ť\001\000\001V\001È\003(\001Ť\001#\006\000\bŤ\001Ų\001Ť\001#\001Ť\001#\001Ť\001#\001Ť\001#\001Ť\b#\r\000\001#\001(\001\000\002#\007\000\001#\001Ť\001\000\001T\001Ê\003'\001Ť\001#\006\000\nŤ\001#\001Ť\001#\001Ť\001#\001Ť\001#\001Ť\001U\007#\r\000\001#\001'\001\000\002#\007\000\001#\001Ť\001\000\001a\001Ë\003.\001Ť\001#\006\000\nŤ\001#\001Ť\001#\001Ť\001#\001Ť\001#\001Ť\001b\003#\0011\003#\r\000\001#\001.\001\000\002#\007\000\001#\001Ť\001\000\001X\001Ì\003)\001Ť\001#\006\000\nŤ\001#\001Ť\001#\001Ť\001#\001Ť\001#\001Ť\001Y\005#\001Z\001#\r\000\001#\001)\001\000\002#\007\000\001#\001Ť\001\000\001[\001Í\003*\001Ť\001#\006\000\nŤ\001#\001Ť\001#\001Ť\001#\001Ť\001#\001Ť\003#\0010\004#\r\000\001#\001*\001\000\002#\007\000\001#\001Ť\001\000\001\\\001Î\003+\001Ť\001#\006\000\nŤ\001#\001Ť\001#\001Ť\001#\001Ť\001#\001Ť\007#\001]\r\000\001#\001+\001\000\002#\007\000\001#\001Ť\001\000\001^\001Ï\003,\001Ť\001#\006\000\nŤ\001#\001Ť\001#\001Ť\001#\001Ť\001#\001Ť\001#\001_\006#\r\000\001#\001,\001\000\002#\007\000\001#\001Ť\001\000\001`\001Ð\003-\001Ť\001#\006\000\nŤ\001#\001Ť\001+\001Ť\001#\001Ť\001#\001Ť\b#\r\000\001#\001-\001\000\002#\007\000\001#\001Ť\001\000\001g\001Ñ\0030\001Ť\001#\006\000\001ų\tŤ\001#\001Ť\001#\001Ť\001#\001Ť\001#\001Ť\b#\r\000\001#\0010\001\000\002#\007\000\001#\001Ť\001\000\001c\001Ó\003/\001Ť\001#\006\000\005Ť\001Ŵ\004Ť\001#\001Ť\001#\001Ť\001#\001Ť\001#\001Ť\005#\001e\001f\001#\r\000\001#\001/\001\000\002#\007\000\001#\001Ť\001\000\001O\001Õ\0031\001Ť\001#\006\000\nŤ\001#\001Ť\001#\001Ť\001#\001Ť\001#\001Ť\b#\r\000\001#\0011\001\000\002#\007\000\001#\001Ť\001\000\001\001~\003#\001Ť\001#\006\000\nŤ\001\001Ť\001#\001Ť\001#\001Ť\001#\001Ť\b#\r\000\002#\001\000\002#\007\000\001#\001Ť\001\000\001¦\001~\003#\001Ť\001#\006\000\007Ť\001ŵ\002Ť\001#\001Ť\001#\001Ť\001#\001Ť\001#\001Ť\b#\r\000\002#\001\000\002#\007\000\001#\001Ď\001\000\001O\001~\003#\001Ď\001#\006\000\001Ď\001Ŷ\001ŷ\001Ď\001ŷ\005Ď\001#\001Ď\001#\001Ď\001#\001Ď\001#\001Ď\b#\r\000\002#\001\000\002#\007\000\001#\001Ď\001\000\001O\001~\003#\001Ď\001#\006\000\007Ď\001Ÿ\002Ď\001#\001Ď\001#\001Ď\001#\001Ď\001#\001Ď\b#\r\000\002#\001\000\002#\007\000\001#\001Ď\001\000\001O\001Ĥ\003U\001Ď\001#\006\000\nĎ\001#\001Ď\001#\001Ď\001#\001Ď\001#\001Ď\b#\r\000\001#\001U\001\000\002#\007\000\002#\001\000\001O\001\000\001U\002\000\002#\006\000\032#\r\000\001#\002\000\002#\007\000\001#\001Ď\001\000\001O\001~\003#\001Ď\001#\006\000\001Ď\001Ź\001ź\001Ď\001ź\005Ď\001#\001Ď\001#\001Ď\001#\001Ď\001#\001Ď\b#\r\000\002#\001\000\002#\007\000\001#\001Ď\001\000\001O\001~\003#\001Ď\001#\006\000\tĎ\001Ż\001#\001Ď\001#\001Ď\001#\001Ď\001#\001Ď\b#\r\000\002#\001\000\002#\007\000\001#\001Ď\001\000\001\001Ĩ\003W\001Ď\001#\006\000\nĎ\001\001Ď\001#\001Ď\001#\001Ď\001#\001Ď\b#\r\000\001#\001W\001\000\002#\007\000\002#\001\000\001\001\000\001W\002\000\002#\006\000\n#\001\017#\r\000\001#\002\000\002#\007\000\001#\001¹\001\000\001O\001~\003#\001¹\001#\006\000\001¹\001ż\001Ž\001¹\001Ž\005¹\001#\001¹\001#\001¹\001#\001¹\001#\001¹\b#\r\000\002#\001\000\002#\007\000\001#\001¹\001\000\001O\001~\003#\001¹\001#\006\000\n¹\001#\001ž\001#\001¹\001#\001¹\001#\001¹\b#\r\000\002#\001\000\002#\007\000\001#\001¹\001\000\001O\001ſ\003\001¹\001#\006\000\n¹\001#\001¹\001#\001¹\001#\001¹\001#\001¹\b#\r\000\001#\001\001\000\002#\007\000\001#\001Ď\001\000\001O\001~\003#\001Ď\001#\006\000\001Ď\001ƀ\001Ɓ\001Ď\001Ɓ\004Ď\001Ƃ\001#\001Ƃ\001#\001Ď\001#\001Ď\001#\001Ď\b#\r\000\002#\001\000\002#\007\000\001#\001Ď\001\000\001O\001~\003#\001Ď\001#\006\000\007Ď\001ƃ\002Ď\001#\001Ď\001#\001Ď\001#\001Ď\001#\001Ď\b#\r\000\002#\001\000\002#\007\000\001#\001Ď\001\000\001O\001~\003#\001Ď\001#\006\000\nĎ\001#\001Ď\001#\001Ƅ\001#\001Ď\001#\001Ď\b#\r\000\002#\001\000\002#\007\000\001#\001Ď\001\000\001O\001ı\003Y\001Ď\001#\006\000\nĎ\001#\001Ď\001#\001Ď\001#\001Ď\001#\001Ď\b#\r\000\001#\001Y\001\000\002#\007\000\001#\001Ď\001\000\001O\001Ĳ\003Z\001Ď\001#\006\000\nĎ\001#\001Ď\001#\001Ď\001#\001Ď\001#\001Ď\b#\r\000\001#\001Z\001\000\002#\007\000\002#\001\000\001O\001\000\001Y\002\000\002#\006\000\032#\r\000\001#\002\000\002#\007\000\002#\001\000\001O\001\000\001Z\002\000\002#\006\000\032#\r\000\001#\002\000\002#\007\000\001#\001Ď\001\000\001O\001~\003#\001Ď\001#\006\000\001Ď\001ƅ\007Ď\001Ɔ\001#\001Ɔ\001#\001Ď\001#\001Ď\001#\001Ď\b#\r\000\002#\001\000\002#\007\000\001#\001Ě\001\000\001O\001~\003#\001Ď\001#\006\000\nĎ\001#\001Ď\001#\001Ď\001#\001Ď\001#\001Ď\b#\r\000\002#\001\000\002#\007\000\001#\001Ď\001\000\001O\001~\003#\001Ď\001#\006\000\001Ď\001Ƈ\007Ď\001ƈ\001#\001ƈ\001#\001Ď\001#\001Ď\001#\001Ď\b#\r\000\002#\001\000\002#\007\000\001#\001Ď\001\000\001O\001~\003#\001Ď\001#\006\000\001Ɖ\tĎ\001#\001Ď\001#\001Ď\001#\001Ď\001#\001Ď\b#\r\000\002#\001\000\002#\007\000\001#\001Ď\001\000\001O\001ĸ\003]\001Ď\001#\006\000\nĎ\001#\001Ď\001#\001Ď\001#\001Ď\001#\001Ď\b#\r\000\001#\001]\001\000\002#\007\000\002#\001\000\001O\001\000\001]\002\000\002#\006\000\032#\r\000\001#\002\000\002#\007\000\001#\001Ď\001\000\001O\001~\003#\001Ď\001#\006\000\001Ď\001Ɗ\001Ƌ\001Ď\001Ƌ\005Ď\001#\001Ď\001#\001Ď\001#\001Ď\001#\001Ď\b#\r\000\002#\001\000\002#\007\000\001#\001Ď\001\000\001O\001~\003#\001Ď\001#\006\000\bĎ\001ƌ\001Ď\001#\001Ď\001#\001Ď\001#\001Ď\001#\001Ď\b#\r\000\002#\001\000\002#\007\000\001#\001Ď\001\000\001O\001ļ\003_\001Ď\001#\006\000\nĎ\001#\001Ď\001#\001Ď\001#\001Ď\001#\001Ď\b#\r\000\001#\001_\001\000\002#\007\000\002#\001\000\001O\001\000\001_\002\000\002#\006\000\032#\r\000\001#\002\000\002#\007\000\001#\001Ď\001\000\001O\001~\003#\001Ď\001#\006\000\001Ď\001ƍ\001Ǝ\001Ď\001Ǝ\005Ď\001#\001Ď\001#\001Ď\001#\001Ď\001#\001Ď\b#\r\000\002#\001\000\002#\007\000\001#\001Ď\001\000\001O\001~\003#\001Ď\001#\006\000\nĎ\001#\001Ď\001#\001ė\001#\001Ď\001#\001Ď\b#\r\000\002#\001\000\002#\007\000\001#\001Ď\001\000\001O\001~\003#\001Ď\001#\006\000\001Ď\001Ə\001Ɛ\001Ď\001Ɛ\004Ď\001Ƒ\001#\001Ƒ\001#\001Ď\001#\001Ď\001#\001Ď\b#\r\000\002#\001\000\002#\007\000\001#\001Ď\001\000\001O\001~\003#\001Ď\001#\006\000\007Ď\001ƒ\002Ď\001#\001Ď\001#\001Ď\001#\001Ď\001#\001Ď\b#\r\000\002#\001\000\002#\007\000\001#\001Ď\001\000\001O\001~\003#\001Ď\001#\006\000\006Ď\001Ĝ\003Ď\001#\001Ď\001#\001Ď\001#\001Ď\001#\001Ď\b#\r\000\002#\001\000\002#\007\000\001#\001Ď\001\000\001O\001Ń\003b\001Ď\001#\006\000\nĎ\001#\001Ď\001#\001Ď\001#\001Ď\001#\001Ď\b#\r\000\001#\001b\001\000\002#\007\000\002#\001\000\001O\001\000\001b\002\000\002#\006\000\032#\r\000\001#\002\000\002#\007\000\001#\001Ď\001\000\001O\001~\003#\001Ď\001#\006\000\001Ď\001Ɠ\001Ɣ\001Ď\001Ɣ\004Ď\001ƕ\001#\001ƕ\001#\001Ď\001#\001Ď\001#\001Ď\b#\r\000\002#\001\000\002#\007\000\001#\001Ď\001\000\001O\001~\003#\001Ď\001#\006\000\006Ď\001Ɩ\003Ď\001#\001Ď\001#\001Ď\001#\001Ď\001#\001Ď\b#\r\000\002#\001\000\002#\007\000\001#\001Ď\001\000\001O\001~\003#\001Ď\001#\006\000\002Ď\001Ɨ\007Ď\001#\001Ď\001#\001Ƙ\001#\001Ď\001#\001Ď\b#\r\000\002#\001\000\002#\007\000\001#\001Ď\001\000\001O\001Ŋ\003d\001Ď\001#\006\000\nĎ\001#\001Ď\001#\001Ď\001#\001Ď\001#\001Ď\b#\r\000\001#\001d\001\000\002#\007\000\001#\001Ď\001\000\001O\001ŋ\003e\001Ď\001#\006\000\nĎ\001#\001Ď\001#\001Ď\001#\001Ď\001#\001Ď\b#\r\000\001#\001e\001\000\002#\007\000\001#\001Ď\001\000\001O\001Ō\003f\001Ď\001#\006\000\nĎ\001#\001Ď\001#\001Ď\001#\001Ď\001#\001Ď\b#\r\000\001#\001f\001\000\002#\007\000\002#\001\000\001O\001\000\001d\002\000\002#\006\000\032#\r\000\001#\002\000\002#\007\000\002#\001\000\001O\001\000\001e\002\000\002#\006\000\032#\r\000\001#\002\000\002#\007\000\002#\001\000\001O\001\000\001f\002\000\002#\006\000\032#\r\000\001#\002\000\002#\007\000\001#\001Ď\001\000\001O\001~\003#\001Ď\001#\006\000\001Ď\001ƙ\001ƚ\001Ď\001ƚ\005Ď\001#\001Ď\001#\001Ď\001#\001Ď\001#\001Ď\b#\r\000\002#\001\000\002#\007\000\001#\001Ď\001\000\001O\001~\003#\001Ď\001#\006\000\003Ď\001ƛ\006Ď\001#\001Ď\001#\001Ď\001#\001Ď\001#\001Ď\b#\r\000\002#\001\000\002#\007\000\001#\001Ď\001\000\001¦\001Ő\003h\001Ď\001#\006\000\007Ď\001Ġ\002Ď\001#\001Ď\001#\001Ď\001#\001Ď\001#\001Ď\b#\r\000\001#\001h\001\000\002#\007\000\002#\001\000\001¦\001\000\001h\002\000\002#\006\000\007#\001\022#\r\000\001#\002\000\002#\007\000\001#\001¹\001\000\001O\001~\003#\001¹\001#\006\000\001¹\001Ɯ\001Ɲ\001¹\001Ɲ\005¹\001#\001¹\001#\001¹\001#\001¹\001#\001¹\b#\r\000\002#\001\000\002#\007\000\001#\001¹\001\000\001O\001~\003#\001¹\001#\006\000\002¹\001ž\007¹\001#\001¹\001#\001¹\001#\001¹\001#\001¹\b#\r\000\002#\001\000\002#\007\000\001\002\001ƞ\001\000\001!\001j\003\002\001ƞ\001\002\006\000\nƞ\001\002\001ƞ\001\002\001ƞ\001\002\001ƞ\001\002\001ƞ\b\002\r\000\002\002\001\000\002\002\001\"\006\000\001\b\001Ɵ\001\b\0015\001m\003\b\001Ɵ\001\b\0016\005\b\nƟ\001\b\001Ɵ\001\b\001Ɵ\001\b\001Ɵ\001\b\001Ɵ!\b\001\t\001Ơ\001\t\0017\001o\003\t\001Ơ\002\t\0016\004\t\nƠ\001\t\001Ơ\001\t\001Ơ\001\t\001Ơ\001\t\001Ơ!\t'\000\001ơ\033\000\001C\001Ƣ\001\000\001D\001¯\003C\001Ƣ\001C\006\000\nƢ\001C\001Ƣ\001C\001Ƣ\001C\001Ƣ\001C\001Ƣ\bC\r\000\002C\001\000\002C\007\000\001E\001ƣ\001\000\001F\001±\003E\001ƣ\001E\006\000\nƣ\001E\001ƣ\001E\001ƣ\001E\001ƣ\001E\001ƣ\bE\r\000\002E\001\000\002E\007\000\002E\001\000\001F\004\000\001Ƥ\001E\006\000\032E\r\000\001E\002\000\002E\007\000\002E\001\000\001F\004\000\002E\006\000\bE\001ƥ\021E\r\000\001E\002\000\002E\007\000\002E\001\000\001F\004\000\002E\006\000\027E\001Ʀ\002E\r\000\001E\002\000\002E\007\000\002E\001\000\001F\004\000\002E\006\000\024E\001Ƨ\005E\r\000\001E\002\000\002E\013\000\004ş0\000\001ş\004\000\001č\005\000\001Ĉ\001ƨ\001\000\001ĉ\001Ʃ\003Ĉ\001ƨ\001Ĉ\002\000\004Ĉ\nƨ\001Ĉ\001ƨ\001Ĉ\001ƨ\001Ĉ\001ƨ\001Ĉ\001ƨ\032Ĉ\001\000\001č\005Ĉ\001ċ\001ƪ\002ċ\001ƫ\003ċ\001ƪ\007ċ\nƪ\001ċ\001ƪ\001ċ\001ƪ\001ċ\001ƪ\001ċ\001ƪ!ċ\001Č\001Ƭ\002Č\001ƭ\003Č\001Ƭ\007Č\nƬ\001Č\001Ƭ\001Č\001Ƭ\001Č\001Ƭ\001Č\001Ƭ!Č\001#\001Ʈ\001\000\001O\001~\003#\001Ʈ\001#\006\000\nƮ\001#\001Ʈ\001#\001Ʈ\001#\001Ʈ\001#\001Ʈ\b#\r\000\002#\001\000\002#\007\000\001#\001Ʈ\001\000\001O\001~\003#\001Ʈ\001#\006\000\002Ʈ\001Ư\003Ʈ\001ư\001Ʊ\001Ʈ\001Ʋ\001#\001Ƴ\001#\001ƴ\001#\001Ƶ\001#\001ƶ\b#\r\000\002#\001\000\002#\007\000\001#\001Ʒ\001\000\001O\001~\003#\001Ʈ\001#\006\000\001Ʈ\001Ƹ\004Ʈ\001ƹ\003Ʈ\001#\001Ʈ\001#\001Ʈ\001#\001Ʈ\001#\001Ʈ\b#\r\000\002#\001\000\002#\007\000\001#\001Ʈ\001\000\001V\001È\003(\001Ʈ\001#\006\000\bƮ\001ƺ\001Ʈ\001#\001Ʈ\001#\001Ʈ\001#\001Ʈ\001#\001Ʈ\b#\r\000\001#\001(\001\000\002#\007\000\001#\001Ʈ\001\000\001T\001Ê\003'\001Ʈ\001#\006\000\nƮ\001#\001Ʈ\001#\001Ʈ\001#\001Ʈ\001#\001Ʈ\001U\007#\r\000\001#\001'\001\000\002#\007\000\001#\001Ʈ\001\000\001a\001Ë\003.\001Ʈ\001#\006\000\nƮ\001#\001Ʈ\001#\001Ʈ\001#\001Ʈ\001#\001Ʈ\001b\003#\0011\003#\r\000\001#\001.\001\000\002#\007\000\001#\001Ʈ\001\000\001X\001Ì\003)\001Ʈ\001#\006\000\nƮ\001#\001Ʈ\001#\001Ʈ\001#\001Ʈ\001#\001Ʈ\001Y\005#\001Z\001#\r\000\001#\001)\001\000\002#\007\000\001#\001Ʈ\001\000\001[\001Í\003*\001Ʈ\001#\006\000\nƮ\001#\001Ʈ\001#\001Ʈ\001#\001Ʈ\001#\001Ʈ\003#\0010\004#\r\000\001#\001*\001\000\002#\007\000\001#\001Ʈ\001\000\001\\\001Î\003+\001Ʈ\001#\006\000\nƮ\001#\001Ʈ\001#\001Ʈ\001#\001Ʈ\001#\001Ʈ\007#\001]\r\000\001#\001+\001\000\002#\007\000\001#\001Ʈ\001\000\001^\001Ï\003,\001Ʈ\001#\006\000\nƮ\001#\001Ʈ\001#\001Ʈ\001#\001Ʈ\001#\001Ʈ\001#\001_\006#\r\000\001#\001,\001\000\002#\007\000\001#\001Ʈ\001\000\001`\001Ð\003-\001Ʈ\001#\006\000\nƮ\001#\001Ʈ\001+\001Ʈ\001#\001Ʈ\001#\001Ʈ\b#\r\000\001#\001-\001\000\002#\007\000\001#\001Ʈ\001\000\001g\001Ñ\0030\001Ʈ\001#\006\000\001ƻ\tƮ\001#\001Ʈ\001#\001Ʈ\001#\001Ʈ\001#\001Ʈ\b#\r\000\001#\0010\001\000\002#\007\000\001#\001Ʈ\001\000\001c\001Ó\003/\001Ʈ\001#\006\000\005Ʈ\001Ƽ\004Ʈ\001#\001Ʈ\001#\001Ʈ\001#\001Ʈ\001#\001Ʈ\005#\001e\001f\001#\r\000\001#\001/\001\000\002#\007\000\001#\001Ʈ\001\000\001O\001Õ\0031\001Ʈ\001#\006\000\nƮ\001#\001Ʈ\001#\001Ʈ\001#\001Ʈ\001#\001Ʈ\b#\r\000\001#\0011\001\000\002#\007\000\001#\001Ʈ\001\000\001\001~\003#\001Ʈ\001#\006\000\nƮ\001\001Ʈ\001#\001Ʈ\001#\001Ʈ\001#\001Ʈ\b#\r\000\002#\001\000\002#\007\000\001#\001Ʈ\001\000\001¦\001~\003#\001Ʈ\001#\006\000\007Ʈ\001ƽ\002Ʈ\001#\001Ʈ\001#\001Ʈ\001#\001Ʈ\001#\001Ʈ\b#\r\000\002#\001\000\002#\007\000\001#\001Ť\001\000\001O\001~\003#\001Ť\001#\006\000\002Ť\001ƾ\001Ť\001ƾ\005Ť\001#\001Ť\001#\001Ť\001#\001Ť\001#\001Ť\b#\r\000\002#\001\000\002#\007\000\001#\001Ť\001\000\001O\001~\003#\001Ť\001#\006\000\007Ť\001ƿ\002Ť\001#\001Ť\001#\001Ť\001#\001Ť\001#\001Ť\b#\r\000\002#\001\000\002#\007\000\001#\001Ť\001\000\001O\001Ĥ\003U\001Ť\001#\006\000\nŤ\001#\001Ť\001#\001Ť\001#\001Ť\001#\001Ť\b#\r\000\001#\001U\001\000\002#\007\000\001#\001Ť\001\000\001O\001~\003#\001Ť\001#\006\000\002Ť\001ǀ\001Ť\001ǀ\005Ť\001#\001Ť\001#\001Ť\001#\001Ť\001#\001Ť\b#\r\000\002#\001\000\002#\007\000\001#\001Ť\001\000\001O\001~\003#\001Ť\001#\006\000\tŤ\001ǁ\001#\001Ť\001#\001Ť\001#\001Ť\001#\001Ť\b#\r\000\002#\001\000\002#\007\000\001#\001Ť\001\000\001\001Ĩ\003W\001Ť\001#\006\000\nŤ\001\001Ť\001#\001Ť\001#\001Ť\001#\001Ť\b#\r\000\001#\001W\001\000\002#\007\000\001#\001Ď\001\000\001O\001~\003#\001Ď\001#\006\000\001Ď\001ǂ\001ǃ\001Ď\001ǃ\005Ď\001#\001Ď\001#\001Ď\001#\001Ď\001#\001Ď\b#\r\000\002#\001\000\002#\007\000\001#\001Ď\001\000\001O\001~\003#\001Ď\001#\006\000\nĎ\001#\001Ǆ\001#\001Ď\001#\001Ď\001#\001Ď\b#\r\000\002#\001\000\002#\007\000\001#\001Ď\001\000\001O\001ſ\003\001Ď\001#\006\000\nĎ\001#\001Ď\001#\001Ď\001#\001Ď\001#\001Ď\b#\r\000\001#\001\001\000\002#\007\000\002#\001\000\001O\001\000\001\002\000\002#\006\000\032#\r\000\001#\002\000\002#\007\000\001#\001Ť\001\000\001O\001~\003#\001Ť\001#\006\000\002Ť\001ǅ\001Ť\001ǅ\004Ť\001ǆ\001#\001ǆ\001#\001Ť\001#\001Ť\001#\001Ť\b#\r\000\002#\001\000\002#\007\000\001#\001Ť\001\000\001O\001~\003#\001Ť\001#\006\000\007Ť\001Ǉ\002Ť\001#\001Ť\001#\001Ť\001#\001Ť\001#\001Ť\b#\r\000\002#\001\000\002#\007\000\001#\001Ť\001\000\001O\001~\003#\001Ť\001#\006\000\nŤ\001#\001Ť\001#\001ǈ\001#\001Ť\001#\001Ť\b#\r\000\002#\001\000\002#\007\000\001#\001Ť\001\000\001O\001ı\003Y\001Ť\001#\006\000\nŤ\001#\001Ť\001#\001Ť\001#\001Ť\001#\001Ť\b#\r\000\001#\001Y\001\000\002#\007\000\001#\001Ť\001\000\001O\001Ĳ\003Z\001Ť\001#\006\000\nŤ\001#\001Ť\001#\001Ť\001#\001Ť\001#\001Ť\b#\r\000\001#\001Z\001\000\002#\007\000\001#\001Ť\001\000\001O\001~\003#\001Ť\001#\006\000\tŤ\001ǉ\001#\001ǉ\001#\001Ť\001#\001Ť\001#\001Ť\b#\r\000\002#\001\000\002#\007\000\001#\001ů\001\000\001O\001~\003#\001Ť\001#\006\000\nŤ\001#\001Ť\001#\001Ť\001#\001Ť\001#\001Ť\b#\r\000\002#\001\000\002#\007\000\001#\001Ť\001\000\001O\001~\003#\001Ť\001#\006\000\tŤ\001Ǌ\001#\001Ǌ\001#\001Ť\001#\001Ť\001#\001Ť\b#\r\000\002#\001\000\002#\007\000\001#\001Ť\001\000\001O\001~\003#\001Ť\001#\006\000\001ǋ\tŤ\001#\001Ť\001#\001Ť\001#\001Ť\001#\001Ť\b#\r\000\002#\001\000\002#\007\000\001#\001Ť\001\000\001O\001ĸ\003]\001Ť\001#\006\000\nŤ\001#\001Ť\001#\001Ť\001#\001Ť\001#\001Ť\b#\r\000\001#\001]\001\000\002#\007\000\001#\001Ť\001\000\001O\001~\003#\001Ť\001#\006\000\002Ť\001ǌ\001Ť\001ǌ\005Ť\001#\001Ť\001#\001Ť\001#\001Ť\001#\001Ť\b#\r\000\002#\001\000\002#\007\000\001#\001Ť\001\000\001O\001~\003#\001Ť\001#\006\000\bŤ\001Ǎ\001Ť\001#\001Ť\001#\001Ť\001#\001Ť\001#\001Ť\b#\r\000\002#\001\000\002#\007\000\001#\001Ť\001\000\001O\001ļ\003_\001Ť\001#\006\000\nŤ\001#\001Ť\001#\001Ť\001#\001Ť\001#\001Ť\b#\r\000\001#\001_\001\000\002#\007\000\001#\001Ť\001\000\001O\001~\003#\001Ť\001#\006\000\002Ť\001ǎ\001Ť\001ǎ\005Ť\001#\001Ť\001#\001Ť\001#\001Ť\001#\001Ť\b#\r\000\002#\001\000\002#\007\000\001#\001Ť\001\000\001O\001~\003#\001Ť\001#\006\000\nŤ\001#\001Ť\001#\001Ŭ\001#\001Ť\001#\001Ť\b#\r\000\002#\001\000\002#\007\000\001#\001Ť\001\000\001O\001~\003#\001Ť\001#\006\000\002Ť\001Ǐ\001Ť\001Ǐ\004Ť\001ǐ\001#\001ǐ\001#\001Ť\001#\001Ť\001#\001Ť\b#\r\000\002#\001\000\002#\007\000\001#\001Ť\001\000\001O\001~\003#\001Ť\001#\006\000\007Ť\001Ǒ\002Ť\001#\001Ť\001#\001Ť\001#\001Ť\001#\001Ť\b#\r\000\002#\001\000\002#\007\000\001#\001Ť\001\000\001O\001~\003#\001Ť\001#\006\000\006Ť\001ű\003Ť\001#\001Ť\001#\001Ť\001#\001Ť\001#\001Ť\b#\r\000\002#\001\000\002#\007\000\001#\001Ť\001\000\001O\001Ń\003b\001Ť\001#\006\000\nŤ\001#\001Ť\001#\001Ť\001#\001Ť\001#\001Ť\b#\r\000\001#\001b\001\000\002#\007\000\001#\001Ť\001\000\001O\001~\003#\001Ť\001#\006\000\002Ť\001ǒ\001Ť\001ǒ\004Ť\001Ǔ\001#\001Ǔ\001#\001Ť\001#\001Ť\001#\001Ť\b#\r\000\002#\001\000\002#\007\000\001#\001Ť\001\000\001O\001~\003#\001Ť\001#\006\000\006Ť\001ǔ\003Ť\001#\001Ť\001#\001Ť\001#\001Ť\001#\001Ť\b#\r\000\002#\001\000\002#\007\000\001#\001Ť\001\000\001O\001~\003#\001Ť\001#\006\000\002Ť\001Ǖ\007Ť\001#\001Ť\001#\001ǖ\001#\001Ť\001#\001Ť\b#\r\000\002#\001\000\002#\007\000\001#\001Ť\001\000\001O\001Ŋ\003d\001Ť\001#\006\000\nŤ\001#\001Ť\001#\001Ť\001#\001Ť\001#\001Ť\b#\r\000\001#\001d\001\000\002#\007\000\001#\001Ť\001\000\001O\001ŋ\003e\001Ť\001#\006\000\nŤ\001#\001Ť\001#\001Ť\001#\001Ť\001#\001Ť\b#\r\000\001#\001e\001\000\002#\007\000\001#\001Ť\001\000\001O\001Ō\003f\001Ť\001#\006\000\nŤ\001#\001Ť\001#\001Ť\001#\001Ť\001#\001Ť\b#\r\000\001#\001f\001\000\002#\007\000\001#\001Ť\001\000\001O\001~\003#\001Ť\001#\006\000\002Ť\001Ǘ\001Ť\001Ǘ\005Ť\001#\001Ť\001#\001Ť\001#\001Ť\001#\001Ť\b#\r\000\002#\001\000\002#\007\000\001#\001Ť\001\000\001O\001~\003#\001Ť\001#\006\000\003Ť\001ǘ\006Ť\001#\001Ť\001#\001Ť\001#\001Ť\001#\001Ť\b#\r\000\002#\001\000\002#\007\000\001#\001Ť\001\000\001¦\001Ő\003h\001Ť\001#\006\000\007Ť\001ŵ\002Ť\001#\001Ť\001#\001Ť\001#\001Ť\001#\001Ť\b#\r\000\001#\001h\001\000\002#\007\000\001#\001Ď\001\000\001O\001~\003#\001Ď\001#\006\000\001Ď\001Ǚ\001ǚ\001Ď\001ǚ\005Ď\001#\001Ď\001#\001Ď\001#\001Ď\001#\001Ď\b#\r\000\002#\001\000\002#\007\000\001#\001Ď\001\000\001O\001~\003#\001Ď\001#\006\000\002Ď\001Ǆ\007Ď\001#\001Ď\001#\001Ď\001#\001Ď\001#\001Ď\b#\r\000\002#\001\000\002#\007\000\002\002\001\000\001!\001j\005\002\006\000\032\002\r\000\002\002\001\000\002\002\001\"\006\000\001\b\001Ǜ\001\b\0015\001m\003\b\001Ǜ\001\b\0016\005\b\nǛ\001\b\001Ǜ\001\b\001Ǜ\001\b\001Ǜ\001\b\001Ǜ!\b\001\t\001ǜ\001\t\0017\001o\003\t\001ǜ\002\t\0016\004\t\nǜ\001\t\001ǜ\001\t\001ǜ\001\t\001ǜ\001\t\001ǜ!\t\020\000\001ǝ2\000\001C\001Ǟ\001\000\001D\001¯\003C\001Ǟ\001C\006\000\nǞ\001C\001Ǟ\001C\001Ǟ\001C\001Ǟ\001C\001Ǟ\bC\r\000\002C\001\000\002C\007\000\001E\001ǟ\001\000\001F\001±\003E\001ǟ\001E\006\000\nǟ\001E\001ǟ\001E\001ǟ\001E\001ǟ\001E\001ǟ\bE\r\000\002E\001\000\002E\007\000\002E\001\000\001F\004\000\002E\006\000\001Ǡ\031E\r\000\001E\002\000\002E\007\000\002E\001\000\001F\004\000\002E\006\000\027E\001ǡ\002E\r\000\001E\002\000\002E\007\000\002E\001\000\001F\004\000\002E\006\000\001Ǣ\031E\r\000\001E\002\000\002E\007\000\001Ĉ\001ǣ\001\000\001ĉ\001Ʃ\003Ĉ\001ǣ\001Ĉ\002\000\004Ĉ\nǣ\001Ĉ\001ǣ\001Ĉ\001ǣ\001Ĉ\001ǣ\001Ĉ\001ǣ\032Ĉ\001\000\001č\007Ĉ\001\000\001ĉ\001ş\001Ĉ\002ş\002Ĉ\002\000,Ĉ\001ş\003Ĉ\001\000\001č\005Ĉ\001ċ\001Ǥ\001ċ\001Ţ\001ƫ\003ċ\001Ǥ\001ċ\001ş\005ċ\nǤ\001ċ\001Ǥ\001ċ\001Ǥ\001ċ\001Ǥ\001ċ\001Ǥ$ċ\001Ţ\001\000\002ċ\001\000\002ċ\001ş8ċ\001Č\001ǥ\001Č\001ţ\001ƭ\003Č\001ǥ\002Č\001ş\004Č\nǥ\001Č\001ǥ\001Č\001ǥ\001Č\001ǥ\001Č\001ǥ$Č\001ţ\001\000\002Č\001\000\003Č\001ş7Č\002#\001\000\001O\001~\005#\006\000\032#\r\000\002#\001\000\002#\007\000\002#\001\000\001V\001È\003(\002#\006\000\b#\001W\021#\r\000\001#\001(\001\000\002#\007\000\002#\001\000\001T\001Ê\003'\002#\006\000\022#\001U\007#\r\000\001#\001'\001\000\002#\007\000\002#\001\000\001a\001Ë\003.\002#\006\000\022#\001b\003#\0011\003#\r\000\001#\001.\001\000\002#\007\000\002#\001\000\001X\001Ì\003)\002#\006\000\022#\001Y\005#\001Z\001#\r\000\001#\001)\001\000\002#\007\000\002#\001\000\001[\001Í\003*\002#\006\000\025#\0010\004#\r\000\001#\001*\001\000\002#\007\000\002#\001\000\001\\\001Î\003+\002#\006\000\031#\001]\r\000\001#\001+\001\000\002#\007\000\002#\001\000\001^\001Ï\003,\002#\006\000\023#\001_\006#\r\000\001#\001,\001\000\002#\007\000\002#\001\000\001`\001Ð\003-\002#\006\000\f#\001+\r#\r\000\001#\001-\001\000\002#\007\000\002#\001\000\001g\001Ñ\0030\002#\006\000\001h\031#\r\000\001#\0010\001\000\002#\007\000\002#\001\000\001c\001Ó\003/\002#\006\000\005#\001d\021#\001e\001f\001#\r\000\001#\001/\001\000\002#\007\000\002#\001\000\001O\001Õ\0031\002#\006\000\032#\r\000\001#\0011\001\000\002#\007\000\002#\001\000\001\001~\005#\006\000\n#\001\017#\r\000\002#\001\000\002#\007\000\002#\001\000\001¦\001~\005#\006\000\007#\001\022#\r\000\002#\001\000\002#\007\000\001#\001Ʈ\001\000\001O\001~\003#\001Ʈ\001#\006\000\007Ʈ\001Ǧ\002Ʈ\001#\001Ʈ\001#\001Ʈ\001#\001Ʈ\001#\001Ʈ\b#\r\000\002#\001\000\002#\007\000\001#\001Ʈ\001\000\001O\001Ĥ\003U\001Ʈ\001#\006\000\nƮ\001#\001Ʈ\001#\001Ʈ\001#\001Ʈ\001#\001Ʈ\b#\r\000\001#\001U\001\000\002#\007\000\001#\001Ʈ\001\000\001O\001~\003#\001Ʈ\001#\006\000\tƮ\001ǧ\001#\001Ʈ\001#\001Ʈ\001#\001Ʈ\001#\001Ʈ\b#\r\000\002#\001\000\002#\007\000\001#\001Ʈ\001\000\001\001Ĩ\003W\001Ʈ\001#\006\000\nƮ\001\001Ʈ\001#\001Ʈ\001#\001Ʈ\001#\001Ʈ\b#\r\000\001#\001W\001\000\002#\007\000\001#\001Ť\001\000\001O\001~\003#\001Ť\001#\006\000\002Ť\001Ǩ\001Ť\001Ǩ\005Ť\001#\001Ť\001#\001Ť\001#\001Ť\001#\001Ť\b#\r\000\002#\001\000\002#\007\000\001#\001Ť\001\000\001O\001~\003#\001Ť\001#\006\000\nŤ\001#\001ǩ\001#\001Ť\001#\001Ť\001#\001Ť\b#\r\000\002#\001\000\002#\007\000\001#\001Ť\001\000\001O\001ſ\003\001Ť\001#\006\000\nŤ\001#\001Ť\001#\001Ť\001#\001Ť\001#\001Ť\b#\r\000\001#\001\001\000\002#\007\000\001#\001Ʈ\001\000\001O\001~\003#\001Ʈ\001#\006\000\007Ʈ\001Ǫ\002Ʈ\001#\001Ʈ\001#\001Ʈ\001#\001Ʈ\001#\001Ʈ\b#\r\000\002#\001\000\002#\007\000\001#\001Ʈ\001\000\001O\001~\003#\001Ʈ\001#\006\000\nƮ\001#\001Ʈ\001#\001ǫ\001#\001Ʈ\001#\001Ʈ\b#\r\000\002#\001\000\002#\007\000\001#\001Ʈ\001\000\001O\001ı\003Y\001Ʈ\001#\006\000\nƮ\001#\001Ʈ\001#\001Ʈ\001#\001Ʈ\001#\001Ʈ\b#\r\000\001#\001Y\001\000\002#\007\000\001#\001Ʈ\001\000\001O\001Ĳ\003Z\001Ʈ\001#\006\000\nƮ\001#\001Ʈ\001#\001Ʈ\001#\001Ʈ\001#\001Ʈ\b#\r\000\001#\001Z\001\000\002#\007\000\001#\001Ʒ\001\000\001O\001~\003#\001Ʈ\001#\006\000\nƮ\001#\001Ʈ\001#\001Ʈ\001#\001Ʈ\001#\001Ʈ\b#\r\000\002#\001\000\002#\007\000\001#\001Ʈ\001\000\001O\001~\003#\001Ʈ\001#\006\000\001Ǭ\tƮ\001#\001Ʈ\001#\001Ʈ\001#\001Ʈ\001#\001Ʈ\b#\r\000\002#\001\000\002#\007\000\001#\001Ʈ\001\000\001O\001ĸ\003]\001Ʈ\001#\006\000\nƮ\001#\001Ʈ\001#\001Ʈ\001#\001Ʈ\001#\001Ʈ\b#\r\000\001#\001]\001\000\002#\007\000\001#\001Ʈ\001\000\001O\001~\003#\001Ʈ\001#\006\000\bƮ\001ǭ\001Ʈ\001#\001Ʈ\001#\001Ʈ\001#\001Ʈ\001#\001Ʈ\b#\r\000\002#\001\000\002#\007\000\001#\001Ʈ\001\000\001O\001ļ\003_\001Ʈ\001#\006\000\nƮ\001#\001Ʈ\001#\001Ʈ\001#\001Ʈ\001#\001Ʈ\b#\r\000\001#\001_\001\000\002#\007\000\001#\001Ʈ\001\000\001O\001~\003#\001Ʈ\001#\006\000\nƮ\001#\001Ʈ\001#\001ƴ\001#\001Ʈ\001#\001Ʈ\b#\r\000\002#\001\000\002#\007\000\001#\001Ʈ\001\000\001O\001~\003#\001Ʈ\001#\006\000\007Ʈ\001Ǯ\002Ʈ\001#\001Ʈ\001#\001Ʈ\001#\001Ʈ\001#\001Ʈ\b#\r\000\002#\001\000\002#\007\000\001#\001Ʈ\001\000\001O\001~\003#\001Ʈ\001#\006\000\006Ʈ\001ƹ\003Ʈ\001#\001Ʈ\001#\001Ʈ\001#\001Ʈ\001#\001Ʈ\b#\r\000\002#\001\000\002#\007\000\001#\001Ʈ\001\000\001O\001Ń\003b\001Ʈ\001#\006\000\nƮ\001#\001Ʈ\001#\001Ʈ\001#\001Ʈ\001#\001Ʈ\b#\r\000\001#\001b\001\000\002#\007\000\001#\001Ʈ\001\000\001O\001~\003#\001Ʈ\001#\006\000\006Ʈ\001ǯ\003Ʈ\001#\001Ʈ\001#\001Ʈ\001#\001Ʈ\001#\001Ʈ\b#\r\000\002#\001\000\002#\007\000\001#\001Ʈ\001\000\001O\001~\003#\001Ʈ\001#\006\000\002Ʈ\001ǰ\007Ʈ\001#\001Ʈ\001#\001Ǳ\001#\001Ʈ\001#\001Ʈ\b#\r\000\002#\001\000\002#\007\000\001#\001Ʈ\001\000\001O\001Ŋ\003d\001Ʈ\001#\006\000\nƮ\001#\001Ʈ\001#\001Ʈ\001#\001Ʈ\001#\001Ʈ\b#\r\000\001#\001d\001\000\002#\007\000\001#\001Ʈ\001\000\001O\001ŋ\003e\001Ʈ\001#\006\000\nƮ\001#\001Ʈ\001#\001Ʈ\001#\001Ʈ\001#\001Ʈ\b#\r\000\001#\001e\001\000\002#\007\000\001#\001Ʈ\001\000\001O\001Ō\003f\001Ʈ\001#\006\000\nƮ\001#\001Ʈ\001#\001Ʈ\001#\001Ʈ\001#\001Ʈ\b#\r\000\001#\001f\001\000\002#\007\000\001#\001Ʈ\001\000\001O\001~\003#\001Ʈ\001#\006\000\003Ʈ\001ǲ\006Ʈ\001#\001Ʈ\001#\001Ʈ\001#\001Ʈ\001#\001Ʈ\b#\r\000\002#\001\000\002#\007\000\001#\001Ʈ\001\000\001¦\001Ő\003h\001Ʈ\001#\006\000\007Ʈ\001ƽ\002Ʈ\001#\001Ʈ\001#\001Ʈ\001#\001Ʈ\001#\001Ʈ\b#\r\000\001#\001h\001\000\002#\007\000\001#\001Ť\001\000\001O\001~\003#\001Ť\001#\006\000\002Ť\001ǳ\001Ť\001ǳ\005Ť\001#\001Ť\001#\001Ť\001#\001Ť\001#\001Ť\b#\r\000\002#\001\000\002#\007\000\001#\001Ť\001\000\001O\001~\003#\001Ť\001#\006\000\002Ť\001ǩ\007Ť\001#\001Ť\001#\001Ť\001#\001Ť\001#\001Ť\b#\r\000\002#\001\000\002#\007\000\003\b\0015\001m\005\b\00168\b\003\t\0017\001o\006\t\00167\t#\000\001Ǵ\037\000\002C\001\000\001D\001¯\005C\006\000\032C\r\000\002C\001\000\002C\007\000\002E\001\000\001F\001±\005E\006\000\032E\r\000\002E\001\000\002E\007\000\002E\001\000\001F\004\000\002E\006\000\005E\001ǵ\024E\r\000\001E\002\000\002E\007\000\002E\001\000\001F\004\000\002E\006\000\032E\r\000\001E\001Ƕ\001\000\002E\007\000\002E\001\000\001F\004\000\002E\006\000\005E\001Ƿ\024E\r\000\001E\002\000\002E\007\000\001Ĉ\001Ǹ\001\000\001ĉ\001Ʃ\003Ĉ\001Ǹ\001Ĉ\002\000\004Ĉ\nǸ\001Ĉ\001Ǹ\001Ĉ\001Ǹ\001Ĉ\001Ǹ\001Ĉ\001Ǹ\032Ĉ\001\000\001č\005Ĉ\001ċ\001ǹ\001ċ\001Ţ\001ƫ\003ċ\001ǹ\001ċ\001ş\005ċ\nǹ\001ċ\001ǹ\001ċ\001ǹ\001ċ\001ǹ\001ċ\001ǹ!ċ\001Č\001Ǻ\001Č\001ţ\001ƭ\003Č\001Ǻ\002Č\001ş\004Č\nǺ\001Č\001Ǻ\001Č\001Ǻ\001Č\001Ǻ\001Č\001Ǻ!Č\002#\001\000\001O\001Ĥ\003U\002#\006\000\032#\r\000\001#\001U\001\000\002#\007\000\002#\001\000\001\001Ĩ\003W\002#\006\000\n#\001\017#\r\000\001#\001W\001\000\002#\007\000\001#\001Ʈ\001\000\001O\001~\003#\001Ʈ\001#\006\000\nƮ\001#\001ǻ\001#\001Ʈ\001#\001Ʈ\001#\001Ʈ\b#\r\000\002#\001\000\002#\007\000\001#\001Ʈ\001\000\001O\001ſ\003\001Ʈ\001#\006\000\nƮ\001#\001Ʈ\001#\001Ʈ\001#\001Ʈ\001#\001Ʈ\b#\r\000\001#\001\001\000\002#\007\000\002#\001\000\001O\001ı\003Y\002#\006\000\032#\r\000\001#\001Y\001\000\002#\007\000\002#\001\000\001O\001Ĳ\003Z\002#\006\000\032#\r\000\001#\001Z\001\000\002#\007\000\002#\001\000\001O\001ĸ\003]\002#\006\000\032#\r\000\001#\001]\001\000\002#\007\000\002#\001\000\001O\001ļ\003_\002#\006\000\032#\r\000\001#\001_\001\000\002#\007\000\002#\001\000\001O\001Ń\003b\002#\006\000\032#\r\000\001#\001b\001\000\002#\007\000\002#\001\000\001O\001Ŋ\003d\002#\006\000\032#\r\000\001#\001d\001\000\002#\007\000\002#\001\000\001O\001ŋ\003e\002#\006\000\032#\r\000\001#\001e\001\000\002#\007\000\002#\001\000\001O\001Ō\003f\002#\006\000\032#\r\000\001#\001f\001\000\002#\007\000\002#\001\000\001¦\001Ő\003h\002#\006\000\007#\001\022#\r\000\001#\001h\001\000\002#\007\000\001#\001Ʈ\001\000\001O\001~\003#\001Ʈ\001#\006\000\002Ʈ\001ǻ\007Ʈ\001#\001Ʈ\001#\001Ʈ\001#\001Ʈ\001#\001Ʈ\b#\r\000\002#\001\000\002#.\000\001Ǽ\033\000\002E\001\000\001F\004\000\002E\006\000\bE\001ǽ\021E\r\000\001E\002\000\002E\007\000\002E\001\000\001F\004\000\002E\006\000\bE\001Ǿ\021E\r\000\001E\002\000\002E\007\000\001Ĉ\001ǿ\001\000\001ĉ\001Ʃ\003Ĉ\001ǿ\001Ĉ\002\000\004Ĉ\nǿ\001Ĉ\001ǿ\001Ĉ\001ǿ\001Ĉ\001ǿ\001Ĉ\001ǿ\032Ĉ\001\000\001č\005Ĉ\001ċ\001Ȁ\001ċ\001Ţ\001ƫ\003ċ\001Ȁ\001ċ\001ş\005ċ\nȀ\001ċ\001Ȁ\001ċ\001Ȁ\001ċ\001Ȁ\001ċ\001Ȁ!ċ\001Č\001ȁ\001Č\001ţ\001ƭ\003Č\001ȁ\002Č\001ş\004Č\nȁ\001Č\001ȁ\001Č\001ȁ\001Č\001ȁ\001Č\001ȁ!Č\002#\001\000\001O\001ſ\003\002#\006\000\032#\r\000\001#\001\001\000\002#\007\000\001Ĉ\001Ȃ\001\000\001ĉ\001Ʃ\003Ĉ\001Ȃ\001Ĉ\002\000\004Ĉ\nȂ\001Ĉ\001Ȃ\001Ĉ\001Ȃ\001Ĉ\001Ȃ\001Ĉ\001Ȃ\032Ĉ\001\000\001č\005Ĉ\001ċ\001ȃ\001ċ\001Ţ\001ƫ\003ċ\001ȃ\001ċ\001ş\005ċ\nȃ\001ċ\001ȃ\001ċ\001ȃ\001ċ\001ȃ\001ċ\001ȃ!ċ\001Č\001Ȅ\001Č\001ţ\001ƭ\003Č\001Ȅ\002Č\001ş\004Č\nȄ\001Č\001Ȅ\001Č\001Ȅ\001Č\001Ȅ\001Č\001Ȅ!Č\002Ĉ\001\000\001ĉ\001Ʃ\005Ĉ\002\0000Ĉ\001\000\001č\005Ĉ\001ċ\001ȅ\001ċ\001Ţ\001ƫ\003ċ\001ȅ\001ċ\001ş\005ċ\nȅ\001ċ\001ȅ\001ċ\001ȅ\001ċ\001ȅ\001ċ\001ȅ!ċ\001Č\001Ȇ\001Č\001ţ\001ƭ\003Č\001Ȇ\002Č\001ş\004Č\nȆ\001Č\001Ȇ\001Č\001Ȇ\001Č\001Ȇ\001Č\001Ȇ!Č\003ċ\001Ţ\001ƫ\005ċ\001ş8ċ\003Č\001ţ\001ƭ\006Č\001ş7Č", 0, arrayOfInt);
/* 1437 */     return arrayOfInt;
/*      */   }
/*      */   
/*      */   private static int c(String paramString, int paramInt, int[] paramArrayOfint) {
/* 1441 */     paramInt = 0;
/* 1442 */     byte b = 0;
/* 1443 */     int j = paramString.length();
/* 1444 */     label10: while (paramInt < j) {
/* 1445 */       char c1 = paramString.charAt(paramInt++);
/* 1446 */       char c2 = paramString.charAt(paramInt++);
/* 1447 */       c2--; while (true)
/* 1448 */       { paramArrayOfint[b++] = c2; if (--c1 <= '\000')
/*      */           continue label10;  } 
/* 1450 */     }  return b;
/*      */   }
/*      */ 
/*      */ 
/*      */ 
/*      */ 
/*      */ 
/*      */ 
/*      */ 
/*      */   
/* 1460 */   private static final String[] e = new String[] { "Unkown internal scanner error", "Error: could not match input", "Error: pushback value was too large" };
/*      */ 
/*      */ 
/*      */ 
/*      */ 
/*      */ 
/*      */ 
/*      */ 
/*      */   
/* 1469 */   private static final int[] f = h();
/*      */ 
/*      */ 
/*      */ 
/*      */   
/*      */   private Reader g;
/*      */ 
/*      */ 
/*      */ 
/*      */   
/*      */   private int h;
/*      */ 
/*      */ 
/*      */ 
/*      */ 
/*      */   
/*      */   private static int[] h() {
/* 1486 */     int[] arrayOfInt = new int[518];
/*      */     
/* 1488 */     d("\001\000\002\001\001\t\n\001\001\t\001\001\001\t\003\001\003\t\003\001\006\t\001\000\001\t\001\001\003\000\013\001\001\t\001\001\002\000\001\t\002\000\001\t\001\001\004\000\004\t\001\001\001\000\001\001\001\000\001\001\001\000\006\001\001\000\004\001\001\000\001\001\001\000\001\001\001\000\002\001\002\000\001\001\001\000\001\001\002\000\001\001\001\000\003\001\001\000\003\001\001\t\004\001\004\000\035\001\001\000\024\001\001\000\003\001\002\t\002\000Q\001\001\000\b\001\005\000\001\tI\001\001\000\007\001\002\000\001\001\002\000=\001\001\000\006\001\006\000/\001\001\000\005\001\003\000\016\001\001\000\001\001\001\t\001\001\003\000\001\001\001\t\002\001\b\000", 0, arrayOfInt);
/* 1489 */     return arrayOfInt;
/*      */   }
/*      */   
/*      */   private static int d(String paramString, int paramInt, int[] paramArrayOfint) {
/* 1493 */     paramInt = 0;
/* 1494 */     byte b = 0;
/* 1495 */     int j = paramString.length();
/* 1496 */     label10: while (paramInt < j) {
/* 1497 */       char c1 = paramString.charAt(paramInt++);
/* 1498 */       char c2 = paramString.charAt(paramInt++); while (true)
/* 1499 */       { paramArrayOfint[b++] = c2; if (--c1 <= '\000')
/*      */           continue label10;  } 
/* 1501 */     }  return b;
/*      */   }
/*      */ 
/*      */ 
/*      */ 
/*      */ 
/*      */ 
/*      */ 
/*      */ 
/*      */   
/* 1511 */   private int i = 0;
/*      */ 
/*      */ 
/*      */   
/* 1515 */   private char[] j = new char[16384];
/*      */ 
/*      */ 
/*      */ 
/*      */   
/*      */   private int k;
/*      */ 
/*      */ 
/*      */ 
/*      */   
/*      */   private int l;
/*      */ 
/*      */ 
/*      */ 
/*      */   
/*      */   private int m;
/*      */ 
/*      */ 
/*      */ 
/*      */   
/*      */   private int n;
/*      */ 
/*      */ 
/*      */ 
/*      */   
/*      */   private int o;
/*      */ 
/*      */ 
/*      */ 
/*      */   
/*      */   private int p;
/*      */ 
/*      */ 
/*      */   
/*      */   private boolean q;
/*      */ 
/*      */ 
/*      */ 
/*      */   
/*      */   public final int a() {
/* 1555 */     return this.p;
/*      */   }
/*      */   
/*      */   public final void a(int paramInt) {
/* 1559 */     this.p = 0;
/*      */   }
/*      */ 
/*      */ 
/*      */ 
/*      */ 
/*      */ 
/*      */ 
/*      */ 
/*      */   
/*      */   i(Reader paramReader) {
/* 1570 */     this.g = paramReader;
/*      */   }
/*      */ 
/*      */ 
/*      */ 
/*      */ 
/*      */ 
/*      */ 
/*      */ 
/*      */ 
/*      */ 
/*      */ 
/*      */ 
/*      */ 
/*      */ 
/*      */ 
/*      */ 
/*      */ 
/*      */   
/*      */   private static char[] a(String paramString) {
/* 1590 */     char[] arrayOfChar = new char[65536];
/* 1591 */     byte b1 = 0;
/* 1592 */     byte b2 = 0;
/* 1593 */     label10: while (b1 < 'Ì') {
/* 1594 */       char c1 = paramString.charAt(b1++);
/* 1595 */       char c2 = paramString.charAt(b1++); while (true)
/* 1596 */       { arrayOfChar[b2++] = c2; if (--c1 <= '\000')
/*      */           continue label10;  } 
/* 1598 */     }  return arrayOfChar;
/*      */   }
/*      */ 
/*      */ 
/*      */ 
/*      */ 
/*      */ 
/*      */ 
/*      */ 
/*      */ 
/*      */ 
/*      */ 
/*      */   
/*      */   private boolean i() {
/* 1612 */     if (this.n > 0) {
/* 1613 */       System.arraycopy(this.j, this.n, this.j, 0, this.o - this.n);
/*      */ 
/*      */ 
/*      */ 
/*      */       
/* 1618 */       this.o -= this.n;
/* 1619 */       this.m -= this.n;
/* 1620 */       this.k -= this.n;
/* 1621 */       this.l -= this.n;
/* 1622 */       this.n = 0;
/*      */     } 
/*      */ 
/*      */     
/* 1626 */     if (this.m >= this.j.length) {
/*      */       
/* 1628 */       char[] arrayOfChar = new char[this.m << 1];
/* 1629 */       System.arraycopy(this.j, 0, arrayOfChar, 0, this.j.length);
/* 1630 */       this.j = arrayOfChar;
/*      */     } 
/*      */ 
/*      */     
/*      */     int j;
/*      */ 
/*      */     
/* 1637 */     if ((j = this.g.read(this.j, this.o, this.j.length - this.o)) < 0) {
/* 1638 */       return true;
/*      */     }
/*      */     
/* 1641 */     this.o += j;
/* 1642 */     return false;
/*      */   }
/*      */ 
/*      */ 
/*      */ 
/*      */ 
/*      */ 
/*      */ 
/*      */ 
/*      */ 
/*      */ 
/*      */ 
/*      */ 
/*      */ 
/*      */ 
/*      */ 
/*      */ 
/*      */ 
/*      */ 
/*      */ 
/*      */ 
/*      */ 
/*      */ 
/*      */ 
/*      */ 
/*      */ 
/*      */   
/*      */   public final void a(Reader paramReader) {
/* 1670 */     this.g = paramReader;
/*      */     
/* 1672 */     this.q = false;
/* 1673 */     this.o = this.n = 0;
/* 1674 */     this.m = this.k = this.l = 0;
/* 1675 */     this.p = 0;
/* 1676 */     this.i = 0;
/*      */   }
/*      */ 
/*      */ 
/*      */ 
/*      */ 
/*      */ 
/*      */ 
/*      */ 
/*      */ 
/*      */ 
/*      */ 
/*      */ 
/*      */ 
/*      */ 
/*      */ 
/*      */ 
/*      */ 
/*      */ 
/*      */ 
/*      */ 
/*      */ 
/*      */ 
/*      */ 
/*      */   
/*      */   public final String b() {
/* 1702 */     return new String(this.j, this.n, this.k - this.n);
/*      */   }
/*      */ 
/*      */ 
/*      */ 
/*      */ 
/*      */ 
/*      */ 
/*      */ 
/*      */ 
/*      */ 
/*      */ 
/*      */ 
/*      */ 
/*      */ 
/*      */ 
/*      */ 
/*      */ 
/*      */ 
/*      */ 
/*      */ 
/*      */ 
/*      */   
/*      */   public final int c() {
/* 1726 */     return this.k - this.n;
/*      */   }
/*      */ 
/*      */ 
/*      */ 
/*      */ 
/*      */ 
/*      */ 
/*      */ 
/*      */ 
/*      */ 
/*      */ 
/*      */ 
/*      */ 
/*      */ 
/*      */ 
/*      */ 
/*      */   
/*      */   private static void b(int paramInt) {
/*      */     String str;
/*      */     try {
/* 1747 */       str = e[1];
/*      */     }
/* 1749 */     catch (ArrayIndexOutOfBoundsException arrayIndexOutOfBoundsException) {
/* 1750 */       str = e[0];
/*      */     } 
/*      */     
/* 1753 */     throw new Error(str);
/*      */   }
/*      */   
/*      */   public final k d() {
/*      */     // Byte code:
/*      */     //   0: aload_0
/*      */     //   1: getfield o : I
/*      */     //   4: istore #5
/*      */     //   6: aload_0
/*      */     //   7: getfield j : [C
/*      */     //   10: astore #6
/*      */     //   12: getstatic com/d/c/d/i.a : [C
/*      */     //   15: astore #7
/*      */     //   17: getstatic com/d/c/d/i.d : [I
/*      */     //   20: astore #8
/*      */     //   22: getstatic com/d/c/d/i.c : [I
/*      */     //   25: astore #9
/*      */     //   27: getstatic com/d/c/d/i.f : [I
/*      */     //   30: astore #10
/*      */     //   32: aload_0
/*      */     //   33: getfield k : I
/*      */     //   36: istore #4
/*      */     //   38: iconst_0
/*      */     //   39: istore_1
/*      */     //   40: aload_0
/*      */     //   41: getfield n : I
/*      */     //   44: istore_3
/*      */     //   45: iload_3
/*      */     //   46: iload #4
/*      */     //   48: if_icmpge -> 173
/*      */     //   51: aload #6
/*      */     //   53: iload_3
/*      */     //   54: caload
/*      */     //   55: lookupswitch default -> 165, 10 -> 148, 11 -> 120, 12 -> 120, 13 -> 133, 133 -> 120, 8232 -> 120, 8233 -> 120
/*      */     //   120: aload_0
/*      */     //   121: dup
/*      */     //   122: getfield p : I
/*      */     //   125: iconst_1
/*      */     //   126: iadd
/*      */     //   127: putfield p : I
/*      */     //   130: goto -> 165
/*      */     //   133: aload_0
/*      */     //   134: dup
/*      */     //   135: getfield p : I
/*      */     //   138: iconst_1
/*      */     //   139: iadd
/*      */     //   140: putfield p : I
/*      */     //   143: iconst_1
/*      */     //   144: istore_1
/*      */     //   145: goto -> 167
/*      */     //   148: iload_1
/*      */     //   149: ifne -> 165
/*      */     //   152: aload_0
/*      */     //   153: dup
/*      */     //   154: getfield p : I
/*      */     //   157: iconst_1
/*      */     //   158: iadd
/*      */     //   159: putfield p : I
/*      */     //   162: goto -> 167
/*      */     //   165: iconst_0
/*      */     //   166: istore_1
/*      */     //   167: iinc #3, 1
/*      */     //   170: goto -> 45
/*      */     //   173: iload_1
/*      */     //   174: ifeq -> 272
/*      */     //   177: iload #4
/*      */     //   179: iload #5
/*      */     //   181: if_icmpge -> 204
/*      */     //   184: aload #6
/*      */     //   186: iload #4
/*      */     //   188: caload
/*      */     //   189: bipush #10
/*      */     //   191: if_icmpne -> 198
/*      */     //   194: iconst_1
/*      */     //   195: goto -> 199
/*      */     //   198: iconst_0
/*      */     //   199: istore #11
/*      */     //   201: goto -> 257
/*      */     //   204: aload_0
/*      */     //   205: getfield q : Z
/*      */     //   208: ifne -> 254
/*      */     //   211: aload_0
/*      */     //   212: invokespecial i : ()Z
/*      */     //   215: istore #11
/*      */     //   217: aload_0
/*      */     //   218: getfield o : I
/*      */     //   221: istore #5
/*      */     //   223: aload_0
/*      */     //   224: getfield k : I
/*      */     //   227: istore #4
/*      */     //   229: aload_0
/*      */     //   230: getfield j : [C
/*      */     //   233: astore #6
/*      */     //   235: iload #11
/*      */     //   237: ifne -> 254
/*      */     //   240: aload #6
/*      */     //   242: iload #4
/*      */     //   244: caload
/*      */     //   245: bipush #10
/*      */     //   247: if_icmpne -> 254
/*      */     //   250: iconst_1
/*      */     //   251: goto -> 255
/*      */     //   254: iconst_0
/*      */     //   255: istore #11
/*      */     //   257: iload #11
/*      */     //   259: ifeq -> 272
/*      */     //   262: aload_0
/*      */     //   263: dup
/*      */     //   264: getfield p : I
/*      */     //   267: iconst_1
/*      */     //   268: isub
/*      */     //   269: putfield p : I
/*      */     //   272: iconst_m1
/*      */     //   273: istore_2
/*      */     //   274: aload_0
/*      */     //   275: dup
/*      */     //   276: iload #4
/*      */     //   278: dup_x1
/*      */     //   279: putfield n : I
/*      */     //   282: dup_x1
/*      */     //   283: putfield m : I
/*      */     //   286: istore_3
/*      */     //   287: aload_0
/*      */     //   288: iconst_0
/*      */     //   289: putfield h : I
/*      */     //   292: iload_3
/*      */     //   293: iload #5
/*      */     //   295: if_icmplt -> 360
/*      */     //   298: aload_0
/*      */     //   299: getfield q : Z
/*      */     //   302: ifeq -> 310
/*      */     //   305: iconst_m1
/*      */     //   306: istore_1
/*      */     //   307: goto -> 433
/*      */     //   310: aload_0
/*      */     //   311: iload_3
/*      */     //   312: putfield m : I
/*      */     //   315: aload_0
/*      */     //   316: iload #4
/*      */     //   318: putfield k : I
/*      */     //   321: aload_0
/*      */     //   322: invokespecial i : ()Z
/*      */     //   325: istore #11
/*      */     //   327: aload_0
/*      */     //   328: getfield m : I
/*      */     //   331: istore_3
/*      */     //   332: aload_0
/*      */     //   333: getfield k : I
/*      */     //   336: istore #4
/*      */     //   338: aload_0
/*      */     //   339: getfield j : [C
/*      */     //   342: astore #6
/*      */     //   344: aload_0
/*      */     //   345: getfield o : I
/*      */     //   348: istore #5
/*      */     //   350: iload #11
/*      */     //   352: ifeq -> 360
/*      */     //   355: iconst_m1
/*      */     //   356: istore_1
/*      */     //   357: goto -> 433
/*      */     //   360: aload #6
/*      */     //   362: iload_3
/*      */     //   363: iinc #3, 1
/*      */     //   366: caload
/*      */     //   367: istore_1
/*      */     //   368: aload #8
/*      */     //   370: aload #9
/*      */     //   372: aload_0
/*      */     //   373: getfield h : I
/*      */     //   376: iaload
/*      */     //   377: aload #7
/*      */     //   379: iload_1
/*      */     //   380: caload
/*      */     //   381: iadd
/*      */     //   382: iaload
/*      */     //   383: dup
/*      */     //   384: istore #11
/*      */     //   386: iconst_m1
/*      */     //   387: if_icmpeq -> 433
/*      */     //   390: aload_0
/*      */     //   391: iload #11
/*      */     //   393: putfield h : I
/*      */     //   396: aload #10
/*      */     //   398: aload_0
/*      */     //   399: getfield h : I
/*      */     //   402: iaload
/*      */     //   403: dup
/*      */     //   404: istore #11
/*      */     //   406: iconst_1
/*      */     //   407: iand
/*      */     //   408: iconst_1
/*      */     //   409: if_icmpne -> 430
/*      */     //   412: aload_0
/*      */     //   413: getfield h : I
/*      */     //   416: istore_2
/*      */     //   417: iload_3
/*      */     //   418: istore #4
/*      */     //   420: iload #11
/*      */     //   422: bipush #8
/*      */     //   424: iand
/*      */     //   425: bipush #8
/*      */     //   427: if_icmpeq -> 433
/*      */     //   430: goto -> 292
/*      */     //   433: aload_0
/*      */     //   434: iload #4
/*      */     //   436: putfield k : I
/*      */     //   439: iload_2
/*      */     //   440: ifge -> 447
/*      */     //   443: iload_2
/*      */     //   444: goto -> 452
/*      */     //   447: getstatic com/d/c/d/i.b : [I
/*      */     //   450: iload_2
/*      */     //   451: iaload
/*      */     //   452: tableswitch default -> 1278, 1 -> 1131, 2 -> 1229, 3 -> 1075, 4 -> 1061, 5 -> 1093, 6 -> 1250, 7 -> 1054, 8 -> 1243, 9 -> 1110, 10 -> 998, 11 -> 1257, 12 -> 1100, 13 -> 1173, 14 -> 1159, 15 -> 914, 16 -> 1047, 17 -> 1180, 18 -> 1201, 19 -> 949, 20 -> 1208, 21 -> 1005, 22 -> 921, 23 -> 1166, 24 -> 1236, 25 -> 1194, 26 -> 1040, 27 -> 1222, 28 -> 1138, 29 -> 1271, 30 -> 963, 31 -> 1026, 32 -> 942, 33 -> 1086, 34 -> 1019, 35 -> 984, 36 -> 1264, 37 -> 1033, 38 -> 991, 39 -> 956, 40 -> 935, 41 -> 1124, 42 -> 977, 43 -> 1187, 44 -> 1145, 45 -> 1107, 46 -> 1215, 47 -> 900, 48 -> 1117, 49 -> 1068, 50 -> 970, 51 -> 1152, 52 -> 907, 53 -> 1012, 54 -> 928, 55 -> 904, 56 -> 911, 57 -> 918, 58 -> 925, 59 -> 932, 60 -> 939, 61 -> 946, 62 -> 953, 63 -> 960, 64 -> 967, 65 -> 974, 66 -> 981, 67 -> 988, 68 -> 995, 69 -> 1002, 70 -> 1009, 71 -> 1016, 72 -> 1023, 73 -> 1030, 74 -> 1037, 75 -> 1044, 76 -> 1051, 77 -> 1058, 78 -> 1065, 79 -> 1072, 80 -> 1083, 81 -> 1090, 82 -> 1097, 83 -> 1104, 84 -> 1107, 85 -> 1114, 86 -> 1121, 87 -> 1128, 88 -> 1135, 89 -> 1142, 90 -> 1149, 91 -> 1156, 92 -> 1163, 93 -> 1170, 94 -> 1177, 95 -> 1184, 96 -> 1191, 97 -> 1198, 98 -> 1205, 99 -> 1212, 100 -> 1219, 101 -> 1226, 102 -> 1233, 103 -> 1240, 104 -> 1247, 105 -> 1254, 106 -> 1261, 107 -> 1268, 108 -> 1275
/*      */     //   900: getstatic com/d/c/d/k.r : Lcom/d/c/d/k;
/*      */     //   903: areturn
/*      */     //   904: goto -> 32
/*      */     //   907: getstatic com/d/c/d/k.x : Lcom/d/c/d/k;
/*      */     //   910: areturn
/*      */     //   911: goto -> 32
/*      */     //   914: getstatic com/d/c/d/k.l : Lcom/d/c/d/k;
/*      */     //   917: areturn
/*      */     //   918: goto -> 32
/*      */     //   921: getstatic com/d/c/d/k.N : Lcom/d/c/d/k;
/*      */     //   924: areturn
/*      */     //   925: goto -> 32
/*      */     //   928: getstatic com/d/c/d/k.u : Lcom/d/c/d/k;
/*      */     //   931: areturn
/*      */     //   932: goto -> 32
/*      */     //   935: getstatic com/d/c/d/k.F : Lcom/d/c/d/k;
/*      */     //   938: areturn
/*      */     //   939: goto -> 32
/*      */     //   942: getstatic com/d/c/d/k.p : Lcom/d/c/d/k;
/*      */     //   945: areturn
/*      */     //   946: goto -> 32
/*      */     //   949: getstatic com/d/c/d/k.R : Lcom/d/c/d/k;
/*      */     //   952: areturn
/*      */     //   953: goto -> 32
/*      */     //   956: getstatic com/d/c/d/k.C : Lcom/d/c/d/k;
/*      */     //   959: areturn
/*      */     //   960: goto -> 32
/*      */     //   963: getstatic com/d/c/d/k.f : Lcom/d/c/d/k;
/*      */     //   966: areturn
/*      */     //   967: goto -> 32
/*      */     //   970: getstatic com/d/c/d/k.q : Lcom/d/c/d/k;
/*      */     //   973: areturn
/*      */     //   974: goto -> 32
/*      */     //   977: getstatic com/d/c/d/k.A : Lcom/d/c/d/k;
/*      */     //   980: areturn
/*      */     //   981: goto -> 32
/*      */     //   984: getstatic com/d/c/d/k.y : Lcom/d/c/d/k;
/*      */     //   987: areturn
/*      */     //   988: goto -> 32
/*      */     //   991: getstatic com/d/c/d/k.D : Lcom/d/c/d/k;
/*      */     //   994: areturn
/*      */     //   995: goto -> 32
/*      */     //   998: getstatic com/d/c/d/k.k : Lcom/d/c/d/k;
/*      */     //   1001: areturn
/*      */     //   1002: goto -> 32
/*      */     //   1005: getstatic com/d/c/d/k.V : Lcom/d/c/d/k;
/*      */     //   1008: areturn
/*      */     //   1009: goto -> 32
/*      */     //   1012: getstatic com/d/c/d/k.v : Lcom/d/c/d/k;
/*      */     //   1015: areturn
/*      */     //   1016: goto -> 32
/*      */     //   1019: getstatic com/d/c/d/k.B : Lcom/d/c/d/k;
/*      */     //   1022: areturn
/*      */     //   1023: goto -> 32
/*      */     //   1026: getstatic com/d/c/d/k.g : Lcom/d/c/d/k;
/*      */     //   1029: areturn
/*      */     //   1030: goto -> 32
/*      */     //   1033: getstatic com/d/c/d/k.I : Lcom/d/c/d/k;
/*      */     //   1036: areturn
/*      */     //   1037: goto -> 32
/*      */     //   1040: getstatic com/d/c/d/k.m : Lcom/d/c/d/k;
/*      */     //   1043: areturn
/*      */     //   1044: goto -> 32
/*      */     //   1047: getstatic com/d/c/d/k.T : Lcom/d/c/d/k;
/*      */     //   1050: areturn
/*      */     //   1051: goto -> 32
/*      */     //   1054: getstatic com/d/c/d/k.Q : Lcom/d/c/d/k;
/*      */     //   1057: areturn
/*      */     //   1058: goto -> 32
/*      */     //   1061: getstatic com/d/c/d/k.a : Lcom/d/c/d/k;
/*      */     //   1064: areturn
/*      */     //   1065: goto -> 32
/*      */     //   1068: getstatic com/d/c/d/k.s : Lcom/d/c/d/k;
/*      */     //   1071: areturn
/*      */     //   1072: goto -> 32
/*      */     //   1075: aload_0
/*      */     //   1076: invokevirtual b : ()Ljava/lang/String;
/*      */     //   1079: invokestatic a : (Ljava/lang/String;)Lcom/d/c/d/k;
/*      */     //   1082: areturn
/*      */     //   1083: goto -> 32
/*      */     //   1086: getstatic com/d/c/d/k.w : Lcom/d/c/d/k;
/*      */     //   1089: areturn
/*      */     //   1090: goto -> 32
/*      */     //   1093: getstatic com/d/c/d/k.S : Lcom/d/c/d/k;
/*      */     //   1096: areturn
/*      */     //   1097: goto -> 32
/*      */     //   1100: getstatic com/d/c/d/k.Z : Lcom/d/c/d/k;
/*      */     //   1103: areturn
/*      */     //   1104: goto -> 32
/*      */     //   1107: goto -> 32
/*      */     //   1110: getstatic com/d/c/d/k.W : Lcom/d/c/d/k;
/*      */     //   1113: areturn
/*      */     //   1114: goto -> 32
/*      */     //   1117: getstatic com/d/c/d/k.M : Lcom/d/c/d/k;
/*      */     //   1120: areturn
/*      */     //   1121: goto -> 32
/*      */     //   1124: getstatic com/d/c/d/k.E : Lcom/d/c/d/k;
/*      */     //   1127: areturn
/*      */     //   1128: goto -> 32
/*      */     //   1131: getstatic com/d/c/d/k.o : Lcom/d/c/d/k;
/*      */     //   1134: areturn
/*      */     //   1135: goto -> 32
/*      */     //   1138: getstatic com/d/c/d/k.d : Lcom/d/c/d/k;
/*      */     //   1141: areturn
/*      */     //   1142: goto -> 32
/*      */     //   1145: getstatic com/d/c/d/k.G : Lcom/d/c/d/k;
/*      */     //   1148: areturn
/*      */     //   1149: goto -> 32
/*      */     //   1152: getstatic com/d/c/d/k.t : Lcom/d/c/d/k;
/*      */     //   1155: areturn
/*      */     //   1156: goto -> 32
/*      */     //   1159: getstatic com/d/c/d/k.j : Lcom/d/c/d/k;
/*      */     //   1162: areturn
/*      */     //   1163: goto -> 32
/*      */     //   1166: getstatic com/d/c/d/k.J : Lcom/d/c/d/k;
/*      */     //   1169: areturn
/*      */     //   1170: goto -> 32
/*      */     //   1173: getstatic com/d/c/d/k.i : Lcom/d/c/d/k;
/*      */     //   1176: areturn
/*      */     //   1177: goto -> 32
/*      */     //   1180: getstatic com/d/c/d/k.O : Lcom/d/c/d/k;
/*      */     //   1183: areturn
/*      */     //   1184: goto -> 32
/*      */     //   1187: getstatic com/d/c/d/k.c : Lcom/d/c/d/k;
/*      */     //   1190: areturn
/*      */     //   1191: goto -> 32
/*      */     //   1194: getstatic com/d/c/d/k.K : Lcom/d/c/d/k;
/*      */     //   1197: areturn
/*      */     //   1198: goto -> 32
/*      */     //   1201: getstatic com/d/c/d/k.P : Lcom/d/c/d/k;
/*      */     //   1204: areturn
/*      */     //   1205: goto -> 32
/*      */     //   1208: getstatic com/d/c/d/k.U : Lcom/d/c/d/k;
/*      */     //   1211: areturn
/*      */     //   1212: goto -> 32
/*      */     //   1215: getstatic com/d/c/d/k.b : Lcom/d/c/d/k;
/*      */     //   1218: areturn
/*      */     //   1219: goto -> 32
/*      */     //   1222: getstatic com/d/c/d/k.h : Lcom/d/c/d/k;
/*      */     //   1225: areturn
/*      */     //   1226: goto -> 32
/*      */     //   1229: getstatic com/d/c/d/k.L : Lcom/d/c/d/k;
/*      */     //   1232: areturn
/*      */     //   1233: goto -> 32
/*      */     //   1236: getstatic com/d/c/d/k.H : Lcom/d/c/d/k;
/*      */     //   1239: areturn
/*      */     //   1240: goto -> 32
/*      */     //   1243: getstatic com/d/c/d/k.Y : Lcom/d/c/d/k;
/*      */     //   1246: areturn
/*      */     //   1247: goto -> 32
/*      */     //   1250: getstatic com/d/c/d/k.n : Lcom/d/c/d/k;
/*      */     //   1253: areturn
/*      */     //   1254: goto -> 32
/*      */     //   1257: getstatic com/d/c/d/k.X : Lcom/d/c/d/k;
/*      */     //   1260: areturn
/*      */     //   1261: goto -> 32
/*      */     //   1264: getstatic com/d/c/d/k.z : Lcom/d/c/d/k;
/*      */     //   1267: areturn
/*      */     //   1268: goto -> 32
/*      */     //   1271: getstatic com/d/c/d/k.e : Lcom/d/c/d/k;
/*      */     //   1274: areturn
/*      */     //   1275: goto -> 32
/*      */     //   1278: iload_1
/*      */     //   1279: iconst_m1
/*      */     //   1280: if_icmpne -> 1303
/*      */     //   1283: aload_0
/*      */     //   1284: getfield n : I
/*      */     //   1287: aload_0
/*      */     //   1288: getfield m : I
/*      */     //   1291: if_icmpne -> 1303
/*      */     //   1294: aload_0
/*      */     //   1295: iconst_1
/*      */     //   1296: putfield q : Z
/*      */     //   1299: getstatic com/d/c/d/k.aa : Lcom/d/c/d/k;
/*      */     //   1302: areturn
/*      */     //   1303: iconst_1
/*      */     //   1304: invokestatic b : (I)V
/*      */     //   1307: goto -> 32
/*      */     // Line number table:
/*      */     //   Java source line number -> byte code offset
/*      */     //   #1787	-> 0
/*      */     //   #1788	-> 6
/*      */     //   #1789	-> 12
/*      */     //   #1791	-> 17
/*      */     //   #1792	-> 22
/*      */     //   #1793	-> 27
/*      */     //   #1796	-> 32
/*      */     //   #1798	-> 38
/*      */     //   #1799	-> 40
/*      */     //   #1801	-> 51
/*      */     //   #1807	-> 120
/*      */     //   #1809	-> 130
/*      */     //   #1811	-> 133
/*      */     //   #1812	-> 143
/*      */     //   #1813	-> 145
/*      */     //   #1815	-> 148
/*      */     //   #1818	-> 152
/*      */     //   #1820	-> 162
/*      */     //   #1822	-> 165
/*      */     //   #1800	-> 167
/*      */     //   #1826	-> 173
/*      */     //   #1829	-> 177
/*      */     //   #1830	-> 184
/*      */     //   #1831	-> 204
/*      */     //   #1834	-> 211
/*      */     //   #1835	-> 217
/*      */     //   #1836	-> 223
/*      */     //   #1837	-> 229
/*      */     //   #1838	-> 235
/*      */     //   #1841	-> 240
/*      */     //   #1843	-> 257
/*      */     //   #1845	-> 272
/*      */     //   #1847	-> 274
/*      */     //   #1849	-> 287
/*      */     //   #1855	-> 292
/*      */     //   #1857	-> 298
/*      */     //   #1858	-> 305
/*      */     //   #1859	-> 307
/*      */     //   #1863	-> 310
/*      */     //   #1864	-> 315
/*      */     //   #1865	-> 321
/*      */     //   #1867	-> 327
/*      */     //   #1868	-> 332
/*      */     //   #1869	-> 338
/*      */     //   #1870	-> 344
/*      */     //   #1871	-> 350
/*      */     //   #1872	-> 355
/*      */     //   #1873	-> 357
/*      */     //   #1876	-> 360
/*      */     //   #1879	-> 368
/*      */     //   #1880	-> 384
/*      */     //   #1881	-> 390
/*      */     //   #1883	-> 396
/*      */     //   #1884	-> 404
/*      */     //   #1885	-> 412
/*      */     //   #1886	-> 417
/*      */     //   #1887	-> 420
/*      */     //   #1890	-> 430
/*      */     //   #1894	-> 433
/*      */     //   #1896	-> 439
/*      */     //   #1898	-> 900
/*      */     //   #1900	-> 904
/*      */     //   #1902	-> 907
/*      */     //   #1904	-> 911
/*      */     //   #1906	-> 914
/*      */     //   #1908	-> 918
/*      */     //   #1910	-> 921
/*      */     //   #1912	-> 925
/*      */     //   #1914	-> 928
/*      */     //   #1916	-> 932
/*      */     //   #1918	-> 935
/*      */     //   #1920	-> 939
/*      */     //   #1922	-> 942
/*      */     //   #1924	-> 946
/*      */     //   #1926	-> 949
/*      */     //   #1928	-> 953
/*      */     //   #1930	-> 956
/*      */     //   #1932	-> 960
/*      */     //   #1934	-> 963
/*      */     //   #1936	-> 967
/*      */     //   #1938	-> 970
/*      */     //   #1940	-> 974
/*      */     //   #1942	-> 977
/*      */     //   #1944	-> 981
/*      */     //   #1946	-> 984
/*      */     //   #1948	-> 988
/*      */     //   #1950	-> 991
/*      */     //   #1952	-> 995
/*      */     //   #1954	-> 998
/*      */     //   #1956	-> 1002
/*      */     //   #1958	-> 1005
/*      */     //   #1960	-> 1009
/*      */     //   #1962	-> 1012
/*      */     //   #1964	-> 1016
/*      */     //   #1966	-> 1019
/*      */     //   #1968	-> 1023
/*      */     //   #1970	-> 1026
/*      */     //   #1972	-> 1030
/*      */     //   #1974	-> 1033
/*      */     //   #1976	-> 1037
/*      */     //   #1978	-> 1040
/*      */     //   #1980	-> 1044
/*      */     //   #1982	-> 1047
/*      */     //   #1984	-> 1051
/*      */     //   #1986	-> 1054
/*      */     //   #1988	-> 1058
/*      */     //   #1990	-> 1061
/*      */     //   #1992	-> 1065
/*      */     //   #1994	-> 1068
/*      */     //   #1996	-> 1072
/*      */     //   #1998	-> 1075
/*      */     //   #2000	-> 1083
/*      */     //   #2002	-> 1086
/*      */     //   #2004	-> 1090
/*      */     //   #2006	-> 1093
/*      */     //   #2008	-> 1097
/*      */     //   #2010	-> 1100
/*      */     //   #2012	-> 1104
/*      */     //   #2016	-> 1107
/*      */     //   #2018	-> 1110
/*      */     //   #2020	-> 1114
/*      */     //   #2022	-> 1117
/*      */     //   #2024	-> 1121
/*      */     //   #2026	-> 1124
/*      */     //   #2028	-> 1128
/*      */     //   #2030	-> 1131
/*      */     //   #2032	-> 1135
/*      */     //   #2034	-> 1138
/*      */     //   #2036	-> 1142
/*      */     //   #2038	-> 1145
/*      */     //   #2040	-> 1149
/*      */     //   #2042	-> 1152
/*      */     //   #2044	-> 1156
/*      */     //   #2046	-> 1159
/*      */     //   #2048	-> 1163
/*      */     //   #2050	-> 1166
/*      */     //   #2052	-> 1170
/*      */     //   #2054	-> 1173
/*      */     //   #2056	-> 1177
/*      */     //   #2058	-> 1180
/*      */     //   #2060	-> 1184
/*      */     //   #2062	-> 1187
/*      */     //   #2064	-> 1191
/*      */     //   #2066	-> 1194
/*      */     //   #2068	-> 1198
/*      */     //   #2070	-> 1201
/*      */     //   #2072	-> 1205
/*      */     //   #2074	-> 1208
/*      */     //   #2076	-> 1212
/*      */     //   #2078	-> 1215
/*      */     //   #2080	-> 1219
/*      */     //   #2082	-> 1222
/*      */     //   #2084	-> 1226
/*      */     //   #2086	-> 1229
/*      */     //   #2088	-> 1233
/*      */     //   #2090	-> 1236
/*      */     //   #2092	-> 1240
/*      */     //   #2094	-> 1243
/*      */     //   #2096	-> 1247
/*      */     //   #2098	-> 1250
/*      */     //   #2100	-> 1254
/*      */     //   #2102	-> 1257
/*      */     //   #2104	-> 1261
/*      */     //   #2106	-> 1264
/*      */     //   #2108	-> 1268
/*      */     //   #2110	-> 1271
/*      */     //   #2112	-> 1275
/*      */     //   #2114	-> 1278
/*      */     //   #2115	-> 1294
/*      */     //   #2117	-> 1299
/*      */     //   #2121	-> 1303
/*      */     //   #2124	-> 1307
/*      */   }
/*      */ }


/* Location:              C:\Program Files (x86)\Steam\steamapps\common\Infinitode 2\infinitode-2.jar!\com\d\c\d\i.class
 * Java compiler version: 8 (52.0)
 * JD-Core Version:       1.1.3
 */