/*      */ package b.a.a;
/*      */ 
/*      */ 
/*      */ 
/*      */ 
/*      */ 
/*      */ 
/*      */ 
/*      */ 
/*      */ 
/*      */ 
/*      */ 
/*      */ 
/*      */ 
/*      */ 
/*      */ 
/*      */ 
/*      */ 
/*      */ 
/*      */ 
/*      */ 
/*      */ 
/*      */ 
/*      */ 
/*      */ 
/*      */ 
/*      */ 
/*      */ 
/*      */ 
/*      */ 
/*      */ public final class k
/*      */   implements f
/*      */ {
/*      */   private int[] a;
/*   35 */   private int b = 0;
/*      */ 
/*      */ 
/*      */ 
/*      */   
/*      */   private int[] c;
/*      */ 
/*      */ 
/*      */ 
/*      */   
/*      */   private float[][][] d;
/*      */ 
/*      */ 
/*      */ 
/*      */   
/*      */   private float[][][] e;
/*      */ 
/*      */ 
/*      */ 
/*      */   
/*      */   private float[] f;
/*      */ 
/*      */ 
/*      */ 
/*      */   
/*      */   private float[][] g;
/*      */ 
/*      */ 
/*      */ 
/*      */   
/*      */   private float[][] h;
/*      */ 
/*      */ 
/*      */ 
/*      */   
/*      */   private int[] i;
/*      */ 
/*      */ 
/*      */   
/*      */   private b j;
/*      */ 
/*      */ 
/*      */   
/*      */   private g k;
/*      */ 
/*      */ 
/*      */   
/*      */   private n l;
/*      */ 
/*      */ 
/*      */   
/*      */   private n m;
/*      */ 
/*      */ 
/*      */   
/*      */   private m n;
/*      */ 
/*      */ 
/*      */   
/*      */   private int o;
/*      */ 
/*      */ 
/*      */   
/*      */   private a p;
/*      */ 
/*      */ 
/*      */   
/*      */   private a q;
/*      */ 
/*      */ 
/*      */   
/*      */   private f[] r;
/*      */ 
/*      */ 
/*      */   
/*      */   private f[] s;
/*      */ 
/*      */ 
/*      */   
/*      */   private int t;
/*      */ 
/*      */ 
/*      */   
/*      */   private int u;
/*      */ 
/*      */ 
/*      */   
/*      */   private int v;
/*      */ 
/*      */ 
/*      */   
/*      */   private int w;
/*      */ 
/*      */ 
/*      */   
/*      */   private int x;
/*      */ 
/*      */ 
/*      */   
/*      */   private int y;
/*      */ 
/*      */ 
/*      */   
/*      */   private int z;
/*      */ 
/*      */ 
/*      */   
/*      */   private float[] A;
/*      */ 
/*      */ 
/*      */   
/*      */   private float[] B;
/*      */ 
/*      */ 
/*      */   
/*      */   private final int[] C;
/*      */ 
/*      */ 
/*      */   
/*      */   private int[] D;
/*      */ 
/*      */ 
/*      */   
/*      */   private int[] E;
/*      */ 
/*      */ 
/*      */   
/*      */   private int[] F;
/*      */ 
/*      */ 
/*      */   
/*      */   private int[] G;
/*      */ 
/*      */ 
/*      */   
/*      */   private int[] H;
/*      */ 
/*      */ 
/*      */   
/*      */   private float[] I;
/*      */ 
/*      */ 
/*      */   
/*      */   private float[] J;
/*      */ 
/*      */ 
/*      */   
/*      */   private float[] K;
/*      */ 
/*      */ 
/*      */   
/*      */   private int L;
/*      */ 
/*      */ 
/*      */ 
/*      */   
/*      */   public final void a() {
/*  192 */     b();
/*      */   }
/*      */ 
/*      */ 
/*      */ 
/*      */ 
/*      */ 
/*      */   
/*      */   public k(b paramb, g paramg, n paramn1, n paramn2, m paramm, int paramInt) {
/*  201 */     this.A = new float[32];
/*  202 */     this.B = new float[32];
/*      */ 
/*      */ 
/*      */ 
/*      */ 
/*      */ 
/*      */ 
/*      */ 
/*      */ 
/*      */ 
/*      */ 
/*      */ 
/*      */ 
/*      */ 
/*      */ 
/*      */ 
/*      */ 
/*      */ 
/*      */ 
/*      */ 
/*      */ 
/*      */ 
/*      */ 
/*      */ 
/*      */ 
/*      */ 
/*      */ 
/*      */ 
/*      */ 
/*      */ 
/*      */ 
/*      */ 
/*      */ 
/*      */ 
/*      */ 
/*      */ 
/*      */ 
/*      */ 
/*      */ 
/*      */ 
/*      */ 
/*      */ 
/*      */ 
/*      */ 
/*      */ 
/*      */ 
/*      */ 
/*      */ 
/*      */ 
/*      */ 
/*      */ 
/*      */ 
/*      */ 
/*      */ 
/*      */ 
/*      */ 
/*      */ 
/*      */ 
/*      */ 
/*      */ 
/*      */ 
/*      */ 
/*      */ 
/*      */ 
/*      */ 
/*      */ 
/*      */ 
/*      */ 
/*      */ 
/*      */ 
/*      */ 
/*      */ 
/*      */ 
/*      */ 
/*      */ 
/*      */ 
/*      */ 
/*      */ 
/*      */ 
/*      */ 
/*      */ 
/*      */ 
/*      */ 
/*      */ 
/*      */ 
/*      */ 
/*      */ 
/*      */ 
/*      */ 
/*      */ 
/*      */ 
/*      */ 
/*      */ 
/*      */ 
/*      */ 
/*      */ 
/*      */ 
/*      */ 
/*      */ 
/*      */ 
/*      */ 
/*      */ 
/*      */ 
/*      */ 
/*      */ 
/*      */ 
/*      */ 
/*      */ 
/*      */ 
/*      */ 
/*      */ 
/*      */ 
/*      */ 
/*      */ 
/*      */ 
/*      */ 
/*      */ 
/*      */ 
/*      */ 
/*      */ 
/*      */ 
/*      */ 
/*      */ 
/*      */ 
/*      */ 
/*      */ 
/*      */ 
/*      */ 
/*      */ 
/*      */ 
/*      */ 
/*      */ 
/*      */ 
/*      */ 
/*      */ 
/*      */ 
/*      */ 
/*      */ 
/*      */ 
/*      */ 
/*      */ 
/*      */ 
/*      */ 
/*      */ 
/*      */ 
/*      */ 
/*      */ 
/*      */ 
/*      */ 
/*      */ 
/*      */ 
/*      */ 
/*      */ 
/*      */ 
/*      */ 
/*      */ 
/*      */ 
/*      */ 
/*      */ 
/*      */ 
/*      */ 
/*      */ 
/*      */ 
/*      */ 
/*      */ 
/*      */ 
/*      */ 
/*      */ 
/*      */ 
/*      */ 
/*      */ 
/*      */ 
/*      */ 
/*      */ 
/*      */ 
/*      */ 
/*      */ 
/*      */ 
/*      */ 
/*      */ 
/*      */ 
/*      */ 
/*      */ 
/*      */ 
/*      */ 
/*      */ 
/*      */ 
/*      */ 
/*      */ 
/*      */ 
/*      */ 
/*      */ 
/*      */ 
/*      */ 
/*      */ 
/*      */ 
/*      */ 
/*      */ 
/*      */ 
/*      */ 
/*      */ 
/*      */ 
/*      */ 
/*      */ 
/*      */ 
/*      */ 
/*      */ 
/*      */ 
/*      */ 
/*      */ 
/*      */ 
/*      */ 
/*      */ 
/*      */ 
/*      */ 
/*      */ 
/*      */ 
/*      */ 
/*      */ 
/*      */ 
/*      */ 
/*      */ 
/*      */ 
/*      */ 
/*      */ 
/*      */ 
/*      */ 
/*      */ 
/*      */ 
/*      */ 
/*      */ 
/*      */ 
/*      */ 
/*      */ 
/*      */ 
/*      */ 
/*      */ 
/*      */ 
/*      */ 
/*      */ 
/*      */ 
/*      */ 
/*      */ 
/*      */ 
/*      */ 
/*      */ 
/*      */ 
/*      */ 
/*      */ 
/*      */ 
/*      */ 
/*      */ 
/*      */ 
/*      */ 
/*      */ 
/*      */ 
/*      */ 
/*      */ 
/*      */ 
/*      */ 
/*      */ 
/*      */ 
/*      */ 
/*      */ 
/*      */ 
/*      */ 
/*      */ 
/*      */ 
/*      */ 
/*      */ 
/*      */ 
/*      */ 
/*      */ 
/*      */ 
/*      */ 
/*      */ 
/*      */ 
/*      */ 
/*      */ 
/*      */ 
/*      */ 
/*      */ 
/*      */ 
/*      */ 
/*      */ 
/*      */ 
/*      */ 
/*      */ 
/*      */ 
/*      */ 
/*      */ 
/*      */ 
/*      */ 
/*      */ 
/*      */ 
/*      */ 
/*      */ 
/*      */ 
/*      */ 
/*      */ 
/*      */ 
/*      */ 
/*      */ 
/*      */ 
/*      */ 
/*      */ 
/*      */ 
/*      */ 
/*      */ 
/*      */ 
/*      */ 
/*      */ 
/*      */ 
/*      */ 
/*      */ 
/*      */ 
/*      */ 
/*      */ 
/*      */ 
/*      */ 
/*      */ 
/*      */ 
/*      */ 
/*      */ 
/*      */ 
/*      */ 
/*      */ 
/*      */ 
/*      */ 
/*      */ 
/*      */ 
/*      */ 
/*      */ 
/*      */ 
/*      */ 
/*      */ 
/*      */ 
/*      */ 
/*      */     
/*  541 */     this.C = new int[4];
/*      */ 
/*      */ 
/*      */ 
/*      */ 
/*      */ 
/*      */ 
/*      */ 
/*      */ 
/*      */ 
/*      */ 
/*      */ 
/*      */ 
/*      */ 
/*      */ 
/*      */ 
/*      */ 
/*      */ 
/*      */ 
/*      */ 
/*      */ 
/*      */ 
/*      */ 
/*      */ 
/*      */ 
/*      */ 
/*      */ 
/*      */ 
/*      */ 
/*      */ 
/*      */ 
/*      */ 
/*      */ 
/*      */ 
/*      */ 
/*      */ 
/*      */ 
/*      */ 
/*      */ 
/*      */ 
/*      */ 
/*      */ 
/*      */ 
/*      */ 
/*      */ 
/*      */ 
/*      */ 
/*      */ 
/*      */ 
/*      */ 
/*      */ 
/*      */ 
/*      */ 
/*      */ 
/*      */ 
/*      */ 
/*      */ 
/*      */ 
/*      */ 
/*      */ 
/*      */ 
/*      */ 
/*      */ 
/*      */ 
/*      */ 
/*      */ 
/*      */ 
/*      */ 
/*      */ 
/*      */ 
/*      */ 
/*      */ 
/*      */ 
/*      */ 
/*      */ 
/*      */ 
/*      */ 
/*      */ 
/*      */ 
/*      */ 
/*      */ 
/*      */ 
/*      */ 
/*      */ 
/*      */ 
/*      */ 
/*      */ 
/*      */ 
/*      */ 
/*      */ 
/*      */ 
/*      */ 
/*      */ 
/*      */ 
/*      */ 
/*      */ 
/*      */ 
/*      */ 
/*      */ 
/*      */ 
/*      */ 
/*      */ 
/*      */ 
/*      */ 
/*      */ 
/*      */ 
/*      */ 
/*      */ 
/*      */ 
/*      */ 
/*      */ 
/*      */ 
/*      */ 
/*      */ 
/*      */ 
/*      */ 
/*      */ 
/*      */ 
/*      */ 
/*      */ 
/*      */ 
/*      */ 
/*      */ 
/*      */ 
/*      */ 
/*      */ 
/*      */ 
/*      */ 
/*      */ 
/*      */ 
/*      */ 
/*      */ 
/*      */ 
/*      */ 
/*      */ 
/*      */ 
/*      */ 
/*      */ 
/*      */ 
/*      */ 
/*      */     
/*  682 */     this.D = new int[] { 0 };
/*  683 */     this.E = new int[] { 0 };
/*  684 */     this.F = new int[] { 0 };
/*  685 */     this.G = new int[] { 0 };
/*      */ 
/*      */ 
/*      */ 
/*      */ 
/*      */ 
/*      */ 
/*      */ 
/*      */ 
/*      */ 
/*      */ 
/*      */ 
/*      */ 
/*      */ 
/*      */ 
/*      */ 
/*      */ 
/*      */ 
/*      */ 
/*      */ 
/*      */ 
/*      */ 
/*      */ 
/*      */ 
/*      */ 
/*      */ 
/*      */ 
/*      */ 
/*      */ 
/*      */ 
/*      */ 
/*      */ 
/*      */ 
/*      */ 
/*      */ 
/*      */ 
/*      */ 
/*      */ 
/*      */ 
/*      */ 
/*      */ 
/*      */ 
/*      */ 
/*      */ 
/*      */ 
/*      */ 
/*      */ 
/*      */ 
/*      */ 
/*      */ 
/*      */ 
/*      */ 
/*      */ 
/*      */ 
/*      */ 
/*      */ 
/*      */ 
/*      */ 
/*      */ 
/*      */ 
/*      */ 
/*      */ 
/*      */ 
/*      */ 
/*      */ 
/*      */ 
/*      */ 
/*      */ 
/*      */ 
/*      */ 
/*      */ 
/*      */ 
/*      */ 
/*      */ 
/*      */ 
/*      */ 
/*      */ 
/*      */ 
/*      */ 
/*      */ 
/*      */ 
/*      */ 
/*      */ 
/*      */ 
/*      */ 
/*      */ 
/*      */ 
/*      */ 
/*      */ 
/*      */ 
/*      */ 
/*      */ 
/*      */ 
/*      */ 
/*      */ 
/*      */ 
/*      */ 
/*      */ 
/*      */ 
/*      */ 
/*      */ 
/*      */ 
/*      */ 
/*      */ 
/*      */ 
/*      */ 
/*      */ 
/*      */ 
/*      */ 
/*      */ 
/*      */ 
/*      */ 
/*      */ 
/*      */ 
/*      */ 
/*      */ 
/*      */ 
/*      */ 
/*      */ 
/*      */ 
/*      */ 
/*      */ 
/*      */ 
/*      */ 
/*      */ 
/*      */ 
/*      */ 
/*      */ 
/*      */ 
/*      */ 
/*      */ 
/*      */ 
/*      */ 
/*      */ 
/*      */ 
/*      */ 
/*      */ 
/*      */ 
/*      */ 
/*      */ 
/*      */ 
/*      */ 
/*      */ 
/*      */ 
/*      */ 
/*      */ 
/*      */ 
/*      */ 
/*      */ 
/*      */ 
/*      */ 
/*      */ 
/*      */ 
/*      */ 
/*      */ 
/*      */ 
/*      */ 
/*      */ 
/*      */ 
/*      */ 
/*      */ 
/*      */ 
/*      */ 
/*      */ 
/*      */ 
/*      */ 
/*      */ 
/*      */ 
/*      */ 
/*      */ 
/*      */ 
/*      */ 
/*      */ 
/*      */ 
/*      */ 
/*      */ 
/*      */ 
/*      */ 
/*      */ 
/*      */ 
/*      */ 
/*      */ 
/*      */ 
/*      */ 
/*      */ 
/*      */ 
/*      */ 
/*      */ 
/*      */ 
/*      */ 
/*      */ 
/*      */ 
/*      */ 
/*      */ 
/*      */ 
/*      */ 
/*      */ 
/*      */ 
/*      */ 
/*      */ 
/*      */ 
/*      */ 
/*      */ 
/*      */ 
/*      */ 
/*      */ 
/*      */ 
/*      */ 
/*      */ 
/*      */ 
/*      */ 
/*      */ 
/*      */ 
/*      */ 
/*      */ 
/*      */ 
/*      */ 
/*      */ 
/*      */ 
/*      */ 
/*      */ 
/*      */ 
/*      */ 
/*      */ 
/*      */ 
/*      */ 
/*      */ 
/*      */ 
/*      */ 
/*      */ 
/*      */ 
/*      */ 
/*      */ 
/*      */ 
/*      */ 
/*      */ 
/*      */ 
/*      */ 
/*      */ 
/*      */ 
/*      */ 
/*      */ 
/*      */ 
/*      */ 
/*      */ 
/*      */ 
/*      */ 
/*      */ 
/*      */ 
/*      */ 
/*      */ 
/*      */ 
/*      */ 
/*      */ 
/*      */ 
/*      */ 
/*      */ 
/*      */ 
/*      */ 
/*      */ 
/*      */ 
/*      */ 
/*      */ 
/*      */ 
/*      */ 
/*      */ 
/*      */ 
/*      */ 
/*      */ 
/*      */ 
/*      */ 
/*      */ 
/*      */ 
/*      */ 
/*      */ 
/*      */ 
/*      */ 
/*      */ 
/*      */ 
/*      */ 
/*      */ 
/*      */ 
/*      */ 
/*      */ 
/*      */ 
/*      */ 
/*      */ 
/*      */ 
/*      */ 
/*      */ 
/*      */ 
/*      */ 
/*      */ 
/*      */ 
/*      */ 
/*      */ 
/*      */ 
/*      */ 
/*      */ 
/*      */ 
/*      */ 
/*      */ 
/*      */ 
/*      */ 
/*      */ 
/*      */ 
/*      */ 
/*      */ 
/*      */ 
/*      */ 
/*      */ 
/*      */ 
/*      */ 
/*      */ 
/*      */ 
/*      */ 
/*      */ 
/*      */ 
/*      */ 
/*      */ 
/*      */ 
/*      */ 
/*      */ 
/*      */ 
/*      */ 
/*      */ 
/*      */ 
/*      */ 
/*      */ 
/*      */ 
/*      */ 
/*      */ 
/*      */ 
/*      */ 
/*      */ 
/*      */ 
/*      */ 
/*      */     
/* 1023 */     this.H = new int[576];
/* 1024 */     this.I = new float[576];
/*      */ 
/*      */ 
/*      */ 
/*      */ 
/*      */ 
/*      */ 
/*      */ 
/*      */ 
/*      */ 
/*      */ 
/*      */ 
/*      */ 
/*      */ 
/*      */ 
/*      */ 
/*      */ 
/*      */ 
/*      */ 
/*      */ 
/*      */ 
/*      */ 
/*      */ 
/*      */ 
/*      */ 
/*      */ 
/*      */ 
/*      */ 
/*      */ 
/*      */ 
/*      */ 
/*      */ 
/*      */ 
/*      */ 
/*      */ 
/*      */ 
/*      */ 
/*      */ 
/*      */ 
/*      */ 
/*      */ 
/*      */ 
/*      */ 
/*      */ 
/*      */ 
/*      */ 
/*      */ 
/*      */ 
/*      */ 
/*      */ 
/*      */ 
/*      */ 
/*      */ 
/*      */ 
/*      */ 
/*      */ 
/*      */ 
/*      */ 
/*      */ 
/*      */ 
/*      */ 
/*      */ 
/*      */ 
/*      */ 
/*      */ 
/*      */ 
/*      */ 
/*      */ 
/*      */ 
/*      */ 
/*      */ 
/*      */ 
/*      */ 
/*      */ 
/*      */ 
/*      */ 
/*      */ 
/*      */ 
/*      */ 
/*      */ 
/*      */ 
/*      */ 
/*      */ 
/*      */ 
/*      */ 
/*      */ 
/*      */ 
/*      */ 
/*      */ 
/*      */ 
/*      */ 
/*      */ 
/*      */ 
/*      */ 
/*      */ 
/*      */ 
/*      */ 
/*      */ 
/*      */ 
/*      */ 
/*      */ 
/*      */ 
/*      */ 
/*      */ 
/*      */ 
/*      */ 
/*      */ 
/*      */ 
/*      */ 
/*      */ 
/*      */ 
/*      */ 
/*      */ 
/*      */ 
/*      */ 
/*      */ 
/*      */ 
/*      */ 
/*      */ 
/*      */ 
/*      */ 
/*      */ 
/*      */ 
/*      */ 
/*      */ 
/*      */ 
/*      */ 
/*      */ 
/*      */ 
/*      */ 
/*      */ 
/*      */ 
/*      */ 
/*      */ 
/*      */ 
/*      */ 
/*      */ 
/*      */ 
/*      */ 
/*      */ 
/*      */ 
/*      */ 
/*      */ 
/*      */ 
/*      */ 
/*      */ 
/*      */ 
/*      */ 
/*      */ 
/*      */ 
/*      */ 
/*      */ 
/*      */ 
/*      */ 
/*      */ 
/*      */ 
/*      */ 
/*      */ 
/*      */ 
/*      */ 
/*      */ 
/*      */ 
/*      */ 
/*      */ 
/*      */ 
/*      */ 
/*      */ 
/*      */ 
/*      */ 
/*      */ 
/*      */ 
/*      */ 
/*      */ 
/*      */ 
/*      */ 
/*      */ 
/*      */ 
/*      */ 
/*      */ 
/*      */ 
/*      */ 
/*      */ 
/*      */ 
/*      */ 
/*      */ 
/*      */ 
/*      */ 
/*      */ 
/*      */ 
/*      */ 
/*      */ 
/*      */ 
/*      */ 
/*      */ 
/*      */ 
/*      */ 
/*      */ 
/*      */ 
/*      */ 
/*      */ 
/*      */ 
/*      */ 
/*      */ 
/*      */ 
/*      */ 
/*      */ 
/*      */ 
/*      */ 
/*      */ 
/*      */ 
/*      */ 
/*      */ 
/*      */ 
/*      */ 
/*      */ 
/*      */ 
/*      */ 
/*      */ 
/*      */ 
/*      */ 
/*      */ 
/*      */ 
/*      */ 
/*      */ 
/*      */ 
/*      */ 
/*      */ 
/*      */ 
/*      */ 
/*      */ 
/*      */ 
/*      */ 
/*      */ 
/*      */ 
/*      */ 
/*      */ 
/*      */ 
/*      */ 
/*      */ 
/*      */ 
/*      */ 
/*      */ 
/*      */ 
/*      */ 
/*      */ 
/*      */ 
/*      */ 
/*      */ 
/*      */ 
/*      */ 
/*      */ 
/*      */ 
/*      */ 
/*      */ 
/*      */ 
/*      */ 
/*      */ 
/*      */ 
/*      */ 
/*      */ 
/*      */ 
/*      */ 
/*      */ 
/*      */ 
/*      */ 
/*      */ 
/*      */ 
/*      */ 
/*      */ 
/*      */ 
/*      */ 
/*      */ 
/*      */ 
/*      */ 
/*      */ 
/*      */ 
/*      */ 
/*      */ 
/*      */ 
/*      */ 
/*      */ 
/*      */ 
/*      */ 
/*      */ 
/*      */ 
/*      */ 
/*      */ 
/*      */ 
/*      */ 
/*      */ 
/*      */ 
/*      */ 
/*      */ 
/*      */ 
/*      */ 
/*      */     
/* 1320 */     this.J = new float[18];
/* 1321 */     this.K = new float[36];
/*      */ 
/*      */ 
/*      */ 
/*      */ 
/*      */ 
/*      */ 
/*      */ 
/*      */ 
/*      */ 
/*      */ 
/*      */ 
/*      */ 
/*      */ 
/*      */ 
/*      */ 
/*      */ 
/*      */ 
/*      */ 
/*      */ 
/*      */ 
/*      */ 
/*      */ 
/*      */ 
/*      */ 
/*      */ 
/*      */ 
/*      */ 
/*      */ 
/*      */ 
/*      */ 
/*      */ 
/*      */ 
/*      */ 
/*      */ 
/*      */ 
/*      */ 
/*      */ 
/*      */ 
/*      */ 
/*      */ 
/*      */ 
/*      */ 
/*      */ 
/*      */ 
/*      */ 
/*      */ 
/*      */ 
/*      */ 
/*      */ 
/*      */ 
/*      */ 
/*      */ 
/*      */ 
/*      */ 
/*      */ 
/*      */ 
/*      */ 
/*      */ 
/*      */ 
/*      */ 
/*      */ 
/*      */ 
/*      */ 
/*      */ 
/*      */ 
/*      */ 
/*      */ 
/*      */ 
/*      */ 
/*      */ 
/*      */ 
/*      */ 
/*      */ 
/*      */ 
/*      */ 
/*      */ 
/*      */ 
/*      */ 
/*      */ 
/*      */ 
/*      */ 
/*      */ 
/*      */ 
/*      */ 
/*      */ 
/*      */ 
/*      */ 
/*      */ 
/*      */ 
/*      */ 
/*      */ 
/*      */ 
/*      */ 
/*      */ 
/*      */ 
/*      */ 
/*      */ 
/*      */ 
/*      */ 
/*      */ 
/*      */ 
/*      */ 
/*      */ 
/*      */ 
/*      */ 
/*      */ 
/*      */ 
/*      */ 
/*      */ 
/*      */ 
/*      */ 
/*      */ 
/*      */ 
/*      */ 
/*      */ 
/*      */ 
/*      */ 
/*      */ 
/*      */ 
/*      */ 
/*      */ 
/*      */ 
/*      */ 
/*      */ 
/*      */ 
/*      */ 
/*      */ 
/*      */ 
/*      */ 
/*      */ 
/*      */ 
/*      */ 
/*      */ 
/*      */ 
/*      */ 
/*      */ 
/*      */ 
/*      */ 
/*      */ 
/*      */ 
/*      */ 
/*      */ 
/*      */ 
/*      */ 
/*      */ 
/*      */ 
/*      */ 
/*      */ 
/*      */ 
/*      */ 
/*      */ 
/*      */ 
/*      */ 
/*      */ 
/*      */ 
/*      */ 
/*      */ 
/*      */ 
/*      */ 
/*      */ 
/*      */ 
/*      */ 
/*      */ 
/*      */ 
/*      */ 
/*      */ 
/*      */ 
/*      */ 
/*      */ 
/*      */ 
/*      */ 
/*      */ 
/*      */ 
/*      */ 
/*      */ 
/*      */ 
/*      */ 
/*      */ 
/*      */ 
/*      */ 
/*      */ 
/*      */ 
/*      */ 
/*      */ 
/*      */ 
/*      */ 
/*      */ 
/*      */ 
/*      */ 
/*      */ 
/*      */ 
/*      */ 
/*      */ 
/*      */ 
/*      */ 
/*      */ 
/*      */ 
/*      */ 
/*      */ 
/*      */ 
/*      */ 
/*      */ 
/*      */ 
/*      */ 
/*      */ 
/*      */ 
/*      */ 
/*      */ 
/*      */ 
/*      */ 
/*      */ 
/*      */ 
/*      */ 
/*      */ 
/*      */ 
/*      */ 
/*      */ 
/*      */ 
/*      */ 
/*      */ 
/*      */ 
/*      */ 
/*      */ 
/*      */ 
/*      */ 
/*      */ 
/*      */ 
/*      */ 
/*      */ 
/*      */ 
/*      */ 
/*      */ 
/*      */ 
/*      */ 
/*      */ 
/*      */ 
/*      */ 
/*      */ 
/*      */ 
/*      */ 
/*      */ 
/*      */ 
/*      */ 
/*      */ 
/*      */ 
/*      */ 
/*      */ 
/*      */ 
/*      */ 
/*      */ 
/*      */ 
/*      */ 
/*      */ 
/*      */ 
/*      */ 
/*      */ 
/*      */ 
/*      */ 
/*      */ 
/*      */ 
/*      */ 
/*      */ 
/*      */ 
/*      */ 
/*      */ 
/*      */ 
/*      */ 
/*      */ 
/*      */ 
/*      */ 
/*      */ 
/*      */ 
/*      */ 
/*      */ 
/*      */ 
/*      */ 
/*      */ 
/*      */ 
/*      */ 
/*      */ 
/*      */ 
/*      */ 
/*      */ 
/*      */ 
/*      */ 
/*      */ 
/*      */ 
/*      */ 
/*      */ 
/*      */ 
/*      */ 
/*      */ 
/*      */ 
/*      */ 
/*      */ 
/*      */ 
/*      */ 
/*      */ 
/*      */ 
/*      */ 
/*      */ 
/*      */ 
/*      */ 
/*      */ 
/*      */ 
/*      */ 
/*      */ 
/*      */ 
/*      */ 
/*      */ 
/*      */ 
/*      */ 
/*      */ 
/*      */ 
/*      */ 
/*      */ 
/*      */ 
/*      */ 
/*      */ 
/*      */ 
/*      */ 
/*      */ 
/*      */ 
/*      */ 
/*      */ 
/*      */ 
/*      */ 
/*      */ 
/*      */ 
/*      */ 
/*      */ 
/*      */ 
/*      */ 
/*      */ 
/*      */ 
/*      */ 
/*      */ 
/*      */ 
/*      */ 
/*      */ 
/*      */ 
/*      */ 
/*      */ 
/*      */ 
/*      */ 
/*      */ 
/*      */ 
/*      */ 
/*      */ 
/*      */ 
/*      */ 
/*      */ 
/*      */ 
/*      */ 
/*      */ 
/*      */ 
/*      */ 
/*      */ 
/*      */ 
/*      */ 
/*      */ 
/*      */ 
/*      */ 
/*      */ 
/*      */ 
/*      */ 
/*      */ 
/*      */ 
/*      */ 
/*      */ 
/*      */ 
/*      */ 
/*      */ 
/*      */ 
/*      */ 
/*      */ 
/*      */ 
/*      */ 
/*      */ 
/*      */ 
/*      */ 
/*      */ 
/*      */ 
/*      */ 
/*      */ 
/*      */ 
/*      */ 
/*      */ 
/*      */ 
/*      */ 
/*      */ 
/*      */ 
/*      */ 
/*      */ 
/*      */ 
/*      */ 
/*      */ 
/*      */ 
/*      */ 
/*      */     
/* 1722 */     this.L = 0; o.a(); this.c = new int[580]; this.d = new float[2][32][18]; this.e = new float[2][32][18]; this.f = new float[576]; this.g = new float[2][576]; this.h = new float[2][576]; this.i = new int[2]; this.r = new f[2]; this.r[0] = new f(); this.r[1] = new f(); this.s = this.r; this.O = new b[9]; int[] arrayOfInt1 = { 0, 6, 12, 18, 24, 30, 36, 44, 54, 66, 80, 96, 116, 140, 168, 200, 238, 284, 336, 396, 464, 522, 576 }; int[] arrayOfInt2 = { 0, 4, 8, 12, 18, 24, 32, 42, 56, 74, 100, 132, 174, 192 }; int[] arrayOfInt3 = { 0, 6, 12, 18, 24, 30, 36, 44, 54, 66, 80, 96, 114, 136, 162, 194, 232, 278, 330, 394, 464, 540, 576 }; int[] arrayOfInt4 = { 0, 4, 8, 12, 18, 26, 36, 48, 62, 80, 104, 136, 180, 192 }; int[] arrayOfInt5 = { 0, 6, 12, 18, 24, 30, 36, 44, 54, 66, 80, 96, 116, 140, 168, 200, 238, 284, 336, 396, 464, 522, 576 }; int[] arrayOfInt6 = { 0, 4, 8, 12, 18, 26, 36, 48, 62, 80, 104, 134, 174, 192 }; int[] arrayOfInt7 = { 0, 4, 8, 12, 16, 20, 24, 30, 36, 44, 52, 62, 74, 90, 110, 134, 162, 196, 238, 288, 342, 418, 576 }; int[] arrayOfInt8 = { 0, 4, 8, 12, 16, 22, 30, 40, 52, 66, 84, 106, 136, 192 }; int[] arrayOfInt9 = { 0, 4, 8, 12, 16, 20, 24, 30, 36, 42, 50, 60, 72, 88, 106, 128, 156, 190, 230, 276, 330, 384, 576 }; int[] arrayOfInt10 = { 0, 4, 8, 12, 16, 22, 28, 38, 50, 64, 80, 100, 126, 192 }; int[] arrayOfInt11 = { 0, 4, 8, 12, 16, 20, 24, 30, 36, 44, 54, 66, 82, 102, 126, 156, 194, 240, 296, 364, 448, 550, 576 }; int[] arrayOfInt12 = { 0, 4, 8, 12, 16, 22, 30, 42, 58, 78, 104, 138, 180, 192 }; int[] arrayOfInt13 = { 0, 6, 12, 18, 24, 30, 36, 44, 54, 66, 80, 96, 116, 140, 168, 200, 238, 284, 336, 396, 464, 522, 576 }; int[] arrayOfInt14 = { 0, 4, 8, 12, 18, 26, 36, 48, 62, 80, 104, 134, 174, 192 }; int[] arrayOfInt15 = { 0, 6, 12, 18, 24, 30, 36, 44, 54, 66, 80, 96, 116, 140, 168, 200, 238, 284, 336, 396, 464, 522, 576 }; int[] arrayOfInt16 = { 0, 4, 8, 12, 18, 26, 36, 48, 62, 80, 104, 134, 174, 192 }; int[] arrayOfInt17 = { 0, 12, 24, 36, 48, 60, 72, 88, 108, 132, 160, 192, 232, 280, 336, 400, 476, 566, 568, 570, 
/*      */         572, 574, 576 }; int[] arrayOfInt18 = { 
/*      */         0, 8, 16, 24, 36, 52, 72, 96, 124, 160, 
/*      */         162, 164, 166, 192 }; this.O[0] = new b(arrayOfInt1, arrayOfInt2); this.O[1] = new b(arrayOfInt3, arrayOfInt4); this.O[2] = new b(arrayOfInt5, arrayOfInt6); this.O[3] = new b(arrayOfInt7, arrayOfInt8); this.O[4] = new b(arrayOfInt9, arrayOfInt10); this.O[5] = new b(arrayOfInt11, arrayOfInt12); this.O[6] = new b(arrayOfInt13, arrayOfInt14); this.O[7] = new b(arrayOfInt15, arrayOfInt16); this.O[8] = new b(arrayOfInt17, arrayOfInt18); if (T == null) { T = new int[9][]; for (byte b2 = 0; b2 < 9; b2++) T[b2] = a((this.O[b2]).b);  }  arrayOfInt1 = new int[] { 0, 6, 11, 16, 21 }; arrayOfInt2 = new int[] { 0, 6, 12 }; this.a = new int[54]; this.j = paramb; this.k = paramg; this.l = paramn1; this.m = paramn2; this.n = paramm; this.o = 0; this.u = 0; this.w = (this.k.f() == 3) ? 1 : 2; this.t = (this.k.a() == 1) ? 2 : 1; this.z = this.k.d() + ((this.k.a() == 1) ? 3 : ((this.k.a() == 2) ? 6 : 0)); if (this.w == 2) { switch (this.o) { case 1: case 3: this.x = this.y = 0; break;case 2: this.x = this.y = 1; break;default: this.x = 0; this.y = 1; break; }  } else { this.x = this.y = 0; }  for (byte b1 = 0; b1 < 2; b1++) { for (byte b2 = 0; b2 < 'ɀ'; b2++) this.g[b1][b2] = 0.0F;  }  this.i[1] = 576; this.i[0] = 576; this.p = new a(); this.q = new a();
/*      */   }
/*      */   private void b() { int i = this.k.h(); c(); int j; for (j = 0; j < i; j++) this.p.b(this.j.d(8));  int i1 = this.p.a() >>> 3; if ((j = this.p.a() & 0x7) != 0) { this.p.a(8 - j); i1++; }  j = this.u - i1 - this.q.a; this.u += i; if (j < 0) return;  if (i1 > 4096) { this.u -= 4096; this.p.d(4096); }  for (; j > 0; j--) this.p.a(8);  for (i = 0; i < this.t; i++) { for (j = 0; j < this.w; j++) { this.v = this.p.a(); if (this.k.a() == 1) { a(j, i); } else { c(j, i); }  d(j, i); a(this.d[j], j, i); }  a(i); if (this.o == 3 && this.w > 1) d();  for (j = this.x; j <= this.y; j++) { b(this.e[j], j, i); e(j, i); f(j, i); byte b1; for (b1 = 18; b1 < 'ɀ'; b1 += 36) { for (i1 = 1; i1 < 18; i1 += 2) this.f[b1 + i1] = -this.f[b1 + i1];  }  if (j == 0 || this.o == 2) { for (i1 = 0; i1 < 18; i1++) { byte b2 = 0; for (b1 = 0; b1 < 'ɀ'; b1 += 18) { this.A[b2] = this.f[b1 + i1]; b2++; }  this.l.a(this.A); this.l.a(this.n); }  } else { for (i1 = 0; i1 < 18; i1++) { byte b2 = 0; for (b1 = 0; b1 < 'ɀ'; b1 += 18) { this.B[b2] = this.f[b1 + i1]; b2++; }  this.m.a(this.B); this.m.a(this.n); }  }  }  }  this.L++; }
/*      */   private boolean c() { if (this.k.a() == 1) { this.q.a = this.j.d(9); if (this.w == 1) { this.j.d(5); } else { this.j.d(3); }  byte b1; for (b1 = 0; b1 < this.w; b1++) { (this.q.b[b1]).a[0] = this.j.d(1); (this.q.b[b1]).a[1] = this.j.d(1); (this.q.b[b1]).a[2] = this.j.d(1); (this.q.b[b1]).a[3] = this.j.d(1); }  for (byte b2 = 0; b2 < 2; b2++) { for (b1 = 0; b1 < this.w; b1++) { ((this.q.b[b1]).b[b2]).a = this.j.d(12); ((this.q.b[b1]).b[b2]).b = this.j.d(9); ((this.q.b[b1]).b[b2]).c = this.j.d(8); ((this.q.b[b1]).b[b2]).d = this.j.d(4); ((this.q.b[b1]).b[b2]).e = this.j.d(1); if (((this.q.b[b1]).b[b2]).e != 0) { ((this.q.b[b1]).b[b2]).f = this.j.d(2); ((this.q.b[b1]).b[b2]).g = this.j.d(1); ((this.q.b[b1]).b[b2]).h[0] = this.j.d(5); ((this.q.b[b1]).b[b2]).h[1] = this.j.d(5); ((this.q.b[b1]).b[b2]).i[0] = this.j.d(3); ((this.q.b[b1]).b[b2]).i[1] = this.j.d(3); ((this.q.b[b1]).b[b2]).i[2] = this.j.d(3); if (((this.q.b[b1]).b[b2]).f == 0) return false;  if (((this.q.b[b1]).b[b2]).f == 2 && ((this.q.b[b1]).b[b2]).g == 0) { ((this.q.b[b1]).b[b2]).j = 8; } else { ((this.q.b[b1]).b[b2]).j = 7; }  ((this.q.b[b1]).b[b2]).k = 20 - ((this.q.b[b1]).b[b2]).j; } else { ((this.q.b[b1]).b[b2]).h[0] = this.j.d(5); ((this.q.b[b1]).b[b2]).h[1] = this.j.d(5); ((this.q.b[b1]).b[b2]).h[2] = this.j.d(5); ((this.q.b[b1]).b[b2]).j = this.j.d(4); ((this.q.b[b1]).b[b2]).k = this.j.d(3); ((this.q.b[b1]).b[b2]).f = 0; }  ((this.q.b[b1]).b[b2]).l = this.j.d(1); ((this.q.b[b1]).b[b2]).m = this.j.d(1); ((this.q.b[b1]).b[b2]).n = this.j.d(1); }  }  } else { this.q.a = this.j.d(8); if (this.w == 1) { this.j.d(1); } else { this.j.d(2); }  for (byte b1 = 0; b1 < this.w; b1++) { ((this.q.b[b1]).b[0]).a = this.j.d(12); ((this.q.b[b1]).b[0]).b = this.j.d(9); ((this.q.b[b1]).b[0]).c = this.j.d(8); ((this.q.b[b1]).b[0]).d = this.j.d(9); ((this.q.b[b1]).b[0]).e = this.j.d(1); if (((this.q.b[b1]).b[0]).e != 0) { ((this.q.b[b1]).b[0]).f = this.j.d(2); ((this.q.b[b1]).b[0]).g = this.j.d(1); ((this.q.b[b1]).b[0]).h[0] = this.j.d(5); ((this.q.b[b1]).b[0]).h[1] = this.j.d(5); ((this.q.b[b1]).b[0]).i[0] = this.j.d(3); ((this.q.b[b1]).b[0]).i[1] = this.j.d(3); ((this.q.b[b1]).b[0]).i[2] = this.j.d(3); if (((this.q.b[b1]).b[0]).f == 0) return false;  if (((this.q.b[b1]).b[0]).f == 2 && ((this.q.b[b1]).b[0]).g == 0) { ((this.q.b[b1]).b[0]).j = 8; } else { ((this.q.b[b1]).b[0]).j = 7; ((this.q.b[b1]).b[0]).k = 20 - ((this.q.b[b1]).b[0]).j; }  } else { ((this.q.b[b1]).b[0]).h[0] = this.j.d(5); ((this.q.b[b1]).b[0]).h[1] = this.j.d(5); ((this.q.b[b1]).b[0]).h[2] = this.j.d(5); ((this.q.b[b1]).b[0]).j = this.j.d(4); ((this.q.b[b1]).b[0]).k = this.j.d(3); ((this.q.b[b1]).b[0]).f = 0; }  ((this.q.b[b1]).b[0]).m = this.j.d(1); ((this.q.b[b1]).b[0]).n = this.j.d(1); }  }  return true; }
/*      */   private void a(int paramInt1, int paramInt2) { d d; int i = (d = (this.q.b[paramInt1]).b[paramInt2]).d; int j = M[0][i]; i = M[1][i]; if (d.e != 0 && d.f == 2) { if (d.g != 0) { for (paramInt2 = 0; paramInt2 < 8; paramInt2++) (this.s[paramInt1]).a[paramInt2] = this.p.a(M[0][d.d]);  for (paramInt2 = 3; paramInt2 < 6; paramInt2++) { for (i = 0; i < 3; i++) (this.s[paramInt1]).b[i][paramInt2] = this.p.a(M[0][d.d]);  }  for (paramInt2 = 6; paramInt2 < 12; paramInt2++) { for (i = 0; i < 3; i++) (this.s[paramInt1]).b[i][paramInt2] = this.p.a(M[1][d.d]);  }  for (i = 0; i < 3; i++) (this.s[paramInt1]).b[i][12] = 0;  } else { (this.s[paramInt1]).b[0][0] = this.p.a(j); (this.s[paramInt1]).b[1][0] = this.p.a(j); (this.s[paramInt1]).b[2][0] = this.p.a(j); (this.s[paramInt1]).b[0][1] = this.p.a(j); (this.s[paramInt1]).b[1][1] = this.p.a(j); (this.s[paramInt1]).b[2][1] = this.p.a(j); (this.s[paramInt1]).b[0][2] = this.p.a(j); (this.s[paramInt1]).b[1][2] = this.p.a(j); (this.s[paramInt1]).b[2][2] = this.p.a(j); (this.s[paramInt1]).b[0][3] = this.p.a(j); (this.s[paramInt1]).b[1][3] = this.p.a(j); (this.s[paramInt1]).b[2][3] = this.p.a(j); (this.s[paramInt1]).b[0][4] = this.p.a(j); (this.s[paramInt1]).b[1][4] = this.p.a(j); (this.s[paramInt1]).b[2][4] = this.p.a(j); (this.s[paramInt1]).b[0][5] = this.p.a(j); (this.s[paramInt1]).b[1][5] = this.p.a(j); (this.s[paramInt1]).b[2][5] = this.p.a(j); (this.s[paramInt1]).b[0][6] = this.p.a(i); (this.s[paramInt1]).b[1][6] = this.p.a(i); (this.s[paramInt1]).b[2][6] = this.p.a(i); (this.s[paramInt1]).b[0][7] = this.p.a(i); (this.s[paramInt1]).b[1][7] = this.p.a(i); (this.s[paramInt1]).b[2][7] = this.p.a(i); (this.s[paramInt1]).b[0][8] = this.p.a(i); (this.s[paramInt1]).b[1][8] = this.p.a(i); (this.s[paramInt1]).b[2][8] = this.p.a(i); (this.s[paramInt1]).b[0][9] = this.p.a(i); (this.s[paramInt1]).b[1][9] = this.p.a(i); (this.s[paramInt1]).b[2][9] = this.p.a(i); (this.s[paramInt1]).b[0][10] = this.p.a(i); (this.s[paramInt1]).b[1][10] = this.p.a(i); (this.s[paramInt1]).b[2][10] = this.p.a(i); (this.s[paramInt1]).b[0][11] = this.p.a(i); (this.s[paramInt1]).b[1][11] = this.p.a(i); (this.s[paramInt1]).b[2][11] = this.p.a(i); (this.s[paramInt1]).b[0][12] = 0; (this.s[paramInt1]).b[1][12] = 0; (this.s[paramInt1]).b[2][12] = 0; return; }  } else { if ((this.q.b[paramInt1]).a[0] == 0 || paramInt2 == 0) { (this.s[paramInt1]).a[0] = this.p.a(j); (this.s[paramInt1]).a[1] = this.p.a(j); (this.s[paramInt1]).a[2] = this.p.a(j); (this.s[paramInt1]).a[3] = this.p.a(j); (this.s[paramInt1]).a[4] = this.p.a(j); (this.s[paramInt1]).a[5] = this.p.a(j); }  if ((this.q.b[paramInt1]).a[1] == 0 || paramInt2 == 0) { (this.s[paramInt1]).a[6] = this.p.a(j); (this.s[paramInt1]).a[7] = this.p.a(j); (this.s[paramInt1]).a[8] = this.p.a(j); (this.s[paramInt1]).a[9] = this.p.a(j); (this.s[paramInt1]).a[10] = this.p.a(j); }  if ((this.q.b[paramInt1]).a[2] == 0 || paramInt2 == 0) { (this.s[paramInt1]).a[11] = this.p.a(i); (this.s[paramInt1]).a[12] = this.p.a(i); (this.s[paramInt1]).a[13] = this.p.a(i); (this.s[paramInt1]).a[14] = this.p.a(i); (this.s[paramInt1]).a[15] = this.p.a(i); }  if ((this.q.b[paramInt1]).a[3] == 0 || paramInt2 == 0) { (this.s[paramInt1]).a[16] = this.p.a(i); (this.s[paramInt1]).a[17] = this.p.a(i); (this.s[paramInt1]).a[18] = this.p.a(i); (this.s[paramInt1]).a[19] = this.p.a(i); (this.s[paramInt1]).a[20] = this.p.a(i); }  (this.s[paramInt1]).a[21] = 0; (this.s[paramInt1]).a[22] = 0; }  }
/*      */   private void b(int paramInt1, int paramInt2) { boolean bool; int j = this.k.i(); byte b1 = 0; d d; int i = (d = (this.q.b[paramInt1]).b[paramInt2]).d; if (d.f == 2) { if (d.g == 0) { bool = true; } else if (bool.g == 1) { bool = true; } else { bool = false; }  } else { bool = false; }  if ((j != 1 && j != 3) || paramInt1 != 1) if (i < 400) { this.C[0] = (i >>> 4) / 5; this.C[1] = (i >>> 4) % 5; this.C[2] = (i & 0xF) >>> 2; this.C[3] = i & 0x3; ((this.q.b[paramInt1]).b[paramInt2]).l = 0; b1 = 0; } else if (i < 500) { this.C[0] = (i - 400 >>> 2) / 5; this.C[1] = (i - 400 >>> 2) % 5; this.C[2] = i - 400 & 0x3; this.C[3] = 0; ((this.q.b[paramInt1]).b[paramInt2]).l = 0; b1 = 1; } else if (i < 512) { this.C[0] = (i - 500) / 3; this.C[1] = (i - 500) % 3; this.C[2] = 0; this.C[3] = 0; ((this.q.b[paramInt1]).b[paramInt2]).l = 1; b1 = 2; }   if ((j == 1 || j == 3) && paramInt1 == 1) if ((i = i >>> 1) < 180) { this.C[0] = i / 36; this.C[1] = i % 36 / 6; this.C[2] = i % 36 % 6; this.C[3] = 0; ((this.q.b[paramInt1]).b[paramInt2]).l = 0; b1 = 3; } else if (i < 244) { this.C[0] = (i - 180 & 0x3F) >>> 4; this.C[1] = (i - 180 & 0xF) >>> 2; this.C[2] = i - 180 & 0x3; this.C[3] = 0; ((this.q.b[paramInt1]).b[paramInt2]).l = 0; b1 = 4; } else if (i < 255) { this.C[0] = (i - 244) / 3; this.C[1] = (i - 244) % 3; this.C[2] = 0; this.C[3] = 0; ((this.q.b[paramInt1]).b[paramInt2]).l = 0; b1 = 5; }   for (paramInt2 = 0; paramInt2 < 45; paramInt2++) this.a[paramInt2] = 0;  paramInt1 = 0; for (paramInt2 = 0; paramInt2 < 4; paramInt2++) { for (i = 0; i < X[b1][bool][paramInt2]; i++) { this.a[paramInt1] = (this.C[paramInt2] == 0) ? 0 : this.p.a(this.C[paramInt2]); paramInt1++; }  }  }
/*      */   private void c(int paramInt1, int paramInt2) { byte b1 = 0; d d = (this.q.b[paramInt1]).b[paramInt2]; b(paramInt1, paramInt2); if (d.e != 0 && d.f == 2) { if (d.g != 0) { for (paramInt2 = 0; paramInt2 < 8; paramInt2++) { (this.s[paramInt1]).a[paramInt2] = this.a[b1]; b1++; }  for (paramInt2 = 3; paramInt2 < 12; paramInt2++) { for (byte b3 = 0; b3 < 3; b3++) { (this.s[paramInt1]).b[b3][paramInt2] = this.a[b1]; b1++; }  }  for (byte b2 = 0; b2 < 3; b2++) (this.s[paramInt1]).b[b2][12] = 0;  } else { for (paramInt2 = 0; paramInt2 < 12; paramInt2++) { for (byte b3 = 0; b3 < 3; b3++) { (this.s[paramInt1]).b[b3][paramInt2] = this.a[b1]; b1++; }  }  for (byte b2 = 0; b2 < 3; b2++) (this.s[paramInt1]).b[b2][12] = 0;  }  } else { for (paramInt2 = 0; paramInt2 < 21; paramInt2++) { (this.s[paramInt1]).a[paramInt2] = this.a[b1]; b1++; }  (this.s[paramInt1]).a[21] = 0; (this.s[paramInt1]).a[22] = 0; }  }
/*      */   private void d(int paramInt1, int paramInt2) { int j, i1; this.D[0] = 0; this.E[0] = 0; this.F[0] = 0; this.G[0] = 0; int i = this.v + ((this.q.b[paramInt1]).b[paramInt2]).a; if (((this.q.b[paramInt1]).b[paramInt2]).e != 0 && ((this.q.b[paramInt1]).b[paramInt2]).f == 2) { j = (this.z == 8) ? 72 : 36; i1 = 576; } else { if ((i1 = (j = ((this.q.b[paramInt1]).b[paramInt2]).j + 1) + ((this.q.b[paramInt1]).b[paramInt2]).k + 1) > (this.O[this.z]).a.length - 1) i1 = (this.O[this.z]).a.length - 1;  j = (this.O[this.z]).a[j]; i1 = (this.O[this.z]).a[i1]; }  byte b1 = 0; for (byte b2 = 0; b2 < ((this.q.b[paramInt1]).b[paramInt2]).b << 1; b2 += 2) { o o1; if (b2 < j) { o1 = o.a[((this.q.b[paramInt1]).b[paramInt2]).h[0]]; } else if (b2 < i1) { o1 = o.a[((this.q.b[paramInt1]).b[paramInt2]).h[1]]; } else { o1 = o.a[((this.q.b[paramInt1]).b[paramInt2]).h[2]]; }  o.a(o1, this.D, this.E, this.F, this.G, this.p); this.c[b1++] = this.D[0]; this.c[b1++] = this.E[0]; this.b = this.b + this.D[0] + this.E[0]; }  o o = o.a[((this.q.b[paramInt1]).b[paramInt2]).n + 32]; paramInt2 = this.p.a(); while (paramInt2 < i && b1 < 'ɀ') { o.a(o, this.D, this.E, this.F, this.G, this.p); this.c[b1++] = this.F[0]; this.c[b1++] = this.G[0]; this.c[b1++] = this.D[0]; this.c[b1++] = this.E[0]; this.b = this.b + this.F[0] + this.G[0] + this.D[0] + this.E[0]; paramInt2 = this.p.a(); }  if (paramInt2 > i) { this.p.c(paramInt2 - i); b1 -= 4; }  if ((paramInt2 = this.p.a()) < i) this.p.a(i - paramInt2);  if (b1 < 'ɀ') { this.i[paramInt1] = b1; } else { this.i[paramInt1] = 576; }  if (b1 < 0) b1 = 0;  for (; b1 < 'ɀ'; b1++) this.c[b1] = 0;  }
/*      */   private void a(int paramInt1, int paramInt2, int paramInt3) { if (paramInt1 == 0) { this.h[0][paramInt3] = 1.0F; this.h[1][paramInt3] = 1.0F; return; }  if ((paramInt1 & 0x1) != 0) { this.h[0][paramInt3] = R[paramInt2][paramInt1 + 1 >>> 1]; this.h[1][paramInt3] = 1.0F; return; }  this.h[0][paramInt3] = 1.0F; this.h[1][paramInt3] = R[paramInt2][paramInt1 >>> 1]; }
/*      */   private void a(float[][] paramArrayOffloat, int paramInt1, int paramInt2) { // Byte code:
/*      */     //   0: aload_0
/*      */     //   1: getfield q : Lb/a/a/k$a;
/*      */     //   4: getfield b : [Lb/a/a/k$e;
/*      */     //   7: iload_2
/*      */     //   8: aaload
/*      */     //   9: getfield b : [Lb/a/a/k$d;
/*      */     //   12: iload_3
/*      */     //   13: aaload
/*      */     //   14: astore_3
/*      */     //   15: iconst_0
/*      */     //   16: istore #4
/*      */     //   18: iconst_0
/*      */     //   19: istore #5
/*      */     //   21: iconst_0
/*      */     //   22: istore #6
/*      */     //   24: iconst_0
/*      */     //   25: istore #7
/*      */     //   27: aload_1
/*      */     //   28: astore #10
/*      */     //   30: aload_3
/*      */     //   31: getfield e : I
/*      */     //   34: ifeq -> 81
/*      */     //   37: aload_3
/*      */     //   38: getfield f : I
/*      */     //   41: iconst_2
/*      */     //   42: if_icmpne -> 81
/*      */     //   45: aload_3
/*      */     //   46: getfield g : I
/*      */     //   49: ifne -> 81
/*      */     //   52: aload_0
/*      */     //   53: getfield O : [Lb/a/a/k$b;
/*      */     //   56: aload_0
/*      */     //   57: getfield z : I
/*      */     //   60: aaload
/*      */     //   61: getfield b : [I
/*      */     //   64: iconst_1
/*      */     //   65: iaload
/*      */     //   66: dup
/*      */     //   67: istore #6
/*      */     //   69: iconst_2
/*      */     //   70: ishl
/*      */     //   71: iload #6
/*      */     //   73: isub
/*      */     //   74: istore_1
/*      */     //   75: iconst_0
/*      */     //   76: istore #5
/*      */     //   78: goto -> 96
/*      */     //   81: aload_0
/*      */     //   82: getfield O : [Lb/a/a/k$b;
/*      */     //   85: aload_0
/*      */     //   86: getfield z : I
/*      */     //   89: aaload
/*      */     //   90: getfield a : [I
/*      */     //   93: iconst_1
/*      */     //   94: iaload
/*      */     //   95: istore_1
/*      */     //   96: ldc2_w 2.0
/*      */     //   99: ldc2_w 0.25
/*      */     //   102: aload_3
/*      */     //   103: getfield c : I
/*      */     //   106: i2d
/*      */     //   107: ldc2_w 210.0
/*      */     //   110: dsub
/*      */     //   111: dmul
/*      */     //   112: invokestatic pow : (DD)D
/*      */     //   115: d2f
/*      */     //   116: fstore #8
/*      */     //   118: iconst_0
/*      */     //   119: istore #9
/*      */     //   121: iload #9
/*      */     //   123: aload_0
/*      */     //   124: getfield i : [I
/*      */     //   127: iload_2
/*      */     //   128: iaload
/*      */     //   129: if_icmpge -> 339
/*      */     //   132: iload #9
/*      */     //   134: bipush #18
/*      */     //   136: irem
/*      */     //   137: istore #11
/*      */     //   139: iload #9
/*      */     //   141: iload #11
/*      */     //   143: isub
/*      */     //   144: bipush #18
/*      */     //   146: idiv
/*      */     //   147: istore #12
/*      */     //   149: aload_0
/*      */     //   150: getfield c : [I
/*      */     //   153: iload #9
/*      */     //   155: iaload
/*      */     //   156: ifne -> 171
/*      */     //   159: aload #10
/*      */     //   161: iload #12
/*      */     //   163: aaload
/*      */     //   164: iload #11
/*      */     //   166: fconst_0
/*      */     //   167: fastore
/*      */     //   168: goto -> 333
/*      */     //   171: aload_0
/*      */     //   172: getfield c : [I
/*      */     //   175: iload #9
/*      */     //   177: iaload
/*      */     //   178: dup
/*      */     //   179: istore #13
/*      */     //   181: getstatic b/a/a/k.Q : [F
/*      */     //   184: arraylength
/*      */     //   185: if_icmpge -> 276
/*      */     //   188: aload_0
/*      */     //   189: getfield c : [I
/*      */     //   192: iload #9
/*      */     //   194: iaload
/*      */     //   195: ifle -> 218
/*      */     //   198: aload #10
/*      */     //   200: iload #12
/*      */     //   202: aaload
/*      */     //   203: iload #11
/*      */     //   205: fload #8
/*      */     //   207: getstatic b/a/a/k.Q : [F
/*      */     //   210: iload #13
/*      */     //   212: faload
/*      */     //   213: fmul
/*      */     //   214: fastore
/*      */     //   215: goto -> 333
/*      */     //   218: iload #13
/*      */     //   220: ineg
/*      */     //   221: getstatic b/a/a/k.Q : [F
/*      */     //   224: arraylength
/*      */     //   225: if_icmpge -> 250
/*      */     //   228: aload #10
/*      */     //   230: iload #12
/*      */     //   232: aaload
/*      */     //   233: iload #11
/*      */     //   235: fload #8
/*      */     //   237: fneg
/*      */     //   238: getstatic b/a/a/k.Q : [F
/*      */     //   241: iload #13
/*      */     //   243: ineg
/*      */     //   244: faload
/*      */     //   245: fmul
/*      */     //   246: fastore
/*      */     //   247: goto -> 333
/*      */     //   250: aload #10
/*      */     //   252: iload #12
/*      */     //   254: aaload
/*      */     //   255: iload #11
/*      */     //   257: fload #8
/*      */     //   259: fneg
/*      */     //   260: iload #13
/*      */     //   262: ineg
/*      */     //   263: i2d
/*      */     //   264: ldc2_w 1.3333333333333333
/*      */     //   267: invokestatic pow : (DD)D
/*      */     //   270: d2f
/*      */     //   271: fmul
/*      */     //   272: fastore
/*      */     //   273: goto -> 333
/*      */     //   276: aload_0
/*      */     //   277: getfield c : [I
/*      */     //   280: iload #9
/*      */     //   282: iaload
/*      */     //   283: ifle -> 310
/*      */     //   286: aload #10
/*      */     //   288: iload #12
/*      */     //   290: aaload
/*      */     //   291: iload #11
/*      */     //   293: fload #8
/*      */     //   295: iload #13
/*      */     //   297: i2d
/*      */     //   298: ldc2_w 1.3333333333333333
/*      */     //   301: invokestatic pow : (DD)D
/*      */     //   304: d2f
/*      */     //   305: fmul
/*      */     //   306: fastore
/*      */     //   307: goto -> 333
/*      */     //   310: aload #10
/*      */     //   312: iload #12
/*      */     //   314: aaload
/*      */     //   315: iload #11
/*      */     //   317: fload #8
/*      */     //   319: fneg
/*      */     //   320: iload #13
/*      */     //   322: ineg
/*      */     //   323: i2d
/*      */     //   324: ldc2_w 1.3333333333333333
/*      */     //   327: invokestatic pow : (DD)D
/*      */     //   330: d2f
/*      */     //   331: fmul
/*      */     //   332: fastore
/*      */     //   333: iinc #9, 1
/*      */     //   336: goto -> 121
/*      */     //   339: iconst_0
/*      */     //   340: istore #9
/*      */     //   342: iload #9
/*      */     //   344: aload_0
/*      */     //   345: getfield i : [I
/*      */     //   348: iload_2
/*      */     //   349: iaload
/*      */     //   350: if_icmpge -> 873
/*      */     //   353: iload #9
/*      */     //   355: bipush #18
/*      */     //   357: irem
/*      */     //   358: istore #11
/*      */     //   360: iload #9
/*      */     //   362: iload #11
/*      */     //   364: isub
/*      */     //   365: bipush #18
/*      */     //   367: idiv
/*      */     //   368: istore #12
/*      */     //   370: iload #7
/*      */     //   372: iload_1
/*      */     //   373: if_icmpne -> 697
/*      */     //   376: aload_3
/*      */     //   377: getfield e : I
/*      */     //   380: ifeq -> 676
/*      */     //   383: aload_3
/*      */     //   384: getfield f : I
/*      */     //   387: iconst_2
/*      */     //   388: if_icmpne -> 676
/*      */     //   391: aload_3
/*      */     //   392: getfield g : I
/*      */     //   395: ifeq -> 598
/*      */     //   398: iload #7
/*      */     //   400: aload_0
/*      */     //   401: getfield O : [Lb/a/a/k$b;
/*      */     //   404: aload_0
/*      */     //   405: getfield z : I
/*      */     //   408: aaload
/*      */     //   409: getfield a : [I
/*      */     //   412: bipush #8
/*      */     //   414: iaload
/*      */     //   415: if_icmpne -> 500
/*      */     //   418: aload_0
/*      */     //   419: getfield O : [Lb/a/a/k$b;
/*      */     //   422: aload_0
/*      */     //   423: getfield z : I
/*      */     //   426: aaload
/*      */     //   427: getfield b : [I
/*      */     //   430: iconst_4
/*      */     //   431: iaload
/*      */     //   432: dup
/*      */     //   433: istore_1
/*      */     //   434: iconst_2
/*      */     //   435: ishl
/*      */     //   436: iload_1
/*      */     //   437: isub
/*      */     //   438: istore_1
/*      */     //   439: iconst_3
/*      */     //   440: istore #4
/*      */     //   442: aload_0
/*      */     //   443: getfield O : [Lb/a/a/k$b;
/*      */     //   446: aload_0
/*      */     //   447: getfield z : I
/*      */     //   450: aaload
/*      */     //   451: getfield b : [I
/*      */     //   454: iconst_4
/*      */     //   455: iaload
/*      */     //   456: aload_0
/*      */     //   457: getfield O : [Lb/a/a/k$b;
/*      */     //   460: aload_0
/*      */     //   461: getfield z : I
/*      */     //   464: aaload
/*      */     //   465: getfield b : [I
/*      */     //   468: iconst_3
/*      */     //   469: iaload
/*      */     //   470: isub
/*      */     //   471: istore #6
/*      */     //   473: aload_0
/*      */     //   474: getfield O : [Lb/a/a/k$b;
/*      */     //   477: aload_0
/*      */     //   478: getfield z : I
/*      */     //   481: aaload
/*      */     //   482: getfield b : [I
/*      */     //   485: iconst_3
/*      */     //   486: iaload
/*      */     //   487: dup
/*      */     //   488: istore #5
/*      */     //   490: iconst_2
/*      */     //   491: ishl
/*      */     //   492: iload #5
/*      */     //   494: isub
/*      */     //   495: istore #5
/*      */     //   497: goto -> 697
/*      */     //   500: iload #7
/*      */     //   502: aload_0
/*      */     //   503: getfield O : [Lb/a/a/k$b;
/*      */     //   506: aload_0
/*      */     //   507: getfield z : I
/*      */     //   510: aaload
/*      */     //   511: getfield a : [I
/*      */     //   514: bipush #8
/*      */     //   516: iaload
/*      */     //   517: if_icmplt -> 676
/*      */     //   520: aload_0
/*      */     //   521: getfield O : [Lb/a/a/k$b;
/*      */     //   524: aload_0
/*      */     //   525: getfield z : I
/*      */     //   528: aaload
/*      */     //   529: getfield b : [I
/*      */     //   532: iinc #4, 1
/*      */     //   535: iload #4
/*      */     //   537: iconst_1
/*      */     //   538: iadd
/*      */     //   539: iaload
/*      */     //   540: dup
/*      */     //   541: istore_1
/*      */     //   542: iconst_2
/*      */     //   543: ishl
/*      */     //   544: iload_1
/*      */     //   545: isub
/*      */     //   546: istore_1
/*      */     //   547: aload_0
/*      */     //   548: getfield O : [Lb/a/a/k$b;
/*      */     //   551: aload_0
/*      */     //   552: getfield z : I
/*      */     //   555: aaload
/*      */     //   556: getfield b : [I
/*      */     //   559: iload #4
/*      */     //   561: iaload
/*      */     //   562: istore #5
/*      */     //   564: aload_0
/*      */     //   565: getfield O : [Lb/a/a/k$b;
/*      */     //   568: aload_0
/*      */     //   569: getfield z : I
/*      */     //   572: aaload
/*      */     //   573: getfield b : [I
/*      */     //   576: iload #4
/*      */     //   578: iconst_1
/*      */     //   579: iadd
/*      */     //   580: iaload
/*      */     //   581: iload #5
/*      */     //   583: isub
/*      */     //   584: istore #6
/*      */     //   586: iload #5
/*      */     //   588: iconst_2
/*      */     //   589: ishl
/*      */     //   590: iload #5
/*      */     //   592: isub
/*      */     //   593: istore #5
/*      */     //   595: goto -> 697
/*      */     //   598: aload_0
/*      */     //   599: getfield O : [Lb/a/a/k$b;
/*      */     //   602: aload_0
/*      */     //   603: getfield z : I
/*      */     //   606: aaload
/*      */     //   607: getfield b : [I
/*      */     //   610: iinc #4, 1
/*      */     //   613: iload #4
/*      */     //   615: iconst_1
/*      */     //   616: iadd
/*      */     //   617: iaload
/*      */     //   618: dup
/*      */     //   619: istore_1
/*      */     //   620: iconst_2
/*      */     //   621: ishl
/*      */     //   622: iload_1
/*      */     //   623: isub
/*      */     //   624: istore_1
/*      */     //   625: aload_0
/*      */     //   626: getfield O : [Lb/a/a/k$b;
/*      */     //   629: aload_0
/*      */     //   630: getfield z : I
/*      */     //   633: aaload
/*      */     //   634: getfield b : [I
/*      */     //   637: iload #4
/*      */     //   639: iaload
/*      */     //   640: istore #5
/*      */     //   642: aload_0
/*      */     //   643: getfield O : [Lb/a/a/k$b;
/*      */     //   646: aload_0
/*      */     //   647: getfield z : I
/*      */     //   650: aaload
/*      */     //   651: getfield b : [I
/*      */     //   654: iload #4
/*      */     //   656: iconst_1
/*      */     //   657: iadd
/*      */     //   658: iaload
/*      */     //   659: iload #5
/*      */     //   661: isub
/*      */     //   662: istore #6
/*      */     //   664: iload #5
/*      */     //   666: iconst_2
/*      */     //   667: ishl
/*      */     //   668: iload #5
/*      */     //   670: isub
/*      */     //   671: istore #5
/*      */     //   673: goto -> 697
/*      */     //   676: aload_0
/*      */     //   677: getfield O : [Lb/a/a/k$b;
/*      */     //   680: aload_0
/*      */     //   681: getfield z : I
/*      */     //   684: aaload
/*      */     //   685: getfield a : [I
/*      */     //   688: iinc #4, 1
/*      */     //   691: iload #4
/*      */     //   693: iconst_1
/*      */     //   694: iadd
/*      */     //   695: iaload
/*      */     //   696: istore_1
/*      */     //   697: aload_3
/*      */     //   698: getfield e : I
/*      */     //   701: ifeq -> 806
/*      */     //   704: aload_3
/*      */     //   705: getfield f : I
/*      */     //   708: iconst_2
/*      */     //   709: if_icmpne -> 719
/*      */     //   712: aload_3
/*      */     //   713: getfield g : I
/*      */     //   716: ifeq -> 741
/*      */     //   719: aload_3
/*      */     //   720: getfield f : I
/*      */     //   723: iconst_2
/*      */     //   724: if_icmpne -> 806
/*      */     //   727: aload_3
/*      */     //   728: getfield g : I
/*      */     //   731: ifeq -> 806
/*      */     //   734: iload #9
/*      */     //   736: bipush #36
/*      */     //   738: if_icmplt -> 806
/*      */     //   741: iload #7
/*      */     //   743: iload #5
/*      */     //   745: isub
/*      */     //   746: iload #6
/*      */     //   748: idiv
/*      */     //   749: istore #8
/*      */     //   751: aload_0
/*      */     //   752: getfield s : [Lb/a/a/k$f;
/*      */     //   755: iload_2
/*      */     //   756: aaload
/*      */     //   757: getfield b : [[I
/*      */     //   760: iload #8
/*      */     //   762: aaload
/*      */     //   763: iload #4
/*      */     //   765: iaload
/*      */     //   766: aload_3
/*      */     //   767: getfield m : I
/*      */     //   770: ishl
/*      */     //   771: dup
/*      */     //   772: istore #13
/*      */     //   774: aload_3
/*      */     //   775: getfield i : [I
/*      */     //   778: iload #8
/*      */     //   780: iaload
/*      */     //   781: iconst_2
/*      */     //   782: ishl
/*      */     //   783: iadd
/*      */     //   784: istore #13
/*      */     //   786: aload #10
/*      */     //   788: iload #12
/*      */     //   790: aaload
/*      */     //   791: iload #11
/*      */     //   793: dup2
/*      */     //   794: faload
/*      */     //   795: getstatic b/a/a/k.P : [F
/*      */     //   798: iload #13
/*      */     //   800: faload
/*      */     //   801: fmul
/*      */     //   802: fastore
/*      */     //   803: goto -> 864
/*      */     //   806: aload_0
/*      */     //   807: getfield s : [Lb/a/a/k$f;
/*      */     //   810: iload_2
/*      */     //   811: aaload
/*      */     //   812: getfield a : [I
/*      */     //   815: iload #4
/*      */     //   817: iaload
/*      */     //   818: istore #13
/*      */     //   820: aload_3
/*      */     //   821: getfield l : I
/*      */     //   824: ifeq -> 838
/*      */     //   827: iload #13
/*      */     //   829: getstatic b/a/a/k.N : [I
/*      */     //   832: iload #4
/*      */     //   834: iaload
/*      */     //   835: iadd
/*      */     //   836: istore #13
/*      */     //   838: iload #13
/*      */     //   840: aload_3
/*      */     //   841: getfield m : I
/*      */     //   844: ishl
/*      */     //   845: istore #13
/*      */     //   847: aload #10
/*      */     //   849: iload #12
/*      */     //   851: aaload
/*      */     //   852: iload #11
/*      */     //   854: dup2
/*      */     //   855: faload
/*      */     //   856: getstatic b/a/a/k.P : [F
/*      */     //   859: iload #13
/*      */     //   861: faload
/*      */     //   862: fmul
/*      */     //   863: fastore
/*      */     //   864: iinc #7, 1
/*      */     //   867: iinc #9, 1
/*      */     //   870: goto -> 342
/*      */     //   873: aload_0
/*      */     //   874: getfield i : [I
/*      */     //   877: iload_2
/*      */     //   878: iaload
/*      */     //   879: istore #9
/*      */     //   881: iload #9
/*      */     //   883: sipush #576
/*      */     //   886: if_icmpge -> 937
/*      */     //   889: iload #9
/*      */     //   891: bipush #18
/*      */     //   893: irem
/*      */     //   894: istore #11
/*      */     //   896: iload #9
/*      */     //   898: iload #11
/*      */     //   900: isub
/*      */     //   901: bipush #18
/*      */     //   903: idiv
/*      */     //   904: istore #12
/*      */     //   906: iload #11
/*      */     //   908: ifge -> 914
/*      */     //   911: iconst_0
/*      */     //   912: istore #11
/*      */     //   914: iload #12
/*      */     //   916: ifge -> 922
/*      */     //   919: iconst_0
/*      */     //   920: istore #12
/*      */     //   922: aload #10
/*      */     //   924: iload #12
/*      */     //   926: aaload
/*      */     //   927: iload #11
/*      */     //   929: fconst_0
/*      */     //   930: fastore
/*      */     //   931: iinc #9, 1
/*      */     //   934: goto -> 881
/*      */     //   937: return
/*      */     // Line number table:
/*      */     //   Java source line number -> byte code offset
/*      */     //   #806	-> 0
/*      */     //   #807	-> 15
/*      */     //   #809	-> 18
/*      */     //   #810	-> 21
/*      */     //   #811	-> 24
/*      */     //   #813	-> 27
/*      */     //   #817	-> 30
/*      */     //   #818	-> 45
/*      */     //   #821	-> 52
/*      */     //   #822	-> 67
/*      */     //   #823	-> 75
/*      */     //   #826	-> 81
/*      */     //   #830	-> 96
/*      */     //   #832	-> 118
/*      */     //   #834	-> 132
/*      */     //   #835	-> 139
/*      */     //   #836	-> 149
/*      */     //   #837	-> 159
/*      */     //   #839	-> 171
/*      */     //   #841	-> 179
/*      */     //   #842	-> 188
/*      */     //   #843	-> 198
/*      */     //   #844	-> 218
/*      */     //   #845	-> 228
/*      */     //   #847	-> 250
/*      */     //   #848	-> 276
/*      */     //   #849	-> 286
/*      */     //   #851	-> 310
/*      */     //   #832	-> 333
/*      */     //   #856	-> 339
/*      */     //   #858	-> 353
/*      */     //   #859	-> 360
/*      */     //   #861	-> 370
/*      */     //   #862	-> 391
/*      */     //   #864	-> 398
/*      */     //   #865	-> 418
/*      */     //   #866	-> 433
/*      */     //   #867	-> 439
/*      */     //   #868	-> 442
/*      */     //   #870	-> 473
/*      */     //   #871	-> 488
/*      */     //   #873	-> 500
/*      */     //   #877	-> 520
/*      */     //   #878	-> 541
/*      */     //   #880	-> 547
/*      */     //   #881	-> 564
/*      */     //   #882	-> 586
/*      */     //   #887	-> 598
/*      */     //   #888	-> 619
/*      */     //   #890	-> 625
/*      */     //   #891	-> 642
/*      */     //   #892	-> 664
/*      */     //   #896	-> 676
/*      */     //   #900	-> 697
/*      */     //   #904	-> 741
/*      */     //   #909	-> 751
/*      */     //   #910	-> 772
/*      */     //   #912	-> 786
/*      */     //   #914	-> 803
/*      */     //   #918	-> 806
/*      */     //   #920	-> 820
/*      */     //   #922	-> 838
/*      */     //   #923	-> 847
/*      */     //   #925	-> 864
/*      */     //   #856	-> 867
/*      */     //   #928	-> 873
/*      */     //   #930	-> 889
/*      */     //   #931	-> 896
/*      */     //   #932	-> 906
/*      */     //   #933	-> 914
/*      */     //   #934	-> 922
/*      */     //   #928	-> 931
/*      */     //   #937	-> 937 }
/*      */   private void b(float[][] paramArrayOffloat, int paramInt1, int paramInt2) { d d = (this.q.b[paramInt1]).b[paramInt2]; float[][] arrayOfFloat = paramArrayOffloat; if (d.e != 0 && d.f == 2) { int i; for (i = 0; i < 576; i++) this.f[i] = 0.0F;  if (d.g != 0) { for (i = 0; i < 36; i++) { int j = i % 18; int i1 = (i - j) / 18; this.f[i] = arrayOfFloat[i1][j]; }  for (paramInt2 = 3; paramInt2 < 13; paramInt2++) { i = (this.O[this.z]).b[paramInt2]; int j = (this.O[this.z]).b[paramInt2 + 1] - i; int i1 = (i << 2) - i; byte b1; for (i = 0, b1 = 0; i < j; i++, b1 += 3) { int i2 = i1 + i; int i3 = i1 + b1; int i4 = i2 % 18; int i5 = (i2 - i4) / 18; this.f[i3] = arrayOfFloat[i5][i4]; i2 += j; i3++; i4 = i2 % 18; i5 = (i2 - i4) / 18; this.f[i3] = arrayOfFloat[i5][i4]; i2 += j; i3++; i4 = i2 % 18; i5 = (i2 - i4) / 18; this.f[i3] = arrayOfFloat[i5][i4]; }  }  } else { for (i = 0; i < 576; i++) { int j, i1 = (j = T[this.z][i]) % 18; int i2 = (j - i1) / 18; this.f[i] = arrayOfFloat[i2][i1]; }  }  } else { for (byte b1 = 0; b1 < 'ɀ'; b1++) { int i = b1 % 18; int j = (b1 - i) / 18; this.f[b1] = arrayOfFloat[j][i]; }  }  }
/*      */   private void a(int paramInt) { if (this.w == 1) { for (paramInt = 0; paramInt < 32; paramInt++) { for (byte b1 = 0; b1 < 18; b1 += 3) { this.e[0][paramInt][b1] = this.d[0][paramInt][b1]; this.e[0][paramInt][b1 + 1] = this.d[0][paramInt][b1 + 1]; this.e[0][paramInt][b1 + 2] = this.d[0][paramInt][b1 + 2]; }  }  } else { d d = (this.q.b[0]).b[paramInt]; int i = this.k.i(); boolean bool1 = (this.k.f() == 1 && (i & 0x2) != 0) ? true : false; boolean bool2 = (this.k.f() == 1 && (i & 0x1) != 0) ? true : false; boolean bool3 = (this.k.a() == 0 || this.k.a() == 2) ? true : false; int i1 = d.d & 0x1; int j; for (j = 0; j < 576; j++) { this.H[j] = 7; this.I[j] = 0.0F; }  if (bool2) if (d.e != 0 && d.f == 2) { if (d.g != 0) { int i2 = 0; for (byte b2 = 0; b2 < 3; b2++) { int i4 = 2; for (i = 12; i >= 3; i--) { j = (this.O[this.z]).b[i]; int i5 = (this.O[this.z]).b[i + 1] - j; j = (j << 2) - j + (b2 + 1) * i5 - 1; while (i5 > 0) { if (this.d[1][j / 18][j % 18] != 0.0F) { i4 = i; i = -10; i5 = -10; }  i5--; j--; }  }  if ((i = i4 + 1) > i2) i2 = i;  while (i < 12) { j = (this.O[this.z]).b[i]; int i5 = (this.O[this.z]).b[i + 1] - j; j = (j << 2) - j + b2 * i5; for (; i5 > 0; i5--) { this.H[j] = (this.s[1]).b[b2][i]; if (this.H[j] != 7) if (bool3) { a(this.H[j], i1, j); } else { this.I[j] = S[this.H[j]]; }   j++; }  i++; }  i = (this.O[this.z]).b[10]; int i3 = (this.O[this.z]).b[11] - i; i = (i << 2) - i + b2 * i3; j = (this.O[this.z]).b[11]; i3 = (this.O[this.z]).b[12] - j; j = (j << 2) - j + b2 * i3; for (; i3 > 0; i3--) { this.H[j] = this.H[i]; if (bool3) { this.h[0][j] = this.h[0][i]; this.h[1][j] = this.h[1][i]; } else { this.I[j] = this.I[i]; }  j++; }  }  if (i2 <= 3) { j = 2; i = 17; int i3 = -1; while (j >= 0) { if (this.d[1][j][i] != 0.0F) { i3 = (j << 4) + (j << 1) + i; j = -1; continue; }  i--; if (i < 0) { j--; i = 17; }  }  j = 0; while ((this.O[this.z]).a[j] <= i3) j++;  i = j; j = (this.O[this.z]).a[j]; for (; i < 8; i++) { i3 = (this.O[this.z]).a[i + 1] - (this.O[this.z]).a[i]; for (; i3 > 0; i3--) { this.H[j] = (this.s[1]).a[i]; if (this.H[j] != 7) if (bool3) { a(this.H[j], i1, j); } else { this.I[j] = S[this.H[j]]; }   j++; }  }  }  } else { for (byte b2 = 0; b2 < 3; b2++) { int i3 = -1; for (i = 12; i >= 0; i--) { j = (this.O[this.z]).b[i]; int i4 = (this.O[this.z]).b[i + 1] - j; j = (j << 2) - j + (b2 + 1) * i4 - 1; while (i4 > 0) { if (this.d[1][j / 18][j % 18] != 0.0F) { i3 = i; i = -10; i4 = -10; }  i4--; j--; }  }  i = i3 + 1; while (i < 12) { j = (this.O[this.z]).b[i]; int i4 = (this.O[this.z]).b[i + 1] - j; j = (j << 2) - j + b2 * i4; for (; i4 > 0; i4--) { this.H[j] = (this.s[1]).b[b2][i]; if (this.H[j] != 7) if (bool3) { a(this.H[j], i1, j); } else { this.I[j] = S[this.H[j]]; }   j++; }  i++; }  j = (this.O[this.z]).b[10]; int i2 = (i3 = (this.O[this.z]).b[11]) - j; i = (j << 2) - j + b2 * i2; i2 = (this.O[this.z]).b[12] - i3; j = (i3 << 2) - i3 + b2 * i2; for (; i2 > 0; i2--) { this.H[j] = this.H[i]; if (bool3) { this.h[0][j] = this.h[0][i]; this.h[1][j] = this.h[1][i]; } else { this.I[j] = this.I[i]; }  j++; }  }  }  } else { j = 31; i = 17; int i2 = 0; while (j >= 0) { if (this.d[1][j][i] != 0.0F) { i2 = (j << 4) + (j << 1) + i; j = -1; continue; }  i--; if (i < 0) { j--; i = 17; }  }  j = 0; while ((this.O[this.z]).a[j] <= i2) j++;  i = j; j = (this.O[this.z]).a[j]; for (; i < 21; i++) { i2 = (this.O[this.z]).a[i + 1] - (this.O[this.z]).a[i]; for (; i2 > 0; i2--) { this.H[j] = (this.s[1]).a[i]; if (this.H[j] != 7) if (bool3) { a(this.H[j], i1, j); } else { this.I[j] = S[this.H[j]]; }   j++; }  }  i = (this.O[this.z]).a[20]; for (i2 = 576 - (this.O[this.z]).a[21]; i2 > 0 && j < 576; i2--) { this.H[j] = this.H[i]; if (bool3) { this.h[0][j] = this.h[0][i]; this.h[1][j] = this.h[1][i]; } else { this.I[j] = this.I[i]; }  j++; }  }   j = 0; for (byte b1 = 0; b1 < 32; b1++) { for (i = 0; i < 18; i++) { if (this.H[j] == 7) { if (bool1) { this.e[0][b1][i] = (this.d[0][b1][i] + this.d[1][b1][i]) * 0.70710677F; this.e[1][b1][i] = (this.d[0][b1][i] - this.d[1][b1][i]) * 0.70710677F; } else { this.e[0][b1][i] = this.d[0][b1][i]; this.e[1][b1][i] = this.d[1][b1][i]; }  } else if (bool2) { if (bool3) { this.e[0][b1][i] = this.d[0][b1][i] * this.h[0][j]; this.e[1][b1][i] = this.d[0][b1][i] * this.h[1][j]; } else { this.e[1][b1][i] = this.d[0][b1][i] / (1.0F + this.I[j]); this.e[0][b1][i] = this.e[1][b1][i] * this.I[j]; }  }  j++; }  }  }  }
/*      */   private void e(int paramInt1, int paramInt2) { char c; d d; if ((d = (this.q.b[paramInt1]).b[paramInt2]).e != 0 && d.f == 2 && d.g == 0) return;  if (d.e != 0 && d.g != 0 && d.f == 2) { c = '\022'; } else { c = 'Ȯ'; }  for (byte b1 = 0; b1 < c; b1 += 18) { for (paramInt2 = 0; paramInt2 < 8; paramInt2++) { int i = b1 + 17 - paramInt2; int j = b1 + 18 + paramInt2; float f1 = this.f[i]; float f2 = this.f[j]; this.f[i] = f1 * U[paramInt2] - f2 * V[paramInt2]; this.f[j] = f2 * U[paramInt2] + f1 * V[paramInt2]; }  }  } private void f(int paramInt1, int paramInt2) { d d = (this.q.b[paramInt1]).b[paramInt2]; for (byte b1 = 0; b1 < 'ɀ'; b1 += 18) { paramInt2 = (d.e != 0 && d.g != 0 && b1 < 36) ? 0 : d.f; float[] arrayOfFloat1 = this.f; byte b2; for (b2 = 0; b2 < 18; b2++) this.J[b2] = arrayOfFloat1[b2 + b1];  a(this.J, this.K, paramInt2); for (b2 = 0; b2 < 18; b2++) arrayOfFloat1[b2 + b1] = this.J[b2];  float[][] arrayOfFloat = this.g; arrayOfFloat1[b1 + 0] = this.K[0] + arrayOfFloat[paramInt1][b1]; arrayOfFloat[paramInt1][b1] = this.K[18]; arrayOfFloat1[b1 + 1] = this.K[1] + arrayOfFloat[paramInt1][b1 + 1]; arrayOfFloat[paramInt1][b1 + 1] = this.K[19]; arrayOfFloat1[b1 + 2] = this.K[2] + arrayOfFloat[paramInt1][b1 + 2]; arrayOfFloat[paramInt1][b1 + 2] = this.K[20]; arrayOfFloat1[b1 + 3] = this.K[3] + arrayOfFloat[paramInt1][b1 + 3]; arrayOfFloat[paramInt1][b1 + 3] = this.K[21]; arrayOfFloat1[b1 + 4] = this.K[4] + arrayOfFloat[paramInt1][b1 + 4]; arrayOfFloat[paramInt1][b1 + 4] = this.K[22]; arrayOfFloat1[b1 + 5] = this.K[5] + arrayOfFloat[paramInt1][b1 + 5]; arrayOfFloat[paramInt1][b1 + 5] = this.K[23]; arrayOfFloat1[b1 + 6] = this.K[6] + arrayOfFloat[paramInt1][b1 + 6]; arrayOfFloat[paramInt1][b1 + 6] = this.K[24]; arrayOfFloat1[b1 + 7] = this.K[7] + arrayOfFloat[paramInt1][b1 + 7]; arrayOfFloat[paramInt1][b1 + 7] = this.K[25]; arrayOfFloat1[b1 + 8] = this.K[8] + arrayOfFloat[paramInt1][b1 + 8]; arrayOfFloat[paramInt1][b1 + 8] = this.K[26]; arrayOfFloat1[b1 + 9] = this.K[9] + arrayOfFloat[paramInt1][b1 + 9]; arrayOfFloat[paramInt1][b1 + 9] = this.K[27]; arrayOfFloat1[b1 + 10] = this.K[10] + arrayOfFloat[paramInt1][b1 + 10]; arrayOfFloat[paramInt1][b1 + 10] = this.K[28]; arrayOfFloat1[b1 + 11] = this.K[11] + arrayOfFloat[paramInt1][b1 + 11]; arrayOfFloat[paramInt1][b1 + 11] = this.K[29]; arrayOfFloat1[b1 + 12] = this.K[12] + arrayOfFloat[paramInt1][b1 + 12]; arrayOfFloat[paramInt1][b1 + 12] = this.K[30]; arrayOfFloat1[b1 + 13] = this.K[13] + arrayOfFloat[paramInt1][b1 + 13]; arrayOfFloat[paramInt1][b1 + 13] = this.K[31]; arrayOfFloat1[b1 + 14] = this.K[14] + arrayOfFloat[paramInt1][b1 + 14]; arrayOfFloat[paramInt1][b1 + 14] = this.K[32]; arrayOfFloat1[b1 + 15] = this.K[15] + arrayOfFloat[paramInt1][b1 + 15]; arrayOfFloat[paramInt1][b1 + 15] = this.K[33]; arrayOfFloat1[b1 + 16] = this.K[16] + arrayOfFloat[paramInt1][b1 + 16]; arrayOfFloat[paramInt1][b1 + 16] = this.K[34]; arrayOfFloat1[b1 + 17] = this.K[17] + arrayOfFloat[paramInt1][b1 + 17]; arrayOfFloat[paramInt1][b1 + 17] = this.K[35]; }  } private void d() { for (byte b1 = 0; b1 < 18; b1++) { for (byte b2 = 0; b2 < 18; b2 += 3) { this.e[0][b1][b2] = (this.e[0][b1][b2] + this.e[1][b1][b2]) * 0.5F; this.e[0][b1][b2 + 1] = (this.e[0][b1][b2 + 1] + this.e[1][b1][b2 + 1]) * 0.5F; this.e[0][b1][b2 + 2] = (this.e[0][b1][b2 + 2] + this.e[1][b1][b2 + 2]) * 0.5F; }  }  } private static void a(float[] paramArrayOffloat1, float[] paramArrayOffloat2, int paramInt) { if (paramInt == 2) { paramArrayOffloat2[0] = 0.0F; paramArrayOffloat2[1] = 0.0F; paramArrayOffloat2[2] = 0.0F; paramArrayOffloat2[3] = 0.0F; paramArrayOffloat2[4] = 0.0F; paramArrayOffloat2[5] = 0.0F; paramArrayOffloat2[6] = 0.0F; paramArrayOffloat2[7] = 0.0F; paramArrayOffloat2[8] = 0.0F; paramArrayOffloat2[9] = 0.0F; paramArrayOffloat2[10] = 0.0F; paramArrayOffloat2[11] = 0.0F; paramArrayOffloat2[12] = 0.0F; paramArrayOffloat2[13] = 0.0F; paramArrayOffloat2[14] = 0.0F; paramArrayOffloat2[15] = 0.0F; paramArrayOffloat2[16] = 0.0F; paramArrayOffloat2[17] = 0.0F; paramArrayOffloat2[18] = 0.0F; paramArrayOffloat2[19] = 0.0F; paramArrayOffloat2[20] = 0.0F; paramArrayOffloat2[21] = 0.0F; paramArrayOffloat2[22] = 0.0F; paramArrayOffloat2[23] = 0.0F; paramArrayOffloat2[24] = 0.0F; paramArrayOffloat2[25] = 0.0F; paramArrayOffloat2[26] = 0.0F; paramArrayOffloat2[27] = 0.0F; paramArrayOffloat2[28] = 0.0F; paramArrayOffloat2[29] = 0.0F; paramArrayOffloat2[30] = 0.0F; paramArrayOffloat2[31] = 0.0F; paramArrayOffloat2[32] = 0.0F; paramArrayOffloat2[33] = 0.0F; paramArrayOffloat2[34] = 0.0F; paramArrayOffloat2[35] = 0.0F; byte b1 = 0; for (paramInt = 0; paramInt < 3; paramInt++) { paramArrayOffloat1[paramInt + 15] = paramArrayOffloat1[paramInt + 15] + paramArrayOffloat1[paramInt + 12]; paramArrayOffloat1[paramInt + 12] = paramArrayOffloat1[paramInt + 12] + paramArrayOffloat1[paramInt + 9]; paramArrayOffloat1[paramInt + 9] = paramArrayOffloat1[paramInt + 9] + paramArrayOffloat1[paramInt + 6]; paramArrayOffloat1[paramInt + 6] = paramArrayOffloat1[paramInt + 6] + paramArrayOffloat1[paramInt + 3]; paramArrayOffloat1[paramInt + 3] = paramArrayOffloat1[paramInt + 3] + paramArrayOffloat1[paramInt + 0]; paramArrayOffloat1[paramInt + 15] = paramArrayOffloat1[paramInt + 15] + paramArrayOffloat1[paramInt + 9]; paramArrayOffloat1[paramInt + 9] = paramArrayOffloat1[paramInt + 9] + paramArrayOffloat1[paramInt + 3]; float f36 = paramArrayOffloat1[paramInt + 12] * 0.5F; float f37 = paramArrayOffloat1[paramInt + 6] * 0.8660254F; float f38 = paramArrayOffloat1[paramInt + 0] + f36; float f31 = paramArrayOffloat1[paramInt + 0] - paramArrayOffloat1[paramInt + 12]; float f30 = f38 + f37; float f32 = f38 - f37; f36 = paramArrayOffloat1[paramInt + 15] * 0.5F; f37 = paramArrayOffloat1[paramInt + 9] * 0.8660254F; f38 = paramArrayOffloat1[paramInt + 3] + f36; float f34 = paramArrayOffloat1[paramInt + 3] - paramArrayOffloat1[paramInt + 15]; float f35 = f38 + f37; float f33 = (f33 = f38 - f37) * 1.9318516F; f34 *= 0.70710677F; f35 *= 0.5176381F; float f39 = f30; f30 += f35; f35 = f39 - f35; f39 = f31; f31 += f34; f34 = f39 - f34; f39 = f32; f32 += f33; f33 = f39 - f33; f30 *= 0.5043145F; f31 *= 0.5411961F; f32 *= 0.6302362F; f33 *= 0.8213398F; f34 *= 1.306563F; f35 *= 3.830649F; f38 = -f30 * 0.7933533F; f39 = -f30 * 0.6087614F; f37 = -f31 * 0.9238795F; float f40 = -f31 * 0.38268343F; f36 = -f32 * 0.9914449F; float f41 = -f32 * 0.13052619F; f30 = f33; f31 = f34 * 0.38268343F; f32 = f35 * 0.6087614F; f33 = -f35 * 0.7933533F; f34 = -f34 * 0.9238795F; f35 = -f30 * 0.9914449F; f30 *= 0.13052619F; paramArrayOffloat2[b1 + 6] = paramArrayOffloat2[b1 + 6] + f30; paramArrayOffloat2[b1 + 7] = paramArrayOffloat2[b1 + 7] + f31; paramArrayOffloat2[b1 + 8] = paramArrayOffloat2[b1 + 8] + f32; paramArrayOffloat2[b1 + 9] = paramArrayOffloat2[b1 + 9] + f33; paramArrayOffloat2[b1 + 10] = paramArrayOffloat2[b1 + 10] + f34; paramArrayOffloat2[b1 + 11] = paramArrayOffloat2[b1 + 11] + f35; paramArrayOffloat2[b1 + 12] = paramArrayOffloat2[b1 + 12] + f36; paramArrayOffloat2[b1 + 13] = paramArrayOffloat2[b1 + 13] + f37; paramArrayOffloat2[b1 + 14] = paramArrayOffloat2[b1 + 14] + f38; paramArrayOffloat2[b1 + 15] = paramArrayOffloat2[b1 + 15] + f39; paramArrayOffloat2[b1 + 16] = paramArrayOffloat2[b1 + 16] + f40; paramArrayOffloat2[b1 + 17] = paramArrayOffloat2[b1 + 17] + f41; b1 += 6; }  return; }  paramArrayOffloat1[17] = paramArrayOffloat1[17] + paramArrayOffloat1[16]; paramArrayOffloat1[16] = paramArrayOffloat1[16] + paramArrayOffloat1[15]; paramArrayOffloat1[15] = paramArrayOffloat1[15] + paramArrayOffloat1[14]; paramArrayOffloat1[14] = paramArrayOffloat1[14] + paramArrayOffloat1[13]; paramArrayOffloat1[13] = paramArrayOffloat1[13] + paramArrayOffloat1[12]; paramArrayOffloat1[12] = paramArrayOffloat1[12] + paramArrayOffloat1[11]; paramArrayOffloat1[11] = paramArrayOffloat1[11] + paramArrayOffloat1[10]; paramArrayOffloat1[10] = paramArrayOffloat1[10] + paramArrayOffloat1[9]; paramArrayOffloat1[9] = paramArrayOffloat1[9] + paramArrayOffloat1[8]; paramArrayOffloat1[8] = paramArrayOffloat1[8] + paramArrayOffloat1[7]; paramArrayOffloat1[7] = paramArrayOffloat1[7] + paramArrayOffloat1[6]; paramArrayOffloat1[6] = paramArrayOffloat1[6] + paramArrayOffloat1[5]; paramArrayOffloat1[5] = paramArrayOffloat1[5] + paramArrayOffloat1[4]; paramArrayOffloat1[4] = paramArrayOffloat1[4] + paramArrayOffloat1[3]; paramArrayOffloat1[3] = paramArrayOffloat1[3] + paramArrayOffloat1[2]; paramArrayOffloat1[2] = paramArrayOffloat1[2] + paramArrayOffloat1[1]; paramArrayOffloat1[1] = paramArrayOffloat1[1] + paramArrayOffloat1[0]; paramArrayOffloat1[17] = paramArrayOffloat1[17] + paramArrayOffloat1[15]; paramArrayOffloat1[15] = paramArrayOffloat1[15] + paramArrayOffloat1[13]; paramArrayOffloat1[13] = paramArrayOffloat1[13] + paramArrayOffloat1[11]; paramArrayOffloat1[11] = paramArrayOffloat1[11] + paramArrayOffloat1[9]; paramArrayOffloat1[9] = paramArrayOffloat1[9] + paramArrayOffloat1[7]; paramArrayOffloat1[7] = paramArrayOffloat1[7] + paramArrayOffloat1[5]; paramArrayOffloat1[5] = paramArrayOffloat1[5] + paramArrayOffloat1[3]; paramArrayOffloat1[3] = paramArrayOffloat1[3] + paramArrayOffloat1[1]; float f2, f3, f20 = (f3 = (f2 = paramArrayOffloat1[0] + paramArrayOffloat1[0]) + paramArrayOffloat1[12]) + paramArrayOffloat1[4] * 1.8793852F + paramArrayOffloat1[8] * 1.5320889F + paramArrayOffloat1[16] * 0.34729636F; float f9 = f2 + paramArrayOffloat1[4] - paramArrayOffloat1[8] - paramArrayOffloat1[12] - paramArrayOffloat1[12] - paramArrayOffloat1[16]; float f8 = f3 - paramArrayOffloat1[4] * 0.34729636F - paramArrayOffloat1[8] * 1.8793852F + paramArrayOffloat1[16] * 1.5320889F; float f10 = f3 - paramArrayOffloat1[4] * 1.5320889F + paramArrayOffloat1[8] * 0.34729636F - paramArrayOffloat1[16] * 1.8793852F; float f11 = paramArrayOffloat1[0] - paramArrayOffloat1[4] + paramArrayOffloat1[8] - paramArrayOffloat1[12] + paramArrayOffloat1[16]; f2 = paramArrayOffloat1[6] * 1.7320508F; float f21 = paramArrayOffloat1[2] * 1.9696155F + f2 + paramArrayOffloat1[10] * 1.2855753F + paramArrayOffloat1[14] * 0.6840403F; float f12 = (paramArrayOffloat1[2] - paramArrayOffloat1[10] - paramArrayOffloat1[14]) * 1.7320508F; float f13 = paramArrayOffloat1[2] * 1.2855753F - f2 - paramArrayOffloat1[10] * 0.6840403F + paramArrayOffloat1[14] * 1.9696155F; float f7 = paramArrayOffloat1[2] * 0.6840403F - f2 + paramArrayOffloat1[10] * 1.9696155F - paramArrayOffloat1[14] * 1.2855753F; float f22 = (f3 = (f2 = paramArrayOffloat1[1] + paramArrayOffloat1[1]) + paramArrayOffloat1[13]) + paramArrayOffloat1[5] * 1.8793852F + paramArrayOffloat1[9] * 1.5320889F + paramArrayOffloat1[17] * 0.34729636F; float f23 = f2 + paramArrayOffloat1[5] - paramArrayOffloat1[9] - paramArrayOffloat1[13] - paramArrayOffloat1[13] - paramArrayOffloat1[17]; float f24 = f3 - paramArrayOffloat1[5] * 0.34729636F - paramArrayOffloat1[9] * 1.8793852F + paramArrayOffloat1[17] * 1.5320889F; float f14 = f3 - paramArrayOffloat1[5] * 1.5320889F + paramArrayOffloat1[9] * 0.34729636F - paramArrayOffloat1[17] * 1.8793852F; float f15 = (paramArrayOffloat1[1] - paramArrayOffloat1[5] + paramArrayOffloat1[9] - paramArrayOffloat1[13] + paramArrayOffloat1[17]) * 0.70710677F; f2 = paramArrayOffloat1[7] * 1.7320508F; float f25 = paramArrayOffloat1[3] * 1.9696155F + f2 + paramArrayOffloat1[11] * 1.2855753F + paramArrayOffloat1[15] * 0.6840403F; float f26 = (paramArrayOffloat1[3] - paramArrayOffloat1[11] - paramArrayOffloat1[15]) * 1.7320508F; float f27 = paramArrayOffloat1[3] * 1.2855753F - f2 - paramArrayOffloat1[11] * 0.6840403F + paramArrayOffloat1[15] * 1.9696155F; float f1 = paramArrayOffloat1[3] * 0.6840403F - f2 + paramArrayOffloat1[11] * 1.9696155F - paramArrayOffloat1[15] * 1.2855753F; float f28 = f20 + f21; float f29 = (f22 + f25) * 0.5019099F; f2 = f28 + f29; float f19 = f28 - f29; f28 = f9 + f12; f29 = (f23 + f26) * 0.5176381F; f3 = f28 + f29; float f18 = f28 - f29; f28 = f8 + f13; f29 = (f24 + f27) * 0.55168897F; float f4 = f28 + f29; float f17 = f28 - f29; f28 = f10 + f7; f29 = (f14 + f1) * 0.61038727F; float f5 = f28 + f29; float f16 = f28 - f29; float f6 = f11 + f15; f15 = f11 - f15; f28 = f10 - f7; f29 = (f14 - f1) * 0.8717234F; f7 = f28 + f29; f14 = f28 - f29; f28 = f8 - f13; f29 = (f24 - f27) * 1.1831008F; f8 = f28 + f29; f13 = f28 - f29; f28 = f9 - f12; f29 = (f23 - f26) * 1.9318516F; f9 = f28 + f29; f12 = f28 - f29; f28 = f20 - f21; f29 = (f22 - f25) * 5.7368565F; f10 = f28 + f29; f11 = f28 - f29; float[] arrayOfFloat = W[paramInt]; paramArrayOffloat2[0] = -f11 * arrayOfFloat[0]; paramArrayOffloat2[1] = -f12 * arrayOfFloat[1]; paramArrayOffloat2[2] = -f13 * arrayOfFloat[2]; paramArrayOffloat2[3] = -f14 * arrayOfFloat[3]; paramArrayOffloat2[4] = -f15 * arrayOfFloat[4]; paramArrayOffloat2[5] = -f16 * arrayOfFloat[5]; paramArrayOffloat2[6] = -f17 * arrayOfFloat[6]; paramArrayOffloat2[7] = -f18 * arrayOfFloat[7]; paramArrayOffloat2[8] = -f19 * arrayOfFloat[8]; paramArrayOffloat2[9] = f19 * arrayOfFloat[9]; paramArrayOffloat2[10] = f18 * arrayOfFloat[10]; paramArrayOffloat2[11] = f17 * arrayOfFloat[11]; paramArrayOffloat2[12] = f16 * arrayOfFloat[12]; paramArrayOffloat2[13] = f15 * arrayOfFloat[13]; paramArrayOffloat2[14] = f14 * arrayOfFloat[14]; paramArrayOffloat2[15] = f13 * arrayOfFloat[15]; paramArrayOffloat2[16] = f12 * arrayOfFloat[16]; paramArrayOffloat2[17] = f11 * arrayOfFloat[17]; paramArrayOffloat2[18] = f10 * arrayOfFloat[18]; paramArrayOffloat2[19] = f9 * arrayOfFloat[19]; paramArrayOffloat2[20] = f8 * arrayOfFloat[20]; paramArrayOffloat2[21] = f7 * arrayOfFloat[21]; paramArrayOffloat2[22] = f6 * arrayOfFloat[22]; paramArrayOffloat2[23] = f5 * arrayOfFloat[23]; paramArrayOffloat2[24] = f4 * arrayOfFloat[24]; paramArrayOffloat2[25] = f3 * arrayOfFloat[25]; paramArrayOffloat2[26] = f2 * arrayOfFloat[26]; paramArrayOffloat2[27] = f2 * arrayOfFloat[27]; paramArrayOffloat2[28] = f3 * arrayOfFloat[28]; paramArrayOffloat2[29] = f4 * arrayOfFloat[29]; paramArrayOffloat2[30] = f5 * arrayOfFloat[30]; paramArrayOffloat2[31] = f6 * arrayOfFloat[31]; paramArrayOffloat2[32] = f7 * arrayOfFloat[32]; paramArrayOffloat2[33] = f8 * arrayOfFloat[33]; paramArrayOffloat2[34] = f9 * arrayOfFloat[34]; paramArrayOffloat2[35] = f10 * arrayOfFloat[35]; } static class b
/*      */   {
/* 1739 */     public int[] a; public b() { this.a = new int[23];
/* 1740 */       this.b = new int[14]; }
/*      */     
/*      */     public int[] b;
/*      */     public b(int[] param1ArrayOfint1, int[] param1ArrayOfint2) {
/* 1744 */       this.a = param1ArrayOfint1;
/* 1745 */       this.b = param1ArrayOfint2;
/*      */     }
/*      */   }
/*      */   
/*      */   static class d {
/* 1750 */     public int a = 0;
/* 1751 */     public int b = 0;
/* 1752 */     public int c = 0;
/* 1753 */     public int d = 0;
/* 1754 */     public int e = 0;
/* 1755 */     public int f = 0;
/* 1756 */     public int g = 0;
/*      */     public int[] h;
/*      */     public int[] i;
/* 1759 */     public int j = 0;
/* 1760 */     public int k = 0;
/* 1761 */     public int l = 0;
/* 1762 */     public int m = 0;
/* 1763 */     public int n = 0;
/*      */ 
/*      */ 
/*      */ 
/*      */     
/*      */     public d() {
/* 1769 */       this.h = new int[3];
/* 1770 */       this.i = new int[3];
/*      */     }
/*      */   }
/*      */ 
/*      */   
/*      */   static class e
/*      */   {
/*      */     public int[] a;
/*      */     
/*      */     public k.d[] b;
/*      */     
/*      */     public e() {
/* 1782 */       this.a = new int[4];
/* 1783 */       this.b = new k.d[2];
/* 1784 */       this.b[0] = new k.d();
/* 1785 */       this.b[1] = new k.d();
/*      */     }
/*      */   }
/*      */   
/*      */   static class a
/*      */   {
/* 1791 */     public int a = 0;
/*      */ 
/*      */     
/*      */     public k.e[] b;
/*      */ 
/*      */ 
/*      */     
/*      */     public a() {
/* 1799 */       this.b = new k.e[2];
/* 1800 */       this.b[0] = new k.e();
/* 1801 */       this.b[1] = new k.e();
/*      */     }
/*      */   }
/*      */ 
/*      */ 
/*      */ 
/*      */ 
/*      */ 
/*      */ 
/*      */   
/*      */   static class f
/*      */   {
/* 1813 */     public int[] a = new int[23];
/* 1814 */     public int[][] b = new int[3][13];
/*      */   }
/*      */ 
/*      */ 
/*      */ 
/*      */ 
/*      */ 
/*      */ 
/*      */ 
/*      */ 
/*      */ 
/*      */ 
/*      */ 
/*      */ 
/*      */ 
/*      */   
/* 1830 */   private static final int[][] M = new int[][] { { 0, 0, 0, 0, 3, 1, 1, 1, 2, 2, 2, 3, 3, 3, 4, 4 }, { 0, 1, 2, 3, 0, 1, 2, 3, 1, 2, 3, 1, 2, 3, 2, 3 } };
/*      */ 
/*      */   
/* 1833 */   private static int[] N = new int[] { 0, 0, 0, 0, 0, 0, 0, 0, 0, 0, 0, 1, 1, 1, 1, 2, 2, 3, 3, 3, 2, 0 };
/*      */   
/*      */   private b[] O;
/*      */   
/* 1837 */   private static float[] P = new float[] { 1.0F, 0.70710677F, 0.5F, 0.35355338F, 0.25F, 0.17677669F, 0.125F, 0.088388346F, 0.0625F, 0.044194173F, 0.03125F, 0.022097087F, 0.015625F, 0.011048543F, 0.0078125F, 0.0055242716F, 0.00390625F, 0.0027621358F, 0.001953125F, 0.0013810679F, 9.765625E-4F, 6.9053395E-4F, 4.8828125E-4F, 3.4526698E-4F, 2.4414062E-4F, 1.7263349E-4F, 1.2207031E-4F, 8.6316744E-5F, 6.1035156E-5F, 4.3158372E-5F, 3.0517578E-5F, 2.1579186E-5F, 1.5258789E-5F, 1.0789593E-5F, 7.6293945E-6F, 5.3947965E-6F, 3.8146973E-6F, 2.6973983E-6F, 1.9073486E-6F, 1.3486991E-6F, 9.536743E-7F, 6.7434956E-7F, 4.7683716E-7F, 3.3717478E-7F, 2.3841858E-7F, 1.6858739E-7F, 1.1920929E-7F, 8.4293696E-8F, 5.9604645E-8F, 4.2146848E-8F, 2.9802322E-8F, 2.1073424E-8F, 1.4901161E-8F, 1.0536712E-8F, 7.450581E-9F, 5.268356E-9F, 3.7252903E-9F, 2.634178E-9F, 1.8626451E-9F, 1.317089E-9F, 9.313226E-10F, 6.585445E-10F, 4.656613E-10F, 3.2927225E-10F };
/*      */ 
/*      */ 
/*      */ 
/*      */ 
/*      */ 
/*      */ 
/*      */ 
/*      */ 
/*      */ 
/*      */ 
/*      */ 
/*      */   
/* 1850 */   private static float[] Q = e();
/*      */   
/*      */   private static float[] e() {
/* 1853 */     float[] arrayOfFloat = new float[8192];
/*      */ 
/*      */     
/* 1856 */     for (byte b1 = 0; b1 < ' '; b1++)
/* 1857 */       arrayOfFloat[b1] = (float)Math.pow(b1, 1.3333333333333333D); 
/* 1858 */     return arrayOfFloat;
/*      */   }
/*      */   
/* 1861 */   private static float[][] R = new float[][] { { 1.0F, 0.8408964F, 0.70710677F, 0.59460354F, 0.5F, 0.4204482F, 0.35355338F, 0.29730177F, 0.25F, 0.2102241F, 0.17677669F, 0.14865088F, 0.125F, 0.10511205F, 0.088388346F, 0.07432544F, 0.0625F, 0.052556027F, 0.044194173F, 0.03716272F, 0.03125F, 0.026278013F, 0.022097087F, 0.01858136F, 0.015625F, 0.013139007F, 0.011048543F, 0.00929068F, 0.0078125F, 0.0065695033F, 0.0055242716F, 0.00464534F }, { 1.0F, 0.70710677F, 0.5F, 0.35355338F, 0.25F, 0.17677669F, 0.125F, 0.088388346F, 0.0625F, 0.044194173F, 0.03125F, 0.022097087F, 0.015625F, 0.011048543F, 0.0078125F, 0.0055242716F, 0.00390625F, 0.0027621358F, 0.001953125F, 0.0013810679F, 9.765625E-4F, 6.9053395E-4F, 4.8828125E-4F, 3.4526698E-4F, 2.4414062E-4F, 1.7263349E-4F, 1.2207031E-4F, 8.6316744E-5F, 6.1035156E-5F, 4.3158372E-5F, 3.0517578E-5F, 2.1579186E-5F } };
/*      */ 
/*      */ 
/*      */ 
/*      */ 
/*      */ 
/*      */ 
/*      */ 
/*      */ 
/*      */ 
/*      */ 
/*      */ 
/*      */ 
/*      */   
/* 1875 */   private static float[] S = new float[] { 0.0F, 0.2679492F, 0.57735026F, 1.0F, 1.7320508F, 3.732051F, 1.0E11F, -3.732051F, -1.7320508F, -1.0F, -0.57735026F, -0.2679492F, 0.0F, 0.2679492F, 0.57735026F, 1.0F };
/*      */ 
/*      */ 
/*      */ 
/*      */ 
/*      */ 
/*      */   
/*      */   private static int[][] T;
/*      */ 
/*      */ 
/*      */ 
/*      */ 
/*      */ 
/*      */   
/*      */   private static int[] a(int[] paramArrayOfint) {
/* 1890 */     byte b1 = 0;
/* 1891 */     int[] arrayOfInt = new int[576];
/* 1892 */     for (byte b2 = 0; b2 < 13; b2++) {
/* 1893 */       int i = paramArrayOfint[b2];
/* 1894 */       int j = paramArrayOfint[b2 + 1];
/* 1895 */       for (byte b3 = 0; b3 < 3; b3++) {
/* 1896 */         for (int i1 = i; i1 < j; i1++)
/* 1897 */           arrayOfInt[3 * i1 + b3] = b1++; 
/*      */       } 
/* 1899 */     }  return arrayOfInt;
/*      */   }
/*      */   
/* 1902 */   private static final float[] U = new float[] { 0.8574929F, 0.881742F, 0.94962865F, 0.9833146F, 0.9955178F, 0.9991606F, 0.9998992F, 0.99999315F };
/*      */ 
/*      */   
/* 1905 */   private static final float[] V = new float[] { -0.51449573F, -0.47173196F, -0.31337744F, -0.1819132F, -0.09457419F, -0.040965583F, -0.014198569F, -0.0036999746F };
/*      */ 
/*      */ 
/*      */ 
/*      */ 
/*      */ 
/*      */ 
/*      */ 
/*      */ 
/*      */ 
/*      */ 
/*      */ 
/*      */ 
/*      */ 
/*      */ 
/*      */ 
/*      */ 
/*      */   
/* 1923 */   private static float[][] W = new float[][] { { -0.016141215F, -0.05360318F, -0.100707136F, -0.16280818F, -0.5F, -0.38388735F, -0.6206114F, -1.1659756F, -3.8720753F, -4.225629F, -1.519529F, -0.97416484F, -0.73744076F, -1.2071068F, -0.5163616F, -0.45426053F, -0.40715656F, -0.3696946F, -0.3387627F, -0.31242222F, -0.28939587F, -0.26880082F, -0.5F, -0.23251417F, -0.21596715F, -0.20004979F, -0.18449493F, -0.16905846F, -0.15350361F, -0.13758625F, -0.12103922F, -0.20710678F, -0.084752575F, -0.06415752F, -0.041131172F, -0.014790705F }, { -0.016141215F, -0.05360318F, -0.100707136F, -0.16280818F, -0.5F, -0.38388735F, -0.6206114F, -1.1659756F, -3.8720753F, -4.225629F, -1.519529F, -0.97416484F, -0.73744076F, -1.2071068F, -0.5163616F, -0.45426053F, -0.40715656F, -0.3696946F, -0.33908543F, -0.3151181F, -0.29642227F, -0.28184548F, -0.5411961F, -0.2621323F, -0.25387916F, -0.2329629F, -0.19852729F, -0.15233535F, -0.0964964F, -0.03342383F, 0.0F, 0.0F, 0.0F, 0.0F, 0.0F, 0.0F }, { -0.0483008F, -0.15715657F, -0.28325045F, -0.42953748F, -1.2071068F, -0.8242648F, -1.1451749F, -1.769529F, -4.5470223F, -3.489053F, -0.7329629F, -0.15076515F, 0.0F, 0.0F, 0.0F, 0.0F, 0.0F, 0.0F, 0.0F, 0.0F, 0.0F, 0.0F, 0.0F, 0.0F, 0.0F, 0.0F, 0.0F, 0.0F, 0.0F, 0.0F, 0.0F, 0.0F, 0.0F, 0.0F, 0.0F, 0.0F }, { 0.0F, 0.0F, 0.0F, 0.0F, 0.0F, 0.0F, -0.15076514F, -0.7329629F, -3.489053F, -4.5470223F, -1.769529F, -1.1451749F, -0.8313774F, -1.306563F, -0.54142016F, -0.46528974F, -0.4106699F, -0.3700468F, -0.3387627F, -0.31242222F, -0.28939587F, -0.26880082F, -0.5F, -0.23251417F, -0.21596715F, -0.20004979F, -0.18449493F, -0.16905846F, -0.15350361F, -0.13758625F, -0.12103922F, -0.20710678F, -0.084752575F, -0.06415752F, -0.041131172F, -0.014790705F } };
/*      */ 
/*      */ 
/*      */ 
/*      */ 
/*      */ 
/*      */ 
/*      */ 
/*      */ 
/*      */ 
/*      */ 
/*      */ 
/*      */ 
/*      */ 
/*      */ 
/*      */ 
/*      */ 
/*      */ 
/*      */ 
/*      */ 
/*      */ 
/*      */ 
/*      */ 
/*      */   
/*      */   class c
/*      */   {
/*      */     public c(k this$0, int[] param1ArrayOfint1, int[] param1ArrayOfint2) {}
/*      */   }
/*      */ 
/*      */ 
/*      */ 
/*      */ 
/*      */ 
/*      */ 
/*      */ 
/*      */ 
/*      */ 
/*      */ 
/*      */ 
/*      */ 
/*      */ 
/*      */ 
/*      */ 
/*      */ 
/*      */ 
/*      */ 
/*      */ 
/*      */ 
/*      */ 
/*      */   
/* 1973 */   private static int[][][] X = new int[][][] { { { 6, 5, 5, 5 }, { 9, 9, 9, 9 }, { 6, 9, 9, 9 } }, { { 6, 5, 7, 3 }, { 9, 9, 12, 6 }, { 6, 9, 12, 6 } }, { { 11, 10, 0, 0 }, { 18, 18, 0, 0 }, { 15, 18, 0, 0 } }, { { 7, 7, 7, 0 }, { 12, 12, 12, 0 }, { 6, 15, 12, 0 } }, { { 6, 6, 6, 3 }, { 12, 9, 9, 6 }, { 6, 12, 9, 6 } }, { { 8, 8, 5, 0 }, { 15, 12, 9, 0 }, { 6, 18, 9, 0 } } };
/*      */ }


/* Location:              C:\Program Files (x86)\Steam\steamapps\common\Infinitode 2\infinitode-2.jar!\b\a\a\k.class
 * Java compiler version: 6 (50.0)
 * JD-Core Version:       1.1.3
 */