/*      */ package com.d.e;
/*      */ 
/*      */ import com.a.a.b.c.a;
/*      */ import com.d.c.a.a;
/*      */ import com.d.c.a.c;
/*      */ import com.d.c.b.d;
/*      */ import com.d.c.f.a.a;
/*      */ import com.d.c.f.a.h;
/*      */ import com.d.c.f.c;
/*      */ import com.d.c.f.d;
/*      */ import com.d.i.ac;
/*      */ import com.d.i.ad;
/*      */ import com.d.i.c;
/*      */ import com.d.i.f;
/*      */ import com.d.i.l;
/*      */ import com.d.i.m;
/*      */ import com.d.i.r;
/*      */ import com.d.i.s;
/*      */ import com.d.i.u;
/*      */ import com.d.i.x;
/*      */ import java.util.ArrayList;
/*      */ import java.util.HashMap;
/*      */ import java.util.Iterator;
/*      */ import java.util.List;
/*      */ import java.util.Map;
/*      */ import org.w3c.dom.Element;
/*      */ import org.w3c.dom.Node;
/*      */ import org.w3c.dom.NodeList;
/*      */ 
/*      */ 
/*      */ 
/*      */ 
/*      */ 
/*      */ 
/*      */ 
/*      */ 
/*      */ 
/*      */ 
/*      */ 
/*      */ 
/*      */ 
/*      */ 
/*      */ 
/*      */ 
/*      */ 
/*      */ 
/*      */ 
/*      */ 
/*      */ 
/*      */ 
/*      */ 
/*      */ 
/*      */ 
/*      */ 
/*      */ 
/*      */ 
/*      */ 
/*      */ 
/*      */ 
/*      */ 
/*      */ 
/*      */ 
/*      */ 
/*      */ 
/*      */ 
/*      */ 
/*      */ 
/*      */ 
/*      */ 
/*      */ 
/*      */ 
/*      */ 
/*      */ 
/*      */ 
/*      */ 
/*      */ 
/*      */ 
/*      */ 
/*      */ 
/*      */ 
/*      */ 
/*      */ 
/*      */ 
/*      */ 
/*      */ 
/*      */ 
/*      */ 
/*      */ 
/*      */ 
/*      */ 
/*      */ 
/*      */ 
/*      */ 
/*      */ 
/*      */ 
/*      */ 
/*      */ 
/*      */ 
/*      */ 
/*      */ 
/*      */ 
/*      */ 
/*      */ 
/*      */ 
/*      */ 
/*      */ 
/*      */ 
/*      */ 
/*      */ 
/*      */ 
/*      */ 
/*      */ 
/*      */ 
/*      */ 
/*      */ 
/*      */ 
/*      */ 
/*      */ 
/*      */ 
/*      */ 
/*      */ 
/*      */ 
/*      */ 
/*      */ 
/*      */ 
/*      */ 
/*      */ 
/*      */ 
/*      */ 
/*      */ 
/*      */ 
/*      */ 
/*      */ 
/*      */ 
/*      */ 
/*      */ 
/*      */ 
/*      */ 
/*      */ 
/*      */ 
/*      */ 
/*      */ 
/*      */ 
/*      */ 
/*      */ 
/*      */ 
/*      */ 
/*      */ 
/*      */ 
/*      */ 
/*      */ 
/*      */ 
/*      */ 
/*      */ 
/*      */ 
/*      */ 
/*      */ 
/*      */ 
/*      */ 
/*      */ 
/*      */ 
/*      */ 
/*      */ 
/*      */ 
/*      */ 
/*      */ 
/*      */ 
/*      */ 
/*      */ 
/*      */ 
/*      */ 
/*      */ 
/*      */ 
/*      */ 
/*      */ 
/*      */ 
/*      */ 
/*      */ 
/*      */ 
/*      */ 
/*      */ 
/*      */ 
/*      */ 
/*      */ 
/*      */ 
/*      */ 
/*      */ 
/*      */ 
/*      */ 
/*      */ 
/*      */ 
/*      */ 
/*      */ 
/*      */ 
/*      */ 
/*      */ 
/*      */ 
/*      */ 
/*      */ 
/*      */ 
/*      */ 
/*      */ 
/*      */ 
/*      */ 
/*      */ 
/*      */ 
/*      */ 
/*      */ 
/*      */ 
/*      */ 
/*      */ 
/*      */ 
/*      */ 
/*      */ 
/*      */ 
/*      */ 
/*      */ 
/*      */ 
/*      */ 
/*      */ 
/*      */ 
/*      */ 
/*      */ 
/*      */ 
/*      */ 
/*      */ 
/*      */ 
/*      */ 
/*      */ 
/*      */ 
/*      */ 
/*      */ 
/*      */ 
/*      */ 
/*      */ 
/*      */ 
/*      */ 
/*      */ 
/*      */ 
/*      */ 
/*      */ 
/*      */ 
/*      */ 
/*      */ 
/*      */ 
/*      */ 
/*      */ 
/*      */ 
/*      */ 
/*      */ 
/*      */ 
/*      */ 
/*      */ 
/*      */ 
/*      */ 
/*      */ 
/*      */ 
/*      */ 
/*      */ 
/*      */ 
/*      */ 
/*      */ 
/*      */ 
/*      */ 
/*      */ 
/*      */ 
/*      */ 
/*      */ 
/*      */ 
/*      */ 
/*      */ 
/*      */ 
/*      */ 
/*      */ 
/*      */ 
/*      */ 
/*      */ 
/*      */ 
/*      */ 
/*      */ 
/*      */ 
/*      */ 
/*      */ 
/*      */ 
/*      */ 
/*      */ 
/*      */ 
/*      */ 
/*      */ 
/*      */ 
/*      */ 
/*      */ 
/*      */ 
/*      */ 
/*      */ 
/*      */ 
/*      */ 
/*      */ 
/*      */ 
/*      */ 
/*      */ 
/*      */ 
/*      */ 
/*      */ 
/*      */ 
/*      */ 
/*      */ 
/*      */ 
/*      */ 
/*      */ 
/*      */ 
/*      */ 
/*      */ 
/*      */ 
/*      */ 
/*      */ 
/*      */ 
/*      */ 
/*      */ 
/*      */ 
/*      */ 
/*      */ 
/*      */ 
/*      */ 
/*      */ 
/*      */ 
/*      */ 
/*      */ 
/*      */ 
/*      */ 
/*      */ 
/*      */ 
/*      */ 
/*      */ 
/*      */ 
/*      */ 
/*      */ 
/*      */ 
/*      */ 
/*      */ 
/*      */ 
/*      */ 
/*      */ 
/*      */ 
/*      */ 
/*      */ 
/*      */ 
/*      */ 
/*      */ 
/*      */ 
/*      */ 
/*      */ 
/*      */ 
/*      */ 
/*      */ 
/*      */ 
/*      */ 
/*      */ 
/*      */ 
/*      */ 
/*      */ 
/*      */ 
/*      */ 
/*      */ 
/*      */ 
/*      */ 
/*      */ 
/*      */ 
/*      */ 
/*      */ 
/*      */ 
/*      */ public class q
/*      */   implements d
/*      */ {
/*      */   private final Map<Node, Map<Node, Integer>> a;
/*      */   
/*      */   public static void a(v paramv, c paramc, int paramInt1, int paramInt2) {
/*      */     // Byte code:
/*      */     //   0: aload_1
/*      */     //   1: invokevirtual ai : ()Lorg/w3c/dom/Element;
/*      */     //   4: astore #4
/*      */     //   6: aload_0
/*      */     //   7: invokevirtual f : ()Lcom/d/a/d;
/*      */     //   10: aload #4
/*      */     //   12: invokevirtual a : (Lorg/w3c/dom/Element;)Lcom/d/a/d$b;
/*      */     //   15: dup
/*      */     //   16: astore #4
/*      */     //   18: invokevirtual a : ()B
/*      */     //   21: istore #4
/*      */     //   23: aload_1
/*      */     //   24: invokevirtual d_ : ()I
/*      */     //   27: dup
/*      */     //   28: istore #5
/*      */     //   30: istore #6
/*      */     //   32: aload_0
/*      */     //   33: iload_2
/*      */     //   34: aload_1
/*      */     //   35: invokestatic a : (Lcom/d/e/v;ILcom/d/i/f;)Lcom/d/i/u;
/*      */     //   38: dup
/*      */     //   39: astore #7
/*      */     //   41: iload #4
/*      */     //   43: invokevirtual a : (B)V
/*      */     //   46: aconst_null
/*      */     //   47: astore #8
/*      */     //   49: aconst_null
/*      */     //   50: astore #11
/*      */     //   52: new java/util/HashMap
/*      */     //   55: dup
/*      */     //   56: invokespecial <init> : ()V
/*      */     //   59: astore #12
/*      */     //   61: aload_1
/*      */     //   62: instanceof com/d/i/b
/*      */     //   65: ifeq -> 106
/*      */     //   68: aload_1
/*      */     //   69: checkcast com/d/i/b
/*      */     //   72: invokevirtual f : ()Ljava/util/List;
/*      */     //   75: dup
/*      */     //   76: astore #11
/*      */     //   78: ifnull -> 106
/*      */     //   81: new java/util/ArrayList
/*      */     //   84: dup
/*      */     //   85: aload #11
/*      */     //   87: invokespecial <init> : (Ljava/util/Collection;)V
/*      */     //   90: astore #11
/*      */     //   92: aload_0
/*      */     //   93: aload #7
/*      */     //   95: aload #11
/*      */     //   97: iload #5
/*      */     //   99: aload #12
/*      */     //   101: invokestatic a : (Lcom/d/e/v;Lcom/d/i/u;Ljava/util/List;ILjava/util/Map;)Lcom/d/i/r;
/*      */     //   104: astore #8
/*      */     //   106: aload #11
/*      */     //   108: ifnonnull -> 120
/*      */     //   111: new java/util/ArrayList
/*      */     //   114: dup
/*      */     //   115: invokespecial <init> : ()V
/*      */     //   118: astore #11
/*      */     //   120: iload #6
/*      */     //   122: aload_0
/*      */     //   123: invokevirtual l : ()Lcom/d/e/b;
/*      */     //   126: aload_0
/*      */     //   127: aload #7
/*      */     //   129: iload #6
/*      */     //   131: invokevirtual c : (Lcom/d/c/f/d;Lcom/d/i/u;I)I
/*      */     //   134: isub
/*      */     //   135: istore #6
/*      */     //   137: aload_1
/*      */     //   138: invokevirtual a : ()Lcom/d/c/f/c;
/*      */     //   141: dup
/*      */     //   142: astore #9
/*      */     //   144: aload_0
/*      */     //   145: invokevirtual c : (Lcom/d/c/f/d;)F
/*      */     //   148: f2i
/*      */     //   149: istore #13
/*      */     //   151: aload #9
/*      */     //   153: getstatic com/d/c/a/a.ap : Lcom/d/c/a/a;
/*      */     //   156: iload #5
/*      */     //   158: i2f
/*      */     //   159: aload_0
/*      */     //   160: invokevirtual b : (Lcom/d/c/a/a;FLcom/d/c/f/d;)F
/*      */     //   163: f2i
/*      */     //   164: istore #9
/*      */     //   166: iload #6
/*      */     //   168: iload #9
/*      */     //   170: isub
/*      */     //   171: istore #6
/*      */     //   173: iload #9
/*      */     //   175: iconst_0
/*      */     //   176: iadd
/*      */     //   177: istore #10
/*      */     //   179: aload_0
/*      */     //   180: invokevirtual u : ()Lcom/d/i/x;
/*      */     //   183: dup
/*      */     //   184: astore #14
/*      */     //   186: ifnull -> 219
/*      */     //   189: aload_1
/*      */     //   190: invokevirtual a : ()Lcom/d/c/f/c;
/*      */     //   193: invokevirtual au : ()Z
/*      */     //   196: ifeq -> 219
/*      */     //   199: iload #6
/*      */     //   201: aload #14
/*      */     //   203: invokevirtual e : ()I
/*      */     //   206: isub
/*      */     //   207: istore #6
/*      */     //   209: iload #10
/*      */     //   211: aload #14
/*      */     //   213: invokevirtual e : ()I
/*      */     //   216: iadd
/*      */     //   217: istore #10
/*      */     //   219: aload_0
/*      */     //   220: aconst_null
/*      */     //   221: invokevirtual a : (Lcom/d/i/x;)V
/*      */     //   224: new java/util/ArrayList
/*      */     //   227: dup
/*      */     //   228: invokespecial <init> : ()V
/*      */     //   231: astore #15
/*      */     //   233: iconst_0
/*      */     //   234: istore #16
/*      */     //   236: iconst_0
/*      */     //   237: istore #17
/*      */     //   239: iconst_0
/*      */     //   240: istore #18
/*      */     //   242: new java/util/ArrayList
/*      */     //   245: dup
/*      */     //   246: invokespecial <init> : ()V
/*      */     //   249: astore #19
/*      */     //   251: aload_0
/*      */     //   252: invokevirtual s : ()Lcom/d/e/ab;
/*      */     //   255: invokevirtual b : ()Z
/*      */     //   258: ifeq -> 280
/*      */     //   261: aload_1
/*      */     //   262: aload_0
/*      */     //   263: dup
/*      */     //   264: invokevirtual s : ()Lcom/d/e/ab;
/*      */     //   267: aload_1
/*      */     //   268: invokevirtual a : ()Lcom/d/c/f/c;
/*      */     //   271: invokevirtual a : (Lcom/d/c/f/c;)Lcom/d/c/f/c;
/*      */     //   274: invokevirtual a : (Lcom/d/e/v;Lcom/d/c/f/c;)V
/*      */     //   277: iconst_1
/*      */     //   278: istore #18
/*      */     //   280: aload_0
/*      */     //   281: invokevirtual t : ()Lcom/d/e/ab;
/*      */     //   284: invokevirtual b : ()Z
/*      */     //   287: istore #20
/*      */     //   289: iconst_0
/*      */     //   290: istore #21
/*      */     //   292: iconst_0
/*      */     //   293: istore #22
/*      */     //   295: aload_1
/*      */     //   296: invokevirtual G : ()Ljava/util/List;
/*      */     //   299: invokeinterface iterator : ()Ljava/util/Iterator;
/*      */     //   304: astore #23
/*      */     //   306: aload #23
/*      */     //   308: invokeinterface hasNext : ()Z
/*      */     //   313: ifeq -> 1654
/*      */     //   316: aload #23
/*      */     //   318: invokeinterface next : ()Ljava/lang/Object;
/*      */     //   323: checkcast com/d/e/ac
/*      */     //   326: dup
/*      */     //   327: astore #9
/*      */     //   329: invokeinterface a : ()Lcom/d/c/f/c;
/*      */     //   334: invokevirtual o : ()Z
/*      */     //   337: ifeq -> 1347
/*      */     //   340: aload #9
/*      */     //   342: checkcast com/d/i/q
/*      */     //   345: dup
/*      */     //   346: astore #24
/*      */     //   348: invokevirtual a : ()Lcom/d/c/f/c;
/*      */     //   351: astore #25
/*      */     //   353: aload #24
/*      */     //   355: invokevirtual g : ()Z
/*      */     //   358: ifeq -> 522
/*      */     //   361: aload #8
/*      */     //   363: astore #9
/*      */     //   365: new com/d/i/r
/*      */     //   368: dup
/*      */     //   369: aload_0
/*      */     //   370: aload #24
/*      */     //   372: invokevirtual h : ()Lorg/w3c/dom/Element;
/*      */     //   375: aload #25
/*      */     //   377: iload #5
/*      */     //   379: invokespecial <init> : (Lcom/d/e/v;Lorg/w3c/dom/Element;Lcom/d/c/f/c;I)V
/*      */     //   382: astore #8
/*      */     //   384: aload #11
/*      */     //   386: aload #24
/*      */     //   388: invokeinterface add : (Ljava/lang/Object;)Z
/*      */     //   393: pop
/*      */     //   394: aload #12
/*      */     //   396: aload #24
/*      */     //   398: aload #8
/*      */     //   400: invokeinterface put : (Ljava/lang/Object;Ljava/lang/Object;)Ljava/lang/Object;
/*      */     //   405: pop
/*      */     //   406: aload #9
/*      */     //   408: ifnonnull -> 422
/*      */     //   411: aload #7
/*      */     //   413: aload_0
/*      */     //   414: aload #8
/*      */     //   416: invokevirtual a : (Lcom/d/e/v;Lcom/d/i/f;)V
/*      */     //   419: goto -> 430
/*      */     //   422: aload #9
/*      */     //   424: aload_0
/*      */     //   425: aload #8
/*      */     //   427: invokevirtual a : (Lcom/d/e/v;Ljava/lang/Object;)V
/*      */     //   430: aload #8
/*      */     //   432: invokevirtual ai : ()Lorg/w3c/dom/Element;
/*      */     //   435: ifnull -> 494
/*      */     //   438: aload_0
/*      */     //   439: invokevirtual e : ()Lcom/d/d/l;
/*      */     //   442: aload #8
/*      */     //   444: invokevirtual ai : ()Lorg/w3c/dom/Element;
/*      */     //   447: invokeinterface g : (Lorg/w3c/dom/Element;)Ljava/lang/String;
/*      */     //   452: dup
/*      */     //   453: astore #9
/*      */     //   455: ifnull -> 466
/*      */     //   458: aload_0
/*      */     //   459: aload #9
/*      */     //   461: aload #8
/*      */     //   463: invokevirtual a : (Ljava/lang/String;Lcom/d/i/f;)V
/*      */     //   466: aload_0
/*      */     //   467: invokevirtual e : ()Lcom/d/d/l;
/*      */     //   470: aload #8
/*      */     //   472: invokevirtual ai : ()Lorg/w3c/dom/Element;
/*      */     //   475: invokeinterface b : (Lorg/w3c/dom/Element;)Ljava/lang/String;
/*      */     //   480: dup
/*      */     //   481: astore #26
/*      */     //   483: ifnull -> 494
/*      */     //   486: aload_0
/*      */     //   487: aload #26
/*      */     //   489: aload #8
/*      */     //   491: invokevirtual a : (Ljava/lang/String;Lcom/d/i/f;)V
/*      */     //   494: iload #16
/*      */     //   496: aload #25
/*      */     //   498: aload_0
/*      */     //   499: iload #5
/*      */     //   501: iconst_1
/*      */     //   502: invokevirtual a : (Lcom/d/c/f/d;II)I
/*      */     //   505: iadd
/*      */     //   506: istore #16
/*      */     //   508: iload #17
/*      */     //   510: aload #25
/*      */     //   512: aload_0
/*      */     //   513: iload #5
/*      */     //   515: iconst_2
/*      */     //   516: invokevirtual a : (Lcom/d/c/f/d;II)I
/*      */     //   519: iadd
/*      */     //   520: istore #17
/*      */     //   522: new com/d/e/x
/*      */     //   525: dup
/*      */     //   526: invokespecial <init> : ()V
/*      */     //   529: dup
/*      */     //   530: astore #9
/*      */     //   532: aload #24
/*      */     //   534: invokevirtual c : ()Ljava/lang/String;
/*      */     //   537: invokevirtual a : (Ljava/lang/String;)V
/*      */     //   540: aload #9
/*      */     //   542: aload #24
/*      */     //   544: invokevirtual q : ()Lorg/w3c/dom/Text;
/*      */     //   547: invokevirtual a : (Lorg/w3c/dom/Text;)V
/*      */     //   550: aload #24
/*      */     //   552: invokevirtual j : ()Z
/*      */     //   555: ifeq -> 573
/*      */     //   558: aload #9
/*      */     //   560: aload #24
/*      */     //   562: invokevirtual i : ()Lcom/d/c/b/b;
/*      */     //   565: invokeinterface a : ()Ljava/lang/String;
/*      */     //   570: invokevirtual a : (Ljava/lang/String;)V
/*      */     //   573: aload #9
/*      */     //   575: invokevirtual b : ()V
/*      */     //   578: iconst_0
/*      */     //   579: istore #26
/*      */     //   581: aload #9
/*      */     //   583: invokevirtual e : ()I
/*      */     //   586: ifne -> 598
/*      */     //   589: iconst_0
/*      */     //   590: iload #16
/*      */     //   592: iload #17
/*      */     //   594: iadd
/*      */     //   595: iadd
/*      */     //   596: istore #26
/*      */     //   598: aload #7
/*      */     //   600: aload #25
/*      */     //   602: aload #9
/*      */     //   604: iload #21
/*      */     //   606: invokestatic a : (Lcom/d/i/u;Lcom/d/c/f/c;Lcom/d/e/x;Z)Z
/*      */     //   609: ifeq -> 617
/*      */     //   612: aload #9
/*      */     //   614: invokestatic a : (Lcom/d/e/x;)V
/*      */     //   617: iconst_0
/*      */     //   618: istore #21
/*      */     //   620: aload #9
/*      */     //   622: invokevirtual f : ()Ljava/lang/String;
/*      */     //   625: invokevirtual length : ()I
/*      */     //   628: ifeq -> 1155
/*      */     //   631: iload #20
/*      */     //   633: ifeq -> 706
/*      */     //   636: aload #9
/*      */     //   638: invokevirtual k : ()Z
/*      */     //   641: ifne -> 706
/*      */     //   644: aload_0
/*      */     //   645: aload #7
/*      */     //   647: aload #8
/*      */     //   649: aload #9
/*      */     //   651: iload #5
/*      */     //   653: iload #6
/*      */     //   655: aload #24
/*      */     //   657: invokevirtual b : ()B
/*      */     //   660: invokestatic a : (Lcom/d/e/v;Lcom/d/i/u;Lcom/d/i/r;Lcom/d/e/x;IIB)Lcom/d/i/r;
/*      */     //   663: astore #26
/*      */     //   665: iload #6
/*      */     //   667: aload #26
/*      */     //   669: invokevirtual i : ()I
/*      */     //   672: isub
/*      */     //   673: istore #6
/*      */     //   675: aload #8
/*      */     //   677: invokevirtual g : ()Z
/*      */     //   680: ifeq -> 700
/*      */     //   683: iload #16
/*      */     //   685: aload #8
/*      */     //   687: invokevirtual a : ()Lcom/d/c/f/c;
/*      */     //   690: aload_0
/*      */     //   691: iload #5
/*      */     //   693: iconst_1
/*      */     //   694: invokevirtual a : (Lcom/d/c/f/d;II)I
/*      */     //   697: isub
/*      */     //   698: istore #16
/*      */     //   700: iconst_0
/*      */     //   701: istore #20
/*      */     //   703: goto -> 984
/*      */     //   706: aload #9
/*      */     //   708: invokevirtual m : ()V
/*      */     //   711: aload_0
/*      */     //   712: aload #24
/*      */     //   714: invokevirtual a : ()Lcom/d/c/f/c;
/*      */     //   717: iload #6
/*      */     //   719: iload #26
/*      */     //   721: isub
/*      */     //   722: aload #9
/*      */     //   724: iconst_0
/*      */     //   725: aload #24
/*      */     //   727: invokevirtual b : ()B
/*      */     //   730: invokestatic a : (Lcom/d/e/v;Lcom/d/c/f/c;ILcom/d/e/x;ZB)Lcom/d/i/s;
/*      */     //   733: astore #26
/*      */     //   735: aload #24
/*      */     //   737: invokevirtual a : ()Lcom/d/c/f/c;
/*      */     //   740: invokevirtual aA : ()Z
/*      */     //   743: ifeq -> 764
/*      */     //   746: aload #26
/*      */     //   748: aload #24
/*      */     //   750: invokevirtual a : ()Lcom/d/c/f/c;
/*      */     //   753: getstatic com/d/c/a/a.T : Lcom/d/c/a/a;
/*      */     //   756: fconst_0
/*      */     //   757: aload_0
/*      */     //   758: invokevirtual b : (Lcom/d/c/a/a;FLcom/d/c/f/d;)F
/*      */     //   761: invokevirtual a : (F)V
/*      */     //   764: aload #9
/*      */     //   766: invokevirtual h : ()Z
/*      */     //   769: ifeq -> 843
/*      */     //   772: aload #7
/*      */     //   774: invokevirtual f : ()Z
/*      */     //   777: ifne -> 843
/*      */     //   780: aload_0
/*      */     //   781: invokevirtual l : ()Lcom/d/e/b;
/*      */     //   784: aload_0
/*      */     //   785: aload #7
/*      */     //   787: iload #5
/*      */     //   789: invokevirtual d : (Lcom/d/c/f/d;Lcom/d/i/u;I)I
/*      */     //   792: dup
/*      */     //   793: istore #27
/*      */     //   795: ifle -> 843
/*      */     //   798: aload #7
/*      */     //   800: dup
/*      */     //   801: invokevirtual an : ()I
/*      */     //   804: iload #27
/*      */     //   806: iadd
/*      */     //   807: invokevirtual o : (I)V
/*      */     //   810: aload #7
/*      */     //   812: invokevirtual B : ()V
/*      */     //   815: iload #5
/*      */     //   817: dup
/*      */     //   818: istore #6
/*      */     //   820: aload_0
/*      */     //   821: invokevirtual l : ()Lcom/d/e/b;
/*      */     //   824: aload_0
/*      */     //   825: aload #7
/*      */     //   827: iload #5
/*      */     //   829: invokevirtual c : (Lcom/d/c/f/d;Lcom/d/i/u;I)I
/*      */     //   832: isub
/*      */     //   833: istore #6
/*      */     //   835: aload #9
/*      */     //   837: invokevirtual l : ()V
/*      */     //   840: goto -> 1147
/*      */     //   843: aload #9
/*      */     //   845: invokevirtual h : ()Z
/*      */     //   848: ifeq -> 867
/*      */     //   851: aload #9
/*      */     //   853: invokevirtual h : ()Z
/*      */     //   856: ifeq -> 979
/*      */     //   859: aload #7
/*      */     //   861: invokevirtual f : ()Z
/*      */     //   864: ifne -> 979
/*      */     //   867: aload #24
/*      */     //   869: invokevirtual j : ()Z
/*      */     //   872: ifeq -> 897
/*      */     //   875: aload #26
/*      */     //   877: new com/d/e/o
/*      */     //   880: dup
/*      */     //   881: aload #24
/*      */     //   883: invokevirtual i : ()Lcom/d/c/b/b;
/*      */     //   886: aload #24
/*      */     //   888: invokevirtual o : ()Lcom/d/i/e;
/*      */     //   891: invokespecial <init> : (Lcom/d/c/b/b;Lcom/d/i/e;)V
/*      */     //   894: invokevirtual a : (Lcom/d/e/o;)V
/*      */     //   897: aload #7
/*      */     //   899: aload #26
/*      */     //   901: invokevirtual h : ()Z
/*      */     //   904: invokevirtual c : (Z)V
/*      */     //   907: aload #8
/*      */     //   909: aload_0
/*      */     //   910: aload #26
/*      */     //   912: invokevirtual a : (Lcom/d/e/v;Ljava/lang/Object;)V
/*      */     //   915: aload #7
/*      */     //   917: iconst_1
/*      */     //   918: invokevirtual a : (Z)V
/*      */     //   921: aload #9
/*      */     //   923: dup
/*      */     //   924: invokevirtual c : ()I
/*      */     //   927: invokevirtual b : (I)V
/*      */     //   930: iload #6
/*      */     //   932: aload #26
/*      */     //   934: invokevirtual f : ()I
/*      */     //   937: isub
/*      */     //   938: istore #6
/*      */     //   940: aload #8
/*      */     //   942: invokevirtual g : ()Z
/*      */     //   945: ifeq -> 984
/*      */     //   948: aload #8
/*      */     //   950: invokevirtual a : ()Lcom/d/c/f/c;
/*      */     //   953: aload_0
/*      */     //   954: iload #5
/*      */     //   956: iconst_1
/*      */     //   957: invokevirtual a : (Lcom/d/c/f/d;II)I
/*      */     //   960: istore #27
/*      */     //   962: iload #16
/*      */     //   964: iload #27
/*      */     //   966: isub
/*      */     //   967: istore #16
/*      */     //   969: iload #6
/*      */     //   971: iload #27
/*      */     //   973: isub
/*      */     //   974: istore #6
/*      */     //   976: goto -> 984
/*      */     //   979: aload #9
/*      */     //   981: invokevirtual l : ()V
/*      */     //   984: aload #9
/*      */     //   986: invokevirtual i : ()Z
/*      */     //   989: ifeq -> 1147
/*      */     //   992: aload #24
/*      */     //   994: invokevirtual a : ()Lcom/d/c/f/c;
/*      */     //   997: invokevirtual at : ()Z
/*      */     //   1000: ifeq -> 1009
/*      */     //   1003: aload #7
/*      */     //   1005: aload_0
/*      */     //   1006: invokevirtual a : (Lcom/d/e/v;)V
/*      */     //   1009: aload #7
/*      */     //   1011: aload_0
/*      */     //   1012: aload_1
/*      */     //   1013: iload #13
/*      */     //   1015: iload #5
/*      */     //   1017: aload #15
/*      */     //   1019: iload #18
/*      */     //   1021: aload #19
/*      */     //   1023: aload #14
/*      */     //   1025: iload #10
/*      */     //   1027: aload_0
/*      */     //   1028: aload_1
/*      */     //   1029: iload_3
/*      */     //   1030: iload #22
/*      */     //   1032: invokestatic b : (Lcom/d/e/v;Lcom/d/i/c;II)Z
/*      */     //   1035: invokestatic a : (Lcom/d/i/u;Lcom/d/e/v;Lcom/d/i/c;IILjava/util/List;ZLjava/util/List;Lcom/d/i/x;IZ)V
/*      */     //   1038: iinc #22, 1
/*      */     //   1041: aconst_null
/*      */     //   1042: astore #14
/*      */     //   1044: iconst_0
/*      */     //   1045: istore #10
/*      */     //   1047: aload #7
/*      */     //   1049: invokevirtual c : ()Z
/*      */     //   1052: ifeq -> 1078
/*      */     //   1055: iload #18
/*      */     //   1057: ifeq -> 1078
/*      */     //   1060: aload #9
/*      */     //   1062: aload #24
/*      */     //   1064: invokevirtual c : ()Ljava/lang/String;
/*      */     //   1067: aload #24
/*      */     //   1069: invokevirtual a : ()Lcom/d/c/f/c;
/*      */     //   1072: invokestatic a : (Ljava/lang/String;Lcom/d/c/f/c;)Ljava/lang/String;
/*      */     //   1075: invokevirtual a : (Ljava/lang/String;)V
/*      */     //   1078: aload #7
/*      */     //   1080: astore #6
/*      */     //   1082: aload_0
/*      */     //   1083: aload #6
/*      */     //   1085: aload_1
/*      */     //   1086: invokestatic a : (Lcom/d/e/v;Lcom/d/i/u;Lcom/d/i/f;)Lcom/d/i/u;
/*      */     //   1089: dup
/*      */     //   1090: astore #7
/*      */     //   1092: iload #4
/*      */     //   1094: invokevirtual a : (B)V
/*      */     //   1097: aload_0
/*      */     //   1098: aload #7
/*      */     //   1100: aload #11
/*      */     //   1102: iload #5
/*      */     //   1104: aload #12
/*      */     //   1106: invokestatic a : (Lcom/d/e/v;Lcom/d/i/u;Ljava/util/List;ILjava/util/Map;)Lcom/d/i/r;
/*      */     //   1109: dup
/*      */     //   1110: astore #8
/*      */     //   1112: invokevirtual U : ()Lcom/d/i/f;
/*      */     //   1115: instanceof com/d/i/u
/*      */     //   1118: ifne -> 1127
/*      */     //   1121: aload #8
/*      */     //   1123: invokevirtual U : ()Lcom/d/i/f;
/*      */     //   1126: pop
/*      */     //   1127: iload #5
/*      */     //   1129: dup
/*      */     //   1130: istore #6
/*      */     //   1132: aload_0
/*      */     //   1133: invokevirtual l : ()Lcom/d/e/b;
/*      */     //   1136: aload_0
/*      */     //   1137: aload #7
/*      */     //   1139: iload #6
/*      */     //   1141: invokevirtual c : (Lcom/d/c/f/d;Lcom/d/i/u;I)I
/*      */     //   1144: isub
/*      */     //   1145: istore #6
/*      */     //   1147: aload #9
/*      */     //   1149: invokevirtual k : ()Z
/*      */     //   1152: ifeq -> 573
/*      */     //   1155: aload #24
/*      */     //   1157: invokevirtual f : ()Z
/*      */     //   1160: ifeq -> 1344
/*      */     //   1163: aload #25
/*      */     //   1165: aload_0
/*      */     //   1166: iload #5
/*      */     //   1168: iconst_2
/*      */     //   1169: invokevirtual a : (Lcom/d/c/f/d;II)I
/*      */     //   1172: istore #26
/*      */     //   1174: iload #17
/*      */     //   1176: iload #26
/*      */     //   1178: isub
/*      */     //   1179: istore #17
/*      */     //   1181: iload #6
/*      */     //   1183: iload #26
/*      */     //   1185: isub
/*      */     //   1186: istore #6
/*      */     //   1188: aload #11
/*      */     //   1190: dup
/*      */     //   1191: invokeinterface size : ()I
/*      */     //   1196: iconst_1
/*      */     //   1197: isub
/*      */     //   1198: invokeinterface remove : (I)Ljava/lang/Object;
/*      */     //   1203: pop
/*      */     //   1204: aload #8
/*      */     //   1206: invokevirtual h : ()Z
/*      */     //   1209: ifeq -> 1228
/*      */     //   1212: aload #8
/*      */     //   1214: aload_0
/*      */     //   1215: invokevirtual a : (Lcom/d/e/v;)V
/*      */     //   1218: aload #8
/*      */     //   1220: aload #24
/*      */     //   1222: invokevirtual g : ()Z
/*      */     //   1225: invokevirtual b : (Z)V
/*      */     //   1228: aload #8
/*      */     //   1230: iconst_1
/*      */     //   1231: invokevirtual a : (Z)V
/*      */     //   1234: aload #8
/*      */     //   1236: invokevirtual a : ()Lcom/d/c/f/c;
/*      */     //   1239: invokevirtual O : ()Z
/*      */     //   1242: ifeq -> 1319
/*      */     //   1245: aload #8
/*      */     //   1247: invokevirtual h : ()Z
/*      */     //   1250: ifne -> 1289
/*      */     //   1253: aload #8
/*      */     //   1255: invokevirtual ai : ()Lorg/w3c/dom/Element;
/*      */     //   1258: ifnull -> 1279
/*      */     //   1261: aload #8
/*      */     //   1263: invokevirtual ai : ()Lorg/w3c/dom/Element;
/*      */     //   1266: aload_0
/*      */     //   1267: invokevirtual o : ()Lcom/d/e/t;
/*      */     //   1270: invokevirtual f : ()Lcom/d/i/f;
/*      */     //   1273: invokevirtual ai : ()Lorg/w3c/dom/Element;
/*      */     //   1276: if_acmpeq -> 1289
/*      */     //   1279: new java/lang/RuntimeException
/*      */     //   1282: dup
/*      */     //   1283: ldc 'internal error'
/*      */     //   1285: invokespecial <init> : (Ljava/lang/String;)V
/*      */     //   1288: athrow
/*      */     //   1289: aload #8
/*      */     //   1291: invokevirtual h : ()Z
/*      */     //   1294: ifne -> 1319
/*      */     //   1297: aload_0
/*      */     //   1298: invokevirtual o : ()Lcom/d/e/t;
/*      */     //   1301: pop
/*      */     //   1302: aload_0
/*      */     //   1303: invokevirtual n : ()V
/*      */     //   1306: aload #19
/*      */     //   1308: aload #8
/*      */     //   1310: invokevirtual af : ()Lcom/d/e/t;
/*      */     //   1313: invokeinterface add : (Ljava/lang/Object;)Z
/*      */     //   1318: pop
/*      */     //   1319: aload #8
/*      */     //   1321: invokevirtual U : ()Lcom/d/i/f;
/*      */     //   1324: instanceof com/d/i/u
/*      */     //   1327: ifeq -> 1334
/*      */     //   1330: aconst_null
/*      */     //   1331: goto -> 1342
/*      */     //   1334: aload #8
/*      */     //   1336: invokevirtual U : ()Lcom/d/i/f;
/*      */     //   1339: checkcast com/d/i/r
/*      */     //   1342: astore #8
/*      */     //   1344: goto -> 306
/*      */     //   1347: aload #9
/*      */     //   1349: checkcast com/d/i/c
/*      */     //   1352: dup
/*      */     //   1353: astore #24
/*      */     //   1355: invokevirtual a : ()Lcom/d/c/f/c;
/*      */     //   1358: invokevirtual ag : ()Z
/*      */     //   1361: ifeq -> 1384
/*      */     //   1364: iload #6
/*      */     //   1366: aload_0
/*      */     //   1367: aload #7
/*      */     //   1369: aload #24
/*      */     //   1371: iload #6
/*      */     //   1373: aload #15
/*      */     //   1375: invokestatic a : (Lcom/d/e/v;Lcom/d/i/u;Lcom/d/i/c;ILjava/util/List;)I
/*      */     //   1378: isub
/*      */     //   1379: istore #6
/*      */     //   1381: goto -> 306
/*      */     //   1384: aload #24
/*      */     //   1386: invokevirtual a : ()Lcom/d/c/f/c;
/*      */     //   1389: invokevirtual p : ()Z
/*      */     //   1392: ifne -> 1406
/*      */     //   1395: aload #24
/*      */     //   1397: invokevirtual a : ()Lcom/d/c/f/c;
/*      */     //   1400: invokevirtual r : ()Z
/*      */     //   1403: ifeq -> 1651
/*      */     //   1406: aload_0
/*      */     //   1407: aload_1
/*      */     //   1408: aload #24
/*      */     //   1410: iload_2
/*      */     //   1411: invokestatic a : (Lcom/d/e/v;Lcom/d/i/c;Lcom/d/i/c;I)V
/*      */     //   1414: aload #24
/*      */     //   1416: invokevirtual Q : ()I
/*      */     //   1419: iload #6
/*      */     //   1421: if_icmple -> 1561
/*      */     //   1424: aload #7
/*      */     //   1426: invokevirtual f : ()Z
/*      */     //   1429: ifeq -> 1561
/*      */     //   1432: aload #7
/*      */     //   1434: aload_0
/*      */     //   1435: aload_1
/*      */     //   1436: iload #13
/*      */     //   1438: iload #5
/*      */     //   1440: aload #15
/*      */     //   1442: iload #18
/*      */     //   1444: aload #19
/*      */     //   1446: aload #14
/*      */     //   1448: iload #10
/*      */     //   1450: aload_0
/*      */     //   1451: aload_1
/*      */     //   1452: iload_3
/*      */     //   1453: iload #22
/*      */     //   1455: invokestatic b : (Lcom/d/e/v;Lcom/d/i/c;II)Z
/*      */     //   1458: invokestatic a : (Lcom/d/i/u;Lcom/d/e/v;Lcom/d/i/c;IILjava/util/List;ZLjava/util/List;Lcom/d/i/x;IZ)V
/*      */     //   1461: iinc #22, 1
/*      */     //   1464: aconst_null
/*      */     //   1465: astore #14
/*      */     //   1467: iconst_0
/*      */     //   1468: istore #10
/*      */     //   1470: aload #7
/*      */     //   1472: astore #6
/*      */     //   1474: aload_0
/*      */     //   1475: aload #6
/*      */     //   1477: aload_1
/*      */     //   1478: invokestatic a : (Lcom/d/e/v;Lcom/d/i/u;Lcom/d/i/f;)Lcom/d/i/u;
/*      */     //   1481: dup
/*      */     //   1482: astore #7
/*      */     //   1484: iload #4
/*      */     //   1486: invokevirtual a : (B)V
/*      */     //   1489: aload_0
/*      */     //   1490: aload #7
/*      */     //   1492: aload #11
/*      */     //   1494: iload #5
/*      */     //   1496: aload #12
/*      */     //   1498: invokestatic a : (Lcom/d/e/v;Lcom/d/i/u;Ljava/util/List;ILjava/util/Map;)Lcom/d/i/r;
/*      */     //   1501: dup
/*      */     //   1502: astore #8
/*      */     //   1504: ifnull -> 1518
/*      */     //   1507: aload #8
/*      */     //   1509: invokevirtual U : ()Lcom/d/i/f;
/*      */     //   1512: instanceof com/d/i/u
/*      */     //   1515: ifeq -> 1521
/*      */     //   1518: goto -> 1527
/*      */     //   1521: aload #8
/*      */     //   1523: invokevirtual U : ()Lcom/d/i/f;
/*      */     //   1526: pop
/*      */     //   1527: iload #5
/*      */     //   1529: dup
/*      */     //   1530: istore #6
/*      */     //   1532: aload_0
/*      */     //   1533: invokevirtual l : ()Lcom/d/e/b;
/*      */     //   1536: aload_0
/*      */     //   1537: aload #7
/*      */     //   1539: iload #6
/*      */     //   1541: invokevirtual c : (Lcom/d/c/f/d;Lcom/d/i/u;I)I
/*      */     //   1544: isub
/*      */     //   1545: istore #6
/*      */     //   1547: aload #24
/*      */     //   1549: aload_0
/*      */     //   1550: invokevirtual c : (Lcom/d/e/v;)V
/*      */     //   1553: aload_0
/*      */     //   1554: aload_1
/*      */     //   1555: aload #24
/*      */     //   1557: iload_2
/*      */     //   1558: invokestatic a : (Lcom/d/e/v;Lcom/d/i/c;Lcom/d/i/c;I)V
/*      */     //   1561: aload #8
/*      */     //   1563: ifnonnull -> 1577
/*      */     //   1566: aload #7
/*      */     //   1568: aload_0
/*      */     //   1569: aload #24
/*      */     //   1571: invokevirtual a : (Lcom/d/e/v;Lcom/d/i/f;)V
/*      */     //   1574: goto -> 1585
/*      */     //   1577: aload #8
/*      */     //   1579: aload_0
/*      */     //   1580: aload #24
/*      */     //   1582: invokevirtual a : (Lcom/d/e/v;Ljava/lang/Object;)V
/*      */     //   1585: aload #7
/*      */     //   1587: iconst_1
/*      */     //   1588: invokevirtual a : (Z)V
/*      */     //   1591: aload #7
/*      */     //   1593: iconst_1
/*      */     //   1594: invokevirtual b : (Z)V
/*      */     //   1597: iload #6
/*      */     //   1599: aload #24
/*      */     //   1601: invokevirtual Q : ()I
/*      */     //   1604: isub
/*      */     //   1605: istore #6
/*      */     //   1607: aload #8
/*      */     //   1609: ifnull -> 1637
/*      */     //   1612: aload #8
/*      */     //   1614: invokevirtual g : ()Z
/*      */     //   1617: ifeq -> 1637
/*      */     //   1620: iload #16
/*      */     //   1622: aload #8
/*      */     //   1624: invokevirtual a : ()Lcom/d/c/f/c;
/*      */     //   1627: aload_0
/*      */     //   1628: iload #5
/*      */     //   1630: iconst_1
/*      */     //   1631: invokevirtual a : (Lcom/d/c/f/d;II)I
/*      */     //   1634: isub
/*      */     //   1635: istore #16
/*      */     //   1637: iconst_0
/*      */     //   1638: istore #20
/*      */     //   1640: aload #24
/*      */     //   1642: invokevirtual Q : ()I
/*      */     //   1645: ifne -> 1651
/*      */     //   1648: iconst_1
/*      */     //   1649: istore #21
/*      */     //   1651: goto -> 306
/*      */     //   1654: aload #7
/*      */     //   1656: aload_0
/*      */     //   1657: invokevirtual a : (Lcom/d/e/v;)V
/*      */     //   1660: aload #7
/*      */     //   1662: aload_0
/*      */     //   1663: aload_1
/*      */     //   1664: iload #13
/*      */     //   1666: iload #5
/*      */     //   1668: aload #15
/*      */     //   1670: iload #18
/*      */     //   1672: aload #19
/*      */     //   1674: aload #14
/*      */     //   1676: iload #10
/*      */     //   1678: aload_0
/*      */     //   1679: aload_1
/*      */     //   1680: iload_3
/*      */     //   1681: iload #22
/*      */     //   1683: invokestatic b : (Lcom/d/e/v;Lcom/d/i/c;II)Z
/*      */     //   1686: invokestatic a : (Lcom/d/i/u;Lcom/d/e/v;Lcom/d/i/c;IILjava/util/List;ZLjava/util/List;Lcom/d/i/x;IZ)V
/*      */     //   1689: aload #7
/*      */     //   1691: invokevirtual c : ()Z
/*      */     //   1694: ifeq -> 1716
/*      */     //   1697: aload #7
/*      */     //   1699: invokevirtual as : ()I
/*      */     //   1702: ifne -> 1716
/*      */     //   1705: aload #14
/*      */     //   1707: ifnull -> 1716
/*      */     //   1710: aload_0
/*      */     //   1711: aload #14
/*      */     //   1713: invokevirtual a : (Lcom/d/i/x;)V
/*      */     //   1716: aload_1
/*      */     //   1717: iload #5
/*      */     //   1719: invokevirtual u : (I)V
/*      */     //   1722: aload_1
/*      */     //   1723: aload #7
/*      */     //   1725: invokevirtual an : ()I
/*      */     //   1728: aload #7
/*      */     //   1730: invokevirtual as : ()I
/*      */     //   1733: iadd
/*      */     //   1734: invokevirtual t : (I)V
/*      */     //   1737: return
/*      */     // Line number table:
/*      */     //   Java source line number -> byte code offset
/*      */     //   #60	-> 0
/*      */     //   #61	-> 6
/*      */     //   #62	-> 16
/*      */     //   #64	-> 23
/*      */     //   #65	-> 28
/*      */     //   #67	-> 32
/*      */     //   #68	-> 39
/*      */     //   #71	-> 46
/*      */     //   #76	-> 49
/*      */     //   #78	-> 52
/*      */     //   #80	-> 61
/*      */     //   #81	-> 68
/*      */     //   #82	-> 76
/*      */     //   #83	-> 81
/*      */     //   #84	-> 92
/*      */     //   #89	-> 106
/*      */     //   #90	-> 111
/*      */     //   #93	-> 120
/*      */     //   #95	-> 137
/*      */     //   #96	-> 142
/*      */     //   #97	-> 151
/*      */     //   #98	-> 166
/*      */     //   #99	-> 173
/*      */     //   #101	-> 179
/*      */     //   #102	-> 184
/*      */     //   #103	-> 199
/*      */     //   #104	-> 209
/*      */     //   #106	-> 219
/*      */     //   #108	-> 224
/*      */     //   #109	-> 233
/*      */     //   #110	-> 236
/*      */     //   #112	-> 239
/*      */     //   #113	-> 242
/*      */     //   #115	-> 251
/*      */     //   #116	-> 261
/*      */     //   #117	-> 277
/*      */     //   #120	-> 280
/*      */     //   #121	-> 289
/*      */     //   #123	-> 292
/*      */     //   #125	-> 295
/*      */     //   #127	-> 327
/*      */     //   #128	-> 340
/*      */     //   #130	-> 346
/*      */     //   #131	-> 353
/*      */     //   #132	-> 361
/*      */     //   #133	-> 365
/*      */     //   #135	-> 384
/*      */     //   #136	-> 394
/*      */     //   #138	-> 406
/*      */     //   #139	-> 411
/*      */     //   #141	-> 422
/*      */     //   #144	-> 430
/*      */     //   #145	-> 438
/*      */     //   #146	-> 453
/*      */     //   #147	-> 458
/*      */     //   #149	-> 466
/*      */     //   #150	-> 481
/*      */     //   #151	-> 486
/*      */     //   #156	-> 494
/*      */     //   #158	-> 508
/*      */     //   #162	-> 522
/*      */     //   #163	-> 530
/*      */     //   #164	-> 540
/*      */     //   #165	-> 550
/*      */     //   #166	-> 558
/*      */     //   #170	-> 573
/*      */     //   #172	-> 578
/*      */     //   #173	-> 581
/*      */     //   #174	-> 589
/*      */     //   #178	-> 598
/*      */     //   #181	-> 612
/*      */     //   #186	-> 617
/*      */     //   #188	-> 620
/*      */     //   #192	-> 631
/*      */     //   #193	-> 644
/*      */     //   #195	-> 657
/*      */     //   #194	-> 660
/*      */     //   #196	-> 665
/*      */     //   #198	-> 675
/*      */     //   #199	-> 683
/*      */     //   #203	-> 700
/*      */     //   #204	-> 703
/*      */     //   #205	-> 706
/*      */     //   #206	-> 711
/*      */     //   #207	-> 714
/*      */     //   #206	-> 730
/*      */     //   #209	-> 735
/*      */     //   #210	-> 746
/*      */     //   #213	-> 764
/*      */     //   #214	-> 780
/*      */     //   #215	-> 793
/*      */     //   #216	-> 798
/*      */     //   #217	-> 810
/*      */     //   #218	-> 815
/*      */     //   #219	-> 818
/*      */     //   #220	-> 835
/*      */     //   #221	-> 840
/*      */     //   #225	-> 843
/*      */     //   #226	-> 853
/*      */     //   #227	-> 867
/*      */     //   #228	-> 875
/*      */     //   #229	-> 883
/*      */     //   #228	-> 894
/*      */     //   #232	-> 897
/*      */     //   #233	-> 907
/*      */     //   #234	-> 915
/*      */     //   #235	-> 921
/*      */     //   #236	-> 930
/*      */     //   #238	-> 940
/*      */     //   #239	-> 948
/*      */     //   #240	-> 950
/*      */     //   #242	-> 962
/*      */     //   #243	-> 969
/*      */     //   #244	-> 976
/*      */     //   #246	-> 979
/*      */     //   #250	-> 984
/*      */     //   #251	-> 992
/*      */     //   #252	-> 1003
/*      */     //   #255	-> 1009
/*      */     //   #258	-> 1032
/*      */     //   #255	-> 1035
/*      */     //   #259	-> 1038
/*      */     //   #260	-> 1041
/*      */     //   #261	-> 1044
/*      */     //   #262	-> 1047
/*      */     //   #263	-> 1060
/*      */     //   #265	-> 1078
/*      */     //   #266	-> 1082
/*      */     //   #267	-> 1090
/*      */     //   #268	-> 1097
/*      */     //   #270	-> 1110
/*      */     //   #271	-> 1121
/*      */     //   #272	-> 1127
/*      */     //   #273	-> 1130
/*      */     //   #275	-> 1147
/*      */     //   #277	-> 1155
/*      */     //   #278	-> 1163
/*      */     //   #281	-> 1174
/*      */     //   #282	-> 1181
/*      */     //   #284	-> 1188
/*      */     //   #286	-> 1204
/*      */     //   #287	-> 1212
/*      */     //   #290	-> 1218
/*      */     //   #293	-> 1228
/*      */     //   #295	-> 1234
/*      */     //   #296	-> 1245
/*      */     //   #297	-> 1263
/*      */     //   #298	-> 1279
/*      */     //   #300	-> 1289
/*      */     //   #301	-> 1297
/*      */     //   #302	-> 1302
/*      */     //   #303	-> 1306
/*      */     //   #308	-> 1319
/*      */     //   #309	-> 1330
/*      */     //   #311	-> 1344
/*      */     //   #312	-> 1347
/*      */     //   #314	-> 1353
/*      */     //   #315	-> 1364
/*      */     //   #317	-> 1384
/*      */     //   #318	-> 1406
/*      */     //   #320	-> 1414
/*      */     //   #321	-> 1432
/*      */     //   #324	-> 1455
/*      */     //   #321	-> 1458
/*      */     //   #325	-> 1461
/*      */     //   #326	-> 1464
/*      */     //   #327	-> 1467
/*      */     //   #328	-> 1470
/*      */     //   #329	-> 1474
/*      */     //   #330	-> 1482
/*      */     //   #331	-> 1489
/*      */     //   #333	-> 1502
/*      */     //   #334	-> 1518
/*      */     //   #335	-> 1527
/*      */     //   #336	-> 1530
/*      */     //   #338	-> 1547
/*      */     //   #339	-> 1553
/*      */     //   #342	-> 1561
/*      */     //   #343	-> 1566
/*      */     //   #345	-> 1577
/*      */     //   #348	-> 1585
/*      */     //   #349	-> 1591
/*      */     //   #351	-> 1597
/*      */     //   #353	-> 1607
/*      */     //   #354	-> 1620
/*      */     //   #358	-> 1637
/*      */     //   #360	-> 1640
/*      */     //   #361	-> 1648
/*      */     //   #365	-> 1651
/*      */     //   #367	-> 1654
/*      */     //   #368	-> 1660
/*      */     //   #371	-> 1683
/*      */     //   #368	-> 1686
/*      */     //   #372	-> 1689
/*      */     //   #373	-> 1710
/*      */     //   #377	-> 1716
/*      */     //   #378	-> 1722
/*      */     //   #379	-> 1737
/*      */   }
/*      */   
/*      */   private static boolean b(v paramv, c paramc, int paramInt1, int paramInt2) {
/*  382 */     if (paramc.n(paramv)) {
/*  383 */       return (paramInt2 == paramInt1);
/*      */     }
/*  385 */     return (paramInt1 > 0 && paramInt2 == paramInt1);
/*      */   }
/*      */ 
/*      */ 
/*      */ 
/*      */ 
/*      */   
/*      */   private static r a(v paramv, u paramu, r paramr, x paramx, int paramInt1, int paramInt2, byte paramByte) {
/*  393 */     c c = paramr.a();
/*      */     
/*  395 */     paramr.a(paramv.t().a(paramr.a()));
/*      */     
/*      */     r r1;
/*  398 */     (r1 = new r(paramv, null, paramr.a(), paramInt1)).b(true);
/*  399 */     r1.a(true);
/*      */     
/*  401 */     paramr.a(paramv, r1);
/*  402 */     paramu.a(true);
/*      */     
/*  404 */     s s = a(paramv, r1.a(), paramInt2, paramx, true, paramByte);
/*      */     
/*  406 */     if (r1.a().aA()) {
/*  407 */       s.a(r1.a().b(a.T, 0.0F, paramv));
/*      */     }
/*      */     
/*  410 */     r1.a(paramv, s);
/*  411 */     r1.c(s.f());
/*      */     
/*  413 */     paramx.b(paramx.c());
/*      */     
/*  415 */     paramv.t().c();
/*  416 */     paramr.a(c);
/*      */     
/*  418 */     return r1;
/*      */   }
/*      */ 
/*      */   
/*      */   private static void a(v paramv, c paramc1, c paramc2, int paramInt) {
/*  423 */     paramc2.g((f)paramc1);
/*  424 */     paramc2.b(paramv.o());
/*  425 */     paramc2.a(paramv, paramc1, paramInt);
/*  426 */     paramc2.B();
/*  427 */     paramc2.b(paramv);
/*      */   }
/*      */ 
/*      */ 
/*      */ 
/*      */ 
/*      */ 
/*      */ 
/*      */   
/*      */   public static int a(d paramd, f paramf, int paramInt1, int paramInt2) {
/*  437 */     int i = paramInt1;
/*      */     
/*  439 */     r r = null;
/*      */ 
/*      */ 
/*      */ 
/*      */ 
/*      */ 
/*      */     
/*  446 */     for (byte b = 0; b < paramf.V(); b++) {
/*      */       r r1;
/*      */       f f1;
/*  449 */       if (f1 = paramf.k(b) instanceof r) {
/*  450 */         r1 = (r)f1;
/*  451 */         int j = a(paramd, r1, i, paramInt2);
/*  452 */         a(paramd, r1, i, j);
/*  453 */         i -= j;
/*  454 */         r1.n(i);
/*      */       } else {
/*      */         
/*  457 */         i -= r1.Q();
/*  458 */         r1.n(i);
/*      */       } 
/*      */     } 
/*      */     
/*  462 */     if (r != null) {
/*  463 */       i -= r.a(paramd);
/*  464 */       r.c(paramInt1 - i);
/*      */     } 
/*      */     
/*  467 */     return paramInt1 - i;
/*      */   }
/*      */ 
/*      */ 
/*      */   
/*      */   private static int a(d paramd, r paramr, int paramInt1, int paramInt2) {
/*  473 */     int i = paramInt1;
/*  474 */     int j = paramInt2;
/*      */ 
/*      */     
/*  477 */     int k = paramr.c(paramd);
/*  478 */     i -= k;
/*  479 */     j -= k;
/*      */     
/*  481 */     for (byte b = 0; b < paramr.e(); b++) {
/*      */       int m;
/*      */       
/*      */       Object object;
/*  485 */       if (object = paramr.b(b) instanceof r) {
/*  486 */         r r1 = (r)object;
/*      */ 
/*      */ 
/*      */         
/*  490 */         m = a(paramd, r1, i, paramInt2);
/*  491 */         m = a(paramd, r1, i, m);
/*  492 */         r1.n(i - m);
/*  493 */         i -= m;
/*  494 */         j -= m;
/*  495 */       } else if (m instanceof s) {
/*  496 */         s s = (s)m;
/*  497 */         i -= s.f();
/*  498 */         j -= s.f();
/*  499 */         s.a(j);
/*  500 */       } else if (m instanceof f) {
/*  501 */         f f = (f)m;
/*  502 */         i -= f.Q();
/*  503 */         j -= f.Q();
/*  504 */         f.n(i);
/*      */       } 
/*      */     } 
/*      */     
/*  508 */     k = paramr.a(paramd);
/*  509 */     i -= k;
/*      */ 
/*      */     
/*  512 */     paramr.c(paramInt1 - i);
/*  513 */     return paramInt1 - i;
/*      */   }
/*      */ 
/*      */   
/*      */   public static int a(d paramd, f paramf, int paramInt) {
/*  518 */     paramInt = 0;
/*      */     
/*  520 */     r r = null;
/*      */ 
/*      */ 
/*      */ 
/*      */ 
/*      */ 
/*      */     
/*  527 */     for (byte b = 0; b < paramf.V(); b++) {
/*      */       r r1; f f1;
/*  529 */       if (f1 = paramf.k(b) instanceof r) {
/*      */         
/*  531 */         (r1 = (r)paramf.k(b)).n(paramInt);
/*  532 */         paramInt += a(paramd, r1, paramInt);
/*      */       } else {
/*  534 */         r1.n(paramInt);
/*  535 */         paramInt += r1.Q();
/*      */       } 
/*      */     } 
/*      */     
/*  539 */     if (r != null) {
/*  540 */       paramInt += r.c(paramd);
/*  541 */       r.c(paramInt);
/*      */     } 
/*      */     
/*  544 */     return paramInt;
/*      */   }
/*      */ 
/*      */ 
/*      */   
/*      */   private static int a(d paramd, r paramr, int paramInt) {
/*  550 */     int i = (i = paramInt) + paramr.a(paramd);
/*      */     
/*  552 */     for (byte b = 0; b < paramr.e(); b++) {
/*      */       Object object;
/*  554 */       if (object = paramr.b(b) instanceof r) {
/*      */         
/*  556 */         (object = object).n(i);
/*  557 */         i += a(paramd, (r)object, i);
/*  558 */       } else if (object instanceof s) {
/*      */         
/*  560 */         (object = object).a(i - paramInt);
/*  561 */         i += object.f();
/*  562 */       } else if (object instanceof f) {
/*      */         
/*  564 */         (object = object).n(i);
/*  565 */         i += object.Q();
/*      */       } 
/*      */     } 
/*      */     
/*  569 */     i += paramr.c(paramd);
/*      */     
/*  571 */     paramr.c(i - paramInt);
/*      */     
/*  573 */     return i - paramInt;
/*      */   }
/*      */   
/*      */   public static ac a(v paramv, f paramf) {
/*  577 */     l l = paramf.a().e(paramv);
/*  578 */     p p = a(paramv, paramf, l);
/*      */     
/*  580 */     return new ac(l
/*  581 */         .a(), p.a(), l.b());
/*      */   }
/*      */ 
/*      */   
/*      */   private static void a(v paramv, f paramf, u paramu, x paramx) {
/*  586 */     if (paramu.V() == 0 || !paramu.l()) {
/*  587 */       paramu.t(0); return;
/*      */     } 
/*  589 */     l l = paramf.a().e(paramv);
/*  590 */     af af = new af();
/*  591 */     p p = a(paramv, paramf, l);
/*  592 */     af.b(p);
/*      */     
/*      */     List<ad> list;
/*      */     
/*  596 */     if ((list = a(paramf, p.a(), l)) != null) {
/*  597 */       paramu.a(list);
/*      */     }
/*      */     int i;
/*  600 */     for (i = 0; i < paramu.V(); i++) {
/*  601 */       f f1 = paramu.k(i);
/*  602 */       a(paramv, af, f1);
/*      */     } 
/*      */     
/*  605 */     af.h();
/*      */     
/*  607 */     paramu.t(af.c());
/*      */     
/*  609 */     i = af.g();
/*  610 */     int j = af.f();
/*      */     
/*  612 */     if (af.b() < 0) {
/*  613 */       a(paramu, -af.b());
/*  614 */       if (list != null) {
/*  615 */         for (Iterator<ad> iterator = list.iterator(); iterator.hasNext();) {
/*  616 */           (ad = iterator.next()).a(ad.a() - af.b());
/*      */         }
/*      */       }
/*  619 */       i -= af.b();
/*  620 */       j -= af.b();
/*      */     } 
/*      */     
/*  623 */     if (paramx != null) {
/*      */       ac ac;
/*  625 */       (ac = paramx.d()).a(p.a() - af.b());
/*  626 */       paramx.a(paramu);
/*  627 */       paramu.a(paramx);
/*      */     } 
/*      */     
/*  630 */     paramu.d(p.a() - af.b());
/*      */     
/*  632 */     paramu.b(i);
/*  633 */     paramu.a(j - i);
/*      */   }
/*      */ 
/*      */ 
/*      */   
/*      */   private static void a(v paramv, af paramaf, r paramr) {
/*  639 */     p p = a(paramv, paramr, paramaf);
/*  640 */     paramaf.a(p);
/*  641 */     b(paramv, paramr, paramaf);
/*  642 */     paramaf.e();
/*      */   }
/*      */ 
/*      */ 
/*      */   
/*      */   private static void a(v paramv, af paramaf, c paramc) {
/*  648 */     int i = paramc.d(paramv), j = i;
/*  649 */     i = paramc.as() - i;
/*  650 */     a(paramv, (f)paramc, j, i, paramaf);
/*      */     
/*  652 */     paramaf.a(paramc.an());
/*  653 */     paramaf.b(paramc.an());
/*      */     
/*  655 */     paramaf.c(paramc.an() + paramc.as());
/*  656 */     paramaf.d(paramc.an() + paramc.as());
/*      */   }
/*      */   
/*      */   private static void a(u paramu, int paramInt) {
/*  660 */     for (byte b = 0; b < paramu.V(); b++) {
/*      */       f f;
/*  662 */       (f = paramu.k(b)).o(f.an() + paramInt);
/*  663 */       if (f instanceof r) {
/*  664 */         a((r)f, paramInt);
/*      */       }
/*      */     } 
/*      */   }
/*      */   
/*      */   private static void a(r paramr, int paramInt) {
/*  670 */     for (byte b = 0; b < paramr.e(); b++) {
/*      */       Object object;
/*  672 */       if (object = paramr.b(b) instanceof f) {
/*  673 */         ((f)object).o(((f)object).an() + paramInt);
/*      */         
/*  675 */         if (object instanceof r) {
/*  676 */           a((r)object, paramInt);
/*      */         }
/*      */       } 
/*      */     } 
/*      */   }
/*      */ 
/*      */   
/*      */   private static p a(v paramv, r paramr, af paramaf) {
/*  684 */     l l = paramr.a().e(paramv);
/*      */     
/*      */     c c;
/*      */     
/*      */     float f;
/*      */     int i;
/*  690 */     if ((i = Math.round(((f = (c = paramr.a()).c(paramv)) - (paramr.a().b(paramv)).a) / 2.0F)) > 0) {
/*  691 */       i = Math.round((f - l
/*  692 */           .b() + l.a()) / 2.0F);
/*      */     }
/*      */     
/*  695 */     paramr.a(Math.round(l.a()));
/*      */     
/*  697 */     a(paramv, (f)paramr, l.a(), l.b(), paramaf);
/*      */     List<ad> list;
/*  699 */     if ((list = a((f)paramr, paramr.c(), l)) != null) {
/*  700 */       paramr.a(list);
/*      */     }
/*      */     
/*      */     p p;
/*  704 */     (p = new p()).a(paramr.an() + paramr.c());
/*  705 */     p.c(paramr.an() - i);
/*  706 */     p.b(Math.round(p.c() + f));
/*  707 */     p.e(paramr.an());
/*  708 */     p.d((int)(p.a() + l.b()));
/*      */     
/*  710 */     h h = paramr.o(paramv);
/*  711 */     a a = paramr.b(paramv);
/*      */     
/*  713 */     p.g((int)Math.floor((paramr.an() - a.t() - h.t())));
/*  714 */     p.f((int)Math.ceil((paramr.an() + l
/*  715 */           .a() + l.b() + a
/*  716 */           .v() + h.v())));
/*      */     
/*  718 */     return p;
/*      */   }
/*      */ 
/*      */   
/*      */   private static List<ad> a(f paramf, int paramInt, l paraml) {
/*  723 */     ArrayList<ad> arrayList = null;
/*      */     
/*      */     List list;
/*      */     c c;
/*  727 */     if ((list = (c = paramf.a()).ar()) != null) {
/*  728 */       arrayList = new ArrayList(list.size());
/*  729 */       if (list.contains(c.bk)) {
/*  730 */         ad ad = new ad(c.bk);
/*      */ 
/*      */         
/*  733 */         if (paraml.e() == 0.0F) {
/*  734 */           ad.a(Math.round(paramInt + paraml.f()));
/*      */         } else {
/*  736 */           ad.a(Math.round(paramInt + paraml.e()));
/*      */         } 
/*  738 */         ad.b(Math.round(paraml.f()));
/*      */ 
/*      */ 
/*      */ 
/*      */         
/*  743 */         if (paraml.e() == 0.0F) {
/*      */           
/*  745 */           int i = paramInt + (int)paraml.b() - ad.b();
/*  746 */           if (ad.a() > i) {
/*  747 */             ad.a(i);
/*      */           }
/*      */         } 
/*  750 */         arrayList.add(ad);
/*      */       } 
/*      */       
/*  753 */       if (list.contains(c.ad)) {
/*      */         ad ad;
/*  755 */         (ad = new ad(c.ad)).a(Math.round(paramInt + paraml.c()));
/*  756 */         ad.b(Math.round(paraml.d()));
/*  757 */         arrayList.add(ad);
/*      */       } 
/*      */       
/*  760 */       if (list.contains(c.ax)) {
/*      */         ad ad;
/*  762 */         (ad = new ad(c.ax)).a(0);
/*  763 */         ad.b(Math.round(paraml.f()));
/*  764 */         arrayList.add(ad);
/*      */       } 
/*      */     } 
/*      */     
/*  768 */     return arrayList;
/*      */   }
/*      */ 
/*      */ 
/*      */ 
/*      */ 
/*      */   
/*      */   private static void a(v paramv, f paramf, float paramFloat1, float paramFloat2, af paramaf) {
/*  776 */     p p = paramaf.d();
/*      */     
/*      */     c c1;
/*      */     
/*  780 */     if ((c1 = paramf.a()).g(a.as)) {
/*  781 */       paramf.o(
/*  782 */           (int)(p.a() - paramFloat1 - c1.a(a.as, c1.c(paramv), paramv)));
/*      */       return;
/*      */     } 
/*      */     c c;
/*  786 */     if ((c = c1.e(a.as)) != c.g) {
/*      */       
/*  788 */       if (c == c.bf) {
/*  789 */         paramf.o(p.e()); return;
/*  790 */       }  if (c == c.be) {
/*  791 */         paramf.o(Math.round(p.d() - paramFloat2 - paramFloat1)); return;
/*  792 */       }  if (c == c.al) {
/*      */         
/*  794 */         paramf.o(Math.round(((p.a() - p.e()) / 2) - (paramFloat1 + paramFloat2) / 2.0F)); return;
/*      */       } 
/*  796 */       if (c == c.aU) {
/*  797 */         paramf.o(Math.round(p.a() - 3.0F * paramFloat1 / 2.0F)); return;
/*  798 */       }  if (c == c.aT) {
/*  799 */         paramf.o(Math.round(p.a() - paramFloat1 / 2.0F)); return;
/*      */       } 
/*  801 */     }  paramf.o(Math.round(p.a() - paramFloat1));
/*      */   }
/*      */ 
/*      */ 
/*      */ 
/*      */ 
/*      */ 
/*      */   
/*      */   private static p a(v paramv, f paramf, l paraml) {
/*      */     int i;
/*      */     float f1;
/*  812 */     if ((i = Math.round(((f1 = paramf.a().c(paramv)) - (paramf.a().b(paramv)).a) / 2.0F)) > 0) {
/*  813 */       i = Math.round((f1 - paraml
/*  814 */           .b() + paraml.a()) / 2.0F);
/*      */     }
/*      */     
/*      */     p p;
/*  818 */     (p = new p()).a((int)(i + paraml.a()));
/*  819 */     p.e(i);
/*  820 */     p.d((int)(p.a() + paraml.b()));
/*  821 */     p.c(i);
/*  822 */     p.b((int)(i + f1));
/*      */     
/*  824 */     return p;
/*      */   }
/*      */ 
/*      */   
/*      */   private static void b(v paramv, r paramr, af paramaf) {
/*  829 */     for (byte b = 0; b < paramr.e(); b++) {
/*      */       Object object;
/*  831 */       if (object = paramr.b(b) instanceof f) {
/*  832 */         a(paramv, paramaf, (f)object);
/*      */       }
/*      */     } 
/*      */   }
/*      */ 
/*      */   
/*      */   private static void a(v paramv, af paramaf, f paramf) {
/*  839 */     af af1 = paramaf; c c;
/*  840 */     if (!paramf.a().g(a.as) && ((
/*      */ 
/*      */       
/*  843 */       c = paramf.a().e(a.as)) == c.bi || c == c.l)) {
/*  844 */       af1 = paramaf.a(paramf);
/*      */     }
/*      */     
/*  847 */     if (paramf instanceof r) {
/*  848 */       r r = (r)paramf;
/*  849 */       a(paramv, af1, r); return;
/*      */     } 
/*  851 */     a(paramv, af1, (c)paramf);
/*      */   }
/*      */ 
/*      */ 
/*      */ 
/*      */ 
/*      */ 
/*      */   
/*      */   private static void a(u paramu, v paramv, c paramc, int paramInt1, int paramInt2, List<m> paramList, boolean paramBoolean1, List<t> paramList1, x paramx, int paramInt3, boolean paramBoolean2) {
/*  860 */     paramu.c(paramInt3);
/*  861 */     paramu.e();
/*      */ 
/*      */ 
/*      */     
/*  865 */     if (paramu.n()) {
/*  866 */       paramInt3 = a(paramv, (f)paramu, 0, 0);
/*  867 */       a(paramv, (f)paramu, paramInt3, paramInt3);
/*      */     } else {
/*      */       
/*  870 */       paramInt3 = a(paramv, (f)paramu, 0);
/*      */     } 
/*      */     
/*  873 */     paramu.u(paramInt3);
/*      */     
/*  875 */     a(paramv, (f)paramc, paramu, paramx);
/*      */ 
/*      */ 
/*      */     
/*  879 */     if (paramu.as() != 0 && paramu
/*  880 */       .as() < paramInt1 && 
/*  881 */       !paramu.k()) {
/*  882 */       paramu.t(paramInt1);
/*      */     }
/*      */     
/*  885 */     if (paramv.r()) {
/*  886 */       paramu.a(paramv, paramBoolean2);
/*      */     }
/*      */     
/*  889 */     a(paramv, paramu, paramInt2);
/*      */     
/*  891 */     paramu.C();
/*      */     
/*  893 */     paramc.a(paramv, (f)paramu);
/*      */     
/*  895 */     if (paramList1.size() > 0) {
/*  896 */       a(paramv, paramList1);
/*  897 */       paramList1.clear();
/*      */     } 
/*      */     
/*  900 */     if (paramBoolean1 && paramu.c()) {
/*  901 */       paramv.s().c();
/*  902 */       paramc.a_(paramv);
/*      */     } 
/*      */     
/*  905 */     if (paramList.size() > 0) {
/*  906 */       for (m m : paramList) {
/*  907 */         a.a(paramv, paramu, m.b(), paramInt2, null);
/*  908 */         paramu.a(m.b());
/*      */       } 
/*  910 */       paramList.clear();
/*      */     } 
/*      */   }
/*      */   
/*      */   private static void a(v paramv, u paramu, int paramInt) {
/*  915 */     if (!paramu.i() && !paramu.U().a().at()) {
/*  916 */       paramu.a(new r(paramv, paramu, paramInt));
/*      */     } else {
/*      */       m m;
/*      */ 
/*      */ 
/*      */ 
/*      */ 
/*      */ 
/*      */ 
/*      */ 
/*      */       
/*  927 */       (m = new m()).a(paramv
/*  928 */           .l().a(paramv, paramu, paramInt));
/*      */       
/*  930 */       m.b(paramv
/*  931 */           .l().b(paramv, paramu, paramInt));
/*      */       
/*  933 */       paramu.a(m);
/*      */     } 
/*  935 */     paramu.a(false, paramv);
/*  936 */     if (!paramu.i() && !paramu.U().a().at()) {
/*  937 */       paramu.a(null);
/*      */     }
/*      */   }
/*      */   
/*      */   private static void a(v paramv, List<t> paramList) {
/*  942 */     for (Iterator<t> iterator = paramList.iterator(); iterator.hasNext();) {
/*  943 */       (t = iterator.next()).b(paramv);
/*      */     }
/*      */   }
/*      */ 
/*      */   
/*      */   private static s a(v paramv, c paramc, int paramInt, x paramx, boolean paramBoolean, byte paramByte) {
/*  949 */     s s = new s();
/*  950 */     String str = paramx.d();
/*      */     
/*  952 */     if (paramBoolean) {
/*  953 */       str = ad.b(str, paramc);
/*  954 */       paramx.a(str);
/*  955 */       j.a(paramv, paramx, paramInt, paramc);
/*      */     } else {
/*  957 */       j.b(paramv, paramx, paramInt, paramc);
/*      */     } 
/*      */     
/*  960 */     s.a(str);
/*  961 */     paramx.n();
/*  962 */     s.a(paramx.e(), paramx.c());
/*  963 */     s.b(paramx.j());
/*  964 */     s.a(paramByte);
/*      */     
/*  966 */     return s;
/*      */   }
/*      */ 
/*      */ 
/*      */   
/*      */   private static int a(v paramv, u paramu, c paramc, int paramInt, List<m> paramList) {
/*  972 */     int i = 0;
/*      */     c c1;
/*  974 */     if ((c1 = paramc.a()).A() || c1.B())
/*  975 */     { a.a(paramv, paramu, paramc);
/*  976 */       paramu.a(paramc); }
/*  977 */     else { m m; if (c1.C()) {
/*      */ 
/*      */         
/*  980 */         if ((m = a.a(paramv, paramu, paramc, paramInt, paramList)).a()) {
/*  981 */           paramList.add(m);
/*      */         } else {
/*  983 */           i = m.b().Q();
/*  984 */           paramu.a(m.b());
/*      */         } 
/*  986 */       } else if (c1.P()) {
/*  987 */         paramc.a((f)paramu);
/*  988 */         m.p().c(paramc);
/*      */       }  }
/*      */     
/*  991 */     return i;
/*      */   }
/*      */ 
/*      */   
/*      */   private static boolean a(u paramu, c paramc, x paramx, boolean paramBoolean) {
/*      */     c c1;
/*  997 */     if ((!paramu.f() || paramBoolean) && paramx
/*  998 */       .f().startsWith(" ") && ((
/*      */       
/* 1000 */       c1 = paramc.i()) == c.aq || c1 == c.ar || c1 == c.aC || (c1 == c.aD && paramx
/*      */ 
/*      */ 
/*      */       
/* 1004 */       .e() > 0 && paramx
/* 1005 */       .d().length() > paramx.e() - 1 && paramx
/* 1006 */       .d().charAt(paramx.e() - 1) != '\n'))) {
/* 1007 */       return true;
/*      */     }
/*      */     
/* 1010 */     return false;
/*      */   }
/*      */   
/*      */   private static void a(x paramx) {
/* 1014 */     String str = paramx.f();
/* 1015 */     byte b = 0;
/* 1016 */     while (b < str.length() && str.charAt(b) == ' ') {
/* 1017 */       b++;
/*      */     }
/* 1019 */     paramx.b(paramx.e() + b);
/*      */   }
/*      */   
/*      */   private static u a(v paramv, u paramu, f paramf) {
/* 1023 */     int i = 0;
/*      */     
/* 1025 */     if (paramu != null) {
/* 1026 */       i = paramu.an() + paramu.as();
/*      */     }
/*      */     
/* 1029 */     return a(paramv, i, paramf);
/*      */   }
/*      */   
/*      */   private static u a(v paramv, int paramInt, f paramf) {
/*      */     u u;
/* 1034 */     (u = new u()).a(paramf.a().a(c.h));
/* 1035 */     u.f(paramf);
/* 1036 */     u.r(paramv);
/*      */     
/* 1038 */     u.o(paramInt);
/*      */     
/* 1040 */     u.B();
/*      */     
/* 1042 */     return u;
/*      */   }
/*      */ 
/*      */ 
/*      */   
/*      */   private static r a(v paramv, u paramu, List<com.d.i.q> paramList, int paramInt, Map<com.d.i.q, r> paramMap) {
/* 1048 */     r r1 = null;
/* 1049 */     r r2 = null;
/*      */     
/* 1051 */     boolean bool = true;
/* 1052 */     for (com.d.i.q q1 : paramList) {
/*      */       
/* 1054 */       r1 = new r(paramv, q1.h(), q1.a(), paramInt);
/*      */       
/*      */       r r;
/* 1057 */       if ((r = paramMap.get(q1)) != null) {
/* 1058 */         r1.c(r.h());
/*      */       }
/*      */       
/* 1061 */       paramMap.put(q1, r1);
/*      */       
/* 1063 */       if (bool) {
/* 1064 */         paramu.a(paramv, (f)r1);
/* 1065 */         bool = false;
/*      */       } else {
/* 1067 */         r2.a(paramv, r1, false);
/*      */       } 
/* 1069 */       r2 = r1;
/*      */     } 
/*      */     
/* 1072 */     return r1;
/*      */   }
/*      */ 
/*      */ 
/*      */ 
/*      */ 
/*      */ 
/*      */ 
/*      */ 
/*      */ 
/*      */ 
/*      */ 
/*      */ 
/*      */ 
/*      */ 
/*      */ 
/*      */ 
/*      */ 
/*      */ 
/*      */ 
/*      */ 
/*      */ 
/*      */ 
/*      */ 
/*      */ 
/*      */ 
/*      */ 
/*      */ 
/*      */ 
/*      */ 
/*      */ 
/*      */ 
/*      */ 
/*      */ 
/*      */ 
/*      */ 
/*      */ 
/*      */ 
/*      */ 
/*      */ 
/*      */ 
/*      */ 
/*      */ 
/*      */ 
/*      */ 
/*      */ 
/*      */ 
/*      */ 
/*      */ 
/*      */ 
/*      */ 
/*      */ 
/*      */ 
/*      */ 
/*      */ 
/*      */ 
/*      */ 
/*      */ 
/*      */ 
/*      */ 
/*      */ 
/*      */ 
/*      */ 
/*      */ 
/*      */ 
/*      */ 
/*      */ 
/*      */ 
/*      */ 
/*      */ 
/*      */ 
/*      */ 
/*      */ 
/*      */ 
/*      */ 
/*      */ 
/*      */ 
/*      */ 
/*      */ 
/*      */ 
/*      */ 
/*      */ 
/*      */ 
/*      */ 
/*      */ 
/*      */ 
/*      */ 
/*      */ 
/*      */ 
/*      */ 
/*      */ 
/*      */ 
/*      */ 
/*      */ 
/*      */ 
/*      */ 
/*      */ 
/*      */ 
/*      */ 
/*      */ 
/*      */ 
/*      */ 
/*      */ 
/*      */ 
/*      */ 
/*      */ 
/*      */ 
/*      */ 
/*      */ 
/*      */ 
/*      */ 
/*      */ 
/*      */ 
/*      */ 
/*      */ 
/*      */ 
/*      */ 
/*      */ 
/*      */ 
/*      */ 
/*      */ 
/*      */ 
/*      */ 
/*      */ 
/*      */ 
/*      */ 
/*      */ 
/*      */ 
/*      */ 
/*      */ 
/*      */ 
/*      */ 
/*      */ 
/*      */ 
/*      */ 
/*      */ 
/*      */ 
/*      */ 
/*      */ 
/*      */ 
/*      */ 
/*      */ 
/*      */ 
/*      */ 
/*      */ 
/*      */ 
/*      */ 
/*      */ 
/*      */ 
/*      */ 
/*      */ 
/*      */ 
/*      */ 
/*      */ 
/*      */ 
/*      */ 
/*      */ 
/*      */ 
/*      */ 
/*      */ 
/*      */ 
/*      */ 
/*      */ 
/*      */ 
/*      */ 
/*      */ 
/*      */ 
/*      */ 
/*      */ 
/*      */ 
/*      */ 
/*      */ 
/*      */ 
/*      */ 
/*      */ 
/*      */ 
/*      */ 
/*      */ 
/*      */ 
/*      */ 
/*      */ 
/*      */ 
/*      */ 
/*      */ 
/*      */ 
/*      */ 
/*      */ 
/*      */ 
/*      */ 
/*      */ 
/*      */ 
/*      */ 
/*      */ 
/*      */ 
/*      */ 
/*      */ 
/*      */ 
/*      */ 
/*      */ 
/*      */ 
/*      */ 
/*      */ 
/*      */ 
/*      */ 
/*      */ 
/*      */ 
/*      */ 
/*      */ 
/*      */ 
/*      */ 
/*      */ 
/*      */ 
/*      */ 
/*      */ 
/*      */ 
/*      */ 
/*      */ 
/*      */ 
/*      */ 
/*      */ 
/*      */ 
/*      */ 
/*      */ 
/*      */ 
/*      */ 
/*      */ 
/*      */ 
/*      */ 
/*      */ 
/*      */ 
/*      */ 
/*      */ 
/*      */ 
/*      */ 
/*      */ 
/*      */ 
/*      */ 
/*      */ 
/*      */ 
/*      */ 
/*      */ 
/*      */ 
/*      */ 
/*      */ 
/*      */ 
/*      */ 
/*      */ 
/*      */ 
/*      */ 
/*      */ 
/*      */ 
/*      */ 
/*      */ 
/*      */ 
/*      */ 
/*      */ 
/*      */ 
/*      */ 
/*      */ 
/*      */ 
/*      */ 
/*      */ 
/*      */ 
/*      */ 
/*      */ 
/*      */ 
/*      */ 
/*      */ 
/*      */ 
/*      */ 
/*      */ 
/*      */ 
/*      */ 
/*      */ 
/*      */ 
/*      */ 
/*      */ 
/*      */ 
/*      */ 
/*      */ 
/*      */ 
/*      */ 
/*      */ 
/*      */ 
/*      */ 
/*      */ 
/*      */ 
/*      */ 
/*      */ 
/*      */ 
/*      */ 
/*      */ 
/*      */ 
/*      */ 
/*      */ 
/*      */ 
/*      */ 
/*      */ 
/*      */ 
/*      */ 
/*      */ 
/*      */ 
/*      */ 
/*      */ 
/*      */ 
/*      */ 
/*      */ 
/*      */ 
/*      */ 
/*      */ 
/*      */ 
/*      */ 
/*      */ 
/*      */ 
/*      */ 
/*      */ 
/*      */ 
/*      */ 
/*      */ 
/*      */ 
/*      */ 
/*      */ 
/*      */ 
/*      */ 
/*      */ 
/*      */ 
/*      */ 
/*      */ 
/*      */ 
/*      */ 
/*      */ 
/*      */ 
/*      */ 
/*      */ 
/*      */ 
/*      */ 
/*      */ 
/*      */ 
/*      */ 
/*      */ 
/*      */ 
/*      */ 
/*      */ 
/*      */ 
/*      */ 
/*      */ 
/*      */ 
/*      */ 
/*      */ 
/*      */ 
/*      */ 
/*      */ 
/*      */ 
/*      */ 
/*      */ 
/*      */ 
/*      */ 
/*      */ 
/*      */ 
/*      */ 
/*      */ 
/*      */ 
/*      */ 
/*      */ 
/*      */ 
/*      */ 
/*      */ 
/*      */ 
/*      */ 
/*      */ 
/*      */ 
/*      */ 
/*      */ 
/*      */ 
/*      */ 
/*      */ 
/*      */ 
/*      */ 
/*      */ 
/*      */ 
/*      */ 
/*      */ 
/*      */ 
/*      */ 
/*      */ 
/*      */ 
/*      */ 
/*      */ 
/*      */ 
/*      */ 
/*      */ 
/*      */ 
/*      */ 
/*      */ 
/*      */ 
/*      */ 
/*      */ 
/*      */ 
/*      */ 
/*      */ 
/*      */ 
/*      */ 
/*      */ 
/*      */ 
/*      */ 
/*      */ 
/*      */ 
/*      */ 
/*      */ 
/*      */ 
/*      */ 
/*      */ 
/*      */ 
/*      */ 
/*      */ 
/*      */ 
/*      */ 
/*      */ 
/*      */ 
/*      */ 
/*      */ 
/*      */ 
/*      */ 
/*      */ 
/*      */ 
/*      */ 
/*      */ 
/*      */ 
/*      */ 
/*      */ 
/*      */ 
/*      */ 
/*      */ 
/*      */ 
/*      */ 
/*      */ 
/*      */ 
/*      */ 
/*      */ 
/*      */ 
/*      */ 
/*      */ 
/*      */ 
/*      */ 
/*      */ 
/*      */ 
/*      */ 
/*      */ 
/*      */ 
/*      */ 
/*      */ 
/*      */ 
/*      */ 
/*      */ 
/*      */ 
/*      */ 
/*      */ 
/*      */ 
/*      */ 
/*      */ 
/*      */ 
/*      */ 
/*      */ 
/*      */ 
/*      */ 
/*      */ 
/*      */ 
/*      */ 
/*      */ 
/*      */ 
/*      */ 
/*      */ 
/*      */ 
/*      */ 
/*      */ 
/*      */ 
/*      */ 
/*      */ 
/*      */ 
/*      */ 
/*      */ 
/*      */ 
/*      */ 
/*      */ 
/*      */ 
/*      */ 
/*      */ 
/*      */ 
/*      */ 
/*      */ 
/*      */ 
/*      */ 
/*      */ 
/*      */ 
/*      */ 
/*      */ 
/*      */ 
/*      */ 
/*      */ 
/*      */ 
/*      */ 
/*      */ 
/*      */ 
/*      */ 
/*      */ 
/*      */ 
/*      */ 
/*      */ 
/*      */ 
/*      */ 
/*      */ 
/*      */ 
/*      */ 
/*      */ 
/*      */ 
/*      */ 
/*      */ 
/*      */ 
/*      */ 
/*      */ 
/*      */ 
/*      */ 
/*      */ 
/*      */ 
/*      */ 
/*      */ 
/*      */ 
/*      */ 
/*      */ 
/*      */ 
/*      */ 
/*      */ 
/*      */ 
/*      */ 
/*      */ 
/*      */ 
/*      */ 
/*      */ 
/*      */ 
/*      */ 
/*      */ 
/*      */ 
/*      */ 
/*      */ 
/*      */ 
/*      */ 
/*      */ 
/*      */ 
/*      */ 
/*      */ 
/*      */ 
/*      */ 
/*      */ 
/*      */ 
/*      */ 
/*      */ 
/*      */ 
/*      */ 
/*      */ 
/*      */ 
/*      */ 
/*      */ 
/*      */ 
/*      */ 
/*      */ 
/*      */ 
/*      */ 
/*      */ 
/*      */ 
/*      */ 
/*      */ 
/*      */ 
/*      */ 
/*      */ 
/*      */ 
/*      */ 
/*      */ 
/*      */ 
/*      */ 
/*      */ 
/*      */ 
/*      */ 
/*      */ 
/*      */ 
/*      */ 
/*      */ 
/*      */ 
/*      */ 
/*      */ 
/*      */ 
/*      */ 
/*      */ 
/*      */ 
/*      */ 
/*      */ 
/*      */ 
/*      */ 
/*      */ 
/*      */ 
/*      */ 
/*      */ 
/*      */ 
/*      */ 
/*      */ 
/*      */ 
/*      */ 
/*      */ 
/*      */ 
/*      */ 
/*      */ 
/*      */ 
/*      */ 
/*      */ 
/*      */ 
/*      */ 
/*      */ 
/*      */ 
/*      */ 
/*      */ 
/*      */ 
/*      */ 
/*      */ 
/*      */ 
/*      */ 
/*      */ 
/*      */ 
/*      */ 
/*      */ 
/*      */ 
/*      */ 
/*      */ 
/*      */ 
/*      */ 
/*      */ 
/*      */ 
/*      */ 
/*      */ 
/*      */ 
/*      */ 
/*      */ 
/*      */ 
/*      */ 
/*      */ 
/*      */ 
/*      */ 
/*      */ 
/*      */ 
/*      */ 
/*      */ 
/*      */ 
/*      */ 
/*      */ 
/*      */ 
/*      */ 
/*      */ 
/*      */ 
/*      */ 
/*      */ 
/*      */ 
/*      */ 
/*      */ 
/*      */ 
/*      */ 
/*      */ 
/*      */ 
/*      */ 
/*      */ 
/*      */ 
/*      */ 
/*      */ 
/*      */ 
/*      */ 
/*      */ 
/*      */ 
/*      */ 
/*      */ 
/*      */ 
/*      */ 
/*      */ 
/*      */ 
/*      */ 
/*      */ 
/*      */ 
/*      */ 
/*      */ 
/*      */ 
/*      */ 
/*      */ 
/*      */ 
/*      */ 
/*      */ 
/*      */ 
/*      */ 
/*      */ 
/*      */ 
/*      */ 
/*      */ 
/*      */ 
/*      */ 
/*      */ 
/*      */ 
/*      */ 
/*      */ 
/*      */ 
/*      */ 
/*      */ 
/*      */ 
/*      */ 
/*      */ 
/*      */ 
/*      */ 
/*      */ 
/*      */ 
/*      */ 
/*      */ 
/*      */ 
/*      */ 
/*      */ 
/*      */ 
/*      */ 
/*      */ 
/*      */ 
/*      */ 
/*      */ 
/*      */ 
/*      */ 
/*      */ 
/*      */ 
/*      */ 
/*      */ 
/*      */ 
/*      */ 
/*      */ 
/*      */ 
/*      */ 
/*      */ 
/*      */ 
/*      */ 
/*      */ 
/*      */ 
/*      */ 
/*      */ 
/*      */ 
/*      */ 
/*      */ 
/*      */ 
/*      */ 
/*      */ 
/*      */ 
/*      */ 
/*      */ 
/*      */ 
/*      */ 
/*      */ 
/*      */ 
/*      */ 
/*      */ 
/*      */ 
/*      */ 
/*      */ 
/*      */ 
/*      */ 
/*      */ 
/*      */ 
/*      */ 
/*      */ 
/*      */ 
/*      */ 
/*      */ 
/*      */ 
/*      */ 
/*      */ 
/*      */ 
/*      */ 
/*      */ 
/*      */ 
/*      */ 
/*      */ 
/*      */ 
/*      */ 
/*      */ 
/*      */ 
/*      */ 
/*      */ 
/*      */ 
/*      */ 
/*      */ 
/*      */ 
/*      */ 
/*      */ 
/*      */ 
/*      */ 
/*      */ 
/*      */ 
/*      */ 
/*      */ 
/*      */ 
/*      */ 
/*      */ 
/*      */ 
/*      */ 
/*      */ 
/*      */ 
/*      */ 
/*      */ 
/*      */ 
/*      */ 
/*      */ 
/*      */ 
/*      */ 
/*      */ 
/*      */ 
/*      */ 
/*      */ 
/*      */ 
/*      */ 
/*      */ 
/*      */ 
/*      */ 
/*      */ 
/*      */ 
/*      */ 
/*      */ 
/*      */ 
/*      */ 
/*      */ 
/*      */ 
/*      */ 
/*      */ 
/*      */ 
/*      */ 
/*      */ 
/*      */ 
/*      */ 
/*      */ 
/*      */ 
/*      */ 
/*      */ 
/*      */ 
/*      */ 
/*      */ 
/*      */ 
/*      */ 
/*      */ 
/*      */ 
/*      */ 
/*      */ 
/*      */ 
/*      */ 
/*      */ 
/*      */ 
/*      */ 
/*      */ 
/*      */ 
/*      */ 
/*      */ 
/*      */ 
/*      */ 
/*      */ 
/*      */ 
/*      */ 
/*      */ 
/*      */ 
/*      */ 
/*      */ 
/*      */ 
/*      */ 
/*      */ 
/*      */ 
/*      */ 
/*      */ 
/*      */ 
/*      */ 
/*      */ 
/*      */ 
/*      */ 
/*      */ 
/*      */ 
/*      */ 
/*      */ 
/*      */ 
/*      */ 
/*      */ 
/*      */ 
/*      */ 
/*      */ 
/*      */ 
/*      */ 
/*      */ 
/*      */ 
/*      */ 
/*      */ 
/*      */ 
/*      */ 
/*      */ 
/*      */ 
/*      */ 
/*      */ 
/*      */ 
/*      */ 
/*      */ 
/*      */ 
/*      */ 
/*      */ 
/*      */ 
/*      */ 
/*      */ 
/*      */ 
/*      */ 
/*      */ 
/*      */ 
/*      */ 
/*      */ 
/*      */ 
/*      */ 
/*      */ 
/*      */ 
/*      */ 
/*      */ 
/*      */ 
/*      */ 
/*      */ 
/*      */ 
/*      */ 
/*      */ 
/*      */ 
/*      */ 
/*      */ 
/*      */ 
/*      */ 
/*      */ 
/*      */ 
/*      */ 
/*      */ 
/*      */ 
/*      */ 
/*      */ 
/*      */ 
/*      */ 
/*      */ 
/*      */ 
/*      */ 
/*      */ 
/*      */ 
/*      */ 
/*      */ 
/*      */ 
/*      */ 
/*      */ 
/*      */ 
/*      */ 
/*      */ 
/*      */ 
/*      */ 
/*      */ 
/*      */ 
/*      */ 
/*      */ 
/*      */ 
/*      */ 
/*      */ 
/*      */ 
/*      */ 
/*      */ 
/*      */ 
/*      */ 
/*      */ 
/*      */   
/*      */   public q() {
/* 2041 */     this.a = new HashMap<>();
/*      */   }
/*      */   
/*      */   public Object a(Object paramObject) {
/* 2045 */     if ((paramObject = ((Element)paramObject).getParentNode()).getNodeType() != 1) paramObject = null; 
/* 2046 */     return paramObject;
/*      */   }
/*      */   
/*      */   public Object b(Object paramObject) {
/* 2050 */     paramObject = ((Element)paramObject).getPreviousSibling();
/* 2051 */     while (paramObject != null && paramObject.getNodeType() != 1) {
/* 2052 */       paramObject = paramObject.getPreviousSibling();
/*      */     }
/* 2054 */     if (paramObject == null || paramObject.getNodeType() != 1) {
/* 2055 */       return null;
/*      */     }
/* 2057 */     return paramObject;
/*      */   }
/*      */ 
/*      */ 
/*      */ 
/*      */ 
/*      */ 
/*      */ 
/*      */ 
/*      */   
/*      */   public boolean c(Object paramObject) {
/* 2068 */     Node node = (node = ((Element)paramObject).getParentNode()).getFirstChild();
/* 2069 */     while (node != null && node.getNodeType() != 1) {
/* 2070 */       node = node.getNextSibling();
/*      */     }
/* 2072 */     return (node == paramObject);
/*      */   }
/*      */ 
/*      */   
/*      */   public boolean d(Object paramObject) {
/* 2077 */     Node node = (node = ((Element)paramObject).getParentNode()).getLastChild();
/* 2078 */     while (node != null && node.getNodeType() != 1) {
/* 2079 */       node = node.getPreviousSibling();
/*      */     }
/* 2081 */     return (node == paramObject);
/*      */   }
/*      */ 
/*      */ 
/*      */   
/*      */   public boolean a(Object paramObject, String paramString1, String paramString2) {
/*      */     String str2;
/*      */     String str1;
/* 2089 */     if ((str1 = (paramObject = paramObject).getLocalName()) == null) {
/* 2090 */       str2 = paramObject.getNodeName();
/*      */     } else {
/* 2092 */       str2 = str1;
/*      */     } 
/*      */     
/* 2095 */     if (paramString1 != null)
/* 2096 */       return (paramString2.equals(str1) && paramString1.equals(paramObject.getNamespaceURI())); 
/* 2097 */     if (paramString1 == "") {
/* 2098 */       return (paramString2.equals(str2) && paramObject.getNamespaceURI() == null);
/*      */     }
/* 2100 */     return paramString2.equals(str2);
/*      */   }
/*      */ 
/*      */ 
/*      */   
/*      */   public int e(Object paramObject) {
/* 2106 */     Node node = ((Element)paramObject).getParentNode();
/*      */     
/*      */     Map<Object, Object> map;
/*      */     
/* 2110 */     if ((map = (Map)this.a.get(node)) == null) {
/*      */       NodeList nodeList;
/* 2112 */       int i = (nodeList = node.getChildNodes()).getLength();
/*      */       
/* 2114 */       map = new HashMap<>();
/*      */       
/* 2116 */       byte b1 = 0;
/* 2117 */       for (byte b2 = 0; b2 < i; b2++) {
/*      */         Node node1;
/*      */         
/* 2120 */         if ((node1 = nodeList.item(b2)).getNodeType() == 1) {
/* 2121 */           map.put(node1, Integer.valueOf(b1++));
/*      */         }
/*      */       } 
/*      */       
/* 2125 */       this.a.put(node, map);
/*      */     } 
/*      */     
/* 2128 */     return ((Integer)map.get(paramObject)).intValue();
/*      */   }
/*      */ }


/* Location:              C:\Program Files (x86)\Steam\steamapps\common\Infinitode 2\infinitode-2.jar!\com\d\e\q.class
 * Java compiler version: 8 (52.0)
 * JD-Core Version:       1.1.3
 */