/*      */ package com.d.c.d.a;
/*      */ 
/*      */ import java.util.ArrayList;
/*      */ import java.util.Arrays;
/*      */ import java.util.BitSet;
/*      */ import java.util.Collections;
/*      */ import java.util.Iterator;
/*      */ import java.util.List;
/*      */ 
/*      */ 
/*      */ 
/*      */ 
/*      */ 
/*      */ 
/*      */ 
/*      */ 
/*      */ 
/*      */ 
/*      */ 
/*      */ 
/*      */ 
/*      */ 
/*      */ 
/*      */ 
/*      */ 
/*      */ 
/*      */ 
/*      */ 
/*      */ public final class l
/*      */ {
/*   31 */   public static final BitSet a = b(new com.d.c.a.c[] { com.d.c.a.c.ap, com.d.c.a.c.P, com.d.c.a.c.y, com.d.c.a.c.u, com.d.c.a.c.aQ, com.d.c.a.c.z, com.d.c.a.c.O, com.d.c.a.c.aI, com.d.c.a.c.U, com.d.c.a.c.av });
/*      */ 
/*      */ 
/*      */ 
/*      */ 
/*      */ 
/*      */   
/*   38 */   public static final BitSet b = b(new com.d.c.a.c[] { com.d.c.a.c.bh, com.d.c.a.c.bx, com.d.c.a.c.bg });
/*      */ 
/*      */   
/*   41 */   public static final BitSet c = b(new com.d.c.a.c[] { com.d.c.a.c.ak, com.d.c.a.c.aK, com.d.c.a.c.e });
/*      */ 
/*      */ 
/*      */   
/*   45 */   public static final BitSet d = b(new com.d.c.a.c[] { com.d.c.a.c.aq, com.d.c.a.c.aP });
/*      */ 
/*      */   
/*   48 */   public static final BitSet e = b(new com.d.c.a.c[] { com.d.c.a.c.bR, com.d.c.a.c.bQ });
/*      */ 
/*      */   
/*   51 */   public static final BitSet f = b(new com.d.c.a.c[] { com.d.c.a.c.aR, com.d.c.a.c.o, com.d.c.a.c.bS, com.d.c.a.c.bU, com.d.c.a.c.bV, com.d.c.a.c.bT });
/*      */ 
/*      */ 
/*      */   
/*   55 */   public static final BitSet g = b(new com.d.c.a.c[] { com.d.c.a.c.aq, com.d.c.a.c.W, com.d.c.a.c.at });
/*      */ 
/*      */   
/*   58 */   public static final BitSet h = b(new com.d.c.a.c[] { com.d.c.a.c.aq, com.d.c.a.c.i, com.d.c.a.c.j, com.d.c.a.c.ab });
/*      */ 
/*      */   
/*   61 */   public static final BitSet i = b(new com.d.c.a.c[] { com.d.c.a.c.e, com.d.c.a.c.aA, com.d.c.a.c.Z });
/*      */ 
/*      */ 
/*      */   
/*   65 */   public static final BitSet j = b(new com.d.c.a.c[] { com.d.c.a.c.V, com.d.c.a.c.aw });
/*      */ 
/*      */ 
/*      */ 
/*      */ 
/*      */ 
/*      */   
/*   72 */   public static final BitSet k = b(new com.d.c.a.c[] { com.d.c.a.c.x, com.d.c.a.c.o, com.d.c.a.c.aR, com.d.c.a.c.v, com.d.c.a.c.w, com.d.c.a.c.ai, com.d.c.a.c.bn, com.d.c.a.c.ag, com.d.c.a.c.ah, com.d.c.a.c.bm, com.d.c.a.c.d, com.d.c.a.c.N, com.d.c.a.c.af, com.d.c.a.c.bl, com.d.c.a.c.ap });
/*      */ 
/*      */ 
/*      */ 
/*      */ 
/*      */ 
/*      */ 
/*      */ 
/*      */ 
/*      */   
/*   82 */   public static final BitSet l = b(new com.d.c.a.c[] { com.d.c.a.c.aF, com.d.c.a.c.aG, com.d.c.a.c.aH, com.d.c.a.c.ao });
/*      */ 
/*      */ 
/*      */ 
/*      */ 
/*      */   
/*   88 */   public static final BitSet m = b(new com.d.c.a.c[] { com.d.c.a.c.aM, com.d.c.a.c.B });
/*      */ 
/*      */ 
/*      */   
/*   92 */   public static final BitSet n = b(new com.d.c.a.c[] { com.d.c.a.c.aa, com.d.c.a.c.aJ, com.d.c.a.c.bi, com.d.c.a.c.l, com.d.c.a.c.n });
/*      */ 
/*      */ 
/*      */ 
/*      */   
/*   97 */   public static final BitSet o = b(new com.d.c.a.c[] { com.d.c.a.c.bP, com.d.c.a.c.bN, com.d.c.a.c.bF, com.d.c.a.c.bx, com.d.c.a.c.bv, com.d.c.a.c.bM, com.d.c.a.c.bO });
/*      */ 
/*      */ 
/*      */ 
/*      */ 
/*      */   
/*  103 */   public static final BitSet p = b(new com.d.c.a.c[] { com.d.c.a.c.bG, com.d.c.a.c.bw });
/*      */ 
/*      */ 
/*      */   
/*  107 */   public static final m q = new bm((byte)0);
/*  108 */   public static final m r = new bk((byte)0);
/*  109 */   public static final m s = new bl((byte)0);
/*  110 */   public static final m t = new cl((byte)0);
/*  111 */   public static final m u = new bt((byte)0);
/*  112 */   public static final m v = new cl((byte)0);
/*      */   
/*      */   private static BitSet b(com.d.c.a.c[] paramArrayOfc) {
/*  115 */     BitSet bitSet = new BitSet(com.d.c.a.c.a());
/*  116 */     for (byte b = 0; b < paramArrayOfc.length; b++) {
/*  117 */       com.d.c.a.c c1 = paramArrayOfc[b];
/*  118 */       bitSet.set(c1.a);
/*      */     } 
/*  120 */     return bitSet;
/*      */   }
/*      */   
/*      */   static abstract class cz
/*      */     extends a {
/*      */     private cz() {}
/*      */     
/*      */     public List a(com.d.c.a.a param1a, List<com.d.c.d.d> param1List, int param1Int, boolean param1Boolean1, boolean param1Boolean2) {
/*  128 */       a(param1a, 1, param1List.size());
/*      */       com.d.c.d.d d;
/*  130 */       a(d = param1List.get(0), param1Boolean2);
/*  131 */       if (d.e() != 0) {
/*  132 */         a(param1a, d);
/*  133 */         com.d.c.a.c c = b(d);
/*      */         
/*  135 */         a(param1a, a(), c);
/*      */       } 
/*      */       
/*  138 */       return Collections.singletonList(new com.d.i.v(param1a, d, param1Boolean1, param1Int));
/*      */     }
/*      */     
/*      */     protected abstract BitSet a(); }
/*      */   
/*      */   static class bm extends a { private bm() {}
/*      */     
/*  145 */     private static final BitSet a = l.a(new com.d.c.a.c[] { com.d.c.a.c.bj });
/*      */ 
/*      */ 
/*      */     
/*      */     public List a(com.d.c.a.a param1a, List<com.d.c.d.d> param1List, int param1Int, boolean param1Boolean1, boolean param1Boolean2) {
/*  150 */       a(param1a, 1, param1List.size());
/*      */       com.d.c.d.d d;
/*  152 */       a(d = param1List.get(0), param1Boolean2);
/*  153 */       if (d.e() != 0) {
/*  154 */         c(param1a, d);
/*      */         
/*  156 */         if (d.a() == 21) {
/*      */           com.d.c.d.h h;
/*  158 */           if ((h = f.a(d.c())) != null) {
/*  159 */             return Collections.singletonList(new com.d.i.v(param1a, (com.d.c.d.d)new com.d.c.d.j((com.d.c.d.g)h), param1Boolean1, param1Int));
/*      */           }
/*      */ 
/*      */ 
/*      */ 
/*      */ 
/*      */ 
/*      */           
/*  167 */           com.d.c.a.c c = b(d);
/*  168 */           a(param1a, a, c);
/*      */         } 
/*      */       } 
/*      */       
/*  172 */       return Collections.singletonList(new com.d.i.v(param1a, d, param1Boolean1, param1Int));
/*      */     } }
/*      */ 
/*      */   
/*      */   static class bk extends cz { private bk() {
/*  177 */       super((byte)0);
/*      */     } protected final BitSet a() {
/*  179 */       return l.a;
/*      */     } }
/*      */   
/*      */   public static class af extends cz { public af() {
/*  183 */       super((byte)0);
/*      */     }
/*      */     protected final BitSet a() {
/*  186 */       return l.c;
/*      */     } }
/*      */   
/*      */   static class bl extends a { private bl() {}
/*      */     
/*      */     public List a(com.d.c.a.a param1a, List<com.d.c.d.j> param1List, int param1Int, boolean param1Boolean1, boolean param1Boolean2) {
/*      */       com.d.c.a.c c;
/*  193 */       a(param1a, 1, param1List.size());
/*      */       com.d.c.d.j j;
/*  195 */       a((com.d.c.d.d)(j = param1List.get(0)), param1Boolean2);
/*  196 */       if (j.e() != 0) {
/*  197 */         f(param1a, (com.d.c.d.d)j);
/*      */         
/*  199 */         if (j.a() == 21) {
/*  200 */           c = b((com.d.c.d.d)j);
/*  201 */           a(param1a, l.b, c);
/*      */           
/*  203 */           return Collections.singletonList(new com.d.i.v(param1a, 
/*      */                 
/*  205 */                 (com.d.c.d.d)f.b(c.toString()), param1Boolean1, param1Int));
/*      */         } 
/*  207 */         if (c.f() < 0.0F) {
/*  208 */           throw new com.d.c.d.b(param1a + " may not be negative", -1);
/*      */         }
/*      */       } 
/*      */ 
/*      */       
/*  213 */       return Collections.singletonList(new com.d.i.v(param1a, (com.d.c.d.d)c, param1Boolean1, param1Int));
/*      */     } }
/*      */ 
/*      */   
/*      */   static class bj extends a {
/*      */     private bj() {}
/*      */     
/*      */     public List a(com.d.c.a.a param1a, List<com.d.c.d.j> param1List, int param1Int, boolean param1Boolean1, boolean param1Boolean2) {
/*  221 */       a(param1a, 1, 2, param1List.size());
/*      */       
/*  223 */       com.d.c.d.j j1 = param1List.get(0);
/*  224 */       com.d.c.d.j j2 = null;
/*  225 */       if (param1List.size() == 2) {
/*  226 */         j2 = param1List.get(1);
/*      */       }
/*      */       
/*  229 */       a((com.d.c.d.d)j1, param1Boolean2);
/*      */       
/*  231 */       if (j2 != null) {
/*  232 */         a((com.d.c.d.d)j2, false);
/*      */       }
/*      */       
/*  235 */       i(param1a, (com.d.c.d.d)j1);
/*  236 */       if (j2 == null) {
/*  237 */         return l.a(param1a, (com.d.c.d.d)j1, (com.d.c.d.d)j1, param1Int, param1Boolean1);
/*      */       }
/*  239 */       i(param1a, (com.d.c.d.d)j2);
/*  240 */       return l.a(param1a, (com.d.c.d.d)j1, (com.d.c.d.d)j2, param1Int, param1Boolean1);
/*      */     }
/*      */   }
/*      */   
/*      */   static abstract class bw
/*      */     extends a
/*      */   {
/*      */     private bw() {}
/*      */     
/*      */     public List a(com.d.c.a.a param1a, List<com.d.c.d.j> param1List, int param1Int, boolean param1Boolean1, boolean param1Boolean2) {
/*  250 */       a(param1a, 1, param1List.size());
/*      */       com.d.c.d.j j;
/*  252 */       a((com.d.c.d.d)(j = param1List.get(0)), param1Boolean2);
/*  253 */       if (j.e() != 0) {
/*  254 */         f(param1a, (com.d.c.d.d)j);
/*      */         
/*  256 */         if (j.a() == 21) {
/*  257 */           com.d.c.a.c c = b((com.d.c.d.d)j);
/*  258 */           a(param1a, a(), c);
/*      */         } 
/*      */       } 
/*      */ 
/*      */ 
/*      */       
/*  264 */       return Collections.singletonList(new com.d.i.v(param1a, (com.d.c.d.d)j, param1Boolean1, param1Int));
/*      */     }
/*      */ 
/*      */     
/*      */     protected abstract BitSet a();
/*      */   }
/*      */ 
/*      */   
/*      */   static abstract class bu
/*      */     extends a
/*      */   {
/*      */     private bu() {}
/*      */ 
/*      */     
/*      */     public List a(com.d.c.a.a param1a, List<com.d.c.d.j> param1List, int param1Int, boolean param1Boolean1, boolean param1Boolean2) {
/*  279 */       a(param1a, 1, param1List.size());
/*      */       com.d.c.d.j j;
/*  281 */       a((com.d.c.d.d)(j = param1List.get(0)), param1Boolean2);
/*  282 */       if (j.e() != 0) {
/*  283 */         h(param1a, (com.d.c.d.d)j);
/*      */         
/*  285 */         if (j.a() == 21) {
/*  286 */           com.d.c.a.c c = b((com.d.c.d.d)j);
/*  287 */           a(param1a, a(), c);
/*  288 */         } else if (!b() && j.f() < 0.0F) {
/*  289 */           throw new com.d.c.d.b(param1a + " may not be negative", -1);
/*      */         } 
/*      */       } 
/*      */       
/*  293 */       return Collections.singletonList(new com.d.i.v(param1a, (com.d.c.d.d)j, param1Boolean1, param1Int));
/*      */     }
/*      */ 
/*      */ 
/*      */     
/*      */     protected boolean b() {
/*  299 */       return true;
/*      */     }
/*      */     
/*      */     protected abstract BitSet a(); }
/*      */   
/*      */   static class bs extends a {
/*      */     public List a(com.d.c.a.a param1a, List<com.d.c.d.j> param1List, int param1Int, boolean param1Boolean1, boolean param1Boolean2) {
/*  306 */       a(param1a, 1, param1List.size());
/*      */       com.d.c.d.j j;
/*  308 */       a((com.d.c.d.d)(j = param1List.get(0)), param1Boolean2);
/*  309 */       if (j.e() != 0) {
/*  310 */         i(param1a, (com.d.c.d.d)j);
/*      */         
/*  312 */         if (!a() && j.f() < 0.0F) {
/*  313 */           throw new com.d.c.d.b(param1a + " may not be negative", -1);
/*      */         }
/*      */       } 
/*      */       
/*  317 */       return Collections.singletonList(new com.d.i.v(param1a, (com.d.c.d.d)j, param1Boolean1, param1Int));
/*      */     }
/*      */     
/*      */     private bs() {}
/*      */     
/*      */     protected boolean a() {
/*  323 */       return true;
/*      */     } }
/*      */   
/*      */   static class cl extends bs { private cl() {
/*  327 */       super((byte)0);
/*      */     } protected final boolean a() {
/*  329 */       return false;
/*      */     } }
/*      */   
/*      */   static class aa extends a { private aa() {}
/*      */     
/*      */     public List a(com.d.c.a.a param1a, List<com.d.c.d.j> param1List, int param1Int, boolean param1Boolean1, boolean param1Boolean2) {
/*  335 */       a(param1a, 1, param1List.size());
/*      */       com.d.c.d.j j;
/*  337 */       a((com.d.c.d.d)(j = param1List.get(0)), param1Boolean2);
/*  338 */       if (j.e() != 0) {
/*  339 */         k(param1a, (com.d.c.d.d)j);
/*      */         
/*  341 */         if (j.f() < 1.0F) {
/*  342 */           throw new com.d.c.d.b("colspan/rowspan must be greater than zero", -1);
/*      */         }
/*      */       } 
/*      */       
/*  346 */       return Collections.singletonList(new com.d.i.v(param1a, (com.d.c.d.d)j, param1Boolean1, param1Int));
/*      */     } }
/*      */ 
/*      */   
/*      */   static class cw extends a {
/*      */     private cw() {}
/*      */     
/*      */     public List a(com.d.c.a.a param1a, List<com.d.c.d.j> param1List, int param1Int, boolean param1Boolean1, boolean param1Boolean2) {
/*  354 */       a(param1a, 1, param1List.size());
/*      */       com.d.c.d.j j;
/*  356 */       a((com.d.c.d.d)(j = param1List.get(0)), param1Boolean2);
/*  357 */       if (j.e() != 0) {
/*  358 */         e(param1a, (com.d.c.d.d)j);
/*      */         
/*  360 */         if (!a() && j.f() < 0.0F) {
/*  361 */           throw new com.d.c.d.b(param1a + " may not be negative", -1);
/*      */         }
/*      */       } 
/*      */       
/*  365 */       return Collections.singletonList(new com.d.i.v(param1a, (com.d.c.d.d)j, param1Boolean1, param1Int));
/*      */     }
/*      */ 
/*      */ 
/*      */     
/*      */     protected boolean a() {
/*  371 */       return true;
/*      */     } }
/*      */   
/*      */   static class br extends a {
/*      */     private br() {}
/*      */     
/*      */     public List a(com.d.c.a.a param1a, List<com.d.c.d.j> param1List, int param1Int, boolean param1Boolean1, boolean param1Boolean2) {
/*  378 */       a(param1a, 1, param1List.size());
/*      */       com.d.c.d.j j;
/*  380 */       a((com.d.c.d.d)(j = param1List.get(0)), param1Boolean2);
/*  381 */       if (j.e() != 0) {
/*  382 */         j(param1a, (com.d.c.d.d)j);
/*      */       }
/*      */ 
/*      */ 
/*      */ 
/*      */ 
/*      */       
/*  389 */       return Collections.singletonList(new com.d.i.v(param1a, (com.d.c.d.d)j, param1Boolean1, param1Int));
/*      */     }
/*      */   }
/*      */ 
/*      */ 
/*      */ 
/*      */ 
/*      */ 
/*      */ 
/*      */ 
/*      */ 
/*      */ 
/*      */ 
/*      */ 
/*      */ 
/*      */ 
/*      */ 
/*      */ 
/*      */ 
/*      */ 
/*      */ 
/*      */ 
/*      */ 
/*      */ 
/*      */ 
/*      */ 
/*      */ 
/*      */ 
/*      */ 
/*      */ 
/*      */ 
/*      */ 
/*      */ 
/*      */ 
/*      */ 
/*      */ 
/*      */ 
/*      */ 
/*      */ 
/*      */ 
/*      */ 
/*      */ 
/*      */ 
/*      */ 
/*      */ 
/*      */ 
/*      */ 
/*      */ 
/*      */ 
/*      */ 
/*      */ 
/*      */ 
/*      */ 
/*      */ 
/*      */ 
/*      */ 
/*      */ 
/*      */ 
/*      */ 
/*      */   
/*      */   static class bt
/*      */     extends bu
/*      */   {
/*      */     private bt() {
/*  453 */       super((byte)0);
/*      */     }
/*  455 */     private static final BitSet a = l.a(new com.d.c.a.c[] { com.d.c.a.c.e });
/*      */ 
/*      */     
/*      */     protected final BitSet a() {
/*  459 */       return a;
/*      */     } }
/*      */   
/*      */   static class bx extends bw { private bx() {
/*  463 */       super((byte)0);
/*      */     }
/*  465 */     private static final BitSet a = l.a(new com.d.c.a.c[] { com.d.c.a.c.aq });
/*      */ 
/*      */     
/*      */     protected final BitSet a() {
/*  469 */       return a;
/*      */     } }
/*      */   
/*      */   static class bv extends bu { private bv() {
/*  473 */       super((byte)0);
/*      */     }
/*  475 */     private static final BitSet a = l.a(new com.d.c.a.c[] { com.d.c.a.c.ap });
/*      */ 
/*      */     
/*      */     protected final BitSet a() {
/*  479 */       return a;
/*      */     } }
/*      */   
/*      */   static class bn extends a {
/*      */     private bn() {}
/*      */     
/*  485 */     private static final BitSet a = l.a(new com.d.c.a.c[] { com.d.c.a.c.ap });
/*      */ 
/*      */     
/*      */     public List a(com.d.c.a.a param1a, List<com.d.c.d.d> param1List, int param1Int, boolean param1Boolean1, boolean param1Boolean2) {
/*  489 */       a(param1a, 1, param1List.size());
/*      */       com.d.c.d.d d;
/*  491 */       a(d = param1List.get(0), param1Boolean2);
/*  492 */       if (d.e() != 0) {
/*  493 */         b(param1a, d);
/*      */         
/*  495 */         if (d.a() == 21) {
/*  496 */           com.d.c.a.c c = b(d);
/*  497 */           a(param1a, a, c);
/*      */         } 
/*      */       } 
/*  500 */       return Collections.singletonList(new com.d.i.v(param1a, d, param1Boolean1, param1Int));
/*      */     }
/*      */   }
/*      */   
/*      */   public static class a extends cz { public a() {
/*  505 */       super((byte)0);
/*      */     } protected final BitSet a() {
/*  507 */       return l.m;
/*      */     } }
/*      */   
/*      */   public static class b extends bm { public b() {
/*  511 */       super((byte)0);
/*      */     } }
/*      */   public static class c extends bn { public c() {
/*  514 */       super((byte)0);
/*      */     } }
/*      */   
/*      */   public static class f extends a {
/*  518 */     private static final BitSet a = l.a(new com.d.c.a.c[] { com.d.c.a.c.e, com.d.c.a.c.r, com.d.c.a.c.s });
/*      */ 
/*      */ 
/*      */     
/*      */     public final List a(com.d.c.a.a param1a, List<com.d.c.d.d> param1List, int param1Int, boolean param1Boolean1, boolean param1Boolean2) {
/*  523 */       a(param1a, 1, 2, param1List.size());
/*      */       
/*  525 */       com.d.c.d.d d1 = param1List.get(0);
/*  526 */       com.d.c.d.d d2 = null;
/*  527 */       if (param1List.size() == 2) {
/*  528 */         d2 = param1List.get(1);
/*      */       }
/*      */       
/*  531 */       a(d1, param1Boolean2);
/*  532 */       if (param1List.size() == 1 && d1
/*  533 */         .e() == 0) {
/*  534 */         return Collections.singletonList(new com.d.i.v(param1a, d1, param1Boolean1, param1Int));
/*      */       }
/*      */ 
/*      */       
/*  538 */       if (d2 != null) {
/*  539 */         a(d2, false);
/*      */       }
/*      */       
/*  542 */       h(param1a, d1);
/*  543 */       if (d2 == null) {
/*  544 */         if (d1.a() == 21) {
/*  545 */           com.d.c.a.c c = b(d1);
/*  546 */           a(param1a, a, c);
/*      */           
/*  548 */           if (c == com.d.c.a.c.r || c == com.d.c.a.c.s) {
/*  549 */             return Collections.singletonList(new com.d.i.v(param1a, d1, param1Boolean1, param1Int));
/*      */           }
/*      */           
/*  552 */           return l.a(com.d.c.a.a.h, d1, d1, param1Int, param1Boolean1);
/*      */         } 
/*      */         
/*  555 */         return l.a(com.d.c.a.a.h, d1, (com.d.c.d.d)new com.d.c.d.j(com.d.c.a.c.e), param1Int, param1Boolean1);
/*      */       } 
/*      */       
/*  558 */       h(param1a, d2);
/*      */       
/*  560 */       if (d1.a() == 21) {
/*      */         com.d.c.a.c c;
/*  562 */         if ((c = b(d1)) != com.d.c.a.c.e) {
/*  563 */           throw new com.d.c.d.b("The only ident value allowed here is 'auto'", -1);
/*      */         }
/*  565 */       } else if (((com.d.c.d.j)d1).f() < 0.0F) {
/*  566 */         throw new com.d.c.d.b(param1a + " values cannot be negative", -1);
/*      */       } 
/*      */       
/*  569 */       if (d2.a() == 21) {
/*      */         com.d.c.a.c c;
/*  571 */         if ((c = b(d2)) != com.d.c.a.c.e) {
/*  572 */           throw new com.d.c.d.b("The only ident value allowed here is 'auto'", -1);
/*      */         }
/*  574 */       } else if (((com.d.c.d.j)d2).f() < 0.0F) {
/*  575 */         throw new com.d.c.d.b(param1a + " values cannot be negative", -1);
/*      */       } 
/*      */       
/*  578 */       return l.a(com.d.c.a.a.h, d1, d2, param1Int, param1Boolean1);
/*      */     }
/*      */   }
/*      */ 
/*      */   
/*      */   public static class d
/*      */     extends a
/*      */   {
/*      */     public final List a(com.d.c.a.a param1a, List<com.d.c.d.d> param1List, int param1Int, boolean param1Boolean1, boolean param1Boolean2) {
/*  587 */       a(param1a, 1, 2, param1List.size());
/*      */       
/*  589 */       com.d.c.d.d d1 = param1List.get(0);
/*  590 */       com.d.c.d.d d2 = null;
/*  591 */       if (param1List.size() == 2) {
/*  592 */         d2 = param1List.get(1);
/*      */       }
/*      */       
/*  595 */       a(d1, param1Boolean2);
/*  596 */       if (param1List.size() == 1 && d1
/*  597 */         .e() == 0) {
/*  598 */         return Collections.singletonList(new com.d.i.v(param1a, d1, param1Boolean1, param1Int));
/*      */       }
/*      */ 
/*      */       
/*  602 */       if (d2 != null) {
/*  603 */         a(d2, false);
/*      */       }
/*      */       
/*  606 */       h(param1a, d1);
/*  607 */       if (d2 == null) {
/*  608 */         if (a(d1) || d1.a() == 2) {
/*      */           ArrayList<com.d.c.d.d> arrayList;
/*  610 */           (arrayList = new ArrayList<>(2)).add(d1);
/*  611 */           arrayList.add(new com.d.c.d.j((short)2, 50.0F, "50%"));
/*      */           
/*  613 */           return Collections.singletonList(new com.d.i.v(com.d.c.a.a.g, (com.d.c.d.d)new com.d.c.d.j(arrayList), param1Boolean1, param1Int));
/*      */         }
/*      */       
/*      */       } else {
/*      */         
/*  618 */         h(param1a, d2);
/*      */       } 
/*      */ 
/*      */       
/*  622 */       com.d.c.a.c c1 = null;
/*  623 */       if (d1.a() == 21) {
/*  624 */         c1 = b(d1);
/*  625 */         a(param1a, a(), c1);
/*      */       } 
/*      */       
/*  628 */       com.d.c.a.c c2 = null;
/*  629 */       if (d2 == null) {
/*  630 */         c2 = com.d.c.a.c.n;
/*  631 */       } else if (d2.a() == 21) {
/*  632 */         c2 = b(d2);
/*  633 */         a(param1a, a(), c2);
/*      */       } 
/*      */       
/*  636 */       if (c1 == null && c2 == null) {
/*  637 */         return Collections.singletonList(new com.d.i.v(com.d.c.a.a.g, (com.d.c.d.d)new com.d.c.d.j(param1List), param1Boolean1, param1Int));
/*      */       }
/*  639 */       if (c1 != null && c2 != null) {
/*  640 */         if (c1 == com.d.c.a.c.bi || c1 == com.d.c.a.c.l || c2 == com.d.c.a.c.aa || c2 == com.d.c.a.c.aJ) {
/*      */           
/*  642 */           com.d.c.a.c c = c1;
/*  643 */           c1 = c2;
/*  644 */           c2 = c;
/*      */         } 
/*      */         
/*  647 */         a(param1a, c1, c2);
/*      */         
/*  649 */         return a(
/*  650 */             a(c1), 
/*  651 */             a(c2), param1Boolean1, param1Int);
/*      */       } 
/*      */ 
/*      */       
/*  655 */       a(param1a, c1, c2);
/*      */       
/*  657 */       param1List = new ArrayList<>(2);
/*      */       
/*  659 */       if (c1 == null) {
/*  660 */         param1List.add(d1);
/*  661 */         param1List.add(b(c2));
/*      */       } else {
/*  663 */         param1List.add(b(c1));
/*  664 */         param1List.add(d2);
/*      */       } 
/*      */       
/*  667 */       return Collections.singletonList(new com.d.i.v(com.d.c.a.a.g, (com.d.c.d.d)new com.d.c.d.j(param1List), param1Boolean1, param1Int));
/*      */     }
/*      */ 
/*      */ 
/*      */ 
/*      */     
/*      */     private static void a(com.d.c.a.a param1a, com.d.c.a.c param1c1, com.d.c.a.c param1c2) {
/*  674 */       if (param1c1 == com.d.c.a.c.bi || param1c1 == com.d.c.a.c.l || param1c2 == com.d.c.a.c.aa || param1c2 == com.d.c.a.c.aJ)
/*      */       {
/*  676 */         throw new com.d.c.d.b("Invalid combination of keywords in " + param1a, -1);
/*      */       }
/*      */     }
/*      */     
/*      */     private static float a(com.d.c.a.c param1c) {
/*  681 */       float f = 0.0F;
/*      */       
/*  683 */       if (param1c == com.d.c.a.c.n) {
/*  684 */         f = 50.0F;
/*  685 */       } else if (param1c == com.d.c.a.c.l || param1c == com.d.c.a.c.aJ) {
/*  686 */         f = 100.0F;
/*      */       } 
/*      */       
/*  689 */       return f;
/*      */     }
/*      */     
/*      */     private com.d.c.d.j b(com.d.c.a.c param1c) {
/*  693 */       float f = a(param1c);
/*  694 */       return new com.d.c.d.j((short)2, f, f + "%");
/*      */     }
/*      */ 
/*      */ 
/*      */     
/*      */     private static List a(float param1Float1, float param1Float2, boolean param1Boolean, int param1Int) {
/*  700 */       com.d.c.d.j j1 = new com.d.c.d.j((short)2, param1Float1, param1Float1 + "%");
/*      */       
/*  702 */       com.d.c.d.j j2 = new com.d.c.d.j((short)2, param1Float2, param1Float2 + "%");
/*      */       
/*      */       ArrayList<com.d.c.d.j> arrayList;
/*      */       
/*  706 */       (arrayList = new ArrayList<>(2)).add(j1);
/*  707 */       arrayList.add(j2);
/*      */ 
/*      */       
/*      */       com.d.i.v v;
/*      */ 
/*      */       
/*  713 */       return Collections.singletonList(v = new com.d.i.v(com.d.c.a.a.g, (com.d.c.d.d)new com.d.c.d.j(arrayList), param1Boolean, param1Int));
/*      */     }
/*      */     
/*      */     private static BitSet a() {
/*  717 */       return l.n;
/*      */     } }
/*      */   
/*      */   public static class e extends cz { public e() {
/*  721 */       super((byte)0);
/*      */     } protected final BitSet a() {
/*  723 */       return l.l;
/*      */     } }
/*      */   
/*      */   public static class l extends cz { public l() {
/*  727 */       super((byte)0);
/*      */     }
/*  729 */     private static final BitSet a = l.a(new com.d.c.a.c[] { com.d.c.a.c.q, com.d.c.a.c.aN });
/*      */ 
/*      */     
/*      */     protected final BitSet a() {
/*  733 */       return a;
/*      */     } }
/*      */   
/*      */   public static class r extends bm { public r() {
/*  737 */       super((byte)0);
/*      */     } }
/*      */ 
/*      */   
/*      */   public static class g extends bm {
/*      */     public g() {
/*  743 */       super((byte)0);
/*      */     } }
/*      */   public static class m extends bm { public m() {
/*  746 */       super((byte)0);
/*      */     } }
/*      */   public static class u extends bk { public u() {
/*  749 */       super((byte)0);
/*      */     } }
/*      */   public static class p extends bk { public p() {
/*  752 */       super((byte)0);
/*      */     } }
/*      */   public static class j extends bk { public j() {
/*  755 */       super((byte)0);
/*      */     } }
/*      */   public static class n extends bk { public n() {
/*  758 */       super((byte)0);
/*      */     } }
/*      */   public static class v extends bl { public v() {
/*  761 */       super((byte)0);
/*      */     } }
/*      */   public static class q extends bl { public q() {
/*  764 */       super((byte)0);
/*      */     } }
/*      */   public static class k extends bl { public k() {
/*  767 */       super((byte)0);
/*      */     } }
/*      */   public static class o extends bl { public o() {
/*  770 */       super((byte)0);
/*      */     } }
/*      */   public static class s extends bj { public s() {
/*  773 */       super((byte)0);
/*      */     } }
/*      */   public static class t extends bj { public t() {
/*  776 */       super((byte)0);
/*      */     } }
/*      */   public static class i extends bj { public i() {
/*  779 */       super((byte)0);
/*      */     } }
/*      */   public static class h extends bj { public h() {
/*  782 */       super((byte)0);
/*      */     } }
/*      */   public static class w extends bt { public w() {
/*  785 */       super((byte)0);
/*      */     } }
/*      */   public static class y extends cz { public y() {
/*  788 */       super((byte)0);
/*      */     }
/*  790 */     private static final BitSet a = l.a(new com.d.c.a.c[] { com.d.c.a.c.bi, com.d.c.a.c.l });
/*      */ 
/*      */     
/*      */     protected final BitSet a() {
/*  794 */       return a;
/*      */     } }
/*      */   
/*      */   public static class z extends cz { public z() {
/*  798 */       super((byte)0);
/*      */     }
/*  800 */     private static final BitSet a = l.a(new com.d.c.a.c[] { com.d.c.a.c.ap, com.d.c.a.c.aa, com.d.c.a.c.aJ, com.d.c.a.c.k });
/*      */ 
/*      */     
/*      */     protected final BitSet a() {
/*  804 */       return a;
/*      */     } }
/*      */   
/*      */   public static class ab extends bm { public ab() {
/*  808 */       super((byte)0);
/*      */     } }
/*      */   public static class ae extends cz { public ae() {
/*  811 */       super((byte)0);
/*      */     }
/*      */ 
/*      */     
/*  815 */     private static final BitSet a = l.a(new com.d.c.a.c[] { com.d.c.a.c.e, com.d.c.a.c.bq, com.d.c.a.c.br, com.d.c.a.c.az, com.d.c.a.c.by, com.d.c.a.c.bt, com.d.c.a.c.bA, com.d.c.a.c.bB, com.d.c.a.c.bz, com.d.c.a.c.bE, com.d.c.a.c.bI, com.d.c.a.c.bD, com.d.c.a.c.bK, com.d.c.a.c.bJ, com.d.c.a.c.bL, com.d.c.a.c.bu, com.d.c.a.c.bC });
/*      */ 
/*      */ 
/*      */ 
/*      */ 
/*      */ 
/*      */ 
/*      */ 
/*      */ 
/*      */ 
/*      */ 
/*      */     
/*      */     protected final BitSet a() {
/*  828 */       return a;
/*      */     } }
/*      */   
/*      */   public static class ag extends cz { public ag() {
/*  832 */       super((byte)0);
/*      */     }
/*      */ 
/*      */ 
/*      */     
/*  837 */     private static final BitSet a = l.a(new com.d.c.a.c[] { com.d.c.a.c.R, com.d.c.a.c.h, com.d.c.a.c.ae, com.d.c.a.c.S, com.d.c.a.c.aV, com.d.c.a.c.T, com.d.c.a.c.bd, com.d.c.a.c.bb, com.d.c.a.c.ba, com.d.c.a.c.bc, com.d.c.a.c.aZ, com.d.c.a.c.aY, com.d.c.a.c.aX, com.d.c.a.c.aW, com.d.c.a.c.ap });
/*      */ 
/*      */ 
/*      */ 
/*      */ 
/*      */ 
/*      */ 
/*      */ 
/*      */ 
/*      */ 
/*      */     
/*      */     protected final BitSet a() {
/*  849 */       return a;
/*      */     } }
/*      */   
/*      */   public static class ah extends cz { public ah() {
/*  853 */       super((byte)0);
/*      */     }
/*  855 */     private static final BitSet a = l.a(new com.d.c.a.c[] { com.d.c.a.c.aO, com.d.c.a.c.Q });
/*      */ 
/*      */     
/*      */     protected final BitSet a() {
/*  859 */       return a;
/*      */     } }
/*      */   
/*      */   public static class bd extends cz { public bd() {
/*  863 */       super((byte)0);
/*      */     }
/*  865 */     private static final BitSet a = l.a(new com.d.c.a.c[] { com.d.c.a.c.aa, com.d.c.a.c.aJ, com.d.c.a.c.ap });
/*      */ 
/*      */     
/*      */     protected final BitSet a() {
/*  869 */       return a;
/*      */     } }
/*      */ 
/*      */ 
/*      */   
/*      */   public static class be
/*      */     extends a
/*      */   {
/*      */     public final List a(com.d.c.a.a param1a, List<com.d.c.d.d> param1List, int param1Int, boolean param1Boolean1, boolean param1Boolean2) {
/*  878 */       if (param1List.size() == 1) {
/*      */         com.d.c.d.d d;
/*  880 */         a(d = param1List.get(0), param1Boolean2);
/*  881 */         if (d.e() == 0) {
/*  882 */           return Collections.singletonList(new com.d.i.v(param1a, d, param1Boolean1, param1Int));
/*      */         }
/*      */       } 
/*      */ 
/*      */ 
/*      */ 
/*      */ 
/*      */ 
/*      */       
/*  891 */       ArrayList<String> arrayList2 = new ArrayList();
/*  892 */       ArrayList<String> arrayList1 = new ArrayList(param1List.size());
/*  893 */       for (Iterator<com.d.c.d.d> iterator = param1List.iterator(); iterator.hasNext(); ) {
/*      */         com.d.c.d.j j1;
/*      */         
/*      */         com.d.c.d.k k;
/*  897 */         if ((k = (j1 = (com.d.c.d.j)iterator.next()).j()) != null && k != com.d.c.d.k.l) {
/*  898 */           throw new com.d.c.d.b("Invalid font-family definition", -1);
/*      */         }
/*      */         
/*  901 */         if (k != null && 
/*  902 */           arrayList2.size() > 0) {
/*  903 */           arrayList1.add(a(arrayList2, ' '));
/*  904 */           arrayList2.clear();
/*      */         } 
/*      */ 
/*      */         
/*  908 */         a((com.d.c.d.d)j1, false);
/*      */         short s;
/*  910 */         if ((s = j1.a()) == 19) {
/*  911 */           if (arrayList2.size() > 0) {
/*  912 */             arrayList1.add(a(arrayList2, ' '));
/*  913 */             arrayList2.clear();
/*      */           } 
/*  915 */           arrayList1.add(j1.c()); continue;
/*  916 */         }  if (s == 21) {
/*  917 */           arrayList2.add(j1.c()); continue;
/*      */         } 
/*  919 */         throw new com.d.c.d.b("Invalid font-family definition", -1);
/*      */       } 
/*      */       
/*  922 */       if (arrayList2.size() > 0) {
/*  923 */         arrayList1.add(a(arrayList2, ' '));
/*      */       }
/*      */       
/*  926 */       String str = a(arrayList1, ',');
/*      */       
/*      */       com.d.c.d.j j;
/*  929 */       (j = new com.d.c.d.j((short)19, str, str)).a(arrayList1.<String>toArray(new String[arrayList1.size()]));
/*      */       
/*  931 */       return Collections.singletonList(new com.d.i.v(param1a, (com.d.c.d.d)j, param1Boolean1, param1Int));
/*      */     }
/*      */ 
/*      */     
/*      */     private static String a(List param1List, char param1Char) {
/*  936 */       StringBuilder stringBuilder = new StringBuilder(64);
/*  937 */       for (Iterator<String> iterator = param1List.iterator(); iterator.hasNext(); ) {
/*  938 */         String str = iterator.next();
/*  939 */         stringBuilder.append(str);
/*  940 */         if (iterator.hasNext()) {
/*  941 */           stringBuilder.append(param1Char);
/*      */         }
/*      */       } 
/*  944 */       return stringBuilder.toString();
/*      */     }
/*      */   }
/*      */   
/*      */   public static class bf
/*      */     extends a
/*      */   {
/*      */     private static final BitSet a;
/*      */     
/*      */     static {
/*  954 */       (a = new BitSet(com.d.c.a.c.a())).or(l.o);
/*  955 */       a.or(l.p);
/*      */     }
/*      */ 
/*      */     
/*      */     public final List a(com.d.c.a.a param1a, List<com.d.c.d.j> param1List, int param1Int, boolean param1Boolean1, boolean param1Boolean2) {
/*  960 */       a(param1a, 1, param1List.size());
/*      */       com.d.c.d.j j;
/*  962 */       a((com.d.c.d.d)(j = param1List.get(0)), param1Boolean2);
/*  963 */       if (j.e() != 0) {
/*  964 */         h(param1a, (com.d.c.d.d)j);
/*      */         
/*  966 */         if (j.a() == 21) {
/*  967 */           com.d.c.a.c c = b((com.d.c.d.d)j);
/*  968 */           a(param1a, a, c);
/*  969 */         } else if (j.f() < 0.0F) {
/*  970 */           throw new com.d.c.d.b("font-size may not be negative", -1);
/*      */         } 
/*      */       } 
/*      */       
/*  974 */       return Collections.singletonList(new com.d.i.v(param1a, (com.d.c.d.d)j, param1Boolean1, param1Int));
/*      */     }
/*      */   }
/*      */   
/*      */   public static class bg extends cz {
/*      */     public bg() {
/*  980 */       super((byte)0);
/*      */     } protected final BitSet a() {
/*  982 */       return l.g;
/*      */     } }
/*      */   
/*      */   public static class bh extends cz { public bh() {
/*  986 */       super((byte)0);
/*      */     } protected final BitSet a() {
/*  988 */       return l.d;
/*      */     } }
/*      */ 
/*      */   
/*      */   public static class bi
/*      */     extends a
/*      */   {
/*      */     public final List a(com.d.c.a.a param1a, List<com.d.c.d.j> param1List, int param1Int, boolean param1Boolean1, boolean param1Boolean2) {
/*  996 */       a(param1a, 1, param1List.size());
/*      */       com.d.c.d.j j;
/*  998 */       a((com.d.c.d.d)(j = param1List.get(0)), param1Boolean2);
/*  999 */       if (j.e() != 0) {
/* 1000 */         com.d.c.a.c c; g(param1a, (com.d.c.d.d)j);
/*      */         
/*      */         short s;
/* 1003 */         if ((s = j.a()) == 21) {
/* 1004 */           a(param1a, (com.d.c.d.d)j);
/* 1005 */           c = b((com.d.c.d.d)j);
/*      */           
/* 1007 */           a(param1a, a(), c);
/* 1008 */         } else if (c == true) {
/*      */           
/* 1010 */           if ((c = f.a(j.f())) == null) {
/* 1011 */             throw new com.d.c.d.b(j + " is not a valid font weight", -1);
/*      */           }
/*      */ 
/*      */ 
/*      */           
/* 1016 */           (j = new com.d.c.d.j((short)21, c.toString(), c.toString())).a(c);
/* 1017 */           return Collections.singletonList(new com.d.i.v(param1a, (com.d.c.d.d)j, param1Boolean1, param1Int));
/*      */         } 
/*      */       } 
/*      */ 
/*      */ 
/*      */       
/* 1023 */       return Collections.singletonList(new com.d.i.v(param1a, (com.d.c.d.d)j, param1Boolean1, param1Int));
/*      */     }
/*      */ 
/*      */     
/*      */     private static BitSet a() {
/* 1028 */       return l.h;
/*      */     } }
/*      */   
/*      */   public static class ai extends br { public ai() {
/* 1032 */       super((byte)0);
/*      */     } }
/*      */   public static class aj extends br { public aj() {
/* 1035 */       super((byte)0);
/*      */     } }
/*      */   public static class an extends cz { public an() {
/* 1038 */       super((byte)0);
/*      */     }
/*      */     protected final BitSet a() {
/* 1041 */       return l.e;
/*      */     } }
/*      */   
/*      */   public static class ak extends cz { public ak() {
/* 1045 */       super((byte)0);
/*      */     }
/*      */     protected final BitSet a() {
/* 1048 */       return l.f;
/*      */     } }
/*      */   
/*      */   public static class av extends bt { public av() {
/* 1052 */       super((byte)0);
/*      */     } protected final boolean b() {
/* 1054 */       return false;
/*      */     } }
/*      */   
/*      */   public static class ay extends bt { public ay() {
/* 1058 */       super((byte)0);
/*      */     } protected final boolean b() {
/* 1060 */       return false;
/*      */     } }
/*      */   
/*      */   public static class ax extends cz { public ax() {
/* 1064 */       super((byte)0);
/*      */     }
/* 1066 */     private static final BitSet a = l.a(new com.d.c.a.c[] { com.d.c.a.c.bH, com.d.c.a.c.e });
/*      */ 
/*      */     
/*      */     protected final BitSet a() {
/* 1070 */       return a;
/*      */     } }
/*      */   
/*      */   public static class aw extends cz { public aw() {
/* 1074 */       super((byte)0);
/*      */     } protected final BitSet a() {
/* 1076 */       return l.i;
/*      */     } }
/*      */   
/*      */   public static class as extends cz { public as() {
/* 1080 */       super((byte)0);
/*      */     }
/* 1082 */     private static final BitSet a = l.a(new com.d.c.a.c[] { com.d.c.a.c.e, com.d.c.a.c.bs });
/*      */ 
/*      */     
/*      */     protected final BitSet a() {
/* 1086 */       return a;
/*      */     } }
/*      */ 
/*      */   
/*      */   public static class at
/*      */     extends a {
/*      */     public final List a(com.d.c.a.a param1a, List<com.d.c.d.d> param1List, int param1Int, boolean param1Boolean1, boolean param1Boolean2) {
/* 1093 */       a(param1a, 1, param1List.size());
/*      */       com.d.c.d.d d;
/* 1095 */       a(d = param1List.get(0), param1Boolean2);
/* 1096 */       if (d.e() != 0) {
/* 1097 */         m(param1a, d);
/*      */         
/* 1099 */         if (d.a() == 21)
/*      */         {
/* 1101 */           return Collections.singletonList(new com.d.i.v(param1a, (com.d.c.d.d)new com.d.c.d.j((short)19, d
/*      */ 
/*      */ 
/*      */ 
/*      */                   
/* 1106 */                   .c(), d
/* 1107 */                   .d()), param1Boolean1, param1Int));
/*      */         }
/*      */       } 
/*      */ 
/*      */ 
/*      */       
/* 1113 */       return Collections.singletonList(new com.d.i.v(param1a, d, param1Boolean1, param1Int));
/*      */     }
/*      */   }
/*      */   
/*      */   public static class az extends aa { public az() {
/* 1118 */       super((byte)0);
/*      */     } }
/*      */   public static class ba extends aa { public ba() {
/* 1121 */       super((byte)0);
/*      */     } }
/*      */   public static class bb extends cz { public bb() {
/* 1124 */       super((byte)0);
/* 1125 */     } private static final BitSet a = l.a(new com.d.c.a.c[] { com.d.c.a.c.ay, com.d.c.a.c.e });
/*      */ 
/*      */     
/*      */     protected final BitSet a() {
/* 1129 */       return a;
/*      */     } }
/*      */   
/*      */   public static class bc extends cz { public bc() {
/* 1133 */       super((byte)0);
/* 1134 */     } private static final BitSet a = l.a(new com.d.c.a.c[] { com.d.c.a.c.ac, com.d.c.a.c.h });
/*      */ 
/*      */     
/*      */     protected final BitSet a() {
/* 1138 */       return a;
/*      */     } }
/*      */   
/*      */   public static class am extends bt { public am() {
/* 1142 */       super((byte)0);
/*      */     } protected final boolean b() {
/* 1144 */       return false;
/*      */     } }
/*      */   
/*      */   public static class bo extends bt { public bo() {
/* 1148 */       super((byte)0);
/*      */     } protected final boolean b() {
/* 1150 */       return false;
/*      */     } }
/*      */   
/*      */   public static class al extends cz { public al() {
/* 1154 */       super((byte)0);
/* 1155 */     } private static final BitSet a = l.a(new com.d.c.a.c[] { com.d.c.a.c.A, com.d.c.a.c.aS });
/*      */ 
/*      */     
/*      */     protected final BitSet a() {
/* 1159 */       return a;
/*      */     } }
/*      */   
/*      */   public static class ao extends cz { public ao() {
/* 1163 */       super((byte)0);
/*      */     }
/* 1165 */     private static final BitSet a = l.a(new com.d.c.a.c[] { com.d.c.a.c.e, com.d.c.a.c.Y });
/*      */ 
/*      */     
/*      */     protected final BitSet a() {
/* 1169 */       return a;
/*      */     } }
/*      */   
/*      */   public static class aq extends cz { public aq() {
/* 1173 */       super((byte)0);
/*      */     }
/* 1175 */     private static final BitSet a = l.a(new com.d.c.a.c[] { com.d.c.a.c.ap, com.d.c.a.c.t });
/*      */ 
/*      */     
/*      */     protected final BitSet a() {
/* 1179 */       return a;
/*      */     } }
/*      */   
/*      */   public static class bq extends bt { public bq() {
/* 1183 */       super((byte)0);
/*      */     } }
/*      */   public static class by extends bx { public by() {
/* 1186 */       super((byte)0);
/*      */     } }
/*      */ 
/*      */   
/*      */   public static class bz extends a {
/* 1191 */     private static final BitSet a = l.a(new com.d.c.a.c[] { com.d.c.a.c.aq });
/*      */ 
/*      */ 
/*      */     
/*      */     public final List a(com.d.c.a.a param1a, List<com.d.c.d.j> param1List, int param1Int, boolean param1Boolean1, boolean param1Boolean2) {
/* 1196 */       a(param1a, 1, param1List.size());
/*      */       com.d.c.d.j j;
/* 1198 */       a((com.d.c.d.d)(j = param1List.get(0)), param1Boolean2);
/* 1199 */       if (j.e() != 0) {
/* 1200 */         n(param1a, (com.d.c.d.d)j);
/*      */         
/* 1202 */         if (j.a() == 21) {
/* 1203 */           com.d.c.a.c c = b((com.d.c.d.d)j);
/* 1204 */           a(param1a, a, c);
/* 1205 */         } else if (j.f() < 0.0D) {
/* 1206 */           throw new com.d.c.d.b("line-height may not be negative", -1);
/*      */         } 
/*      */       } 
/* 1209 */       return Collections.singletonList(new com.d.i.v(param1a, (com.d.c.d.d)j, param1Boolean1, param1Int));
/*      */     }
/*      */   }
/*      */   
/*      */   public static class ca extends bn { public ca() {
/* 1214 */       super((byte)0);
/*      */     } }
/*      */   public static class cb extends cz { public cb() {
/* 1217 */       super((byte)0);
/*      */     } protected final BitSet a() {
/* 1219 */       return l.j;
/*      */     } }
/*      */   
/*      */   public static class cc extends cz { public cc() {
/* 1223 */       super((byte)0);
/*      */     } protected final BitSet a() {
/* 1225 */       return l.k;
/*      */     } }
/*      */   
/*      */   public static class cg extends bt { public cg() {
/* 1229 */       super((byte)0);
/*      */     } }
/*      */   public static class cf extends bt { public cf() {
/* 1232 */       super((byte)0);
/*      */     } }
/*      */   public static class cd extends bt { public cd() {
/* 1235 */       super((byte)0);
/*      */     } }
/*      */   public static class ce extends bt { public ce() {
/* 1238 */       super((byte)0);
/*      */     } }
/*      */   public static class ch extends bv { public ch() {
/* 1241 */       super((byte)0);
/*      */     } protected final boolean b() {
/* 1243 */       return false;
/*      */     } }
/*      */   
/*      */   public static class ci extends bv { public ci() {
/* 1247 */       super((byte)0);
/*      */     } protected final boolean b() {
/* 1249 */       return false;
/*      */     } }
/*      */   
/*      */   public static class cj extends cl { public cj() {
/* 1253 */       super((byte)0);
/*      */     } }
/*      */   public static class ck extends cl { public ck() {
/* 1256 */       super((byte)0);
/*      */     } }
/*      */   public static class au extends cl { public au() {
/* 1259 */       super((byte)0);
/*      */     } }
/*      */   public static class cm extends cw { public cm() {
/* 1262 */       super((byte)0);
/*      */     } protected final boolean a() {
/* 1264 */       return false;
/*      */     } }
/*      */   
/*      */   public static class cn extends cz { public cn() {
/* 1268 */       super((byte)0);
/*      */     }
/* 1270 */     private static final BitSet a = l.a(new com.d.c.a.c[] { com.d.c.a.c.bp, com.d.c.a.c.P });
/*      */ 
/*      */ 
/*      */ 
/*      */ 
/*      */ 
/*      */     
/*      */     protected final BitSet a() {
/* 1278 */       return a;
/*      */     } }
/*      */   
/*      */   public static class cr extends cl { public cr() {
/* 1282 */       super((byte)0);
/*      */     } }
/*      */   public static class cq extends cl { public cq() {
/* 1285 */       super((byte)0);
/*      */     } }
/*      */   public static class co extends cl { public co() {
/* 1288 */       super((byte)0);
/*      */     } }
/*      */   public static class cp extends cl { public cp() {
/* 1291 */       super((byte)0);
/*      */     } }
/*      */   public static class cu extends cz { public cu() {
/* 1294 */       super((byte)0);
/*      */     }
/* 1296 */     private static final BitSet a = l.a(new com.d.c.a.c[] { com.d.c.a.c.e, com.d.c.a.c.c, com.d.c.a.c.f, com.d.c.a.c.aa, com.d.c.a.c.aJ });
/*      */ 
/*      */ 
/*      */ 
/*      */ 
/*      */     
/*      */     protected final BitSet a() {
/* 1303 */       return a;
/*      */     } }
/*      */ 
/*      */   
/*      */   public static class cs extends a {
/*      */     public final List a(com.d.c.a.a param1a, List<com.d.c.d.d> param1List, int param1Int, boolean param1Boolean1, boolean param1Boolean2) {
/*      */       com.d.c.d.j j;
/* 1310 */       a(param1a, 1, param1List.size());
/*      */       com.d.c.d.d d;
/* 1312 */       a(d = param1List.get(0), param1Boolean2);
/* 1313 */       if (d.e() != 0) {
/* 1314 */         a(param1a, d);
/*      */         
/* 1316 */         if (!d.c().equals("auto"))
/*      */         {
/*      */           
/* 1319 */           j = new com.d.c.d.j((short)19, d.c(), d.d());
/*      */         }
/*      */       } 
/*      */       
/* 1323 */       return Collections.singletonList(new com.d.i.v(param1a, (com.d.c.d.d)j, param1Boolean1, param1Int));
/*      */     }
/*      */   }
/*      */   
/*      */   public static class ct
/*      */     extends cz {
/*      */     public ct() {
/* 1330 */       super((byte)0);
/*      */     }
/* 1332 */     private static final BitSet a = l.a(new com.d.c.a.c[] { com.d.c.a.c.e, com.d.c.a.c.c, com.d.c.a.c.f, com.d.c.a.c.aa, com.d.c.a.c.aJ });
/*      */ 
/*      */ 
/*      */ 
/*      */ 
/*      */     
/*      */     protected final BitSet a() {
/* 1339 */       return a;
/*      */     } }
/*      */   
/*      */   public static class cv extends cz { public cv() {
/* 1343 */       super((byte)0);
/*      */     }
/* 1345 */     private static final BitSet a = l.a(new com.d.c.a.c[] { com.d.c.a.c.f, com.d.c.a.c.e });
/*      */ 
/*      */ 
/*      */     
/*      */     protected final BitSet a() {
/* 1350 */       return a;
/*      */     } }
/*      */ 
/*      */   
/*      */   public static class cx
/*      */     extends a {
/* 1356 */     private static final BitSet a = l.a(new com.d.c.a.c[] { com.d.c.a.c.aS, com.d.c.a.c.aE, com.d.c.a.c.b, com.d.c.a.c.B });
/*      */ 
/*      */ 
/*      */ 
/*      */ 
/*      */     
/*      */     public final List a(com.d.c.a.a param1a, List<com.d.c.d.j> param1List, int param1Int, boolean param1Boolean1, boolean param1Boolean2) {
/* 1363 */       a(param1a, 1, param1List.size());
/*      */       com.d.c.d.j j;
/* 1365 */       a((com.d.c.d.d)(j = param1List.get(0)), param1Boolean2);
/* 1366 */       if (j.e() != 0) {
/* 1367 */         if (j.a() == 21) {
/* 1368 */           a(param1a, (com.d.c.d.d)j);
/* 1369 */           com.d.c.a.c c = b((com.d.c.d.d)j);
/*      */           
/* 1371 */           a(param1a, a(), c);
/* 1372 */         } else if (j.i() == 7) {
/*      */           com.d.i.e e;
/* 1374 */           if ((e = j.n()).a().equals("running")) {
/*      */             List<?> list;
/* 1376 */             if ((list = e.b()).size() == 1) {
/*      */               com.d.c.d.j j1;
/* 1378 */               if ((j1 = (com.d.c.d.j)list.get(0)).a() != 21) {
/* 1379 */                 throw new com.d.c.d.b("The running function takes an identifier as a parameter", -1);
/*      */               }
/*      */             } else {
/* 1382 */               throw new com.d.c.d.b("The running function takes one parameter", -1);
/*      */             } 
/*      */           } else {
/* 1385 */             throw new com.d.c.d.b("Only the running function is supported here", -1);
/*      */           } 
/*      */         } else {
/* 1388 */           throw new com.d.c.d.b("Value for " + param1a + " must be an identifier or function", -1);
/*      */         } 
/*      */       }
/*      */       
/* 1392 */       return Collections.singletonList(new com.d.i.v(param1a, (com.d.c.d.d)j, param1Boolean1, param1Int));
/*      */     }
/*      */ 
/*      */ 
/*      */     
/*      */     private static BitSet a() {
/* 1398 */       return a;
/*      */     } }
/*      */   
/*      */   public static class cy extends bt { public cy() {
/* 1402 */       super((byte)0);
/*      */     } }
/*      */   public static class da extends bn { public da() {
/* 1405 */       super((byte)0);
/*      */     } }
/*      */   public static class db extends cw { public db() {
/* 1408 */       super((byte)0);
/*      */     } protected final boolean a() {
/* 1410 */       return false;
/*      */     } }
/*      */   
/*      */   public static class dh extends bt { public dh() {
/* 1414 */       super((byte)0);
/*      */     } }
/*      */   public static class dc extends cz { public dc() {
/* 1417 */       super((byte)0);
/*      */     }
/* 1419 */     private static final BitSet a = l.a(new com.d.c.a.c[] { com.d.c.a.c.e, com.d.c.a.c.B });
/*      */ 
/*      */ 
/*      */     
/*      */     protected final BitSet a() {
/* 1424 */       return a;
/*      */     } }
/*      */   
/*      */   public static class dd extends cz { public dd() {
/* 1428 */       super((byte)0);
/*      */     }
/* 1430 */     private static final BitSet a = l.a(new com.d.c.a.c[] { com.d.c.a.c.aa, com.d.c.a.c.aJ, com.d.c.a.c.n, com.d.c.a.c.X, com.d.c.a.c.bH });
/*      */ 
/*      */ 
/*      */ 
/*      */     
/*      */     protected final BitSet a() {
/* 1436 */       return a;
/*      */     } }
/*      */ 
/*      */   
/*      */   public static class de
/*      */     extends a {
/* 1442 */     private static final BitSet a = l.a(new com.d.c.a.c[] { com.d.c.a.c.bk, com.d.c.a.c.ax, com.d.c.a.c.ad });
/*      */ 
/*      */ 
/*      */ 
/*      */ 
/*      */     
/*      */     private static BitSet a() {
/* 1449 */       return a;
/*      */     }
/*      */ 
/*      */     
/*      */     public final List a(com.d.c.a.a param1a, List<com.d.c.d.d> param1List, int param1Int, boolean param1Boolean1, boolean param1Boolean2) {
/* 1454 */       if (param1List.size() == 1) {
/* 1455 */         com.d.c.d.d d = param1List.get(0);
/* 1456 */         boolean bool = false;
/* 1457 */         if (d.e() == 0) {
/* 1458 */           bool = true;
/*      */         } else {
/* 1460 */           a(com.d.c.a.a.ao, d);
/*      */           com.d.c.a.c c;
/* 1462 */           if ((c = b(d)) == com.d.c.a.c.ap) {
/* 1463 */             bool = true;
/*      */           }
/*      */         } 
/*      */         
/* 1467 */         if (bool) {
/* 1468 */           return Collections.singletonList(new com.d.i.v(param1a, d, param1Boolean1, param1Int));
/*      */         }
/*      */       } 
/*      */ 
/*      */       
/* 1473 */       for (Iterator<com.d.c.d.d> iterator = param1List.iterator(); iterator.hasNext(); ) {
/*      */         com.d.c.d.j j;
/* 1475 */         a((com.d.c.d.d)(j = (com.d.c.d.j)iterator.next()), false);
/* 1476 */         a(param1a, (com.d.c.d.d)j);
/*      */         com.d.c.a.c c;
/* 1478 */         if ((c = b((com.d.c.d.d)j)) == com.d.c.a.c.ap) {
/* 1479 */           throw new com.d.c.d.b("Value none may not be used in this position", -1);
/*      */         }
/* 1481 */         a(param1a, a(), c);
/*      */       } 
/*      */       
/* 1484 */       return Collections.singletonList(new com.d.i.v(param1a, (com.d.c.d.d)new com.d.c.d.j(param1List), param1Boolean1, param1Int));
/*      */     }
/*      */   }
/*      */   
/*      */   public static class df extends bs {
/*      */     public df() {
/* 1490 */       super((byte)0);
/*      */     } }
/*      */   public static class dg extends cz { public dg() {
/* 1493 */       super((byte)0);
/*      */     }
/* 1495 */     private static final BitSet a = l.a(new com.d.c.a.c[] { com.d.c.a.c.m, com.d.c.a.c.bo, com.d.c.a.c.aj, com.d.c.a.c.ap });
/*      */ 
/*      */ 
/*      */ 
/*      */     
/*      */     protected final BitSet a() {
/* 1501 */       return a;
/*      */     } }
/*      */   
/*      */   public static class dm extends bu { public dm() {
/* 1505 */       super((byte)0);
/*      */     }
/*      */     
/* 1508 */     private static final BitSet a = l.a(new com.d.c.a.c[] { com.d.c.a.c.g, com.d.c.a.c.aT, com.d.c.a.c.aU, com.d.c.a.c.bi, com.d.c.a.c.bf, com.d.c.a.c.al, com.d.c.a.c.l, com.d.c.a.c.be });
/*      */ 
/*      */ 
/*      */ 
/*      */ 
/*      */ 
/*      */     
/*      */     protected final BitSet a() {
/* 1516 */       return a;
/*      */     } }
/*      */   
/*      */   public static class dn extends cz { public dn() {
/* 1520 */       super((byte)0);
/*      */     }
/* 1522 */     private static final BitSet a = l.a(new com.d.c.a.c[] { com.d.c.a.c.bp, com.d.c.a.c.P, com.d.c.a.c.q, com.d.c.a.c.M });
/*      */ 
/*      */ 
/*      */ 
/*      */     
/*      */     protected final BitSet a() {
/* 1528 */       return a;
/*      */     } }
/*      */   
/*      */   public static class do extends cz { public do() {
/* 1532 */       super((byte)0);
/*      */     }
/* 1534 */     private static final BitSet a = l.a(new com.d.c.a.c[] { com.d.c.a.c.aq, com.d.c.a.c.aB, com.d.c.a.c.ar, com.d.c.a.c.aD, com.d.c.a.c.aC });
/*      */ 
/*      */ 
/*      */ 
/*      */     
/*      */     protected final BitSet a() {
/* 1540 */       return a;
/*      */     } }
/*      */   
/*      */   public static class ds extends cz { public ds() {
/* 1544 */       super((byte)0);
/*      */     }
/* 1546 */     private static final BitSet a = l.a(new com.d.c.a.c[] { com.d.c.a.c.aq, com.d.c.a.c.as });
/*      */ 
/*      */ 
/*      */     
/*      */     protected final BitSet a() {
/* 1551 */       return a;
/*      */     } }
/*      */ 
/*      */   
/*      */   public static class dp extends cw { public dp() {
/* 1556 */       super((byte)0);
/*      */     } protected final boolean a() {
/* 1558 */       return false;
/*      */     } }
/*      */   
/*      */   public static class dq extends bt { public dq() {
/* 1562 */       super((byte)0);
/*      */     } protected final boolean b() {
/* 1564 */       return false;
/*      */     } }
/*      */   
/*      */   public static class dr extends bx { public dr() {
/* 1568 */       super((byte)0);
/*      */     } }
/*      */ 
/*      */   
/*      */   public static class dt extends a {
/* 1573 */     private static final BitSet a = l.a(new com.d.c.a.c[] { com.d.c.a.c.e });
/*      */ 
/*      */ 
/*      */     
/*      */     public final List a(com.d.c.a.a param1a, List<com.d.c.d.d> param1List, int param1Int, boolean param1Boolean1, boolean param1Boolean2) {
/* 1578 */       a(param1a, 1, param1List.size());
/*      */       com.d.c.d.d d;
/* 1580 */       a(d = param1List.get(0), param1Boolean2);
/* 1581 */       if (d.e() != 0) {
/* 1582 */         d(param1a, d);
/*      */         
/* 1584 */         if (d.a() == 21) {
/* 1585 */           com.d.c.a.c c = b(d);
/* 1586 */           a(param1a, a, c);
/*      */         } 
/*      */       } 
/*      */       
/* 1590 */       return Collections.singletonList(new com.d.i.v(param1a, d, param1Boolean1, param1Int));
/*      */     }
/*      */   }
/*      */   
/*      */   public static class ac
/*      */     extends a
/*      */   {
/* 1597 */     private static final BitSet a = l.a(new com.d.c.a.c[] { com.d.c.a.c.e });
/*      */ 
/*      */ 
/*      */ 
/*      */     
/*      */     public final List a(com.d.c.a.a param1a, List<com.d.c.d.d> param1List, int param1Int, boolean param1Boolean1, boolean param1Boolean2) {
/* 1603 */       a(param1a, 1, param1List.size());
/*      */       com.d.c.d.d d;
/* 1605 */       a(d = param1List.get(0), param1Boolean2);
/* 1606 */       if (d.e() != 0) {
/* 1607 */         d(param1a, d);
/*      */         
/* 1609 */         if (d.a() == 21) {
/* 1610 */           com.d.c.a.c c = b(d);
/* 1611 */           a(param1a, a, c);
/* 1612 */         } else if (d.b() < 1.0F) {
/* 1613 */           throw new com.d.c.d.b("column-count must be one or greater", -1);
/*      */         } 
/*      */       } 
/*      */       
/* 1617 */       return Collections.singletonList(new com.d.i.v(param1a, d, param1Boolean1, param1Int));
/*      */     } }
/*      */   
/*      */   public static class ad extends bu {
/*      */     public ad() {
/* 1622 */       super((byte)0);
/*      */     }
/* 1624 */     private static final BitSet a = l.a(new com.d.c.a.c[] { com.d.c.a.c.aq });
/*      */ 
/*      */ 
/*      */     
/*      */     protected final BitSet a() {
/* 1629 */       return a;
/*      */     }
/*      */   }
/*      */ 
/*      */ 
/*      */   
/*      */   private static List b(com.d.c.a.a parama, com.d.c.d.d paramd1, com.d.c.d.d paramd2, int paramInt, boolean paramBoolean) {
/*      */     ArrayList<com.d.c.d.d> arrayList;
/* 1637 */     (arrayList = new ArrayList<>(2)).add(paramd1);
/* 1638 */     arrayList.add(paramd2);
/*      */ 
/*      */     
/*      */     com.d.i.v v;
/*      */ 
/*      */     
/* 1644 */     return Collections.singletonList(v = new com.d.i.v(parama, (com.d.c.d.d)new com.d.c.d.j(arrayList), paramBoolean, paramInt));
/*      */   }
/*      */   
/*      */   public static class dl
/*      */     extends a {
/* 1649 */     private static final BitSet a = l.a(new com.d.c.a.c[] { com.d.c.a.c.ap });
/*      */ 
/*      */ 
/*      */ 
/*      */ 
/*      */ 
/*      */ 
/*      */ 
/*      */ 
/*      */ 
/*      */ 
/*      */ 
/*      */ 
/*      */ 
/*      */ 
/*      */ 
/*      */ 
/*      */ 
/*      */ 
/*      */ 
/*      */ 
/*      */ 
/*      */ 
/*      */ 
/*      */ 
/*      */ 
/*      */ 
/*      */ 
/*      */ 
/*      */ 
/*      */ 
/*      */ 
/*      */ 
/*      */ 
/*      */ 
/*      */ 
/*      */ 
/*      */ 
/*      */ 
/*      */ 
/*      */ 
/*      */ 
/*      */ 
/*      */ 
/*      */ 
/*      */ 
/*      */ 
/*      */ 
/*      */ 
/*      */     
/*      */     public final List a(com.d.c.a.a param1a, List<com.d.c.d.d> param1List, int param1Int, boolean param1Boolean1, boolean param1Boolean2) {
/*      */       // Byte code:
/*      */       //   0: aload_1
/*      */       //   1: iconst_1
/*      */       //   2: ldc 2147483647
/*      */       //   4: aload_2
/*      */       //   5: invokeinterface size : ()I
/*      */       //   10: invokestatic a : (Lcom/d/c/a/a;III)V
/*      */       //   13: aload_2
/*      */       //   14: iconst_0
/*      */       //   15: invokeinterface get : (I)Ljava/lang/Object;
/*      */       //   20: checkcast com/d/c/d/d
/*      */       //   23: iload #5
/*      */       //   25: invokestatic a : (Lcom/d/c/d/d;Z)V
/*      */       //   28: aload_2
/*      */       //   29: iconst_0
/*      */       //   30: invokeinterface get : (I)Ljava/lang/Object;
/*      */       //   35: checkcast com/d/c/d/j
/*      */       //   38: invokevirtual e : ()S
/*      */       //   41: ifne -> 69
/*      */       //   44: new com/d/i/v
/*      */       //   47: dup
/*      */       //   48: aload_1
/*      */       //   49: aload_2
/*      */       //   50: iconst_0
/*      */       //   51: invokeinterface get : (I)Ljava/lang/Object;
/*      */       //   56: checkcast com/d/c/d/d
/*      */       //   59: iload #4
/*      */       //   61: iload_3
/*      */       //   62: invokespecial <init> : (Lcom/d/c/a/a;Lcom/d/c/d/d;ZI)V
/*      */       //   65: invokestatic singletonList : (Ljava/lang/Object;)Ljava/util/List;
/*      */       //   68: areturn
/*      */       //   69: aload_2
/*      */       //   70: invokeinterface size : ()I
/*      */       //   75: iconst_1
/*      */       //   76: if_icmpne -> 137
/*      */       //   79: aload_2
/*      */       //   80: iconst_0
/*      */       //   81: invokeinterface get : (I)Ljava/lang/Object;
/*      */       //   86: checkcast com/d/c/d/d
/*      */       //   89: dup
/*      */       //   90: astore #5
/*      */       //   92: invokeinterface a : ()S
/*      */       //   97: bipush #21
/*      */       //   99: if_icmpne -> 137
/*      */       //   102: aload #5
/*      */       //   104: invokestatic b : (Lcom/d/c/d/d;)Lcom/d/c/a/c;
/*      */       //   107: astore #6
/*      */       //   109: aload_1
/*      */       //   110: getstatic com/d/c/d/a/l$dl.a : Ljava/util/BitSet;
/*      */       //   113: aload #6
/*      */       //   115: invokestatic a : (Lcom/d/c/a/a;Ljava/util/BitSet;Lcom/d/c/a/c;)V
/*      */       //   118: new com/d/i/v
/*      */       //   121: dup
/*      */       //   122: getstatic com/d/c/a/a.ay : Lcom/d/c/a/a;
/*      */       //   125: aload #5
/*      */       //   127: iload #4
/*      */       //   129: iload_3
/*      */       //   130: invokespecial <init> : (Lcom/d/c/a/a;Lcom/d/c/d/d;ZI)V
/*      */       //   133: invokestatic singletonList : (Ljava/lang/Object;)Ljava/util/List;
/*      */       //   136: areturn
/*      */       //   137: aload_2
/*      */       //   138: invokeinterface iterator : ()Ljava/util/Iterator;
/*      */       //   143: astore #5
/*      */       //   145: aload #5
/*      */       //   147: invokeinterface hasNext : ()Z
/*      */       //   152: ifeq -> 973
/*      */       //   155: aload #5
/*      */       //   157: invokeinterface next : ()Ljava/lang/Object;
/*      */       //   162: dup
/*      */       //   163: astore #6
/*      */       //   165: checkcast com/d/c/d/j
/*      */       //   168: dup
/*      */       //   169: astore #6
/*      */       //   171: invokevirtual i : ()S
/*      */       //   174: bipush #7
/*      */       //   176: if_icmpeq -> 190
/*      */       //   179: new com/d/c/d/b
/*      */       //   182: dup
/*      */       //   183: ldc 'One or more functions must be provided for transform property'
/*      */       //   185: iconst_m1
/*      */       //   186: invokespecial <init> : (Ljava/lang/String;I)V
/*      */       //   189: athrow
/*      */       //   190: aload #6
/*      */       //   192: invokevirtual n : ()Lcom/d/i/e;
/*      */       //   195: invokevirtual a : ()Ljava/lang/String;
/*      */       //   198: dup
/*      */       //   199: astore #7
/*      */       //   201: ldc 'matrix'
/*      */       //   203: invokevirtual equalsIgnoreCase : (Ljava/lang/String;)Z
/*      */       //   206: ifeq -> 262
/*      */       //   209: bipush #6
/*      */       //   211: istore #7
/*      */       //   213: aload #6
/*      */       //   215: invokevirtual n : ()Lcom/d/i/e;
/*      */       //   218: invokevirtual b : ()Ljava/util/List;
/*      */       //   221: invokeinterface iterator : ()Ljava/util/Iterator;
/*      */       //   226: astore #8
/*      */       //   228: aload #8
/*      */       //   230: invokeinterface hasNext : ()Z
/*      */       //   235: ifeq -> 259
/*      */       //   238: aload #8
/*      */       //   240: invokeinterface next : ()Ljava/lang/Object;
/*      */       //   245: astore #9
/*      */       //   247: aload_1
/*      */       //   248: aload #9
/*      */       //   250: checkcast com/d/c/d/d
/*      */       //   253: invokestatic k : (Lcom/d/c/a/a;Lcom/d/c/d/d;)V
/*      */       //   256: goto -> 228
/*      */       //   259: goto -> 951
/*      */       //   262: aload #7
/*      */       //   264: ldc 'translate'
/*      */       //   266: invokevirtual equalsIgnoreCase : (Ljava/lang/String;)Z
/*      */       //   269: ifeq -> 325
/*      */       //   272: iconst_2
/*      */       //   273: istore #7
/*      */       //   275: aload #6
/*      */       //   277: invokevirtual n : ()Lcom/d/i/e;
/*      */       //   280: invokevirtual b : ()Ljava/util/List;
/*      */       //   283: invokeinterface iterator : ()Ljava/util/Iterator;
/*      */       //   288: astore #8
/*      */       //   290: aload #8
/*      */       //   292: invokeinterface hasNext : ()Z
/*      */       //   297: ifeq -> 322
/*      */       //   300: aload #8
/*      */       //   302: invokeinterface next : ()Ljava/lang/Object;
/*      */       //   307: astore #9
/*      */       //   309: aload_0
/*      */       //   310: aload_1
/*      */       //   311: aload #9
/*      */       //   313: checkcast com/d/c/d/d
/*      */       //   316: invokevirtual i : (Lcom/d/c/a/a;Lcom/d/c/d/d;)V
/*      */       //   319: goto -> 290
/*      */       //   322: goto -> 951
/*      */       //   325: aload #7
/*      */       //   327: ldc 'translateX'
/*      */       //   329: invokevirtual equalsIgnoreCase : (Ljava/lang/String;)Z
/*      */       //   332: ifeq -> 388
/*      */       //   335: iconst_1
/*      */       //   336: istore #7
/*      */       //   338: aload #6
/*      */       //   340: invokevirtual n : ()Lcom/d/i/e;
/*      */       //   343: invokevirtual b : ()Ljava/util/List;
/*      */       //   346: invokeinterface iterator : ()Ljava/util/Iterator;
/*      */       //   351: astore #8
/*      */       //   353: aload #8
/*      */       //   355: invokeinterface hasNext : ()Z
/*      */       //   360: ifeq -> 385
/*      */       //   363: aload #8
/*      */       //   365: invokeinterface next : ()Ljava/lang/Object;
/*      */       //   370: astore #9
/*      */       //   372: aload_0
/*      */       //   373: aload_1
/*      */       //   374: aload #9
/*      */       //   376: checkcast com/d/c/d/d
/*      */       //   379: invokevirtual i : (Lcom/d/c/a/a;Lcom/d/c/d/d;)V
/*      */       //   382: goto -> 353
/*      */       //   385: goto -> 951
/*      */       //   388: aload #7
/*      */       //   390: ldc 'translateY'
/*      */       //   392: invokevirtual equalsIgnoreCase : (Ljava/lang/String;)Z
/*      */       //   395: ifeq -> 451
/*      */       //   398: iconst_1
/*      */       //   399: istore #7
/*      */       //   401: aload #6
/*      */       //   403: invokevirtual n : ()Lcom/d/i/e;
/*      */       //   406: invokevirtual b : ()Ljava/util/List;
/*      */       //   409: invokeinterface iterator : ()Ljava/util/Iterator;
/*      */       //   414: astore #8
/*      */       //   416: aload #8
/*      */       //   418: invokeinterface hasNext : ()Z
/*      */       //   423: ifeq -> 448
/*      */       //   426: aload #8
/*      */       //   428: invokeinterface next : ()Ljava/lang/Object;
/*      */       //   433: astore #9
/*      */       //   435: aload_0
/*      */       //   436: aload_1
/*      */       //   437: aload #9
/*      */       //   439: checkcast com/d/c/d/d
/*      */       //   442: invokevirtual i : (Lcom/d/c/a/a;Lcom/d/c/d/d;)V
/*      */       //   445: goto -> 416
/*      */       //   448: goto -> 951
/*      */       //   451: aload #7
/*      */       //   453: ldc 'scale'
/*      */       //   455: invokevirtual equalsIgnoreCase : (Ljava/lang/String;)Z
/*      */       //   458: ifeq -> 533
/*      */       //   461: iconst_2
/*      */       //   462: istore #7
/*      */       //   464: aload #6
/*      */       //   466: invokevirtual n : ()Lcom/d/i/e;
/*      */       //   469: invokevirtual b : ()Ljava/util/List;
/*      */       //   472: invokeinterface iterator : ()Ljava/util/Iterator;
/*      */       //   477: astore #8
/*      */       //   479: aload #8
/*      */       //   481: invokeinterface hasNext : ()Z
/*      */       //   486: ifeq -> 510
/*      */       //   489: aload #8
/*      */       //   491: invokeinterface next : ()Ljava/lang/Object;
/*      */       //   496: astore #9
/*      */       //   498: aload_1
/*      */       //   499: aload #9
/*      */       //   501: checkcast com/d/c/d/d
/*      */       //   504: invokestatic k : (Lcom/d/c/a/a;Lcom/d/c/d/d;)V
/*      */       //   507: goto -> 479
/*      */       //   510: aload #6
/*      */       //   512: invokevirtual n : ()Lcom/d/i/e;
/*      */       //   515: invokevirtual b : ()Ljava/util/List;
/*      */       //   518: invokeinterface size : ()I
/*      */       //   523: iconst_1
/*      */       //   524: if_icmpne -> 951
/*      */       //   527: iconst_1
/*      */       //   528: istore #7
/*      */       //   530: goto -> 951
/*      */       //   533: aload #7
/*      */       //   535: ldc 'scaleX'
/*      */       //   537: invokevirtual equalsIgnoreCase : (Ljava/lang/String;)Z
/*      */       //   540: ifeq -> 595
/*      */       //   543: iconst_1
/*      */       //   544: istore #7
/*      */       //   546: aload #6
/*      */       //   548: invokevirtual n : ()Lcom/d/i/e;
/*      */       //   551: invokevirtual b : ()Ljava/util/List;
/*      */       //   554: invokeinterface iterator : ()Ljava/util/Iterator;
/*      */       //   559: astore #8
/*      */       //   561: aload #8
/*      */       //   563: invokeinterface hasNext : ()Z
/*      */       //   568: ifeq -> 592
/*      */       //   571: aload #8
/*      */       //   573: invokeinterface next : ()Ljava/lang/Object;
/*      */       //   578: astore #9
/*      */       //   580: aload_1
/*      */       //   581: aload #9
/*      */       //   583: checkcast com/d/c/d/d
/*      */       //   586: invokestatic k : (Lcom/d/c/a/a;Lcom/d/c/d/d;)V
/*      */       //   589: goto -> 561
/*      */       //   592: goto -> 951
/*      */       //   595: aload #7
/*      */       //   597: ldc 'scaleY'
/*      */       //   599: invokevirtual equalsIgnoreCase : (Ljava/lang/String;)Z
/*      */       //   602: ifeq -> 657
/*      */       //   605: iconst_1
/*      */       //   606: istore #7
/*      */       //   608: aload #6
/*      */       //   610: invokevirtual n : ()Lcom/d/i/e;
/*      */       //   613: invokevirtual b : ()Ljava/util/List;
/*      */       //   616: invokeinterface iterator : ()Ljava/util/Iterator;
/*      */       //   621: astore #8
/*      */       //   623: aload #8
/*      */       //   625: invokeinterface hasNext : ()Z
/*      */       //   630: ifeq -> 654
/*      */       //   633: aload #8
/*      */       //   635: invokeinterface next : ()Ljava/lang/Object;
/*      */       //   640: astore #9
/*      */       //   642: aload_1
/*      */       //   643: aload #9
/*      */       //   645: checkcast com/d/c/d/d
/*      */       //   648: invokestatic k : (Lcom/d/c/a/a;Lcom/d/c/d/d;)V
/*      */       //   651: goto -> 623
/*      */       //   654: goto -> 951
/*      */       //   657: aload #7
/*      */       //   659: ldc 'skew'
/*      */       //   661: invokevirtual equalsIgnoreCase : (Ljava/lang/String;)Z
/*      */       //   664: ifeq -> 739
/*      */       //   667: iconst_2
/*      */       //   668: istore #7
/*      */       //   670: aload #6
/*      */       //   672: invokevirtual n : ()Lcom/d/i/e;
/*      */       //   675: invokevirtual b : ()Ljava/util/List;
/*      */       //   678: invokeinterface iterator : ()Ljava/util/Iterator;
/*      */       //   683: astore #8
/*      */       //   685: aload #8
/*      */       //   687: invokeinterface hasNext : ()Z
/*      */       //   692: ifeq -> 716
/*      */       //   695: aload #8
/*      */       //   697: invokeinterface next : ()Ljava/lang/Object;
/*      */       //   702: astore #9
/*      */       //   704: aload_1
/*      */       //   705: aload #9
/*      */       //   707: checkcast com/d/c/d/d
/*      */       //   710: invokestatic l : (Lcom/d/c/a/a;Lcom/d/c/d/d;)V
/*      */       //   713: goto -> 685
/*      */       //   716: aload #6
/*      */       //   718: invokevirtual n : ()Lcom/d/i/e;
/*      */       //   721: invokevirtual b : ()Ljava/util/List;
/*      */       //   724: invokeinterface size : ()I
/*      */       //   729: iconst_1
/*      */       //   730: if_icmpne -> 951
/*      */       //   733: iconst_1
/*      */       //   734: istore #7
/*      */       //   736: goto -> 951
/*      */       //   739: aload #7
/*      */       //   741: ldc 'skewX'
/*      */       //   743: invokevirtual equalsIgnoreCase : (Ljava/lang/String;)Z
/*      */       //   746: ifeq -> 801
/*      */       //   749: iconst_1
/*      */       //   750: istore #7
/*      */       //   752: aload #6
/*      */       //   754: invokevirtual n : ()Lcom/d/i/e;
/*      */       //   757: invokevirtual b : ()Ljava/util/List;
/*      */       //   760: invokeinterface iterator : ()Ljava/util/Iterator;
/*      */       //   765: astore #8
/*      */       //   767: aload #8
/*      */       //   769: invokeinterface hasNext : ()Z
/*      */       //   774: ifeq -> 798
/*      */       //   777: aload #8
/*      */       //   779: invokeinterface next : ()Ljava/lang/Object;
/*      */       //   784: astore #9
/*      */       //   786: aload_1
/*      */       //   787: aload #9
/*      */       //   789: checkcast com/d/c/d/d
/*      */       //   792: invokestatic l : (Lcom/d/c/a/a;Lcom/d/c/d/d;)V
/*      */       //   795: goto -> 767
/*      */       //   798: goto -> 951
/*      */       //   801: aload #7
/*      */       //   803: ldc 'skewY'
/*      */       //   805: invokevirtual equalsIgnoreCase : (Ljava/lang/String;)Z
/*      */       //   808: ifeq -> 863
/*      */       //   811: iconst_1
/*      */       //   812: istore #7
/*      */       //   814: aload #6
/*      */       //   816: invokevirtual n : ()Lcom/d/i/e;
/*      */       //   819: invokevirtual b : ()Ljava/util/List;
/*      */       //   822: invokeinterface iterator : ()Ljava/util/Iterator;
/*      */       //   827: astore #8
/*      */       //   829: aload #8
/*      */       //   831: invokeinterface hasNext : ()Z
/*      */       //   836: ifeq -> 860
/*      */       //   839: aload #8
/*      */       //   841: invokeinterface next : ()Ljava/lang/Object;
/*      */       //   846: astore #9
/*      */       //   848: aload_1
/*      */       //   849: aload #9
/*      */       //   851: checkcast com/d/c/d/d
/*      */       //   854: invokestatic l : (Lcom/d/c/a/a;Lcom/d/c/d/d;)V
/*      */       //   857: goto -> 829
/*      */       //   860: goto -> 951
/*      */       //   863: aload #7
/*      */       //   865: ldc 'rotate'
/*      */       //   867: invokevirtual equalsIgnoreCase : (Ljava/lang/String;)Z
/*      */       //   870: ifeq -> 925
/*      */       //   873: iconst_1
/*      */       //   874: istore #7
/*      */       //   876: aload #6
/*      */       //   878: invokevirtual n : ()Lcom/d/i/e;
/*      */       //   881: invokevirtual b : ()Ljava/util/List;
/*      */       //   884: invokeinterface iterator : ()Ljava/util/Iterator;
/*      */       //   889: astore #8
/*      */       //   891: aload #8
/*      */       //   893: invokeinterface hasNext : ()Z
/*      */       //   898: ifeq -> 922
/*      */       //   901: aload #8
/*      */       //   903: invokeinterface next : ()Ljava/lang/Object;
/*      */       //   908: astore #9
/*      */       //   910: aload_1
/*      */       //   911: aload #9
/*      */       //   913: checkcast com/d/c/d/d
/*      */       //   916: invokestatic l : (Lcom/d/c/a/a;Lcom/d/c/d/d;)V
/*      */       //   919: goto -> 891
/*      */       //   922: goto -> 951
/*      */       //   925: new com/d/c/d/b
/*      */       //   928: dup
/*      */       //   929: new java/lang/StringBuilder
/*      */       //   932: dup
/*      */       //   933: ldc 'Unsupported function provided in transform property: '
/*      */       //   935: invokespecial <init> : (Ljava/lang/String;)V
/*      */       //   938: aload #7
/*      */       //   940: invokevirtual append : (Ljava/lang/String;)Ljava/lang/StringBuilder;
/*      */       //   943: invokevirtual toString : ()Ljava/lang/String;
/*      */       //   946: iconst_m1
/*      */       //   947: invokespecial <init> : (Ljava/lang/String;I)V
/*      */       //   950: athrow
/*      */       //   951: aload_1
/*      */       //   952: iload #7
/*      */       //   954: aload #6
/*      */       //   956: invokevirtual n : ()Lcom/d/i/e;
/*      */       //   959: invokevirtual b : ()Ljava/util/List;
/*      */       //   962: invokeinterface size : ()I
/*      */       //   967: invokestatic a : (Lcom/d/c/a/a;II)V
/*      */       //   970: goto -> 145
/*      */       //   973: new com/d/i/v
/*      */       //   976: dup
/*      */       //   977: getstatic com/d/c/a/a.ay : Lcom/d/c/a/a;
/*      */       //   980: new com/d/c/d/j
/*      */       //   983: dup
/*      */       //   984: aload_2
/*      */       //   985: invokespecial <init> : (Ljava/util/List;)V
/*      */       //   988: iload #4
/*      */       //   990: iload_3
/*      */       //   991: invokespecial <init> : (Lcom/d/c/a/a;Lcom/d/c/d/d;ZI)V
/*      */       //   994: invokestatic singletonList : (Ljava/lang/Object;)Ljava/util/List;
/*      */       //   997: areturn
/*      */       // Line number table:
/*      */       //   Java source line number -> byte code offset
/*      */       //   #1654	-> 0
/*      */       //   #1655	-> 13
/*      */       //   #1657	-> 28
/*      */       //   #1658	-> 44
/*      */       //   #1661	-> 69
/*      */       //   #1662	-> 79
/*      */       //   #1663	-> 90
/*      */       //   #1664	-> 102
/*      */       //   #1665	-> 109
/*      */       //   #1666	-> 118
/*      */       //   #1671	-> 137
/*      */       //   #1672	-> 163
/*      */       //   #1674	-> 169
/*      */       //   #1675	-> 179
/*      */       //   #1678	-> 190
/*      */       //   #1681	-> 199
/*      */       //   #1682	-> 209
/*      */       //   #1683	-> 213
/*      */       //   #1684	-> 247
/*      */       //   #1685	-> 256
/*      */       //   #1686	-> 262
/*      */       //   #1687	-> 272
/*      */       //   #1688	-> 275
/*      */       //   #1689	-> 309
/*      */       //   #1690	-> 319
/*      */       //   #1691	-> 325
/*      */       //   #1692	-> 335
/*      */       //   #1693	-> 338
/*      */       //   #1694	-> 372
/*      */       //   #1695	-> 382
/*      */       //   #1696	-> 388
/*      */       //   #1697	-> 398
/*      */       //   #1698	-> 401
/*      */       //   #1699	-> 435
/*      */       //   #1700	-> 445
/*      */       //   #1701	-> 451
/*      */       //   #1702	-> 461
/*      */       //   #1703	-> 464
/*      */       //   #1704	-> 498
/*      */       //   #1705	-> 507
/*      */       //   #1706	-> 510
/*      */       //   #1707	-> 527
/*      */       //   #1708	-> 533
/*      */       //   #1709	-> 543
/*      */       //   #1710	-> 546
/*      */       //   #1711	-> 580
/*      */       //   #1712	-> 589
/*      */       //   #1713	-> 595
/*      */       //   #1714	-> 605
/*      */       //   #1715	-> 608
/*      */       //   #1716	-> 642
/*      */       //   #1717	-> 651
/*      */       //   #1718	-> 657
/*      */       //   #1719	-> 667
/*      */       //   #1720	-> 670
/*      */       //   #1721	-> 704
/*      */       //   #1722	-> 713
/*      */       //   #1723	-> 716
/*      */       //   #1724	-> 733
/*      */       //   #1725	-> 739
/*      */       //   #1726	-> 749
/*      */       //   #1727	-> 752
/*      */       //   #1728	-> 786
/*      */       //   #1729	-> 795
/*      */       //   #1730	-> 801
/*      */       //   #1731	-> 811
/*      */       //   #1732	-> 814
/*      */       //   #1733	-> 848
/*      */       //   #1734	-> 857
/*      */       //   #1735	-> 863
/*      */       //   #1736	-> 873
/*      */       //   #1737	-> 876
/*      */       //   #1738	-> 910
/*      */       //   #1739	-> 919
/*      */       //   #1741	-> 925
/*      */       //   #1744	-> 951
/*      */       //   #1745	-> 970
/*      */       //   #1747	-> 973
/*      */     }
/*      */   }
/*      */ 
/*      */ 
/*      */ 
/*      */ 
/*      */ 
/*      */ 
/*      */ 
/*      */ 
/*      */ 
/*      */ 
/*      */ 
/*      */ 
/*      */ 
/*      */ 
/*      */ 
/*      */ 
/*      */ 
/*      */ 
/*      */ 
/*      */ 
/*      */ 
/*      */ 
/*      */ 
/*      */ 
/*      */ 
/*      */ 
/*      */ 
/*      */ 
/*      */ 
/*      */ 
/*      */ 
/*      */ 
/*      */ 
/*      */ 
/*      */ 
/*      */ 
/*      */ 
/*      */ 
/*      */ 
/*      */ 
/*      */ 
/*      */ 
/*      */ 
/*      */ 
/*      */ 
/*      */ 
/*      */ 
/*      */   
/*      */   public static class dj
/*      */     extends a
/*      */   {
/* 1754 */     private static final BitSet a = l.a(new com.d.c.a.c[] { com.d.c.a.c.aa, com.d.c.a.c.n, com.d.c.a.c.aJ });
/*      */     
/*      */     public final List a(com.d.c.a.a param1a, List<com.d.c.d.d> param1List, int param1Int, boolean param1Boolean1, boolean param1Boolean2) {
/*      */       com.d.c.a.c c;
/* 1758 */       a(param1a, 1, param1List.size());
/*      */       com.d.c.d.d d;
/* 1760 */       a(d = param1List.get(0), param1Boolean2);
/*      */       
/* 1762 */       if (d.e() == 0) {
/* 1763 */         return Collections.singletonList(new com.d.i.v(param1a, d, param1Boolean1, param1Int));
/*      */       }
/*      */       
/* 1766 */       if (d.a() == 21) {
/* 1767 */         c = b(d);
/* 1768 */         a(param1a, a, c);
/* 1769 */         if (c == com.d.c.a.c.aa)
/* 1770 */           return Collections.singletonList(new com.d.i.v(param1a, (com.d.c.d.d)new com.d.c.d.j((short)2, 0.0F, "0%"), param1Boolean1, param1Int)); 
/* 1771 */         if (c == com.d.c.a.c.n) {
/* 1772 */           return Collections.singletonList(new com.d.i.v(param1a, (com.d.c.d.d)new com.d.c.d.j((short)2, 50.0F, "50%"), param1Boolean1, param1Int));
/*      */         }
/* 1774 */         return Collections.singletonList(new com.d.i.v(param1a, (com.d.c.d.d)new com.d.c.d.j((short)2, 100.0F, "100%"), param1Boolean1, param1Int));
/*      */       } 
/*      */       
/* 1777 */       i(param1a, (com.d.c.d.d)c);
/* 1778 */       return Collections.singletonList(new com.d.i.v(param1a, (com.d.c.d.d)c, param1Boolean1, param1Int));
/*      */     }
/*      */   }
/*      */   
/*      */   public static class dk
/*      */     extends a
/*      */   {
/* 1785 */     private static final BitSet a = l.a(new com.d.c.a.c[] { com.d.c.a.c.bi, com.d.c.a.c.n, com.d.c.a.c.l });
/*      */     
/*      */     public final List a(com.d.c.a.a param1a, List<com.d.c.d.d> param1List, int param1Int, boolean param1Boolean1, boolean param1Boolean2) {
/*      */       com.d.c.a.c c;
/* 1789 */       a(param1a, 1, param1List.size());
/*      */       com.d.c.d.d d;
/* 1791 */       a(d = param1List.get(0), param1Boolean2);
/*      */       
/* 1793 */       if (d.e() == 0) {
/* 1794 */         return Collections.singletonList(new com.d.i.v(param1a, d, param1Boolean1, param1Int));
/*      */       }
/*      */       
/* 1797 */       if (d.a() == 21) {
/* 1798 */         c = b(d);
/* 1799 */         a(param1a, a, c);
/* 1800 */         if (c == com.d.c.a.c.bi)
/* 1801 */           return Collections.singletonList(new com.d.i.v(param1a, (com.d.c.d.d)new com.d.c.d.j((short)2, 0.0F, "0%"), param1Boolean1, param1Int)); 
/* 1802 */         if (c == com.d.c.a.c.n) {
/* 1803 */           return Collections.singletonList(new com.d.i.v(param1a, (com.d.c.d.d)new com.d.c.d.j((short)2, 50.0F, "50%"), param1Boolean1, param1Int));
/*      */         }
/* 1805 */         return Collections.singletonList(new com.d.i.v(param1a, (com.d.c.d.d)new com.d.c.d.j((short)2, 100.0F, "100%"), param1Boolean1, param1Int));
/*      */       } 
/*      */       
/* 1808 */       i(param1a, (com.d.c.d.d)c);
/* 1809 */       return Collections.singletonList(new com.d.i.v(param1a, (com.d.c.d.d)c, param1Boolean1, param1Int));
/*      */     }
/*      */   }
/*      */ 
/*      */   
/*      */   public static class di
/*      */     extends a
/*      */   {
/*      */     public final List a(com.d.c.a.a param1a, List<com.d.c.d.d> param1List, int param1Int, boolean param1Boolean1, boolean param1Boolean2) {
/* 1818 */       a(param1a, 2, 3, param1List.size());
/* 1819 */       com.d.c.d.d d1 = param1List.get(0);
/* 1820 */       com.d.c.d.d d2 = param1List.get(1);
/*      */       
/* 1822 */       return Arrays.asList(new Object[] { (new l.dj())
/* 1823 */             .a(com.d.c.a.a.az, Collections.singletonList(d1), param1Int, param1Boolean1).get(0), (new l.dk())
/* 1824 */             .a(com.d.c.a.a.aA, Collections.singletonList(d2), param1Int, param1Boolean1).get(0) });
/*      */     }
/*      */   }
/*      */   
/*      */   public static class bp extends cz { public bp() {
/* 1829 */       super((byte)0);
/*      */     }
/* 1831 */     private static final BitSet a = l.a(new com.d.c.a.c[] { com.d.c.a.c.e, com.d.c.a.c.bW, com.d.c.a.c.bX });
/*      */ 
/*      */ 
/*      */ 
/*      */     
/*      */     protected final BitSet a() {
/* 1837 */       return a;
/*      */     } }
/*      */   
/*      */   public static class x extends cz { public x() {
/* 1841 */       super((byte)0);
/*      */     }
/* 1843 */     private static final BitSet a = l.a(new com.d.c.a.c[] { com.d.c.a.c.bY, com.d.c.a.c.bZ });
/*      */ 
/*      */     
/*      */     protected final BitSet a() {
/* 1847 */       return a;
/*      */     } }
/*      */   
/*      */   public static class ap extends cw { public ap() {
/* 1851 */       super((byte)0);
/*      */     }
/*      */     protected final boolean a() {
/* 1854 */       return false;
/*      */     } }
/*      */   
/*      */   public static class ar extends cz { public ar() {
/* 1858 */       super((byte)0);
/* 1859 */     } private static final BitSet a = l.a(new com.d.c.a.c[] { com.d.c.a.c.ak, com.d.c.a.c.aK });
/*      */ 
/*      */     
/*      */     protected final BitSet a() {
/* 1863 */       return a;
/*      */     } }
/*      */ 
/*      */ }


/* Location:              C:\Program Files (x86)\Steam\steamapps\common\Infinitode 2\infinitode-2.jar!\com\d\c\d\a\l.class
 * Java compiler version: 8 (52.0)
 * JD-Core Version:       1.1.3
 */